Workbook

Sheet README
A1: Reserve Clinic — Driver-based financial model (proposed concept; prepared 2026-09-02)
A3: Purpose: illustrate the economics of a compliant premium consumer-health + telehealth + commerce model under three scenarios. Nothing here is a forecast of results; every number is an assumption or a formula on assumptions.
A4: How to use: edit BLUE cells on the Assumptions sheet only. Yellow-filled cells are the highest-sensitivity inputs and should be validated first (see Validation method column).
A5: Sheets: Scenario Summary (outputs) · Assumptions (inputs) · Assumptions Register (rationale) · Model_Conservative / Model_Base / Model_Upside (36 monthly columns) · Sensitivity (LTV:CAC, payback, price×churn grids) · Celebrity Economics (hypothetical partner structures).
A6: Color code: blue = input; black = formula; green = link to another sheet; yellow fill = key assumption.
A7: Structure caveats: prescription-program revenue is modeled as an all-in monthly program price. Whether the brand entity, the affiliated medical practice, or the pharmacy is merchant of record for medication depends on corporate-practice-of-medicine and fee-splitting analysis by counsel; revenue recognition may differ (e.g., management-fee model). Clinician prescribing rate is a clinical outcome that is monitored for safety, never targeted.
A8: Scenario A vs B: set 'Named-partner model active?' to 1 (Scenario A: brand-partner retainer, royalty and traffic uplift apply) or 0 (Scenario B: independent brand).
A9: Sources for benchmark-informed assumptions are summarized in 08_ReserveClinic_Evidence_Ledger.xlsx and research/06_market_size_benchmarks.md; each assumption's rationale is on the Assumptions sheet.
A10: This model is not investment, legal, medical, or tax advice.

Sheet Assumptions
A1: Reserve Clinic — Financial Model Assumptions (all values are FINANCIAL ASSUMPTIONS unless a source is cited)
A2: Blue = editable input. Three scenario columns drive Model_Conservative, Model_Base, Model_Upside. Change blue cells only; every other sheet recalculates. Prepared 2026-09-02; proposed concept.
A4: Key | B4: Assumption | C4: Unit | D4: Conservative | E4: Base | F4: Upside | G4: Rationale / source | H4: Confidence | I4: Sensitivity | J4: Validation method
A5: Timing
A6: launch_month | B6: Public launch month (model month #) | C6: month | D6: 9 | E6: 8 | F6: 7 | G6: Phase plan in 06_ReserveClinic_Launch_Plan.md: Phase 0-3 precede launch; conservative adds one month of slippage. | H6: Medium | I6: High | J6: Phase exit criteria
A7: beta_month | B7: Private beta start month | C7: month | D7: 6 | E7: 5 | F7: 5 | G7: Phase 2 begins after internal pilot. | H7: Medium | I7: Low | J7: Phase exit criteria
A8: Traffic
A9: organic_m1 | B9: Organic + direct sessions in month 1 | C9: sessions | D9: 1500 | E9: 2500 | F9: 4000 | G9: Prototype site with 20 library entries; comparable early-stage health content sites. Analyst assumption. | H9: Low | I9: Medium | J9: GA4 after month 1
A10: organic_growth | B10: Organic monthly growth rate | C10: % | D10: 0.07 | E10: 0.09 | F10: 0.11 | G10: Library-led SEO compounding; DTC health benchmarks show 8-15%/mo early growth from a small base (analyst inference from research/06 benchmarks). | H10: Low | I10: High | J10: Search Console trend, quarterly
A11: organic_cap | B11: Organic + direct sessions ceiling per month | C11: sessions | D11: 150000 | E11: 300000 | F11: 400000 | G11: Caps compounding growth; category-level informational search demand is finite (analyst inference). | H11: Low | I11: Medium | J11: Search Console
A12: cps | B12: Cost per paid session (blended) | C12: $ | D12: 2.3 | E12: 2 | F12: 1.8 | G12: Health/wellness CPC and CPM proxies; Meta health-category restrictions raise cost. Analyst assumption. | H12: Medium | I12: High | J12: Ad platform reports
A13: paid_pre | B13: Paid media spend per month, months 1 to beta-1 | C13: $ | D13: 10000 | E13: 20000 | F13: 30000 | G13: Waitlist/education ads only. | H13: Medium | I13: Low | J13: Budget actuals
A14: paid_beta | B14: Paid media spend per month, beta to launch-1 | C14: $ | D14: 30000 | E14: 60000 | F14: 100000 | G14: Waitlist building (Phase 3). | H14: Medium | I14: Medium | J14: Budget actuals
A15: paid_launch | B15: Paid media spend, launch month | C15: $ | D15: 200000 | E15: 350000 | F15: 500000 | G15: Phase 4 budget range. | H15: Medium | I15: Medium | J15: Budget actuals
A16: paid_post | B16: Paid media spend per month after launch (month launch+1) | C16: $ | D16: 100000 | E16: 180000 | F16: 250000 | G16: Phase 5 operating range; scaled by growth below. | H16: Medium | I16: High | J16: Payback discipline gate
A17: paid_growth | B17: Monthly growth in post-launch paid spend | C17: % | D17: 0.02 | E17: 0.03 | F17: 0.04 | G17: Spend grows only while payback <= target. | H17: Medium | I17: Medium | J17: Monthly CAC review
A18: Funnel (prescription programs)
A19: quiz_start | B19: Quiz start rate (starts / sessions) | C19: % | D19: 0.09 | E19: 0.1 | F19: 0.12 | G19: Telehealth quiz-start benchmarks 5-10% (analyst inference). | H19: Medium | I19: High | J19: Analytics
A20: quiz_complete | B20: Quiz completion rate | C20: % | D20: 0.6 | E20: 0.7 | F20: 0.75 | G20: One-question-per-screen quizzes typically 55-75%. | H20: Medium | I20: Medium | J20: Analytics
A21: eligible_outcome | B21: Share of completes with an eligible outcome | C21: % | D21: 0.5 | E21: 0.6 | F21: 0.65 | G21: Red-flag and state screening remove 40-55%. | H21: Medium | I21: Medium | J21: Analytics
A22: state_cov_launch | B22: Share of US population in served states at launch | C22: % | D22: 0.35 | E22: 0.4 | F22: 0.45 | G22: 4-6 pilot states incl. large states (TX, FL) if licensure achieved. | H22: Medium | I22: High | J22: State readiness tracker
A23: state_cov_step | B23: Monthly increase in population coverage after launch | C23: % | D23: 0.02 | E23: 0.03 | F23: 0.035 | G23: Tranche-based expansion. | H23: Medium | I23: Medium | J23: State readiness tracker
A24: state_cov_cap | B24: Maximum population coverage | C24: % | D24: 0.75 | E24: 0.85 | F24: 0.9 | G24: Some states excluded for CPOM/async restrictions. | H24: Medium | I24: Low | J24: Counsel memo
A25: intake_submit | B25: Intake submission rate (eligible → intake) | C25: % | D25: 0.48 | E25: 0.55 | F25: 0.6 | G25: ID verification and consent friction. | H25: Medium | I25: High | J25: Analytics
A26: consult_complete | B26: Consult completion rate | C26: % | D26: 0.75 | E26: 0.82 | F26: 0.88 | G26: Async review completes higher than video. | H26: Medium | I26: Medium | J26: EHR data
A27: rx_rate | B27: Clinician prescribing rate (clinical decision; not a target) | C27: % | D27: 0.55 | E27: 0.62 | F27: 0.68 | G27: Observed ranges for telehealth GLP-1/hormone programs 50-70% (third-party reports); monitored for safety only. | H27: Low | I27: High | J27: Medical director audit
A28: enroll_rate | B28: Enrollment (paid) rate after prescription | C28: % | D28: 0.58 | E28: 0.65 | F28: 0.68 | G28: Price shock at plan stage; all-in pricing shown earlier improves this. | H28: Medium | I28: High | J28: Analytics
A29: Pricing
A30: program_price | B30: All-in program price per member-month (blended) | C30: $ | D30: 249 | E30: 275 | F30: 299 | G30: Competitive bands in 03_Peptide_Product_and_Pricing_Audit.xlsx: compounded peptide programs ~$150-$450/mo; premium positioning. | H30: Medium | I30: High | J30: Van Westendorp + tests
A31: consult_fee | B31: Consultation fee (charged at intake) | C31: $ | D31: 49 | E31: 79 | F31: 99 | G31: Range $0-$150 among competitors; refundable if not eligible is common. | H31: Medium | I31: Medium | J31: Pricing test
A32: lab_attach | B32: Share of new intakes ordering labs | C32: % | D32: 0.4 | E32: 0.5 | F32: 0.6 | G32: Programs requiring labs (hormone/metabolic). | H32: Medium | I32: Medium | J32: EHR data
A33: lab_price | B33: Lab panel price charged | C33: $ | D33: 99 | E33: 119 | F33: 139 | G33: Direct-pay panels via lab partners. | H33: Medium | I33: Low | J33: Vendor quotes
A34: member_price | B34: Membership price per month (education, navigation, member pricing) | C34: $ | D34: 19 | E34: 29 | F34: 39 | G34: Function Health $499/yr, Superpower $199-499/yr and Lifeforce $129/mo bracket the range; Reserve Clinic tier is lighter. | H34: Medium | I34: Medium | J34: Pricing test
A35: member_attach_nonelig | B35: Membership attach among non-eligible quiz completers | C35: % | D35: 0.04 | E35: 0.06 | F35: 0.08 | G35: Analyst assumption. | H35: Low | I35: Medium | J35: Analytics
A36: member_attach_traffic | B36: Membership sign-ups per session (organic) | C36: % | D36: 0.0005 | E36: 0.001 | F36: 0.0015 | G36: Analyst assumption. | H36: Low | I36: Low | J36: Analytics
A37: shop_conv | B37: Non-Rx shop conversion (orders / sessions) | C37: % | D37: 0.006 | E37: 0.009 | F37: 0.012 | G37: DTC supplement conversion 0.5-1.5%. | H37: Medium | I37: Medium | J37: Shopify analytics
A38: shop_aov | B38: Non-Rx average order value | C38: $ | D38: 65 | E38: 75 | F38: 85 | G38: Premium supplement/cosmetic AOV. | H38: Medium | I38: Low | J38: Shopify analytics
A39: shop_repeat | B39: Monthly reorder rate of prior shop customers | C39: % | D39: 0.12 | E39: 0.15 | F39: 0.18 | G39: Subscription attach on consumables. | H39: Low | I39: Medium | J39: Shopify analytics
A40: Retention
A41: rx_churn | B41: Monthly churn, prescription programs (blended) | C41: % | D41: 0.13 | E41: 0.11 | F41: 0.1 | G41: DTC health subscription churn 8-15%/mo; GLP-1 programs higher. Third-party benchmarks in research/06. | H41: Low | I41: High | J41: Cohort analysis
A42: member_churn | B42: Monthly churn, membership | C42: % | D42: 0.08 | E42: 0.06 | F42: 0.05 | G42: Content memberships 5-8%. | H42: Low | I42: Medium | J42: Cohort analysis
A43: Cost of revenue
A44: pharm_cost | B44: Pharmacy/medication cost per Rx member-month | C44: $ | D44: 110 | E44: 95 | F44: 85 | G44: Compounded peptide and GLP-1 wholesale-to-telehealth cost bands (third-party reports); volume tiers reduce cost. | H44: Low | I44: High | J44: Pharmacy contracts
A45: clin_consult_cost | B45: Clinician cost per completed consult | C45: $ | D45: 45 | E45: 40 | F45: 35 | G45: Async visit cost via provider networks ~$25-60. | H45: Medium | I45: Medium | J45: Vendor contracts
A46: clin_refill_cost | B46: Clinician cost per active Rx member-month (monitoring/refill review) | C46: $ | D46: 10 | E46: 8 | F46: 7 | G46: Monthly check-in review. | H46: Medium | I46: Medium | J46: Vendor contracts
A47: ship_cost | B47: Fulfillment + shipping per Rx shipment (cold chain where needed) | C47: $ | D47: 18 | E47: 15 | F47: 13 | G47: Pharmacy carrier programs. | H47: Medium | I47: Low | J47: Pharmacy contracts
A48: lab_cost | B48: Lab panel cost | C48: $ | D48: 85 | E48: 80 | F48: 75 | G48: Direct-pay lab wholesale. | H48: Medium | I48: Low | J48: Vendor quotes
A49: pay_fee | B49: Payment processing fee (% of revenue) | C49: % | D49: 0.032 | E49: 0.029 | F49: 0.027 | G49: Card fees 2.7-3.2% + fixed; high-risk processors cost more. | H49: High | I49: Low | J49: Processor statements
A50: refund_pct | B50: Refunds and chargebacks (% of revenue) | C50: % | D50: 0.05 | E50: 0.035 | F50: 0.025 | G50: Benchmark 2-5%. | H50: Medium | I50: Medium | J50: Finance actuals
A51: support_cost | B51: Support cost per active member-month (non-clinical) | C51: $ | D51: 6 | E51: 5 | F51: 4 | G51: Tooling + staffing per member. | H51: Medium | I51: Low | J51: Support actuals
A52: shop_cogs_pct | B52: Non-Rx product COGS (% of revenue) | C52: % | D52: 0.4 | E52: 0.35 | F52: 0.32 | G52: Premium supplements 30-40%. | H52: Medium | I52: Low | J52: Supplier quotes
A53: shop_fulfil | B53: Non-Rx fulfillment per order | C53: $ | D53: 9 | E53: 8 | F53: 7 | G53: 3PL pick/pack/ship. | H53: Medium | I53: Low | J53: 3PL quotes
A54: member_cogs | B54: Membership delivery cost per member-month | C54: $ | D54: 3 | E54: 2 | F54: 2 | G54: Platform + content amortization. | H54: Medium | I54: Low | J54: Actuals
A55: Operating expenses (monthly, fully loaded)
A56: team_p0 | B56: Team cost per month, months 1-3 | C56: $ | D56: 45000 | E56: 60000 | F56: 80000 | G56: GM, product lead, compliance (fractional), engineering contractors. | H56: Medium | I56: Medium | J56: Hiring plan
A57: team_p1 | B57: Team cost per month, month 4 to launch-1 | C57: $ | D57: 90000 | E57: 120000 | F57: 160000 | G57: Adds content, support, ops. | H57: Medium | I57: Medium | J57: Hiring plan
A58: team_p2 | B58: Team cost per month, launch to month 12 | C58: $ | D58: 140000 | E58: 180000 | F58: 240000 | G58: Growth, support scaling. | H58: Medium | I58: Medium | J58: Hiring plan
A59: team_p3 | B59: Team cost per month, months 13-24 | C59: $ | D59: 160000 | E59: 260000 | F59: 340000 | H59: Low | I59: Medium | J59: Hiring plan
A60: team_p4 | B60: Team cost per month, months 25-36 | C60: $ | D60: 190000 | E60: 340000 | F60: 450000 | H60: Low | I60: Medium | J60: Hiring plan
A61: med_lead | B61: Medical leadership (medical director + advisory) per month | C61: $ | D61: 15000 | E61: 20000 | F61: 25000 | G61: Fractional medical director retainers $10-25k/mo (analyst inference); compensation never tied to Rx volume. | H61: Medium | I61: Low | J61: Agreement
A62: tech_pre | B62: Technology & software per month, pre-launch | C62: $ | D62: 8000 | E62: 12000 | F62: 18000 | G62: Vendor sandboxes, CMS, analytics, CMP. | H62: Medium | I62: Low | J62: Vendor quotes
A63: tech_post | B63: Technology & software per month, post-launch | C63: $ | D63: 20000 | E63: 30000 | F63: 45000 | G63: Telehealth/EHR platform fees, Shopify, Stripe, warehouse, support tools. | H63: Medium | I63: Medium | J63: Vendor quotes
A64: build_capex | B64: Site & portal build per month, months 1-4 (one-time) | C64: $ | D64: 40000 | E64: 60000 | F64: 80000 | G64: Option C build $150-300k in 05_ReserveClinic_Website_Strategy.md. | H64: Medium | I64: Low | J64: SOW
A65: legal_p0 | B65: Legal, regulatory & compliance per month, months 1-3 | C65: $ | D65: 40000 | E65: 50000 | F65: 60000 | G65: Structuring, CPOM memos, formulary review, trademark, contracts. | H65: Medium | I65: Low | J65: Counsel estimates
A66: legal_post | B66: Legal & compliance per month thereafter | C66: $ | D66: 15000 | E66: 20000 | F66: 25000 | G66: Ongoing review, state expansion, claims review. | H66: Medium | I66: Low | J66: Counsel estimates
A67: insurance | B67: Insurance per month (from launch) | C67: $ | D67: 6000 | E67: 8000 | F67: 10000 | G67: Professional, product, cyber, D&O. | H67: Medium | I67: Low | J67: Broker quotes
A68: creative_pre | B68: Creative & content production per month, pre-launch | C68: $ | D68: 15000 | E68: 25000 | F68: 40000 | G68: Library, video series, photography. | H68: Medium | I68: Low | J68: Agency quotes
A69: creative_post | B69: Creative & content production per month, post-launch | C69: $ | D69: 25000 | E69: 40000 | F69: 60000 | H69: Medium | I69: Low | J69: Agency quotes
A70: launch_pr | B70: Launch PR/events one-time (launch month) | C70: $ | D70: 60000 | E70: 90000 | F70: 120000 | G70: Phase 4 budget. | H70: Medium | I70: Low | J70: Agency quotes
A71: influ_pre | B71: Influencer/affiliate per month, beta to launch-1 | C71: $ | D71: 10000 | E71: 25000 | F71: 50000 | G71: Disclosed creator seeding. | H71: Medium | I71: Medium | J71: Contracts
A72: influ_post | B72: Influencer/affiliate per month, post-launch | C72: $ | D72: 20000 | E72: 50000 | F72: 100000 | H72: Medium | I72: Medium | J72: Contracts
A73: Principal (celebrity) economics — hypothetical; no terms offered or accepted
A74: named_partner | B74: Named-partner model active? (1 = Scenario A, 0 = Scenario B) | C74: flag | D74: 1 | E74: 1 | F74: 1 | G74: Toggle to compare Scenario A vs B. Set to 0 for the independent-brand model. | H74: n/a | I74: High | J74: Founder decision
A75: celeb_cash | B75: Brand partner cash retainer per month (from beta month) | C75: $ | D75: 25000 | E75: 30000 | F75: 40000 | G75: Hypothetical mixed structure; see Celebrity Economics sheet for alternatives. | H75: Low | I75: High | J75: Negotiation
A76: celeb_royalty | B76: Brand partner royalty (% of net revenue) | C76: % | D76: 0.03 | E76: 0.03 | F76: 0.03 | G76: Hypothetical; licensing royalties in consumer brands commonly 3-10% (third-party reports). | H76: Low | I76: High | J76: Negotiation
A77: celeb_equity | B77: Brand partner equity (% fully diluted; non-cash, for reference) | C77: % | D77: 0.05 | E77: 0.08 | F77: 0.12 | G77: Hypothetical. | H77: Low | I77: n/a | J77: Negotiation
A78: celeb_lift | B78: Traffic uplift multiplier when named-partner model is active (post-launch organic/direct) | C78: x | D78: 1.1 | E78: 1.25 | F78: 1.3 | G78: Celebrity-founded brands show launch-window demand spikes (see 04_Celebrity_Founder_Database.xlsx lessons); durability uncertain. | H78: Low | I78: High | J78: Brand-lift study
A79: Working capital
A80: inv_months | B80: Non-Rx inventory on hand (months of COGS) | C80: months | D80: 2 | E80: 1.5 | F80: 1.5 | G80: Initial stock. | H80: Medium | I80: Low | J80: Ops
A81: opening_cash | B81: Opening cash (for cash-balance line; capital requirement computed separately) | C81: $ | D81: 0 | E81: 0 | F81: 0 | G81: Set to committed capital once known. | H81: n/a | I81: n/a | J81: Cap table
B83: Legend: yellow fill = high-sensitivity assumption to validate first. Scenario columns are independent; edit any of them.

Sheet Scenario Summary
A1: Reserve Clinic — Scenario summary (all cells link to model sheets; green = cross-sheet link)
A2: Proposed concept. Outputs are projections from labeled assumptions, not forecasts of results. Break-even = first month with positive EBITDA; capital required = most negative cumulative cash flow plus 15% contingency.
A4: Metric | B4: Unit | C4: Conservative | D4: Base | E4: Upside
A5: Year 1 net revenue | B5: $ | C5: =SUM(Model_Conservative!D43:O43) -> 443993.13 | D5: =SUM(Model_Base!D43:O43) -> 3428128.3 | E5: =SUM(Model_Upside!D43:O43) -> 14728834
A6: Year 2 net revenue | B6: $ | C6: =SUM(Model_Conservative!P43:AA43) -> 2517835.9 | D6: =SUM(Model_Base!P43:AA43) -> 19830860 | E6: =SUM(Model_Upside!P43:AA43) -> 83677545
A7: Year 3 net revenue | B7: $ | C7: =SUM(Model_Conservative!AB43:AM43) -> 5056214.6 | D7: =SUM(Model_Base!AB43:AM43) -> 42820608 | E7: =SUM(Model_Upside!AB43:AM43) -> 1.9417842e+08
A8: Year 1 gross profit | B8: $ | C8: =SUM(Model_Conservative!D54:O54) -> 147653.37 | D8: =SUM(Model_Base!D54:O54) -> 1717740.4 | E8: =SUM(Model_Upside!D54:O54) -> 8785277.8
A9: Year 2 gross profit | B9: $ | C9: =SUM(Model_Conservative!P54:AA54) -> 865047.33 | D9: =SUM(Model_Base!P54:AA54) -> 10009261 | E9: =SUM(Model_Upside!P54:AA54) -> 50035951
A10: Year 3 gross profit | B10: $ | C10: =SUM(Model_Conservative!AB54:AM54) -> 1738951 | D10: =SUM(Model_Base!AB54:AM54) -> 21570746 | E10: =SUM(Model_Upside!AB54:AM54) -> 1.1588844e+08
A11: Year 1 EBITDA | B11: $ | C11: =SUM(Model_Conservative!D77:O77) -> -2984706.4 | D11: =SUM(Model_Base!D77:O77) -> -3422156.3 | E11: =SUM(Model_Upside!D77:O77) -> 806332.09
A12: Year 2 EBITDA | B12: $ | C12: =SUM(Model_Conservative!P77:AA77) -> -4065789.4 | D12: =SUM(Model_Base!P77:AA77) -> 1043149.4 | E12: =SUM(Model_Upside!P77:AA77) -> 35215327
A13: Year 3 EBITDA | B13: $ | C13: =SUM(Model_Conservative!AB77:AM77) -> -4009826.1 | D13: =SUM(Model_Base!AB77:AM77) -> 9730800 | E13: =SUM(Model_Upside!AB77:AM77) -> 93685889
A14: Year 3 gross margin % | B14: % | C14: =IF(SUM(Model_Conservative!AB43:AM43)=0,0,SUM(Model_Conservative!AB54:AM54)/SUM(Model_Conservative!AB43:AM43)) -> 0.34392351 | D14: =IF(SUM(Model_Base!AB43:AM43)=0,0,SUM(Model_Base!AB54:AM54)/SUM(Model_Base!AB43:AM43)) -> 0.50374684 | E14: =IF(SUM(Model_Upside!AB43:AM43)=0,0,SUM(Model_Upside!AB54:AM54)/SUM(Model_Upside!AB43:AM43)) -> 0.59681419
A15: Active Rx members, month 12 | B15: # | C15: =Model_Conservative!O24 -> 229.05324 | D15: =Model_Base!O24 -> 1687.9488 | E15: =Model_Upside!O24 -> 6762.9762
A16: Active Rx members, month 24 | B16: # | C16: =Model_Conservative!AA24 -> 705.82123 | D16: =Model_Base!AA24 -> 6030.7692 | E16: =Model_Upside!AA24 -> 24843.633
A17: Active Rx members, month 36 | B17: # | C17: =Model_Conservative!AM24 -> 1302.8292 | D17: =Model_Base!AM24 -> 11437.582 | E17: =Model_Upside!AM24 -> 52299.684
A18: Active members (membership), month 36 | B18: # | C18: =Model_Conservative!AM29 -> 1595.8394 | D18: =Model_Base!AM29 -> 8289.8763 | E18: =Model_Upside!AM29 -> 27495.424
A19: Total sessions, 36 months | B19: # | C19: =Model_Conservative!C15 -> 1928704.1 | D19: =Model_Base!C15 -> 4900922.5 | E19: =Model_Upside!C15 -> 9779343.7
A20: Blended CAC, month 12 | B20: $ | C20: =Model_Conservative!O65 -> 268.39026 | D20: =Model_Base!O65 -> 137.51169 | E20: =Model_Upside!O65 -> 82.172491
A21: CAC per Rx member, month 12 | B21: $ | C21: =Model_Conservative!O66 -> 2003.1918 | D21: =Model_Base!O66 -> 584.03571 | E21: =Model_Upside!O66 -> 245.79703
A22: CAC per Rx member, month 24 | B22: $ | C22: =Model_Conservative!AA66 -> 1156.4848 | D22: =Model_Base!AA66 -> 312.62201 | E22: =Model_Upside!AA66 -> 139.24484
A23: Contribution per Rx member-month | B23: $ | C23: =Model_Conservative!O85 -> 84.582 | D23: =Model_Base!O85 -> 134.4 | E23: =Model_Upside!O85 -> 174.452
A24: LTV (contribution-based) | B24: $ | C24: =Model_Conservative!O86 -> 650.63077 | D24: =Model_Base!O86 -> 1221.8182 | E24: =Model_Upside!O86 -> 1744.52
A25: LTV : CAC, month 24 | B25: x | C25: =Model_Conservative!AA87 -> 0.56259347 | D25: =Model_Base!AA87 -> 3.9082923 | E25: =Model_Upside!AA87 -> 12.528435
A26: CAC payback, month 24 (months) | B26: months | C26: =Model_Conservative!AA88 -> 13.672942 | D26: =Model_Base!AA88 -> 2.3260566 | E26: =Model_Upside!AA88 -> 0.79818426
A27: Net revenue per active customer, month 36 | B27: $ | C27: =Model_Conservative!AM89 -> 181.046 | D27: =Model_Base!AM89 -> 232.11902 | E27: =Model_Upside!AM89 -> 275.67357
A28: Break-even month (first positive EBITDA) | B28: month | C28: =IF(MIN(Model_Conservative!D82:AM82)=999,"Not within 36 months",MIN(Model_Conservative!D82:AM82)) -> Not within 36 months | D28: =IF(MIN(Model_Base!D82:AM82)=999,"Not within 36 months",MIN(Model_Base!D82:AM82)) -> 18 | E28: =IF(MIN(Model_Upside!D82:AM82)=999,"Not within 36 months",MIN(Model_Upside!D82:AM82)) -> 8
A29: Peak cumulative cash burn | B29: $ | C29: =MIN(Model_Conservative!D80:AM80) -> -11189400 | D29: =MIN(Model_Base!D80:AM80) -> -4165450.1 | E29: =MIN(Model_Upside!D80:AM80) -> -2325279.2
A30: Capital required (peak burn + 15% contingency) | B30: $ | C30: =-MIN(Model_Conservative!D80:AM80)*1.15 -> 12867810 | D30: =-MIN(Model_Base!D80:AM80)*1.15 -> 4790267.6 | E30: =-MIN(Model_Upside!D80:AM80)*1.15 -> 2674071.1
A31: Cumulative cash flow, month 36 | B31: $ | C31: =Model_Conservative!AM80 -> -11189400 | D31: =Model_Base!AM80 -> 6911807.9 | E31: =Model_Upside!AM80 -> 1.283219e+08
A32: Brand partner cash + royalty paid, 36 months | B32: $ | C32: =-(Model_Conservative!C60+Model_Conservative!C61) -> 1015541.3 | D32: =-(Model_Base!C60+Model_Base!C61) -> 2942387.9 | E32: =-(Model_Upside!C60+Model_Upside!C61) -> 10057544

Sheet Model_Conservative
A1: Reserve Clinic monthly model — Conservative scenario (all cells are formulas driven by the Assumptions sheet)
A2: Units: $ unless noted. Month 1 = start of Phase 0. Prescription programs run through an affiliated medical practice and licensed pharmacies; revenue recognition and merchant-of-record structure subject to counsel.
A3: Line | B3: Unit | C3: 36-mo total | D3: 1 | E3: 2 | F3: 3 | G3: 4 | H3: 5 | I3: 6 | J3: 7 | K3: 8 | L3: 9 | M3: 10 | N3: 11 | O3: 12 | P3: 13 | Q3: 14 | R3: 15 | S3: 16 | T3: 17 | U3: 18 | V3: 19 | W3: 20 | X3: 21 | Y3: 22 | Z3: 23 | AA3: 24 | AB3: 25 | AC3: 26 | AD3: 27 | AE3: 28 | AF3: 29 | AG3: 30 | AH3: 31 | AI3: 32 | AJ3: 33 | AK3: 34 | AL3: 35 | AM3: 36
A4: Timing & coverage
A5: Model month | B5: # | D5: =D$3 -> 1 | E5: =E$3 -> 2 | F5: =F$3 -> 3 | G5: =G$3 -> 4 | H5: =H$3 -> 5 | I5: =I$3 -> 6 | J5: =J$3 -> 7 | K5: =K$3 -> 8 | ... AM5: =AM$3 -> 36
A6: Pre-beta phase flag | B6: flag | D6: =IF(D$3<Assumptions!$D$7,1,0) -> 1 | E6: =IF(E$3<Assumptions!$D$7,1,0) -> 1 | F6: =IF(F$3<Assumptions!$D$7,1,0) -> 1 | G6: =IF(G$3<Assumptions!$D$7,1,0) -> 1 | H6: =IF(H$3<Assumptions!$D$7,1,0) -> 1 | I6: =IF(I$3<Assumptions!$D$7,1,0) -> 0 | J6: =IF(J$3<Assumptions!$D$7,1,0) -> 0 | K6: =IF(K$3<Assumptions!$D$7,1,0) -> 0 | ... AM6: =IF(AM$3<Assumptions!$D$7,1,0) -> 0
A7: Beta/waitlist phase flag | B7: flag | D7: =IF(AND(D$3>=Assumptions!$D$7,D$3<Assumptions!$D$6),1,0) -> 0 | E7: =IF(AND(E$3>=Assumptions!$D$7,E$3<Assumptions!$D$6),1,0) -> 0 | F7: =IF(AND(F$3>=Assumptions!$D$7,F$3<Assumptions!$D$6),1,0) -> 0 | G7: =IF(AND(G$3>=Assumptions!$D$7,G$3<Assumptions!$D$6),1,0) -> 0 | H7: =IF(AND(H$3>=Assumptions!$D$7,H$3<Assumptions!$D$6),1,0) -> 0 | I7: =IF(AND(I$3>=Assumptions!$D$7,I$3<Assumptions!$D$6),1,0) -> 1 | J7: =IF(AND(J$3>=Assumptions!$D$7,J$3<Assumptions!$D$6),1,0) -> 1 | K7: =IF(AND(K$3>=Assumptions!$D$7,K$3<Assumptions!$D$6),1,0) -> 1 | ... AM7: =IF(AND(AM$3>=Assumptions!$D$7,AM$3<Assumptions!$D$6),1,0) -> 0
A8: Launch month flag | B8: flag | D8: =IF(D$3=Assumptions!$D$6,1,0) -> 0 | E8: =IF(E$3=Assumptions!$D$6,1,0) -> 0 | F8: =IF(F$3=Assumptions!$D$6,1,0) -> 0 | G8: =IF(G$3=Assumptions!$D$6,1,0) -> 0 | H8: =IF(H$3=Assumptions!$D$6,1,0) -> 0 | I8: =IF(I$3=Assumptions!$D$6,1,0) -> 0 | J8: =IF(J$3=Assumptions!$D$6,1,0) -> 0 | K8: =IF(K$3=Assumptions!$D$6,1,0) -> 0 | ... AM8: =IF(AM$3=Assumptions!$D$6,1,0) -> 0
A9: Post-launch flag (incl. launch month) | B9: flag | D9: =IF(D$3>=Assumptions!$D$6,1,0) -> 0 | E9: =IF(E$3>=Assumptions!$D$6,1,0) -> 0 | F9: =IF(F$3>=Assumptions!$D$6,1,0) -> 0 | G9: =IF(G$3>=Assumptions!$D$6,1,0) -> 0 | H9: =IF(H$3>=Assumptions!$D$6,1,0) -> 0 | I9: =IF(I$3>=Assumptions!$D$6,1,0) -> 0 | J9: =IF(J$3>=Assumptions!$D$6,1,0) -> 0 | K9: =IF(K$3>=Assumptions!$D$6,1,0) -> 0 | ... AM9: =IF(AM$3>=Assumptions!$D$6,1,0) -> 1
A10: Population coverage of served states (Rx) | B10: % | D10: =IF(D$3<Assumptions!$D$7,0,IF(D$3<Assumptions!$D$6,Assumptions!$D$22*0.5,MIN(Assumptions!$D$24,Assumptions!$D$22+Assumptions!$D$23*(D$3-Assumptions!$D$6)))) -> 0 | E10: =IF(E$3<Assumptions!$D$7,0,IF(E$3<Assumptions!$D$6,Assumptions!$D$22*0.5,MIN(Assumptions!$D$24,Assumptions!$D$22+Assumptions!$D$23*(E$3-Assumptions!$D$6)))) -> 0 | F10: =IF(F$3<Assumptions!$D$7,0,IF(F$3<Assumptions!$D$6,Assumptions!$D$22*0.5,MIN(Assumptions!$D$24,Assumptions!$D$22+Assumptions!$D$23*(F$3-Assumptions!$D$6)))) -> 0 | G10: =IF(G$3<Assumptions!$D$7,0,IF(G$3<Assumptions!$D$6,Assumptions!$D$22*0.5,MIN(Assumptions!$D$24,Assumptions!$D$22+Assumptions!$D$23*(G$3-Assumptions!$D$6)))) -> 0 | H10: =IF(H$3<Assumptions!$D$7,0,IF(H$3<Assumptions!$D$6,Assumptions!$D$22*0.5,MIN(Assumptions!$D$24,Assumptions!$D$22+Assumptions!$D$23*(H$3-Assumptions!$D$6)))) -> 0 | I10: =IF(I$3<Assumptions!$D$7,0,IF(I$3<Assumptions!$D$6,Assumptions!$D$22*0.5,MIN(Assumptions!$D$24,Assumptions!$D$22+Assumptions!$D$23*(I$3-Assumptions!$D$6)))) -> 0.175 | J10: =IF(J$3<Assumptions!$D$7,0,IF(J$3<Assumptions!$D$6,Assumptions!$D$22*0.5,MIN(Assumptions!$D$24,Assumptions!$D$22+Assumptions!$D$23*(J$3-Assumptions!$D$6)))) -> 0.175 | K10: =IF(K$3<Assumptions!$D$7,0,IF(K$3<Assumptions!$D$6,Assumptions!$D$22*0.5,MIN(Assumptions!$D$24,Assumptions!$D$22+Assumptions!$D$23*(K$3-Assumptions!$D$6)))) -> 0.175 | ... AM10: =IF(AM$3<Assumptions!$D$7,0,IF(AM$3<Assumptions!$D$6,Assumptions!$D$22*0.5,MIN(Assumptions!$D$24,Assumptions!$D$22+Assumptions!$D$23*(AM$3-Assumptions!$D$6)))) -> 0.75
A11: Traffic
A12: Paid media spend | B12: $ | C12: =SUM(D12:AM12) -> 3874432.4 | D12: =IF(D$3<Assumptions!$D$7,Assumptions!$D$13,IF(D$3<Assumptions!$D$6,Assumptions!$D$14,IF(D$3=Assumptions!$D$6,Assumptions!$D$15,Assumptions!$D$16*(1+Assumptions!$D$17)^(D$3-Assumptions!$D$6-1)))) -> 10000 | E12: =IF(E$3<Assumptions!$D$7,Assumptions!$D$13,IF(E$3<Assumptions!$D$6,Assumptions!$D$14,IF(E$3=Assumptions!$D$6,Assumptions!$D$15,Assumptions!$D$16*(1+Assumptions!$D$17)^(E$3-Assumptions!$D$6-1)))) -> 10000 | F12: =IF(F$3<Assumptions!$D$7,Assumptions!$D$13,IF(F$3<Assumptions!$D$6,Assumptions!$D$14,IF(F$3=Assumptions!$D$6,Assumptions!$D$15,Assumptions!$D$16*(1+Assumptions!$D$17)^(F$3-Assumptions!$D$6-1)))) -> 10000 | G12: =IF(G$3<Assumptions!$D$7,Assumptions!$D$13,IF(G$3<Assumptions!$D$6,Assumptions!$D$14,IF(G$3=Assumptions!$D$6,Assumptions!$D$15,Assumptions!$D$16*(1+Assumptions!$D$17)^(G$3-Assumptions!$D$6-1)))) -> 10000 | H12: =IF(H$3<Assumptions!$D$7,Assumptions!$D$13,IF(H$3<Assumptions!$D$6,Assumptions!$D$14,IF(H$3=Assumptions!$D$6,Assumptions!$D$15,Assumptions!$D$16*(1+Assumptions!$D$17)^(H$3-Assumptions!$D$6-1)))) -> 10000 | I12: =IF(I$3<Assumptions!$D$7,Assumptions!$D$13,IF(I$3<Assumptions!$D$6,Assumptions!$D$14,IF(I$3=Assumptions!$D$6,Assumptions!$D$15,Assumptions!$D$16*(1+Assumptions!$D$17)^(I$3-Assumptions!$D$6-1)))) -> 30000 | J12: =IF(J$3<Assumptions!$D$7,Assumptions!$D$13,IF(J$3<Assumptions!$D$6,Assumptions!$D$14,IF(J$3=Assumptions!$D$6,Assumptions!$D$15,Assumptions!$D$16*(1+Assumptions!$D$17)^(J$3-Assumptions!$D$6-1)))) -> 30000 | K12: =IF(K$3<Assumptions!$D$7,Assumptions!$D$13,IF(K$3<Assumptions!$D$6,Assumptions!$D$14,IF(K$3=Assumptions!$D$6,Assumptions!$D$15,Assumptions!$D$16*(1+Assumptions!$D$17)^(K$3-Assumptions!$D$6-1)))) -> 30000 | ... AM12: =IF(AM$3<Assumptions!$D$7,Assumptions!$D$13,IF(AM$3<Assumptions!$D$6,Assumptions!$D$14,IF(AM$3=Assumptions!$D$6,Assumptions!$D$15,Assumptions!$D$16*(1+Assumptions!$D$17)^(AM$3-Assumptions!$D$6-1)))) -> 167341.81
A13: Paid sessions | B13: sessions | C13: =SUM(D13:AM13) -> 1684535.8 | D13: =D12/Assumptions!$D$12 -> 4347.8261 | E13: =E12/Assumptions!$D$12 -> 4347.8261 | F13: =F12/Assumptions!$D$12 -> 4347.8261 | G13: =G12/Assumptions!$D$12 -> 4347.8261 | H13: =H12/Assumptions!$D$12 -> 4347.8261 | I13: =I12/Assumptions!$D$12 -> 13043.478 | J13: =J12/Assumptions!$D$12 -> 13043.478 | K13: =K12/Assumptions!$D$12 -> 13043.478 | ... AM13: =AM12/Assumptions!$D$12 -> 72757.309
A14: Organic + direct sessions | B14: sessions | C14: =SUM(D14:AM14) -> 244168.24 | D14: =MIN(Assumptions!$D$11,Assumptions!$D$9*(1+Assumptions!$D$10)^(D$3-1))*IF(AND(D9=1,Assumptions!$D$74=1),Assumptions!$D$78,1) -> 1500 | E14: =MIN(Assumptions!$D$11,Assumptions!$D$9*(1+Assumptions!$D$10)^(E$3-1))*IF(AND(E9=1,Assumptions!$D$74=1),Assumptions!$D$78,1) -> 1605 | F14: =MIN(Assumptions!$D$11,Assumptions!$D$9*(1+Assumptions!$D$10)^(F$3-1))*IF(AND(F9=1,Assumptions!$D$74=1),Assumptions!$D$78,1) -> 1717.35 | G14: =MIN(Assumptions!$D$11,Assumptions!$D$9*(1+Assumptions!$D$10)^(G$3-1))*IF(AND(G9=1,Assumptions!$D$74=1),Assumptions!$D$78,1) -> 1837.5645 | H14: =MIN(Assumptions!$D$11,Assumptions!$D$9*(1+Assumptions!$D$10)^(H$3-1))*IF(AND(H9=1,Assumptions!$D$74=1),Assumptions!$D$78,1) -> 1966.194 | I14: =MIN(Assumptions!$D$11,Assumptions!$D$9*(1+Assumptions!$D$10)^(I$3-1))*IF(AND(I9=1,Assumptions!$D$74=1),Assumptions!$D$78,1) -> 2103.8276 | J14: =MIN(Assumptions!$D$11,Assumptions!$D$9*(1+Assumptions!$D$10)^(J$3-1))*IF(AND(J9=1,Assumptions!$D$74=1),Assumptions!$D$78,1) -> 2251.0955 | K14: =MIN(Assumptions!$D$11,Assumptions!$D$9*(1+Assumptions!$D$10)^(K$3-1))*IF(AND(K9=1,Assumptions!$D$74=1),Assumptions!$D$78,1) -> 2408.6722 | ... AM14: =MIN(Assumptions!$D$11,Assumptions!$D$9*(1+Assumptions!$D$10)^(AM$3-1))*IF(AND(AM9=1,Assumptions!$D$74=1),Assumptions!$D$78,1) -> 17616.359
A15: Total sessions | B15: sessions | C15: =SUM(D15:AM15) -> 1928704.1 | D15: =D13+D14 -> 5847.8261 | E15: =E13+E14 -> 5952.8261 | F15: =F13+F14 -> 6065.1761 | G15: =G13+G14 -> 6185.3906 | H15: =H13+H14 -> 6314.0201 | I15: =I13+I14 -> 15147.306 | J15: =J13+J14 -> 15294.574 | K15: =K13+K14 -> 15452.15 | ... AM15: =AM13+AM14 -> 90373.669
A16: Prescription-program funnel (clinical decisions are independent; rates are monitored, not targeted)
A17: Eligibility quiz starts | B17: # | C17: =SUM(D17:AM17) -> 170850.49 | D17: =D15*Assumptions!$D$19*IF(D$3<Assumptions!$D$7,0,1) -> 0 | E17: =E15*Assumptions!$D$19*IF(E$3<Assumptions!$D$7,0,1) -> 0 | F17: =F15*Assumptions!$D$19*IF(F$3<Assumptions!$D$7,0,1) -> 0 | G17: =G15*Assumptions!$D$19*IF(G$3<Assumptions!$D$7,0,1) -> 0 | H17: =H15*Assumptions!$D$19*IF(H$3<Assumptions!$D$7,0,1) -> 0 | I17: =I15*Assumptions!$D$19*IF(I$3<Assumptions!$D$7,0,1) -> 1363.2575 | J17: =J15*Assumptions!$D$19*IF(J$3<Assumptions!$D$7,0,1) -> 1376.5116 | K17: =K15*Assumptions!$D$19*IF(K$3<Assumptions!$D$7,0,1) -> 1390.6935 | ... AM17: =AM15*Assumptions!$D$19*IF(AM$3<Assumptions!$D$7,0,1) -> 8133.6302
A18: Quiz completions | B18: # | C18: =SUM(D18:AM18) -> 102510.3 | D18: =D17*Assumptions!$D$20 -> 0 | E18: =E17*Assumptions!$D$20 -> 0 | F18: =F17*Assumptions!$D$20 -> 0 | G18: =G17*Assumptions!$D$20 -> 0 | H18: =H17*Assumptions!$D$20 -> 0 | I18: =I17*Assumptions!$D$20 -> 817.95452 | J18: =J17*Assumptions!$D$20 -> 825.90698 | K18: =K17*Assumptions!$D$20 -> 834.41613 | ... AM18: =AM17*Assumptions!$D$20 -> 4880.1781
A19: Eligible outcomes (screen + state) | B19: # | C19: =SUM(D19:AM19) -> 31223.055 | D19: =D18*Assumptions!$D$21*D10 -> 0 | E19: =E18*Assumptions!$D$21*E10 -> 0 | F19: =F18*Assumptions!$D$21*F10 -> 0 | G19: =G18*Assumptions!$D$21*G10 -> 0 | H19: =H18*Assumptions!$D$21*H10 -> 0 | I19: =I18*Assumptions!$D$21*I10 -> 71.57102 | J19: =J18*Assumptions!$D$21*J10 -> 72.266861 | K19: =K18*Assumptions!$D$21*K10 -> 73.011411 | ... AM19: =AM18*Assumptions!$D$21*AM10 -> 1830.0668
A20: Intakes submitted (consult fee charged) | B20: # | C20: =SUM(D20:AM20) -> 14987.066 | D20: =D19*Assumptions!$D$25 -> 0 | E20: =E19*Assumptions!$D$25 -> 0 | F20: =F19*Assumptions!$D$25 -> 0 | G20: =G19*Assumptions!$D$25 -> 0 | H20: =H19*Assumptions!$D$25 -> 0 | I20: =I19*Assumptions!$D$25 -> 34.35409 | J20: =J19*Assumptions!$D$25 -> 34.688093 | K20: =K19*Assumptions!$D$25 -> 35.045477 | ... AM20: =AM19*Assumptions!$D$25 -> 878.43206
A21: Consults completed | B21: # | C21: =SUM(D21:AM21) -> 11240.3 | D21: =D20*Assumptions!$D$26 -> 0 | E21: =E20*Assumptions!$D$26 -> 0 | F21: =F20*Assumptions!$D$26 -> 0 | G21: =G20*Assumptions!$D$26 -> 0 | H21: =H20*Assumptions!$D$26 -> 0 | I21: =I20*Assumptions!$D$26 -> 25.765567 | J21: =J20*Assumptions!$D$26 -> 26.01607 | K21: =K20*Assumptions!$D$26 -> 26.284108 | ... AM21: =AM20*Assumptions!$D$26 -> 658.82405
A22: Prescriptions issued (clinician decision) | B22: # | C22: =SUM(D22:AM22) -> 6182.1648 | D22: =D21*Assumptions!$D$27 -> 0 | E22: =E21*Assumptions!$D$27 -> 0 | F22: =F21*Assumptions!$D$27 -> 0 | G22: =G21*Assumptions!$D$27 -> 0 | H22: =H21*Assumptions!$D$27 -> 0 | I22: =I21*Assumptions!$D$27 -> 14.171062 | J22: =J21*Assumptions!$D$27 -> 14.308839 | K22: =K21*Assumptions!$D$27 -> 14.456259 | ... AM22: =AM21*Assumptions!$D$27 -> 362.35322
A23: New paying Rx program members | B23: # | C23: =SUM(D23:AM23) -> 3585.6556 | D23: =D22*Assumptions!$D$28 -> 0 | E23: =E22*Assumptions!$D$28 -> 0 | F23: =F22*Assumptions!$D$28 -> 0 | G23: =G22*Assumptions!$D$28 -> 0 | H23: =H22*Assumptions!$D$28 -> 0 | I23: =I22*Assumptions!$D$28 -> 8.219216 | J23: =J22*Assumptions!$D$28 -> 8.2991263 | K23: =K22*Assumptions!$D$28 -> 8.3846304 | ... AM23: =AM22*Assumptions!$D$28 -> 210.16487
A24: Active Rx program members (end of month) | B24: # | D24: =D23 -> 0 | E24: =D24*(1-Assumptions!$D$41)+E23 -> 0 | F24: =E24*(1-Assumptions!$D$41)+F23 -> 0 | G24: =F24*(1-Assumptions!$D$41)+G23 -> 0 | H24: =G24*(1-Assumptions!$D$41)+H23 -> 0 | I24: =H24*(1-Assumptions!$D$41)+I23 -> 8.219216 | J24: =I24*(1-Assumptions!$D$41)+J23 -> 15.449844 | K24: =J24*(1-Assumptions!$D$41)+K23 -> 21.825995 | L24: =K24*(1-Assumptions!$D$41)+L23 -> 116.43379 | ... AM24: =AL24*(1-Assumptions!$D$41)+AM23 -> 1302.8292
A25: Rx members churned | B25: # | C25: =SUM(D25:AM25) -> 2282.8264 | D25: =0 -> 0 | E25: =D24*Assumptions!$D$41 -> 0 | F25: =E24*Assumptions!$D$41 -> 0 | G25: =F24*Assumptions!$D$41 -> 0 | H25: =G24*Assumptions!$D$41 -> 0 | I25: =H24*Assumptions!$D$41 -> 0 | J25: =I24*Assumptions!$D$41 -> 1.0684981 | K25: =J24*Assumptions!$D$41 -> 2.0084797 | L25: =K24*Assumptions!$D$41 -> 2.8373793 | ... AM25: =AL24*Assumptions!$D$41 -> 163.27168
A26: Lab panels ordered | B26: # | C26: =SUM(D26:AM26) -> 5994.8265 | D26: =D20*Assumptions!$D$32 -> 0 | E26: =E20*Assumptions!$D$32 -> 0 | F26: =F20*Assumptions!$D$32 -> 0 | G26: =G20*Assumptions!$D$32 -> 0 | H26: =H20*Assumptions!$D$32 -> 0 | I26: =I20*Assumptions!$D$32 -> 13.741636 | J26: =J20*Assumptions!$D$32 -> 13.875237 | K26: =K20*Assumptions!$D$32 -> 14.018191 | ... AM26: =AM20*Assumptions!$D$32 -> 351.37282
A27: Membership and non-prescription commerce
A28: New membership sign-ups | B28: # | C28: =SUM(D28:AM28) -> 3800.6591 | D28: =(D18-D19)*Assumptions!$D$35+D15*Assumptions!$D$36*IF(D$3<Assumptions!$D$7,0,1) -> 0 | E28: =(E18-E19)*Assumptions!$D$35+E15*Assumptions!$D$36*IF(E$3<Assumptions!$D$7,0,1) -> 0 | F28: =(F18-F19)*Assumptions!$D$35+F15*Assumptions!$D$36*IF(F$3<Assumptions!$D$7,0,1) -> 0 | G28: =(G18-G19)*Assumptions!$D$35+G15*Assumptions!$D$36*IF(G$3<Assumptions!$D$7,0,1) -> 0 | H28: =(H18-H19)*Assumptions!$D$35+H15*Assumptions!$D$36*IF(H$3<Assumptions!$D$7,0,1) -> 0 | I28: =(I18-I19)*Assumptions!$D$35+I15*Assumptions!$D$36*IF(I$3<Assumptions!$D$7,0,1) -> 37.428993 | J28: =(J18-J19)*Assumptions!$D$35+J15*Assumptions!$D$36*IF(J$3<Assumptions!$D$7,0,1) -> 37.792892 | K28: =(K18-K19)*Assumptions!$D$35+K15*Assumptions!$D$36*IF(K$3<Assumptions!$D$7,0,1) -> 38.182264 | ... AM28: =(AM18-AM19)*Assumptions!$D$35+AM15*Assumptions!$D$36*IF(AM$3<Assumptions!$D$7,0,1) -> 167.19129
A29: Active members (end of month) | B29: # | D29: =D28 -> 0 | E29: =D29*(1-Assumptions!$D$42)+E28 -> 0 | F29: =E29*(1-Assumptions!$D$42)+F28 -> 0 | G29: =F29*(1-Assumptions!$D$42)+G28 -> 0 | H29: =G29*(1-Assumptions!$D$42)+H28 -> 0 | I29: =H29*(1-Assumptions!$D$42)+I28 -> 37.428993 | J29: =I29*(1-Assumptions!$D$42)+J28 -> 72.227565 | K29: =J29*(1-Assumptions!$D$42)+K28 -> 104.63162 | L29: =K29*(1-Assumptions!$D$42)+L28 -> 301.16536 | ... AM29: =AL29*(1-Assumptions!$D$42)+AM28 -> 1595.8394
A30: Members churned | B30: # | C30: =SUM(D30:AM30) -> 2204.8196 | D30: =0 -> 0 | E30: =D29*Assumptions!$D$42 -> 0 | F30: =E29*Assumptions!$D$42 -> 0 | G30: =F29*Assumptions!$D$42 -> 0 | H30: =G29*Assumptions!$D$42 -> 0 | I30: =H29*Assumptions!$D$42 -> 0 | J30: =I29*Assumptions!$D$42 -> 2.9943194 | K30: =J29*Assumptions!$D$42 -> 5.7782052 | L30: =K29*Assumptions!$D$42 -> 8.3705299 | ... AM30: =AL29*Assumptions!$D$42 -> 124.23027
A31: Non-Rx first orders | B31: # | C31: =SUM(D31:AM31) -> 11390.033 | D31: =D15*Assumptions!$D$37*IF(D$3<Assumptions!$D$7,0,1) -> 0 | E31: =E15*Assumptions!$D$37*IF(E$3<Assumptions!$D$7,0,1) -> 0 | F31: =F15*Assumptions!$D$37*IF(F$3<Assumptions!$D$7,0,1) -> 0 | G31: =G15*Assumptions!$D$37*IF(G$3<Assumptions!$D$7,0,1) -> 0 | H31: =H15*Assumptions!$D$37*IF(H$3<Assumptions!$D$7,0,1) -> 0 | I31: =I15*Assumptions!$D$37*IF(I$3<Assumptions!$D$7,0,1) -> 90.883835 | J31: =J15*Assumptions!$D$37*IF(J$3<Assumptions!$D$7,0,1) -> 91.767443 | K31: =K15*Assumptions!$D$37*IF(K$3<Assumptions!$D$7,0,1) -> 92.712903 | ... AM31: =AM15*Assumptions!$D$37*IF(AM$3<Assumptions!$D$7,0,1) -> 542.24201
A32: Cumulative non-Rx customers | B32: # | D32: =D31 -> 0 | E32: =D32+E31 -> 0 | F32: =E32+F31 -> 0 | G32: =F32+G31 -> 0 | H32: =G32+H31 -> 0 | I32: =H32+I31 -> 90.883835 | J32: =I32+J31 -> 182.65128 | K32: =J32+K31 -> 275.36418 | L32: =K32+L31 -> 814.11335 | ... AM32: =AL32+AM31 -> 11390.033
A33: Non-Rx repeat orders | B33: # | C33: =SUM(D33:AM33) -> 17245.832 | D33: =0 -> 0 | E33: =D32*Assumptions!$D$39 -> 0 | F33: =E32*Assumptions!$D$39 -> 0 | G33: =F32*Assumptions!$D$39 -> 0 | H33: =G32*Assumptions!$D$39 -> 0 | I33: =H32*Assumptions!$D$39 -> 0 | J33: =I32*Assumptions!$D$39 -> 10.90606 | K33: =J32*Assumptions!$D$39 -> 21.918153 | L33: =K32*Assumptions!$D$39 -> 33.043702 | ... AM33: =AL32*Assumptions!$D$39 -> 1301.7349
A34: Total non-Rx orders | B34: # | C34: =SUM(D34:AM34) -> 28635.865 | D34: =D31+D33 -> 0 | E34: =E31+E33 -> 0 | F34: =F31+F33 -> 0 | G34: =G31+G33 -> 0 | H34: =H31+H33 -> 0 | I34: =I31+I33 -> 90.883835 | J34: =J31+J33 -> 102.6735 | K34: =K31+K33 -> 114.63106 | ... AM34: =AM31+AM33 -> 1843.9769
A35: Revenue
A36: Rx program revenue (all-in monthly) | B36: $ | C36: =SUM(D36:AM36) -> 4696895 | D36: =D24*Assumptions!$D$30 -> 0 | E36: =E24*Assumptions!$D$30 -> 0 | F36: =F24*Assumptions!$D$30 -> 0 | G36: =G24*Assumptions!$D$30 -> 0 | H36: =H24*Assumptions!$D$30 -> 0 | I36: =I24*Assumptions!$D$30 -> 2046.5848 | J36: =J24*Assumptions!$D$30 -> 3847.0112 | K36: =K24*Assumptions!$D$30 -> 5434.6727 | ... AM36: =AM24*Assumptions!$D$30 -> 324404.47
A37: Consultation revenue | B37: $ | C37: =SUM(D37:AM37) -> 734366.24 | D37: =D20*Assumptions!$D$31 -> 0 | E37: =E20*Assumptions!$D$31 -> 0 | F37: =F20*Assumptions!$D$31 -> 0 | G37: =G20*Assumptions!$D$31 -> 0 | H37: =H20*Assumptions!$D$31 -> 0 | I37: =I20*Assumptions!$D$31 -> 1683.3504 | J37: =J20*Assumptions!$D$31 -> 1699.7166 | K37: =K20*Assumptions!$D$31 -> 1717.2284 | ... AM37: =AM20*Assumptions!$D$31 -> 43043.171
A38: Lab revenue | B38: $ | C38: =SUM(D38:AM38) -> 593487.82 | D38: =D26*Assumptions!$D$33 -> 0 | E38: =E26*Assumptions!$D$33 -> 0 | F38: =F26*Assumptions!$D$33 -> 0 | G38: =G26*Assumptions!$D$33 -> 0 | H38: =H26*Assumptions!$D$33 -> 0 | I38: =I26*Assumptions!$D$33 -> 1360.422 | J38: =J26*Assumptions!$D$33 -> 1373.6485 | K38: =K26*Assumptions!$D$33 -> 1387.8009 | ... AM38: =AM26*Assumptions!$D$33 -> 34785.91
A39: Membership revenue | B39: $ | C39: =SUM(D39:AM39) -> 553965.61 | D39: =D29*Assumptions!$D$34 -> 0 | E39: =E29*Assumptions!$D$34 -> 0 | F39: =F29*Assumptions!$D$34 -> 0 | G39: =G29*Assumptions!$D$34 -> 0 | H39: =H29*Assumptions!$D$34 -> 0 | I39: =I29*Assumptions!$D$34 -> 711.15086 | J39: =J29*Assumptions!$D$34 -> 1372.3237 | K39: =K29*Assumptions!$D$34 -> 1988.0009 | ... AM39: =AM29*Assumptions!$D$34 -> 30320.949
A40: Non-Rx commerce revenue | B40: $ | C40: =SUM(D40:AM40) -> 1861331.2 | D40: =D34*Assumptions!$D$38 -> 0 | E40: =E34*Assumptions!$D$38 -> 0 | F40: =F34*Assumptions!$D$38 -> 0 | G40: =G34*Assumptions!$D$38 -> 0 | H40: =H34*Assumptions!$D$38 -> 0 | I40: =I34*Assumptions!$D$38 -> 5907.4493 | J40: =J34*Assumptions!$D$38 -> 6673.7777 | K40: =K34*Assumptions!$D$38 -> 7451.0187 | ... AM40: =AM34*Assumptions!$D$38 -> 119858.5
A41: Gross revenue | B41: $ | C41: =SUM(D41:AM41) -> 8440045.9 | D41: =D36+D37+D38+D39+D40 -> 0 | E41: =E36+E37+E38+E39+E40 -> 0 | F41: =F36+F37+F38+F39+F40 -> 0 | G41: =G36+G37+G38+G39+G40 -> 0 | H41: =H36+H37+H38+H39+H40 -> 0 | I41: =I36+I37+I38+I39+I40 -> 11708.957 | J41: =J36+J37+J38+J39+J40 -> 14966.478 | K41: =K36+K37+K38+K39+K40 -> 17978.722 | ... AM41: =AM36+AM37+AM38+AM39+AM40 -> 552413
A42: Refunds & chargebacks | B42: $ | C42: =SUM(D42:AM42) -> -422002.3 | D42: =-D41*Assumptions!$D$50 -> 0 | E42: =-E41*Assumptions!$D$50 -> 0 | F42: =-F41*Assumptions!$D$50 -> 0 | G42: =-G41*Assumptions!$D$50 -> 0 | H42: =-H41*Assumptions!$D$50 -> 0 | I42: =-I41*Assumptions!$D$50 -> -585.44786 | J42: =-J41*Assumptions!$D$50 -> -748.32389 | K42: =-K41*Assumptions!$D$50 -> -898.93608 | ... AM42: =-AM41*Assumptions!$D$50 -> -27620.65
A43: Net revenue | B43: $ | C43: =SUM(D43:AM43) -> 8018043.6 | D43: =D41+D42 -> 0 | E43: =E41+E42 -> 0 | F43: =F41+F42 -> 0 | G43: =G41+G42 -> 0 | H43: =H41+H42 -> 0 | I43: =I41+I42 -> 11123.509 | J43: =J41+J42 -> 14218.154 | K43: =K41+K42 -> 17079.785 | ... AM43: =AM41+AM42 -> 524792.35
A44: Cost of revenue
A45: Pharmacy / medication | B45: $ | C45: =SUM(D45:AM45) -> -2074933.6 | D45: =-D24*Assumptions!$D$44 -> 0 | E45: =-E24*Assumptions!$D$44 -> 0 | F45: =-F24*Assumptions!$D$44 -> 0 | G45: =-G24*Assumptions!$D$44 -> 0 | H45: =-H24*Assumptions!$D$44 -> 0 | I45: =-I24*Assumptions!$D$44 -> -904.11376 | J45: =-J24*Assumptions!$D$44 -> -1699.4829 | K45: =-K24*Assumptions!$D$44 -> -2400.8594 | ... AM45: =-AM24*Assumptions!$D$44 -> -143311.21
A46: Clinical (consults + monitoring) | B46: $ | C46: =SUM(D46:AM46) -> -694443.81 | D46: =-(D21*Assumptions!$D$45+D24*Assumptions!$D$46) -> 0 | E46: =-(E21*Assumptions!$D$45+E24*Assumptions!$D$46) -> 0 | F46: =-(F21*Assumptions!$D$45+F24*Assumptions!$D$46) -> 0 | G46: =-(G21*Assumptions!$D$45+G24*Assumptions!$D$46) -> 0 | H46: =-(H21*Assumptions!$D$45+H24*Assumptions!$D$46) -> 0 | I46: =-(I21*Assumptions!$D$45+I24*Assumptions!$D$46) -> -1241.6427 | J46: =-(J21*Assumptions!$D$45+J24*Assumptions!$D$46) -> -1325.2216 | K46: =-(K21*Assumptions!$D$45+K24*Assumptions!$D$46) -> -1401.0448 | ... AM46: =-(AM21*Assumptions!$D$45+AM24*Assumptions!$D$46) -> -42675.374
A47: Lab costs | B47: $ | C47: =SUM(D47:AM47) -> -509560.25 | D47: =-D26*Assumptions!$D$48 -> 0 | E47: =-E26*Assumptions!$D$48 -> 0 | F47: =-F26*Assumptions!$D$48 -> 0 | G47: =-G26*Assumptions!$D$48 -> 0 | H47: =-H26*Assumptions!$D$48 -> 0 | I47: =-I26*Assumptions!$D$48 -> -1168.039 | J47: =-J26*Assumptions!$D$48 -> -1179.3952 | K47: =-K26*Assumptions!$D$48 -> -1191.5462 | ... AM47: =-AM26*Assumptions!$D$48 -> -29866.69
A48: Rx fulfillment & shipping | B48: $ | C48: =SUM(D48:AM48) -> -339534.58 | D48: =-D24*Assumptions!$D$47 -> 0 | E48: =-E24*Assumptions!$D$47 -> 0 | F48: =-F24*Assumptions!$D$47 -> 0 | G48: =-G24*Assumptions!$D$47 -> 0 | H48: =-H24*Assumptions!$D$47 -> 0 | I48: =-I24*Assumptions!$D$47 -> -147.94589 | J48: =-J24*Assumptions!$D$47 -> -278.0972 | K48: =-K24*Assumptions!$D$47 -> -392.86791 | ... AM48: =-AM24*Assumptions!$D$47 -> -23450.925
A49: Non-Rx COGS + fulfillment | B49: $ | C49: =SUM(D49:AM49) -> -1002255.3 | D49: =-(D40*Assumptions!$D$52+D34*Assumptions!$D$53) -> 0 | E49: =-(E40*Assumptions!$D$52+E34*Assumptions!$D$53) -> 0 | F49: =-(F40*Assumptions!$D$52+F34*Assumptions!$D$53) -> 0 | G49: =-(G40*Assumptions!$D$52+G34*Assumptions!$D$53) -> 0 | H49: =-(H40*Assumptions!$D$52+H34*Assumptions!$D$53) -> 0 | I49: =-(I40*Assumptions!$D$52+I34*Assumptions!$D$53) -> -3180.9342 | J49: =-(J40*Assumptions!$D$52+J34*Assumptions!$D$53) -> -3593.5726 | K49: =-(K40*Assumptions!$D$52+K34*Assumptions!$D$53) -> -4012.087 | ... AM49: =-(AM40*Assumptions!$D$52+AM34*Assumptions!$D$53) -> -64539.192
A50: Membership delivery | B50: $ | C50: =SUM(D50:AM50) -> -87468.254 | D50: =-D29*Assumptions!$D$54 -> 0 | E50: =-E29*Assumptions!$D$54 -> 0 | F50: =-F29*Assumptions!$D$54 -> 0 | G50: =-G29*Assumptions!$D$54 -> 0 | H50: =-H29*Assumptions!$D$54 -> 0 | I50: =-I29*Assumptions!$D$54 -> -112.28698 | J50: =-J29*Assumptions!$D$54 -> -216.6827 | K50: =-K29*Assumptions!$D$54 -> -313.89487 | ... AM50: =-AM29*Assumptions!$D$54 -> -4787.5183
A51: Payment processing | B51: $ | C51: =SUM(D51:AM51) -> -270081.47 | D51: =-D41*Assumptions!$D$49 -> 0 | E51: =-E41*Assumptions!$D$49 -> 0 | F51: =-F41*Assumptions!$D$49 -> 0 | G51: =-G41*Assumptions!$D$49 -> 0 | H51: =-H41*Assumptions!$D$49 -> 0 | I51: =-I41*Assumptions!$D$49 -> -374.68663 | J51: =-J41*Assumptions!$D$49 -> -478.92729 | K51: =-K41*Assumptions!$D$49 -> -575.31909 | ... AM51: =-AM41*Assumptions!$D$49 -> -17677.216
A52: Customer support (variable) | B52: $ | C52: =SUM(D52:AM52) -> -288114.7 | D52: =-(D24+D29)*Assumptions!$D$51 -> 0 | E52: =-(E24+E29)*Assumptions!$D$51 -> 0 | F52: =-(F24+F29)*Assumptions!$D$51 -> 0 | G52: =-(G24+G29)*Assumptions!$D$51 -> 0 | H52: =-(H24+H29)*Assumptions!$D$51 -> 0 | I52: =-(I24+I29)*Assumptions!$D$51 -> -273.88925 | J52: =-(J24+J29)*Assumptions!$D$51 -> -526.06446 | K52: =-(K24+K29)*Assumptions!$D$51 -> -758.74571 | ... AM52: =-(AM24+AM29)*Assumptions!$D$51 -> -17392.012
A53: Total cost of revenue | B53: $ | C53: =SUM(D53:AM53) -> -5266391.9 | D53: =SUM(D45:D52) -> 0 | E53: =SUM(E45:E52) -> 0 | F53: =SUM(F45:F52) -> 0 | G53: =SUM(G45:G52) -> 0 | H53: =SUM(H45:H52) -> 0 | I53: =SUM(I45:I52) -> -7403.5385 | J53: =SUM(J45:J52) -> -9297.4439 | K53: =SUM(K45:K52) -> -11046.365 | ... AM53: =SUM(AM45:AM52) -> -343700.14
A54: Gross profit | B54: $ | C54: =SUM(D54:AM54) -> 2751651.8 | D54: =D43+D53 -> 0 | E54: =E43+E53 -> 0 | F54: =F43+F53 -> 0 | G54: =G43+G53 -> 0 | H54: =H43+H53 -> 0 | I54: =I43+I53 -> 3719.9709 | J54: =J43+J53 -> 4920.71 | K54: =K43+K53 -> 6033.4204 | ... AM54: =AM43+AM53 -> 181092.21
A55: Gross margin % | B55: % | D55: =IF(D43=0,0,D54/D43) -> 0 | E55: =IF(E43=0,0,E54/E43) -> 0 | F55: =IF(F43=0,0,F54/F43) -> 0 | G55: =IF(G43=0,0,G54/G43) -> 0 | H55: =IF(H43=0,0,H54/H43) -> 0 | I55: =IF(I43=0,0,I54/I43) -> 0.33442422 | J55: =IF(J43=0,0,J54/J43) -> 0.34608642 | K55: =IF(K43=0,0,K54/K43) -> 0.35324919 | ... AM55: =IF(AM43=0,0,AM54/AM43) -> 0.34507403
A56: Acquisition and contribution
A57: Paid media | B57: $ | C57: =SUM(D57:AM57) -> -3874432.4 | D57: =-D12 -> -10000 | E57: =-E12 -> -10000 | F57: =-F12 -> -10000 | G57: =-G12 -> -10000 | H57: =-H12 -> -10000 | I57: =-I12 -> -30000 | J57: =-J12 -> -30000 | K57: =-K12 -> -30000 | ... AM57: =-AM12 -> -167341.81
A58: Influencer & affiliate | B58: $ | C58: =SUM(D58:AM58) -> -590000 | D58: =-IF(D$3<Assumptions!$D$7,0,IF(D$3<Assumptions!$D$6,Assumptions!$D$71,Assumptions!$D$72)) -> 0 | E58: =-IF(E$3<Assumptions!$D$7,0,IF(E$3<Assumptions!$D$6,Assumptions!$D$71,Assumptions!$D$72)) -> 0 | F58: =-IF(F$3<Assumptions!$D$7,0,IF(F$3<Assumptions!$D$6,Assumptions!$D$71,Assumptions!$D$72)) -> 0 | G58: =-IF(G$3<Assumptions!$D$7,0,IF(G$3<Assumptions!$D$6,Assumptions!$D$71,Assumptions!$D$72)) -> 0 | H58: =-IF(H$3<Assumptions!$D$7,0,IF(H$3<Assumptions!$D$6,Assumptions!$D$71,Assumptions!$D$72)) -> 0 | I58: =-IF(I$3<Assumptions!$D$7,0,IF(I$3<Assumptions!$D$6,Assumptions!$D$71,Assumptions!$D$72)) -> -10000 | J58: =-IF(J$3<Assumptions!$D$7,0,IF(J$3<Assumptions!$D$6,Assumptions!$D$71,Assumptions!$D$72)) -> -10000 | K58: =-IF(K$3<Assumptions!$D$7,0,IF(K$3<Assumptions!$D$6,Assumptions!$D$71,Assumptions!$D$72)) -> -10000 | ... AM58: =-IF(AM$3<Assumptions!$D$7,0,IF(AM$3<Assumptions!$D$6,Assumptions!$D$71,Assumptions!$D$72)) -> -20000
A59: Launch PR/events (one-time) | B59: $ | C59: =SUM(D59:AM59) -> -60000 | D59: =-D8*Assumptions!$D$70 -> 0 | E59: =-E8*Assumptions!$D$70 -> 0 | F59: =-F8*Assumptions!$D$70 -> 0 | G59: =-G8*Assumptions!$D$70 -> 0 | H59: =-H8*Assumptions!$D$70 -> 0 | I59: =-I8*Assumptions!$D$70 -> 0 | J59: =-J8*Assumptions!$D$70 -> 0 | K59: =-K8*Assumptions!$D$70 -> 0 | ... AM59: =-AM8*Assumptions!$D$70 -> 0
A60: Brand partner cash retainer (Scenario A only) | B60: $ | C60: =SUM(D60:AM60) -> -775000 | D60: =-Assumptions!$D$74*IF(D$3<Assumptions!$D$7,0,Assumptions!$D$75) -> 0 | E60: =-Assumptions!$D$74*IF(E$3<Assumptions!$D$7,0,Assumptions!$D$75) -> 0 | F60: =-Assumptions!$D$74*IF(F$3<Assumptions!$D$7,0,Assumptions!$D$75) -> 0 | G60: =-Assumptions!$D$74*IF(G$3<Assumptions!$D$7,0,Assumptions!$D$75) -> 0 | H60: =-Assumptions!$D$74*IF(H$3<Assumptions!$D$7,0,Assumptions!$D$75) -> 0 | I60: =-Assumptions!$D$74*IF(I$3<Assumptions!$D$7,0,Assumptions!$D$75) -> -25000 | J60: =-Assumptions!$D$74*IF(J$3<Assumptions!$D$7,0,Assumptions!$D$75) -> -25000 | K60: =-Assumptions!$D$74*IF(K$3<Assumptions!$D$7,0,Assumptions!$D$75) -> -25000 | ... AM60: =-Assumptions!$D$74*IF(AM$3<Assumptions!$D$7,0,Assumptions!$D$75) -> -25000
A61: Brand partner royalty (Scenario A only) | B61: $ | C61: =SUM(D61:AM61) -> -240541.31 | D61: =-Assumptions!$D$74*D43*Assumptions!$D$76 -> 0 | E61: =-Assumptions!$D$74*E43*Assumptions!$D$76 -> 0 | F61: =-Assumptions!$D$74*F43*Assumptions!$D$76 -> 0 | G61: =-Assumptions!$D$74*G43*Assumptions!$D$76 -> 0 | H61: =-Assumptions!$D$74*H43*Assumptions!$D$76 -> 0 | I61: =-Assumptions!$D$74*I43*Assumptions!$D$76 -> -333.70528 | J61: =-Assumptions!$D$74*J43*Assumptions!$D$76 -> -426.54461 | K61: =-Assumptions!$D$74*K43*Assumptions!$D$76 -> -512.39356 | ... AM61: =-Assumptions!$D$74*AM43*Assumptions!$D$76 -> -15743.77
A62: Total acquisition & partner cost | B62: $ | C62: =SUM(D62:AM62) -> -5539973.7 | D62: =SUM(D57:D61) -> -10000 | E62: =SUM(E57:E61) -> -10000 | F62: =SUM(F57:F61) -> -10000 | G62: =SUM(G57:G61) -> -10000 | H62: =SUM(H57:H61) -> -10000 | I62: =SUM(I57:I61) -> -65333.705 | J62: =SUM(J57:J61) -> -65426.545 | K62: =SUM(K57:K61) -> -65512.394 | ... AM62: =SUM(AM57:AM61) -> -228085.58
A63: Contribution margin | B63: $ | C63: =SUM(D63:AM63) -> -2788321.9 | D63: =D54+D62 -> -10000 | E63: =E54+E62 -> -10000 | F63: =F54+F62 -> -10000 | G63: =G54+G62 -> -10000 | H63: =H54+H62 -> -10000 | I63: =I54+I62 -> -61613.734 | J63: =J54+J62 -> -60505.835 | K63: =K54+K62 -> -59478.973 | ... AM63: =AM54+AM62 -> -46993.373
A64: New paying customers (Rx + members + first shop orders) | B64: # | C64: =SUM(D64:AM64) -> 18776.348 | D64: =D23+D28+D31 -> 0 | E64: =E23+E28+E31 -> 0 | F64: =F23+F28+F31 -> 0 | G64: =G23+G28+G31 -> 0 | H64: =H23+H28+H31 -> 0 | I64: =I23+I28+I31 -> 136.53204 | J64: =J23+J28+J31 -> 137.85946 | K64: =K23+K28+K31 -> 139.2798 | ... AM64: =AM23+AM28+AM31 -> 919.59817
A65: Blended CAC (acquisition cost / new paying customers) | B65: $ | D65: =IF(D64=0,0,-(D57+D58+D59)/D64) -> 0 | E65: =IF(E64=0,0,-(E57+E58+E59)/E64) -> 0 | F65: =IF(F64=0,0,-(F57+F58+F59)/F64) -> 0 | G65: =IF(G64=0,0,-(G57+G58+G59)/G64) -> 0 | H65: =IF(H64=0,0,-(H57+H58+H59)/H64) -> 0 | I65: =IF(I64=0,0,-(I57+I58+I59)/I64) -> 292.97152 | J65: =IF(J64=0,0,-(J57+J58+J59)/J64) -> 290.15056 | K65: =IF(K64=0,0,-(K57+K58+K59)/K64) -> 287.19169 | ... AM65: =IF(AM64=0,0,-(AM57+AM58+AM59)/AM64) -> 203.72138
A66: CAC per new Rx member (all acquisition cost allocated to Rx) | B66: $ | D66: =IF(D23=0,0,-(D57+D58+D59)/D23) -> 0 | E66: =IF(E23=0,0,-(E57+E58+E59)/E23) -> 0 | F66: =IF(F23=0,0,-(F57+F58+F59)/F23) -> 0 | G66: =IF(G23=0,0,-(G57+G58+G59)/G23) -> 0 | H66: =IF(H23=0,0,-(H57+H58+H59)/H23) -> 0 | I66: =IF(I23=0,0,-(I57+I58+I59)/I23) -> 4866.6442 | J66: =IF(J23=0,0,-(J57+J58+J59)/J23) -> 4819.7844 | K66: =IF(K23=0,0,-(K57+K58+K59)/K23) -> 4770.6336 | ... AM66: =IF(AM23=0,0,-(AM57+AM58+AM59)/AM23) -> 891.40402
A67: Operating expenses
A68: Team (fully loaded) | B68: $ | C68: =SUM(D68:AM68) -> -5345000 | D68: =-IF(D$3<=3,Assumptions!$D$56,IF(D$3<Assumptions!$D$6,Assumptions!$D$57,IF(D$3<=12,Assumptions!$D$58,IF(D$3<=24,Assumptions!$D$59,Assumptions!$D$60)))) -> -45000 | E68: =-IF(E$3<=3,Assumptions!$D$56,IF(E$3<Assumptions!$D$6,Assumptions!$D$57,IF(E$3<=12,Assumptions!$D$58,IF(E$3<=24,Assumptions!$D$59,Assumptions!$D$60)))) -> -45000 | F68: =-IF(F$3<=3,Assumptions!$D$56,IF(F$3<Assumptions!$D$6,Assumptions!$D$57,IF(F$3<=12,Assumptions!$D$58,IF(F$3<=24,Assumptions!$D$59,Assumptions!$D$60)))) -> -45000 | G68: =-IF(G$3<=3,Assumptions!$D$56,IF(G$3<Assumptions!$D$6,Assumptions!$D$57,IF(G$3<=12,Assumptions!$D$58,IF(G$3<=24,Assumptions!$D$59,Assumptions!$D$60)))) -> -90000 | H68: =-IF(H$3<=3,Assumptions!$D$56,IF(H$3<Assumptions!$D$6,Assumptions!$D$57,IF(H$3<=12,Assumptions!$D$58,IF(H$3<=24,Assumptions!$D$59,Assumptions!$D$60)))) -> -90000 | I68: =-IF(I$3<=3,Assumptions!$D$56,IF(I$3<Assumptions!$D$6,Assumptions!$D$57,IF(I$3<=12,Assumptions!$D$58,IF(I$3<=24,Assumptions!$D$59,Assumptions!$D$60)))) -> -90000 | J68: =-IF(J$3<=3,Assumptions!$D$56,IF(J$3<Assumptions!$D$6,Assumptions!$D$57,IF(J$3<=12,Assumptions!$D$58,IF(J$3<=24,Assumptions!$D$59,Assumptions!$D$60)))) -> -90000 | K68: =-IF(K$3<=3,Assumptions!$D$56,IF(K$3<Assumptions!$D$6,Assumptions!$D$57,IF(K$3<=12,Assumptions!$D$58,IF(K$3<=24,Assumptions!$D$59,Assumptions!$D$60)))) -> -90000 | ... AM68: =-IF(AM$3<=3,Assumptions!$D$56,IF(AM$3<Assumptions!$D$6,Assumptions!$D$57,IF(AM$3<=12,Assumptions!$D$58,IF(AM$3<=24,Assumptions!$D$59,Assumptions!$D$60)))) -> -190000
A69: Medical leadership & governance | B69: $ | C69: =SUM(D69:AM69) -> -540000 | D69: =-Assumptions!$D$61 -> -15000 | E69: =-Assumptions!$D$61 -> -15000 | F69: =-Assumptions!$D$61 -> -15000 | G69: =-Assumptions!$D$61 -> -15000 | H69: =-Assumptions!$D$61 -> -15000 | I69: =-Assumptions!$D$61 -> -15000 | J69: =-Assumptions!$D$61 -> -15000 | K69: =-Assumptions!$D$61 -> -15000 | ... AM69: =-Assumptions!$D$61 -> -15000
A70: Technology & software | B70: $ | C70: =SUM(D70:AM70) -> -624000 | D70: =-IF(D9=1,Assumptions!$D$63,Assumptions!$D$62) -> -8000 | E70: =-IF(E9=1,Assumptions!$D$63,Assumptions!$D$62) -> -8000 | F70: =-IF(F9=1,Assumptions!$D$63,Assumptions!$D$62) -> -8000 | G70: =-IF(G9=1,Assumptions!$D$63,Assumptions!$D$62) -> -8000 | H70: =-IF(H9=1,Assumptions!$D$63,Assumptions!$D$62) -> -8000 | I70: =-IF(I9=1,Assumptions!$D$63,Assumptions!$D$62) -> -8000 | J70: =-IF(J9=1,Assumptions!$D$63,Assumptions!$D$62) -> -8000 | K70: =-IF(K9=1,Assumptions!$D$63,Assumptions!$D$62) -> -8000 | ... AM70: =-IF(AM9=1,Assumptions!$D$63,Assumptions!$D$62) -> -20000
A71: Site & portal build (one-time) | B71: $ | C71: =SUM(D71:AM71) -> -160000 | D71: =-IF(D$3<=4,Assumptions!$D$64,0) -> -40000 | E71: =-IF(E$3<=4,Assumptions!$D$64,0) -> -40000 | F71: =-IF(F$3<=4,Assumptions!$D$64,0) -> -40000 | G71: =-IF(G$3<=4,Assumptions!$D$64,0) -> -40000 | H71: =-IF(H$3<=4,Assumptions!$D$64,0) -> 0 | I71: =-IF(I$3<=4,Assumptions!$D$64,0) -> 0 | J71: =-IF(J$3<=4,Assumptions!$D$64,0) -> 0 | K71: =-IF(K$3<=4,Assumptions!$D$64,0) -> 0 | ... AM71: =-IF(AM$3<=4,Assumptions!$D$64,0) -> 0
A72: Legal, regulatory & compliance | B72: $ | C72: =SUM(D72:AM72) -> -615000 | D72: =-IF(D$3<=3,Assumptions!$D$65,Assumptions!$D$66) -> -40000 | E72: =-IF(E$3<=3,Assumptions!$D$65,Assumptions!$D$66) -> -40000 | F72: =-IF(F$3<=3,Assumptions!$D$65,Assumptions!$D$66) -> -40000 | G72: =-IF(G$3<=3,Assumptions!$D$65,Assumptions!$D$66) -> -15000 | H72: =-IF(H$3<=3,Assumptions!$D$65,Assumptions!$D$66) -> -15000 | I72: =-IF(I$3<=3,Assumptions!$D$65,Assumptions!$D$66) -> -15000 | J72: =-IF(J$3<=3,Assumptions!$D$65,Assumptions!$D$66) -> -15000 | K72: =-IF(K$3<=3,Assumptions!$D$65,Assumptions!$D$66) -> -15000 | ... AM72: =-IF(AM$3<=3,Assumptions!$D$65,Assumptions!$D$66) -> -15000
A73: Insurance | B73: $ | C73: =SUM(D73:AM73) -> -168000 | D73: =-IF(D9=1,Assumptions!$D$67,0) -> 0 | E73: =-IF(E9=1,Assumptions!$D$67,0) -> 0 | F73: =-IF(F9=1,Assumptions!$D$67,0) -> 0 | G73: =-IF(G9=1,Assumptions!$D$67,0) -> 0 | H73: =-IF(H9=1,Assumptions!$D$67,0) -> 0 | I73: =-IF(I9=1,Assumptions!$D$67,0) -> 0 | J73: =-IF(J9=1,Assumptions!$D$67,0) -> 0 | K73: =-IF(K9=1,Assumptions!$D$67,0) -> 0 | ... AM73: =-IF(AM9=1,Assumptions!$D$67,0) -> -6000
A74: Creative & content production | B74: $ | C74: =SUM(D74:AM74) -> -820000 | D74: =-IF(D9=1,Assumptions!$D$69,Assumptions!$D$68) -> -15000 | E74: =-IF(E9=1,Assumptions!$D$69,Assumptions!$D$68) -> -15000 | F74: =-IF(F9=1,Assumptions!$D$69,Assumptions!$D$68) -> -15000 | G74: =-IF(G9=1,Assumptions!$D$69,Assumptions!$D$68) -> -15000 | H74: =-IF(H9=1,Assumptions!$D$69,Assumptions!$D$68) -> -15000 | I74: =-IF(I9=1,Assumptions!$D$69,Assumptions!$D$68) -> -15000 | J74: =-IF(J9=1,Assumptions!$D$69,Assumptions!$D$68) -> -15000 | K74: =-IF(K9=1,Assumptions!$D$69,Assumptions!$D$68) -> -15000 | ... AM74: =-IF(AM9=1,Assumptions!$D$69,Assumptions!$D$68) -> -25000
A75: Total operating expenses | B75: $ | C75: =SUM(D75:AM75) -> -8272000 | D75: =SUM(D68:D74) -> -163000 | E75: =SUM(E68:E74) -> -163000 | F75: =SUM(F68:F74) -> -163000 | G75: =SUM(G68:G74) -> -183000 | H75: =SUM(H68:H74) -> -143000 | I75: =SUM(I68:I74) -> -143000 | J75: =SUM(J68:J74) -> -143000 | K75: =SUM(K68:K74) -> -143000 | ... AM75: =SUM(AM68:AM74) -> -271000
A76: Profitability and cash
A77: EBITDA / operating profit (loss) | B77: $ | C77: =SUM(D77:AM77) -> -11060322 | D77: =D63+D75 -> -173000 | E77: =E63+E75 -> -173000 | F77: =F63+F75 -> -173000 | G77: =G63+G75 -> -193000 | H77: =H63+H75 -> -153000 | I77: =I63+I75 -> -204613.73 | J77: =J63+J75 -> -203505.83 | K77: =K63+K75 -> -202478.97 | ... AM77: =AM63+AM75 -> -317993.37
A78: Working capital investment (non-Rx inventory) | B78: $ | C78: =SUM(D78:AM78) -> -129078.38 | D78: =-Assumptions!$D$80*ABS(D49) -> 0 | E78: =-Assumptions!$D$80*(ABS(E49)-ABS(D49)) -> 0 | F78: =-Assumptions!$D$80*(ABS(F49)-ABS(E49)) -> 0 | G78: =-Assumptions!$D$80*(ABS(G49)-ABS(F49)) -> 0 | H78: =-Assumptions!$D$80*(ABS(H49)-ABS(G49)) -> 0 | I78: =-Assumptions!$D$80*(ABS(I49)-ABS(H49)) -> -6361.8685 | J78: =-Assumptions!$D$80*(ABS(J49)-ABS(I49)) -> -825.27675 | K78: =-Assumptions!$D$80*(ABS(K49)-ABS(J49)) -> -837.02873 | L78: =-Assumptions!$D$80*(ABS(L49)-ABS(K49)) -> -32001.327 | ... AM78: =-Assumptions!$D$80*(ABS(AM49)-ABS(AL49)) -> -5508.0631
A79: Net cash flow | B79: $ | C79: =SUM(D79:AM79) -> -11189400 | D79: =D77+D78 -> -173000 | E79: =E77+E78 -> -173000 | F79: =F77+F78 -> -173000 | G79: =G77+G78 -> -193000 | H79: =H77+H78 -> -153000 | I79: =I77+I78 -> -210975.6 | J79: =J77+J78 -> -204331.11 | K79: =K77+K78 -> -203316 | ... AM79: =AM77+AM78 -> -323501.44
A80: Cumulative cash flow | B80: $ | D80: =D79 -> -173000 | E80: =D80+E79 -> -346000 | F80: =E80+F79 -> -519000 | G80: =F80+G79 -> -712000 | H80: =G80+H79 -> -865000 | I80: =H80+I79 -> -1075975.6 | J80: =I80+J79 -> -1280306.7 | K80: =J80+K79 -> -1483622.7 | L80: =K80+L79 -> -2012671.3 | ... AM80: =AL80+AM79 -> -11189400
A81: Cash balance (opening cash + cumulative) | B81: $ | D81: =Assumptions!$D$81+D80 -> -173000 | E81: =Assumptions!$D$81+E80 -> -346000 | F81: =Assumptions!$D$81+F80 -> -519000 | G81: =Assumptions!$D$81+G80 -> -712000 | H81: =Assumptions!$D$81+H80 -> -865000 | I81: =Assumptions!$D$81+I80 -> -1075975.6 | J81: =Assumptions!$D$81+J80 -> -1280306.7 | K81: =Assumptions!$D$81+K80 -> -1483622.7 | ... AM81: =Assumptions!$D$81+AM80 -> -11189400
A82: Break-even helper (month # if EBITDA > 0, else 999) | B82: # | D82: =IF(D77>0,D$3,999) -> 999 | E82: =IF(E77>0,E$3,999) -> 999 | F82: =IF(F77>0,F$3,999) -> 999 | G82: =IF(G77>0,G$3,999) -> 999 | H82: =IF(H77>0,H$3,999) -> 999 | I82: =IF(I77>0,I$3,999) -> 999 | J82: =IF(J77>0,J$3,999) -> 999 | K82: =IF(K77>0,K$3,999) -> 999 | ... AM82: =IF(AM77>0,AM$3,999) -> 999
A83: Unit economics (steady-state view, per active Rx member)
A84: Revenue per active Rx member-month | B84: $ | D84: =IF(D24=0,0,(D36)/D24) -> 0 | E84: =IF(E24=0,0,(E36)/E24) -> 0 | F84: =IF(F24=0,0,(F36)/F24) -> 0 | G84: =IF(G24=0,0,(G36)/G24) -> 0 | H84: =IF(H24=0,0,(H36)/H24) -> 0 | I84: =IF(I24=0,0,(I36)/I24) -> 249 | J84: =IF(J24=0,0,(J36)/J24) -> 249 | K84: =IF(K24=0,0,(K36)/K24) -> 249 | ... AM84: =IF(AM24=0,0,(AM36)/AM24) -> 249
A85: Contribution per Rx member-month before acquisition | B85: $ | D85: =Assumptions!$D$30*(1-Assumptions!$D$50-Assumptions!$D$49)-Assumptions!$D$44-Assumptions!$D$46-Assumptions!$D$47-Assumptions!$D$51 -> 84.582 | E85: =Assumptions!$D$30*(1-Assumptions!$D$50-Assumptions!$D$49)-Assumptions!$D$44-Assumptions!$D$46-Assumptions!$D$47-Assumptions!$D$51 -> 84.582 | F85: =Assumptions!$D$30*(1-Assumptions!$D$50-Assumptions!$D$49)-Assumptions!$D$44-Assumptions!$D$46-Assumptions!$D$47-Assumptions!$D$51 -> 84.582 | G85: =Assumptions!$D$30*(1-Assumptions!$D$50-Assumptions!$D$49)-Assumptions!$D$44-Assumptions!$D$46-Assumptions!$D$47-Assumptions!$D$51 -> 84.582 | H85: =Assumptions!$D$30*(1-Assumptions!$D$50-Assumptions!$D$49)-Assumptions!$D$44-Assumptions!$D$46-Assumptions!$D$47-Assumptions!$D$51 -> 84.582 | I85: =Assumptions!$D$30*(1-Assumptions!$D$50-Assumptions!$D$49)-Assumptions!$D$44-Assumptions!$D$46-Assumptions!$D$47-Assumptions!$D$51 -> 84.582 | J85: =Assumptions!$D$30*(1-Assumptions!$D$50-Assumptions!$D$49)-Assumptions!$D$44-Assumptions!$D$46-Assumptions!$D$47-Assumptions!$D$51 -> 84.582 | K85: =Assumptions!$D$30*(1-Assumptions!$D$50-Assumptions!$D$49)-Assumptions!$D$44-Assumptions!$D$46-Assumptions!$D$47-Assumptions!$D$51 -> 84.582 | ... AM85: =Assumptions!$D$30*(1-Assumptions!$D$50-Assumptions!$D$49)-Assumptions!$D$44-Assumptions!$D$46-Assumptions!$D$47-Assumptions!$D$51 -> 84.582
A86: LTV (contribution-based) = contribution / churn | B86: $ | D86: =D85/Assumptions!$D$41 -> 650.63077 | E86: =E85/Assumptions!$D$41 -> 650.63077 | F86: =F85/Assumptions!$D$41 -> 650.63077 | G86: =G85/Assumptions!$D$41 -> 650.63077 | H86: =H85/Assumptions!$D$41 -> 650.63077 | I86: =I85/Assumptions!$D$41 -> 650.63077 | J86: =J85/Assumptions!$D$41 -> 650.63077 | K86: =K85/Assumptions!$D$41 -> 650.63077 | ... AM86: =AM85/Assumptions!$D$41 -> 650.63077
A87: LTV : CAC (Rx) | B87: x | D87: =IF(D66=0,0,D86/D66) -> 0 | E87: =IF(E66=0,0,E86/E66) -> 0 | F87: =IF(F66=0,0,F86/F66) -> 0 | G87: =IF(G66=0,0,G86/G66) -> 0 | H87: =IF(H66=0,0,H86/H66) -> 0 | I87: =IF(I66=0,0,I86/I66) -> 0.13369187 | J87: =IF(J66=0,0,J86/J66) -> 0.13499167 | K87: =IF(K66=0,0,K86/K66) -> 0.13638246 | ... AM87: =IF(AM66=0,0,AM86/AM66) -> 0.72989436
A88: CAC payback (months) | B88: months | D88: =IF(D85<=0,0,D66/D85) -> 0 | E88: =IF(E85<=0,0,E66/E85) -> 0 | F88: =IF(F85<=0,0,F66/F85) -> 0 | G88: =IF(G85<=0,0,G66/G85) -> 0 | H88: =IF(H85<=0,0,H66/H85) -> 0 | I88: =IF(I85<=0,0,I66/I85) -> 57.537588 | J88: =IF(J85<=0,0,J66/J85) -> 56.983571 | K88: =IF(K85<=0,0,K66/K85) -> 56.402469 | ... AM88: =IF(AM85<=0,0,AM66/AM85) -> 10.538933
A89: Net revenue per active customer (Rx + membership) | B89: $ | D89: =IF((D24+D29)=0,0,D43/(D24+D29)) -> 0 | E89: =IF((E24+E29)=0,0,E43/(E24+E29)) -> 0 | F89: =IF((F24+F29)=0,0,F43/(F24+F29)) -> 0 | G89: =IF((G24+G29)=0,0,G43/(G24+G29)) -> 0 | H89: =IF((H24+H29)=0,0,H43/(H24+H29)) -> 0 | I89: =IF((I24+I29)=0,0,I43/(I24+I29)) -> 243.67899 | J89: =IF((J24+J29)=0,0,J43/(J24+J29)) -> 162.16439 | K89: =IF((K24+K29)=0,0,K43/(K24+K29)) -> 135.06332 | ... AM89: =IF((AM24+AM29)=0,0,AM43/(AM24+AM29)) -> 181.046

Sheet Model_Base
A1: Reserve Clinic monthly model — Base scenario (all cells are formulas driven by the Assumptions sheet)
A2: Units: $ unless noted. Month 1 = start of Phase 0. Prescription programs run through an affiliated medical practice and licensed pharmacies; revenue recognition and merchant-of-record structure subject to counsel.
A3: Line | B3: Unit | C3: 36-mo total | D3: 1 | E3: 2 | F3: 3 | G3: 4 | H3: 5 | I3: 6 | J3: 7 | K3: 8 | L3: 9 | M3: 10 | N3: 11 | O3: 12 | P3: 13 | Q3: 14 | R3: 15 | S3: 16 | T3: 17 | U3: 18 | V3: 19 | W3: 20 | X3: 21 | Y3: 22 | Z3: 23 | AA3: 24 | AB3: 25 | AC3: 26 | AD3: 27 | AE3: 28 | AF3: 29 | AG3: 30 | AH3: 31 | AI3: 32 | AJ3: 33 | AK3: 34 | AL3: 35 | AM3: 36
A4: Timing & coverage
A5: Model month | B5: # | D5: =D$3 -> 1 | E5: =E$3 -> 2 | F5: =F$3 -> 3 | G5: =G$3 -> 4 | H5: =H$3 -> 5 | I5: =I$3 -> 6 | J5: =J$3 -> 7 | K5: =K$3 -> 8 | ... AM5: =AM$3 -> 36
A6: Pre-beta phase flag | B6: flag | D6: =IF(D$3<Assumptions!$E$7,1,0) -> 1 | E6: =IF(E$3<Assumptions!$E$7,1,0) -> 1 | F6: =IF(F$3<Assumptions!$E$7,1,0) -> 1 | G6: =IF(G$3<Assumptions!$E$7,1,0) -> 1 | H6: =IF(H$3<Assumptions!$E$7,1,0) -> 0 | I6: =IF(I$3<Assumptions!$E$7,1,0) -> 0 | J6: =IF(J$3<Assumptions!$E$7,1,0) -> 0 | K6: =IF(K$3<Assumptions!$E$7,1,0) -> 0 | ... AM6: =IF(AM$3<Assumptions!$E$7,1,0) -> 0
A7: Beta/waitlist phase flag | B7: flag | D7: =IF(AND(D$3>=Assumptions!$E$7,D$3<Assumptions!$E$6),1,0) -> 0 | E7: =IF(AND(E$3>=Assumptions!$E$7,E$3<Assumptions!$E$6),1,0) -> 0 | F7: =IF(AND(F$3>=Assumptions!$E$7,F$3<Assumptions!$E$6),1,0) -> 0 | G7: =IF(AND(G$3>=Assumptions!$E$7,G$3<Assumptions!$E$6),1,0) -> 0 | H7: =IF(AND(H$3>=Assumptions!$E$7,H$3<Assumptions!$E$6),1,0) -> 1 | I7: =IF(AND(I$3>=Assumptions!$E$7,I$3<Assumptions!$E$6),1,0) -> 1 | J7: =IF(AND(J$3>=Assumptions!$E$7,J$3<Assumptions!$E$6),1,0) -> 1 | K7: =IF(AND(K$3>=Assumptions!$E$7,K$3<Assumptions!$E$6),1,0) -> 0 | ... AM7: =IF(AND(AM$3>=Assumptions!$E$7,AM$3<Assumptions!$E$6),1,0) -> 0
A8: Launch month flag | B8: flag | D8: =IF(D$3=Assumptions!$E$6,1,0) -> 0 | E8: =IF(E$3=Assumptions!$E$6,1,0) -> 0 | F8: =IF(F$3=Assumptions!$E$6,1,0) -> 0 | G8: =IF(G$3=Assumptions!$E$6,1,0) -> 0 | H8: =IF(H$3=Assumptions!$E$6,1,0) -> 0 | I8: =IF(I$3=Assumptions!$E$6,1,0) -> 0 | J8: =IF(J$3=Assumptions!$E$6,1,0) -> 0 | K8: =IF(K$3=Assumptions!$E$6,1,0) -> 1 | ... AM8: =IF(AM$3=Assumptions!$E$6,1,0) -> 0
A9: Post-launch flag (incl. launch month) | B9: flag | D9: =IF(D$3>=Assumptions!$E$6,1,0) -> 0 | E9: =IF(E$3>=Assumptions!$E$6,1,0) -> 0 | F9: =IF(F$3>=Assumptions!$E$6,1,0) -> 0 | G9: =IF(G$3>=Assumptions!$E$6,1,0) -> 0 | H9: =IF(H$3>=Assumptions!$E$6,1,0) -> 0 | I9: =IF(I$3>=Assumptions!$E$6,1,0) -> 0 | J9: =IF(J$3>=Assumptions!$E$6,1,0) -> 0 | K9: =IF(K$3>=Assumptions!$E$6,1,0) -> 1 | ... AM9: =IF(AM$3>=Assumptions!$E$6,1,0) -> 1
A10: Population coverage of served states (Rx) | B10: % | D10: =IF(D$3<Assumptions!$E$7,0,IF(D$3<Assumptions!$E$6,Assumptions!$E$22*0.5,MIN(Assumptions!$E$24,Assumptions!$E$22+Assumptions!$E$23*(D$3-Assumptions!$E$6)))) -> 0 | E10: =IF(E$3<Assumptions!$E$7,0,IF(E$3<Assumptions!$E$6,Assumptions!$E$22*0.5,MIN(Assumptions!$E$24,Assumptions!$E$22+Assumptions!$E$23*(E$3-Assumptions!$E$6)))) -> 0 | F10: =IF(F$3<Assumptions!$E$7,0,IF(F$3<Assumptions!$E$6,Assumptions!$E$22*0.5,MIN(Assumptions!$E$24,Assumptions!$E$22+Assumptions!$E$23*(F$3-Assumptions!$E$6)))) -> 0 | G10: =IF(G$3<Assumptions!$E$7,0,IF(G$3<Assumptions!$E$6,Assumptions!$E$22*0.5,MIN(Assumptions!$E$24,Assumptions!$E$22+Assumptions!$E$23*(G$3-Assumptions!$E$6)))) -> 0 | H10: =IF(H$3<Assumptions!$E$7,0,IF(H$3<Assumptions!$E$6,Assumptions!$E$22*0.5,MIN(Assumptions!$E$24,Assumptions!$E$22+Assumptions!$E$23*(H$3-Assumptions!$E$6)))) -> 0.2 | I10: =IF(I$3<Assumptions!$E$7,0,IF(I$3<Assumptions!$E$6,Assumptions!$E$22*0.5,MIN(Assumptions!$E$24,Assumptions!$E$22+Assumptions!$E$23*(I$3-Assumptions!$E$6)))) -> 0.2 | J10: =IF(J$3<Assumptions!$E$7,0,IF(J$3<Assumptions!$E$6,Assumptions!$E$22*0.5,MIN(Assumptions!$E$24,Assumptions!$E$22+Assumptions!$E$23*(J$3-Assumptions!$E$6)))) -> 0.2 | K10: =IF(K$3<Assumptions!$E$7,0,IF(K$3<Assumptions!$E$6,Assumptions!$E$22*0.5,MIN(Assumptions!$E$24,Assumptions!$E$22+Assumptions!$E$23*(K$3-Assumptions!$E$6)))) -> 0.4 | ... AM10: =IF(AM$3<Assumptions!$E$7,0,IF(AM$3<Assumptions!$E$6,Assumptions!$E$22*0.5,MIN(Assumptions!$E$24,Assumptions!$E$22+Assumptions!$E$23*(AM$3-Assumptions!$E$6)))) -> 0.85
A11: Traffic
A12: Paid media spend | B12: $ | C12: =SUM(D12:AM12) -> 8337566.1 | D12: =IF(D$3<Assumptions!$E$7,Assumptions!$E$13,IF(D$3<Assumptions!$E$6,Assumptions!$E$14,IF(D$3=Assumptions!$E$6,Assumptions!$E$15,Assumptions!$E$16*(1+Assumptions!$E$17)^(D$3-Assumptions!$E$6-1)))) -> 20000 | E12: =IF(E$3<Assumptions!$E$7,Assumptions!$E$13,IF(E$3<Assumptions!$E$6,Assumptions!$E$14,IF(E$3=Assumptions!$E$6,Assumptions!$E$15,Assumptions!$E$16*(1+Assumptions!$E$17)^(E$3-Assumptions!$E$6-1)))) -> 20000 | F12: =IF(F$3<Assumptions!$E$7,Assumptions!$E$13,IF(F$3<Assumptions!$E$6,Assumptions!$E$14,IF(F$3=Assumptions!$E$6,Assumptions!$E$15,Assumptions!$E$16*(1+Assumptions!$E$17)^(F$3-Assumptions!$E$6-1)))) -> 20000 | G12: =IF(G$3<Assumptions!$E$7,Assumptions!$E$13,IF(G$3<Assumptions!$E$6,Assumptions!$E$14,IF(G$3=Assumptions!$E$6,Assumptions!$E$15,Assumptions!$E$16*(1+Assumptions!$E$17)^(G$3-Assumptions!$E$6-1)))) -> 20000 | H12: =IF(H$3<Assumptions!$E$7,Assumptions!$E$13,IF(H$3<Assumptions!$E$6,Assumptions!$E$14,IF(H$3=Assumptions!$E$6,Assumptions!$E$15,Assumptions!$E$16*(1+Assumptions!$E$17)^(H$3-Assumptions!$E$6-1)))) -> 60000 | I12: =IF(I$3<Assumptions!$E$7,Assumptions!$E$13,IF(I$3<Assumptions!$E$6,Assumptions!$E$14,IF(I$3=Assumptions!$E$6,Assumptions!$E$15,Assumptions!$E$16*(1+Assumptions!$E$17)^(I$3-Assumptions!$E$6-1)))) -> 60000 | J12: =IF(J$3<Assumptions!$E$7,Assumptions!$E$13,IF(J$3<Assumptions!$E$6,Assumptions!$E$14,IF(J$3=Assumptions!$E$6,Assumptions!$E$15,Assumptions!$E$16*(1+Assumptions!$E$17)^(J$3-Assumptions!$E$6-1)))) -> 60000 | K12: =IF(K$3<Assumptions!$E$7,Assumptions!$E$13,IF(K$3<Assumptions!$E$6,Assumptions!$E$14,IF(K$3=Assumptions!$E$6,Assumptions!$E$15,Assumptions!$E$16*(1+Assumptions!$E$17)^(K$3-Assumptions!$E$6-1)))) -> 350000 | ... AM12: =IF(AM$3<Assumptions!$E$7,Assumptions!$E$13,IF(AM$3<Assumptions!$E$6,Assumptions!$E$14,IF(AM$3=Assumptions!$E$6,Assumptions!$E$15,Assumptions!$E$16*(1+Assumptions!$E$17)^(AM$3-Assumptions!$E$6-1)))) -> 399832.02
A13: Paid sessions | B13: sessions | C13: =SUM(D13:AM13) -> 4168783 | D13: =D12/Assumptions!$E$12 -> 10000 | E13: =E12/Assumptions!$E$12 -> 10000 | F13: =F12/Assumptions!$E$12 -> 10000 | G13: =G12/Assumptions!$E$12 -> 10000 | H13: =H12/Assumptions!$E$12 -> 30000 | I13: =I12/Assumptions!$E$12 -> 30000 | J13: =J12/Assumptions!$E$12 -> 30000 | K13: =K12/Assumptions!$E$12 -> 175000 | ... AM13: =AM12/Assumptions!$E$12 -> 199916.01
A14: Organic + direct sessions | B14: sessions | C14: =SUM(D14:AM14) -> 732139.49 | D14: =MIN(Assumptions!$E$11,Assumptions!$E$9*(1+Assumptions!$E$10)^(D$3-1))*IF(AND(D9=1,Assumptions!$E$74=1),Assumptions!$E$78,1) -> 2500 | E14: =MIN(Assumptions!$E$11,Assumptions!$E$9*(1+Assumptions!$E$10)^(E$3-1))*IF(AND(E9=1,Assumptions!$E$74=1),Assumptions!$E$78,1) -> 2725 | F14: =MIN(Assumptions!$E$11,Assumptions!$E$9*(1+Assumptions!$E$10)^(F$3-1))*IF(AND(F9=1,Assumptions!$E$74=1),Assumptions!$E$78,1) -> 2970.25 | G14: =MIN(Assumptions!$E$11,Assumptions!$E$9*(1+Assumptions!$E$10)^(G$3-1))*IF(AND(G9=1,Assumptions!$E$74=1),Assumptions!$E$78,1) -> 3237.5725 | H14: =MIN(Assumptions!$E$11,Assumptions!$E$9*(1+Assumptions!$E$10)^(H$3-1))*IF(AND(H9=1,Assumptions!$E$74=1),Assumptions!$E$78,1) -> 3528.954 | I14: =MIN(Assumptions!$E$11,Assumptions!$E$9*(1+Assumptions!$E$10)^(I$3-1))*IF(AND(I9=1,Assumptions!$E$74=1),Assumptions!$E$78,1) -> 3846.5599 | J14: =MIN(Assumptions!$E$11,Assumptions!$E$9*(1+Assumptions!$E$10)^(J$3-1))*IF(AND(J9=1,Assumptions!$E$74=1),Assumptions!$E$78,1) -> 4192.7503 | K14: =MIN(Assumptions!$E$11,Assumptions!$E$9*(1+Assumptions!$E$10)^(K$3-1))*IF(AND(K9=1,Assumptions!$E$74=1),Assumptions!$E$78,1) -> 5712.6223 | ... AM14: =MIN(Assumptions!$E$11,Assumptions!$E$9*(1+Assumptions!$E$10)^(AM$3-1))*IF(AND(AM9=1,Assumptions!$E$74=1),Assumptions!$E$78,1) -> 63793.65
A15: Total sessions | B15: sessions | C15: =SUM(D15:AM15) -> 4900922.5 | D15: =D13+D14 -> 12500 | E15: =E13+E14 -> 12725 | F15: =F13+F14 -> 12970.25 | G15: =G13+G14 -> 13237.573 | H15: =H13+H14 -> 33528.954 | I15: =I13+I14 -> 33846.56 | J15: =J13+J14 -> 34192.75 | K15: =K13+K14 -> 180712.62 | ... AM15: =AM13+AM14 -> 263709.66
A16: Prescription-program funnel (clinical decisions are independent; rates are monitored, not targeted)
A17: Eligibility quiz starts | B17: # | C17: =SUM(D17:AM17) -> 484948.97 | D17: =D15*Assumptions!$E$19*IF(D$3<Assumptions!$E$7,0,1) -> 0 | E17: =E15*Assumptions!$E$19*IF(E$3<Assumptions!$E$7,0,1) -> 0 | F17: =F15*Assumptions!$E$19*IF(F$3<Assumptions!$E$7,0,1) -> 0 | G17: =G15*Assumptions!$E$19*IF(G$3<Assumptions!$E$7,0,1) -> 0 | H17: =H15*Assumptions!$E$19*IF(H$3<Assumptions!$E$7,0,1) -> 3352.8954 | I17: =I15*Assumptions!$E$19*IF(I$3<Assumptions!$E$7,0,1) -> 3384.656 | J17: =J15*Assumptions!$E$19*IF(J$3<Assumptions!$E$7,0,1) -> 3419.275 | K17: =K15*Assumptions!$E$19*IF(K$3<Assumptions!$E$7,0,1) -> 18071.262 | ... AM17: =AM15*Assumptions!$E$19*IF(AM$3<Assumptions!$E$7,0,1) -> 26370.966
A18: Quiz completions | B18: # | C18: =SUM(D18:AM18) -> 339464.28 | D18: =D17*Assumptions!$E$20 -> 0 | E18: =E17*Assumptions!$E$20 -> 0 | F18: =F17*Assumptions!$E$20 -> 0 | G18: =G17*Assumptions!$E$20 -> 0 | H18: =H17*Assumptions!$E$20 -> 2347.0268 | I18: =I17*Assumptions!$E$20 -> 2369.2592 | J18: =J17*Assumptions!$E$20 -> 2393.4925 | K18: =K17*Assumptions!$E$20 -> 12649.884 | ... AM18: =AM17*Assumptions!$E$20 -> 18459.676
A19: Eligible outcomes (screen + state) | B19: # | C19: =SUM(D19:AM19) -> 152082.7 | D19: =D18*Assumptions!$E$21*D10 -> 0 | E19: =E18*Assumptions!$E$21*E10 -> 0 | F19: =F18*Assumptions!$E$21*F10 -> 0 | G19: =G18*Assumptions!$E$21*G10 -> 0 | H19: =H18*Assumptions!$E$21*H10 -> 281.64321 | I19: =I18*Assumptions!$E$21*I10 -> 284.3111 | J19: =J18*Assumptions!$E$21*J10 -> 287.2191 | K19: =K18*Assumptions!$E$21*K10 -> 3035.9721 | ... AM19: =AM18*Assumptions!$E$21*AM10 -> 9414.4349
A20: Intakes submitted (consult fee charged) | B20: # | C20: =SUM(D20:AM20) -> 83645.484 | D20: =D19*Assumptions!$E$25 -> 0 | E20: =E19*Assumptions!$E$25 -> 0 | F20: =F19*Assumptions!$E$25 -> 0 | G20: =G19*Assumptions!$E$25 -> 0 | H20: =H19*Assumptions!$E$25 -> 154.90377 | I20: =I19*Assumptions!$E$25 -> 156.37111 | J20: =J19*Assumptions!$E$25 -> 157.97051 | K20: =K19*Assumptions!$E$25 -> 1669.7846 | ... AM20: =AM19*Assumptions!$E$25 -> 5177.9392
A21: Consults completed | B21: # | C21: =SUM(D21:AM21) -> 68589.297 | D21: =D20*Assumptions!$E$26 -> 0 | E21: =E20*Assumptions!$E$26 -> 0 | F21: =F20*Assumptions!$E$26 -> 0 | G21: =G20*Assumptions!$E$26 -> 0 | H21: =H20*Assumptions!$E$26 -> 127.02109 | I21: =I20*Assumptions!$E$26 -> 128.22431 | J21: =J20*Assumptions!$E$26 -> 129.53582 | K21: =K20*Assumptions!$E$26 -> 1369.2234 | ... AM21: =AM20*Assumptions!$E$26 -> 4245.9101
A22: Prescriptions issued (clinician decision) | B22: # | C22: =SUM(D22:AM22) -> 42525.364 | D22: =D21*Assumptions!$E$27 -> 0 | E22: =E21*Assumptions!$E$27 -> 0 | F22: =F21*Assumptions!$E$27 -> 0 | G22: =G21*Assumptions!$E$27 -> 0 | H22: =H21*Assumptions!$E$27 -> 78.753075 | I22: =I21*Assumptions!$E$27 -> 79.499071 | J22: =J21*Assumptions!$E$27 -> 80.312205 | K22: =K21*Assumptions!$E$27 -> 848.91851 | ... AM22: =AM21*Assumptions!$E$27 -> 2632.4643
A23: New paying Rx program members | B23: # | C23: =SUM(D23:AM23) -> 27641.487 | D23: =D22*Assumptions!$E$28 -> 0 | E23: =E22*Assumptions!$E$28 -> 0 | F23: =F22*Assumptions!$E$28 -> 0 | G23: =G22*Assumptions!$E$28 -> 0 | H23: =H22*Assumptions!$E$28 -> 51.189499 | I23: =I22*Assumptions!$E$28 -> 51.674396 | J23: =J22*Assumptions!$E$28 -> 52.202934 | K23: =K22*Assumptions!$E$28 -> 551.79703 | ... AM23: =AM22*Assumptions!$E$28 -> 1711.1018
A24: Active Rx program members (end of month) | B24: # | D24: =D23 -> 0 | E24: =D24*(1-Assumptions!$E$41)+E23 -> 0 | F24: =E24*(1-Assumptions!$E$41)+F23 -> 0 | G24: =F24*(1-Assumptions!$E$41)+G23 -> 0 | H24: =G24*(1-Assumptions!$E$41)+H23 -> 51.189499 | I24: =H24*(1-Assumptions!$E$41)+I23 -> 97.23305 | J24: =I24*(1-Assumptions!$E$41)+J23 -> 138.74035 | K24: =J24*(1-Assumptions!$E$41)+K23 -> 675.27594 | L24: =K24*(1-Assumptions!$E$41)+L23 -> 916.85599 | ... AM24: =AL24*(1-Assumptions!$E$41)+AM23 -> 11437.582
A25: Rx members churned | B25: # | C25: =SUM(D25:AM25) -> 16203.905 | D25: =0 -> 0 | E25: =D24*Assumptions!$E$41 -> 0 | F25: =E24*Assumptions!$E$41 -> 0 | G25: =F24*Assumptions!$E$41 -> 0 | H25: =G24*Assumptions!$E$41 -> 0 | I25: =H24*Assumptions!$E$41 -> 5.6308449 | J25: =I24*Assumptions!$E$41 -> 10.695636 | K25: =J24*Assumptions!$E$41 -> 15.261438 | L25: =K24*Assumptions!$E$41 -> 74.280353 | ... AM25: =AL24*Assumptions!$E$41 -> 1202.1492
A26: Lab panels ordered | B26: # | C26: =SUM(D26:AM26) -> 41822.742 | D26: =D20*Assumptions!$E$32 -> 0 | E26: =E20*Assumptions!$E$32 -> 0 | F26: =F20*Assumptions!$E$32 -> 0 | G26: =G20*Assumptions!$E$32 -> 0 | H26: =H20*Assumptions!$E$32 -> 77.451884 | I26: =I20*Assumptions!$E$32 -> 78.185553 | J26: =J20*Assumptions!$E$32 -> 78.985253 | K26: =K20*Assumptions!$E$32 -> 834.89231 | ... AM26: =AM20*Assumptions!$E$32 -> 2588.9696
A27: Membership and non-prescription commerce
A28: New membership sign-ups | B28: # | C28: =SUM(D28:AM28) -> 16092.385 | D28: =(D18-D19)*Assumptions!$E$35+D15*Assumptions!$E$36*IF(D$3<Assumptions!$E$7,0,1) -> 0 | E28: =(E18-E19)*Assumptions!$E$35+E15*Assumptions!$E$36*IF(E$3<Assumptions!$E$7,0,1) -> 0 | F28: =(F18-F19)*Assumptions!$E$35+F15*Assumptions!$E$36*IF(F$3<Assumptions!$E$7,0,1) -> 0 | G28: =(G18-G19)*Assumptions!$E$35+G15*Assumptions!$E$36*IF(G$3<Assumptions!$E$7,0,1) -> 0 | H28: =(H18-H19)*Assumptions!$E$35+H15*Assumptions!$E$36*IF(H$3<Assumptions!$E$7,0,1) -> 157.45197 | I28: =(I18-I19)*Assumptions!$E$35+I15*Assumptions!$E$36*IF(I$3<Assumptions!$E$7,0,1) -> 158.94345 | J28: =(J18-J19)*Assumptions!$E$35+J15*Assumptions!$E$36*IF(J$3<Assumptions!$E$7,0,1) -> 160.56916 | K28: =(K18-K19)*Assumptions!$E$35+K15*Assumptions!$E$36*IF(K$3<Assumptions!$E$7,0,1) -> 757.54731 | ... AM28: =(AM18-AM19)*Assumptions!$E$35+AM15*Assumptions!$E$36*IF(AM$3<Assumptions!$E$7,0,1) -> 806.42414
A29: Active members (end of month) | B29: # | D29: =D28 -> 0 | E29: =D29*(1-Assumptions!$E$42)+E28 -> 0 | F29: =E29*(1-Assumptions!$E$42)+F28 -> 0 | G29: =F29*(1-Assumptions!$E$42)+G28 -> 0 | H29: =G29*(1-Assumptions!$E$42)+H28 -> 157.45197 | I29: =H29*(1-Assumptions!$E$42)+I28 -> 306.9483 | J29: =I29*(1-Assumptions!$E$42)+J28 -> 449.10055 | K29: =J29*(1-Assumptions!$E$42)+K28 -> 1179.7018 | L29: =K29*(1-Assumptions!$E$42)+L28 -> 1505.0275 | ... AM29: =AL29*(1-Assumptions!$E$42)+AM28 -> 8289.8763
A30: Members churned | B30: # | C30: =SUM(D30:AM30) -> 7802.5082 | D30: =0 -> 0 | E30: =D29*Assumptions!$E$42 -> 0 | F30: =E29*Assumptions!$E$42 -> 0 | G30: =F29*Assumptions!$E$42 -> 0 | H30: =G29*Assumptions!$E$42 -> 0 | I30: =H29*Assumptions!$E$42 -> 9.4471181 | J30: =I29*Assumptions!$E$42 -> 18.416898 | K30: =J29*Assumptions!$E$42 -> 26.946033 | L30: =K29*Assumptions!$E$42 -> 70.78211 | ... AM30: =AL29*Assumptions!$E$42 -> 477.66716
A31: Non-Rx first orders | B31: # | C31: =SUM(D31:AM31) -> 43645.407 | D31: =D15*Assumptions!$E$37*IF(D$3<Assumptions!$E$7,0,1) -> 0 | E31: =E15*Assumptions!$E$37*IF(E$3<Assumptions!$E$7,0,1) -> 0 | F31: =F15*Assumptions!$E$37*IF(F$3<Assumptions!$E$7,0,1) -> 0 | G31: =G15*Assumptions!$E$37*IF(G$3<Assumptions!$E$7,0,1) -> 0 | H31: =H15*Assumptions!$E$37*IF(H$3<Assumptions!$E$7,0,1) -> 301.76059 | I31: =I15*Assumptions!$E$37*IF(I$3<Assumptions!$E$7,0,1) -> 304.61904 | J31: =J15*Assumptions!$E$37*IF(J$3<Assumptions!$E$7,0,1) -> 307.73475 | K31: =K15*Assumptions!$E$37*IF(K$3<Assumptions!$E$7,0,1) -> 1626.4136 | ... AM31: =AM15*Assumptions!$E$37*IF(AM$3<Assumptions!$E$7,0,1) -> 2373.3869
A32: Cumulative non-Rx customers | B32: # | D32: =D31 -> 0 | E32: =D32+E31 -> 0 | F32: =E32+F31 -> 0 | G32: =F32+G31 -> 0 | H32: =G32+H31 -> 301.76059 | I32: =H32+I31 -> 606.37963 | J32: =I32+J31 -> 914.11438 | K32: =J32+K31 -> 2540.528 | L32: =K32+L31 -> 3406.5688 | ... AM32: =AL32+AM31 -> 43645.407
A33: Non-Rx repeat orders | B33: # | C33: =SUM(D33:AM33) -> 79349.94 | D33: =0 -> 0 | E33: =D32*Assumptions!$E$39 -> 0 | F33: =E32*Assumptions!$E$39 -> 0 | G33: =F32*Assumptions!$E$39 -> 0 | H33: =G32*Assumptions!$E$39 -> 0 | I33: =H32*Assumptions!$E$39 -> 45.264088 | J33: =I32*Assumptions!$E$39 -> 90.956944 | K33: =J32*Assumptions!$E$39 -> 137.11716 | L33: =K32*Assumptions!$E$39 -> 381.0792 | ... AM33: =AL32*Assumptions!$E$39 -> 6190.803
A34: Total non-Rx orders | B34: # | C34: =SUM(D34:AM34) -> 122995.35 | D34: =D31+D33 -> 0 | E34: =E31+E33 -> 0 | F34: =F31+F33 -> 0 | G34: =G31+G33 -> 0 | H34: =H31+H33 -> 301.76059 | I34: =I31+I33 -> 349.88313 | J34: =J31+J33 -> 398.6917 | K34: =K31+K33 -> 1763.5308 | ... AM34: =AM31+AM33 -> 8564.19
A35: Revenue
A36: Rx program revenue (all-in monthly) | B36: $ | C36: =SUM(D36:AM36) -> 43655096 | D36: =D24*Assumptions!$E$30 -> 0 | E36: =E24*Assumptions!$E$30 -> 0 | F36: =F24*Assumptions!$E$30 -> 0 | G36: =G24*Assumptions!$E$30 -> 0 | H36: =H24*Assumptions!$E$30 -> 14077.112 | I36: =I24*Assumptions!$E$30 -> 26739.089 | J36: =J24*Assumptions!$E$30 -> 38153.596 | K36: =K24*Assumptions!$E$30 -> 185700.88 | ... AM36: =AM24*Assumptions!$E$30 -> 3145335.1
A37: Consultation revenue | B37: $ | C37: =SUM(D37:AM37) -> 6607993.2 | D37: =D20*Assumptions!$E$31 -> 0 | E37: =E20*Assumptions!$E$31 -> 0 | F37: =F20*Assumptions!$E$31 -> 0 | G37: =G20*Assumptions!$E$31 -> 0 | H37: =H20*Assumptions!$E$31 -> 12237.398 | I37: =I20*Assumptions!$E$31 -> 12353.317 | J37: =J20*Assumptions!$E$31 -> 12479.67 | K37: =K20*Assumptions!$E$31 -> 131912.99 | ... AM37: =AM20*Assumptions!$E$31 -> 409057.2
A38: Lab revenue | B38: $ | C38: =SUM(D38:AM38) -> 4976906.3 | D38: =D26*Assumptions!$E$33 -> 0 | E38: =E26*Assumptions!$E$33 -> 0 | F38: =F26*Assumptions!$E$33 -> 0 | G38: =G26*Assumptions!$E$33 -> 0 | H38: =H26*Assumptions!$E$33 -> 9216.7742 | I38: =I26*Assumptions!$E$33 -> 9304.0808 | J38: =J26*Assumptions!$E$33 -> 9399.2451 | K38: =K26*Assumptions!$E$33 -> 99352.185 | ... AM38: =AM26*Assumptions!$E$33 -> 308087.38
A39: Membership revenue | B39: $ | C39: =SUM(D39:AM39) -> 4011618.7 | D39: =D29*Assumptions!$E$34 -> 0 | E39: =E29*Assumptions!$E$34 -> 0 | F39: =F29*Assumptions!$E$34 -> 0 | G39: =G29*Assumptions!$E$34 -> 0 | H39: =H29*Assumptions!$E$34 -> 4566.1071 | I39: =I29*Assumptions!$E$34 -> 8901.5006 | J39: =J29*Assumptions!$E$34 -> 13023.916 | K39: =K29*Assumptions!$E$34 -> 34211.353 | ... AM39: =AM29*Assumptions!$E$34 -> 240406.41
A40: Non-Rx commerce revenue | B40: $ | C40: =SUM(D40:AM40) -> 9224651.1 | D40: =D34*Assumptions!$E$38 -> 0 | E40: =E34*Assumptions!$E$38 -> 0 | F40: =F34*Assumptions!$E$38 -> 0 | G40: =G34*Assumptions!$E$38 -> 0 | H40: =H34*Assumptions!$E$38 -> 22632.044 | I40: =I34*Assumptions!$E$38 -> 26241.235 | J40: =J34*Assumptions!$E$38 -> 29901.877 | K40: =K34*Assumptions!$E$38 -> 132264.81 | ... AM40: =AM34*Assumptions!$E$38 -> 642314.25
A41: Gross revenue | B41: $ | C41: =SUM(D41:AM41) -> 68476266 | D41: =D36+D37+D38+D39+D40 -> 0 | E41: =E36+E37+E38+E39+E40 -> 0 | F41: =F36+F37+F38+F39+F40 -> 0 | G41: =G36+G37+G38+G39+G40 -> 0 | H41: =H36+H37+H38+H39+H40 -> 62729.435 | I41: =I36+I37+I38+I39+I40 -> 83539.222 | J41: =J36+J37+J38+J39+J40 -> 102958.3 | K41: =K36+K37+K38+K39+K40 -> 583442.21 | ... AM41: =AM36+AM37+AM38+AM39+AM40 -> 4745200.3
A42: Refunds & chargebacks | B42: $ | C42: =SUM(D42:AM42) -> -2396669.3 | D42: =-D41*Assumptions!$E$50 -> 0 | E42: =-E41*Assumptions!$E$50 -> 0 | F42: =-F41*Assumptions!$E$50 -> 0 | G42: =-G41*Assumptions!$E$50 -> 0 | H42: =-H41*Assumptions!$E$50 -> -2195.5302 | I42: =-I41*Assumptions!$E$50 -> -2923.8728 | J42: =-J41*Assumptions!$E$50 -> -3603.5406 | K42: =-K41*Assumptions!$E$50 -> -20420.477 | ... AM42: =-AM41*Assumptions!$E$50 -> -166082.01
A43: Net revenue | B43: $ | C43: =SUM(D43:AM43) -> 66079596 | D43: =D41+D42 -> 0 | E43: =E41+E42 -> 0 | F43: =F41+F42 -> 0 | G43: =G41+G42 -> 0 | H43: =H41+H42 -> 60533.905 | I43: =I41+I42 -> 80615.349 | J43: =J41+J42 -> 99354.763 | K43: =K41+K42 -> 563021.74 | ... AM43: =AM41+AM42 -> 4579118.3
A44: Cost of revenue
A45: Pharmacy / medication | B45: $ | C45: =SUM(D45:AM45) -> -15080852 | D45: =-D24*Assumptions!$E$44 -> 0 | E45: =-E24*Assumptions!$E$44 -> 0 | F45: =-F24*Assumptions!$E$44 -> 0 | G45: =-G24*Assumptions!$E$44 -> 0 | H45: =-H24*Assumptions!$E$44 -> -4863.0024 | I45: =-I24*Assumptions!$E$44 -> -9237.1398 | J45: =-J24*Assumptions!$E$44 -> -13180.333 | K45: =-K24*Assumptions!$E$44 -> -64151.214 | ... AM45: =-AM24*Assumptions!$E$44 -> -1086570.3
A46: Clinical (consults + monitoring) | B46: $ | C46: =SUM(D46:AM46) -> -4013538.3 | D46: =-(D21*Assumptions!$E$45+D24*Assumptions!$E$46) -> 0 | E46: =-(E21*Assumptions!$E$45+E24*Assumptions!$E$46) -> 0 | F46: =-(F21*Assumptions!$E$45+F24*Assumptions!$E$46) -> 0 | G46: =-(G21*Assumptions!$E$45+G24*Assumptions!$E$46) -> 0 | H46: =-(H21*Assumptions!$E$45+H24*Assumptions!$E$46) -> -5490.3596 | I46: =-(I21*Assumptions!$E$45+I24*Assumptions!$E$46) -> -5906.8367 | J46: =-(J21*Assumptions!$E$45+J24*Assumptions!$E$46) -> -6291.3554 | K46: =-(K21*Assumptions!$E$45+K24*Assumptions!$E$46) -> -60171.143 | ... AM46: =-(AM21*Assumptions!$E$45+AM24*Assumptions!$E$46) -> -261337.06
A47: Lab costs | B47: $ | C47: =SUM(D47:AM47) -> -3345819.4 | D47: =-D26*Assumptions!$E$48 -> 0 | E47: =-E26*Assumptions!$E$48 -> 0 | F47: =-F26*Assumptions!$E$48 -> 0 | G47: =-G26*Assumptions!$E$48 -> 0 | H47: =-H26*Assumptions!$E$48 -> -6196.1507 | I47: =-I26*Assumptions!$E$48 -> -6254.8443 | J47: =-J26*Assumptions!$E$48 -> -6318.8203 | K47: =-K26*Assumptions!$E$48 -> -66791.385 | ... AM47: =-AM26*Assumptions!$E$48 -> -207117.57
A48: Rx fulfillment & shipping | B48: $ | C48: =SUM(D48:AM48) -> -2381187.1 | D48: =-D24*Assumptions!$E$47 -> 0 | E48: =-E24*Assumptions!$E$47 -> 0 | F48: =-F24*Assumptions!$E$47 -> 0 | G48: =-G24*Assumptions!$E$47 -> 0 | H48: =-H24*Assumptions!$E$47 -> -767.84249 | I48: =-I24*Assumptions!$E$47 -> -1458.4958 | J48: =-J24*Assumptions!$E$47 -> -2081.1052 | K48: =-K24*Assumptions!$E$47 -> -10129.139 | ... AM48: =-AM24*Assumptions!$E$47 -> -171563.73
A49: Non-Rx COGS + fulfillment | B49: $ | C49: =SUM(D49:AM49) -> -4212590.6 | D49: =-(D40*Assumptions!$E$52+D34*Assumptions!$E$53) -> 0 | E49: =-(E40*Assumptions!$E$52+E34*Assumptions!$E$53) -> 0 | F49: =-(F40*Assumptions!$E$52+F34*Assumptions!$E$53) -> 0 | G49: =-(G40*Assumptions!$E$52+G34*Assumptions!$E$53) -> 0 | H49: =-(H40*Assumptions!$E$52+H34*Assumptions!$E$53) -> -10335.3 | I49: =-(I40*Assumptions!$E$52+I34*Assumptions!$E$53) -> -11983.497 | J49: =-(J40*Assumptions!$E$52+J34*Assumptions!$E$53) -> -13655.191 | K49: =-(K40*Assumptions!$E$52+K34*Assumptions!$E$53) -> -60400.928 | ... AM49: =-(AM40*Assumptions!$E$52+AM34*Assumptions!$E$53) -> -293323.51
A50: Membership delivery | B50: $ | C50: =SUM(D50:AM50) -> -276663.36 | D50: =-D29*Assumptions!$E$54 -> 0 | E50: =-E29*Assumptions!$E$54 -> 0 | F50: =-F29*Assumptions!$E$54 -> 0 | G50: =-G29*Assumptions!$E$54 -> 0 | H50: =-H29*Assumptions!$E$54 -> -314.90394 | I50: =-I29*Assumptions!$E$54 -> -613.89659 | J50: =-J29*Assumptions!$E$54 -> -898.20111 | K50: =-K29*Assumptions!$E$54 -> -2359.4037 | ... AM50: =-AM29*Assumptions!$E$54 -> -16579.753
A51: Payment processing | B51: $ | C51: =SUM(D51:AM51) -> -1985811.7 | D51: =-D41*Assumptions!$E$49 -> 0 | E51: =-E41*Assumptions!$E$49 -> 0 | F51: =-F41*Assumptions!$E$49 -> 0 | G51: =-G41*Assumptions!$E$49 -> 0 | H51: =-H41*Assumptions!$E$49 -> -1819.1536 | I51: =-I41*Assumptions!$E$49 -> -2422.6374 | J51: =-J41*Assumptions!$E$49 -> -2985.7908 | K51: =-K41*Assumptions!$E$49 -> -16919.824 | ... AM51: =-AM41*Assumptions!$E$49 -> -137610.81
A52: Customer support (variable) | B52: $ | C52: =SUM(D52:AM52) -> -1485387.4 | D52: =-(D24+D29)*Assumptions!$E$51 -> 0 | E52: =-(E24+E29)*Assumptions!$E$51 -> 0 | F52: =-(F24+F29)*Assumptions!$E$51 -> 0 | G52: =-(G24+G29)*Assumptions!$E$51 -> 0 | H52: =-(H24+H29)*Assumptions!$E$51 -> -1043.2073 | I52: =-(I24+I29)*Assumptions!$E$51 -> -2020.9067 | J52: =-(J24+J29)*Assumptions!$E$51 -> -2939.2045 | K52: =-(K24+K29)*Assumptions!$E$51 -> -9274.8889 | ... AM52: =-(AM24+AM29)*Assumptions!$E$51 -> -98637.292
A53: Total cost of revenue | B53: $ | C53: =SUM(D53:AM53) -> -32781849 | D53: =SUM(D45:D52) -> 0 | E53: =SUM(E45:E52) -> 0 | F53: =SUM(F45:F52) -> 0 | G53: =SUM(G45:G52) -> 0 | H53: =SUM(H45:H52) -> -30829.92 | I53: =SUM(I45:I52) -> -39898.254 | J53: =SUM(J45:J52) -> -48350.001 | K53: =SUM(K45:K52) -> -290197.93 | ... AM53: =SUM(AM45:AM52) -> -2272740
A54: Gross profit | B54: $ | C54: =SUM(D54:AM54) -> 33297747 | D54: =D43+D53 -> 0 | E54: =E43+E53 -> 0 | F54: =F43+F53 -> 0 | G54: =G43+G53 -> 0 | H54: =H43+H53 -> 29703.985 | I54: =I43+I53 -> 40717.095 | J54: =J43+J53 -> 51004.762 | K54: =K43+K53 -> 272823.81 | ... AM54: =AM43+AM53 -> 2306378.3
A55: Gross margin % | B55: % | D55: =IF(D43=0,0,D54/D43) -> 0 | E55: =IF(E43=0,0,E54/E43) -> 0 | F55: =IF(F43=0,0,F54/F43) -> 0 | G55: =IF(G43=0,0,G54/G43) -> 0 | H55: =IF(H43=0,0,H54/H43) -> 0.49069996 | I55: =IF(I43=0,0,I54/I43) -> 0.50507869 | J55: =IF(J43=0,0,J54/J43) -> 0.51336001 | K55: =IF(K43=0,0,K54/K43) -> 0.48457065 | ... AM55: =IF(AM43=0,0,AM54/AM43) -> 0.50367301
A56: Acquisition and contribution
A57: Paid media | B57: $ | C57: =SUM(D57:AM57) -> -8337566.1 | D57: =-D12 -> -20000 | E57: =-E12 -> -20000 | F57: =-F12 -> -20000 | G57: =-G12 -> -20000 | H57: =-H12 -> -60000 | I57: =-I12 -> -60000 | J57: =-J12 -> -60000 | K57: =-K12 -> -350000 | ... AM57: =-AM12 -> -399832.02
A58: Influencer & affiliate | B58: $ | C58: =SUM(D58:AM58) -> -1525000 | D58: =-IF(D$3<Assumptions!$E$7,0,IF(D$3<Assumptions!$E$6,Assumptions!$E$71,Assumptions!$E$72)) -> 0 | E58: =-IF(E$3<Assumptions!$E$7,0,IF(E$3<Assumptions!$E$6,Assumptions!$E$71,Assumptions!$E$72)) -> 0 | F58: =-IF(F$3<Assumptions!$E$7,0,IF(F$3<Assumptions!$E$6,Assumptions!$E$71,Assumptions!$E$72)) -> 0 | G58: =-IF(G$3<Assumptions!$E$7,0,IF(G$3<Assumptions!$E$6,Assumptions!$E$71,Assumptions!$E$72)) -> 0 | H58: =-IF(H$3<Assumptions!$E$7,0,IF(H$3<Assumptions!$E$6,Assumptions!$E$71,Assumptions!$E$72)) -> -25000 | I58: =-IF(I$3<Assumptions!$E$7,0,IF(I$3<Assumptions!$E$6,Assumptions!$E$71,Assumptions!$E$72)) -> -25000 | J58: =-IF(J$3<Assumptions!$E$7,0,IF(J$3<Assumptions!$E$6,Assumptions!$E$71,Assumptions!$E$72)) -> -25000 | K58: =-IF(K$3<Assumptions!$E$7,0,IF(K$3<Assumptions!$E$6,Assumptions!$E$71,Assumptions!$E$72)) -> -50000 | ... AM58: =-IF(AM$3<Assumptions!$E$7,0,IF(AM$3<Assumptions!$E$6,Assumptions!$E$71,Assumptions!$E$72)) -> -50000
A59: Launch PR/events (one-time) | B59: $ | C59: =SUM(D59:AM59) -> -90000 | D59: =-D8*Assumptions!$E$70 -> 0 | E59: =-E8*Assumptions!$E$70 -> 0 | F59: =-F8*Assumptions!$E$70 -> 0 | G59: =-G8*Assumptions!$E$70 -> 0 | H59: =-H8*Assumptions!$E$70 -> 0 | I59: =-I8*Assumptions!$E$70 -> 0 | J59: =-J8*Assumptions!$E$70 -> 0 | K59: =-K8*Assumptions!$E$70 -> -90000 | ... AM59: =-AM8*Assumptions!$E$70 -> 0
A60: Brand partner cash retainer (Scenario A only) | B60: $ | C60: =SUM(D60:AM60) -> -960000 | D60: =-Assumptions!$E$74*IF(D$3<Assumptions!$E$7,0,Assumptions!$E$75) -> 0 | E60: =-Assumptions!$E$74*IF(E$3<Assumptions!$E$7,0,Assumptions!$E$75) -> 0 | F60: =-Assumptions!$E$74*IF(F$3<Assumptions!$E$7,0,Assumptions!$E$75) -> 0 | G60: =-Assumptions!$E$74*IF(G$3<Assumptions!$E$7,0,Assumptions!$E$75) -> 0 | H60: =-Assumptions!$E$74*IF(H$3<Assumptions!$E$7,0,Assumptions!$E$75) -> -30000 | I60: =-Assumptions!$E$74*IF(I$3<Assumptions!$E$7,0,Assumptions!$E$75) -> -30000 | J60: =-Assumptions!$E$74*IF(J$3<Assumptions!$E$7,0,Assumptions!$E$75) -> -30000 | K60: =-Assumptions!$E$74*IF(K$3<Assumptions!$E$7,0,Assumptions!$E$75) -> -30000 | ... AM60: =-Assumptions!$E$74*IF(AM$3<Assumptions!$E$7,0,Assumptions!$E$75) -> -30000
A61: Brand partner royalty (Scenario A only) | B61: $ | C61: =SUM(D61:AM61) -> -1982387.9 | D61: =-Assumptions!$E$74*D43*Assumptions!$E$76 -> 0 | E61: =-Assumptions!$E$74*E43*Assumptions!$E$76 -> 0 | F61: =-Assumptions!$E$74*F43*Assumptions!$E$76 -> 0 | G61: =-Assumptions!$E$74*G43*Assumptions!$E$76 -> 0 | H61: =-Assumptions!$E$74*H43*Assumptions!$E$76 -> -1816.0171 | I61: =-Assumptions!$E$74*I43*Assumptions!$E$76 -> -2418.4605 | J61: =-Assumptions!$E$74*J43*Assumptions!$E$76 -> -2980.6429 | K61: =-Assumptions!$E$74*K43*Assumptions!$E$76 -> -16890.652 | ... AM61: =-Assumptions!$E$74*AM43*Assumptions!$E$76 -> -137373.55
A62: Total acquisition & partner cost | B62: $ | C62: =SUM(D62:AM62) -> -12894954 | D62: =SUM(D57:D61) -> -20000 | E62: =SUM(E57:E61) -> -20000 | F62: =SUM(F57:F61) -> -20000 | G62: =SUM(G57:G61) -> -20000 | H62: =SUM(H57:H61) -> -116816.02 | I62: =SUM(I57:I61) -> -117418.46 | J62: =SUM(J57:J61) -> -117980.64 | K62: =SUM(K57:K61) -> -536890.65 | ... AM62: =SUM(AM57:AM61) -> -617205.57
A63: Contribution margin | B63: $ | C63: =SUM(D63:AM63) -> 20402793 | D63: =D54+D62 -> -20000 | E63: =E54+E62 -> -20000 | F63: =F54+F62 -> -20000 | G63: =G54+G62 -> -20000 | H63: =H54+H62 -> -87112.032 | I63: =I54+I62 -> -76701.365 | J63: =J54+J62 -> -66975.88 | K63: =K54+K62 -> -264066.84 | ... AM63: =AM54+AM62 -> 1689172.7
A64: New paying customers (Rx + members + first shop orders) | B64: # | C64: =SUM(D64:AM64) -> 87379.278 | D64: =D23+D28+D31 -> 0 | E64: =E23+E28+E31 -> 0 | F64: =F23+F28+F31 -> 0 | G64: =G23+G28+G31 -> 0 | H64: =H23+H28+H31 -> 510.40205 | I64: =I23+I28+I31 -> 515.23688 | J64: =J23+J28+J31 -> 520.50684 | K64: =K23+K28+K31 -> 2935.7579 | ... AM64: =AM23+AM28+AM31 -> 4890.9129
A65: Blended CAC (acquisition cost / new paying customers) | B65: $ | D65: =IF(D64=0,0,-(D57+D58+D59)/D64) -> 0 | E65: =IF(E64=0,0,-(E57+E58+E59)/E64) -> 0 | F65: =IF(F64=0,0,-(F57+F58+F59)/F64) -> 0 | G65: =IF(G64=0,0,-(G57+G58+G59)/G64) -> 0 | H65: =IF(H64=0,0,-(H57+H58+H59)/H64) -> 166.53538 | I65: =IF(I64=0,0,-(I57+I58+I59)/I64) -> 164.97266 | J65: =IF(J64=0,0,-(J57+J58+J59)/J64) -> 163.30237 | K65: =IF(K64=0,0,-(K57+K58+K59)/K64) -> 166.90749 | ... AM65: =IF(AM64=0,0,-(AM57+AM58+AM59)/AM64) -> 91.973019
A66: CAC per new Rx member (all acquisition cost allocated to Rx) | B66: $ | D66: =IF(D23=0,0,-(D57+D58+D59)/D23) -> 0 | E66: =IF(E23=0,0,-(E57+E58+E59)/E23) -> 0 | F66: =IF(F23=0,0,-(F57+F58+F59)/F23) -> 0 | G66: =IF(G23=0,0,-(G57+G58+G59)/G23) -> 0 | H66: =IF(H23=0,0,-(H57+H58+H59)/H23) -> 1660.4968 | I66: =IF(I23=0,0,-(I57+I58+I59)/I23) -> 1644.9152 | J66: =IF(J23=0,0,-(J57+J58+J59)/J23) -> 1628.261 | K66: =IF(K23=0,0,-(K57+K58+K59)/K23) -> 888.00768 | ... AM66: =IF(AM23=0,0,-(AM57+AM58+AM59)/AM23) -> 262.89028
A67: Operating expenses
A68: Team (fully loaded) | B68: $ | C68: =SUM(D68:AM68) -> -8760000 | D68: =-IF(D$3<=3,Assumptions!$E$56,IF(D$3<Assumptions!$E$6,Assumptions!$E$57,IF(D$3<=12,Assumptions!$E$58,IF(D$3<=24,Assumptions!$E$59,Assumptions!$E$60)))) -> -60000 | E68: =-IF(E$3<=3,Assumptions!$E$56,IF(E$3<Assumptions!$E$6,Assumptions!$E$57,IF(E$3<=12,Assumptions!$E$58,IF(E$3<=24,Assumptions!$E$59,Assumptions!$E$60)))) -> -60000 | F68: =-IF(F$3<=3,Assumptions!$E$56,IF(F$3<Assumptions!$E$6,Assumptions!$E$57,IF(F$3<=12,Assumptions!$E$58,IF(F$3<=24,Assumptions!$E$59,Assumptions!$E$60)))) -> -60000 | G68: =-IF(G$3<=3,Assumptions!$E$56,IF(G$3<Assumptions!$E$6,Assumptions!$E$57,IF(G$3<=12,Assumptions!$E$58,IF(G$3<=24,Assumptions!$E$59,Assumptions!$E$60)))) -> -120000 | H68: =-IF(H$3<=3,Assumptions!$E$56,IF(H$3<Assumptions!$E$6,Assumptions!$E$57,IF(H$3<=12,Assumptions!$E$58,IF(H$3<=24,Assumptions!$E$59,Assumptions!$E$60)))) -> -120000 | I68: =-IF(I$3<=3,Assumptions!$E$56,IF(I$3<Assumptions!$E$6,Assumptions!$E$57,IF(I$3<=12,Assumptions!$E$58,IF(I$3<=24,Assumptions!$E$59,Assumptions!$E$60)))) -> -120000 | J68: =-IF(J$3<=3,Assumptions!$E$56,IF(J$3<Assumptions!$E$6,Assumptions!$E$57,IF(J$3<=12,Assumptions!$E$58,IF(J$3<=24,Assumptions!$E$59,Assumptions!$E$60)))) -> -120000 | K68: =-IF(K$3<=3,Assumptions!$E$56,IF(K$3<Assumptions!$E$6,Assumptions!$E$57,IF(K$3<=12,Assumptions!$E$58,IF(K$3<=24,Assumptions!$E$59,Assumptions!$E$60)))) -> -180000 | ... AM68: =-IF(AM$3<=3,Assumptions!$E$56,IF(AM$3<Assumptions!$E$6,Assumptions!$E$57,IF(AM$3<=12,Assumptions!$E$58,IF(AM$3<=24,Assumptions!$E$59,Assumptions!$E$60)))) -> -340000
A69: Medical leadership & governance | B69: $ | C69: =SUM(D69:AM69) -> -720000 | D69: =-Assumptions!$E$61 -> -20000 | E69: =-Assumptions!$E$61 -> -20000 | F69: =-Assumptions!$E$61 -> -20000 | G69: =-Assumptions!$E$61 -> -20000 | H69: =-Assumptions!$E$61 -> -20000 | I69: =-Assumptions!$E$61 -> -20000 | J69: =-Assumptions!$E$61 -> -20000 | K69: =-Assumptions!$E$61 -> -20000 | ... AM69: =-Assumptions!$E$61 -> -20000
A70: Technology & software | B70: $ | C70: =SUM(D70:AM70) -> -954000 | D70: =-IF(D9=1,Assumptions!$E$63,Assumptions!$E$62) -> -12000 | E70: =-IF(E9=1,Assumptions!$E$63,Assumptions!$E$62) -> -12000 | F70: =-IF(F9=1,Assumptions!$E$63,Assumptions!$E$62) -> -12000 | G70: =-IF(G9=1,Assumptions!$E$63,Assumptions!$E$62) -> -12000 | H70: =-IF(H9=1,Assumptions!$E$63,Assumptions!$E$62) -> -12000 | I70: =-IF(I9=1,Assumptions!$E$63,Assumptions!$E$62) -> -12000 | J70: =-IF(J9=1,Assumptions!$E$63,Assumptions!$E$62) -> -12000 | K70: =-IF(K9=1,Assumptions!$E$63,Assumptions!$E$62) -> -30000 | ... AM70: =-IF(AM9=1,Assumptions!$E$63,Assumptions!$E$62) -> -30000
A71: Site & portal build (one-time) | B71: $ | C71: =SUM(D71:AM71) -> -240000 | D71: =-IF(D$3<=4,Assumptions!$E$64,0) -> -60000 | E71: =-IF(E$3<=4,Assumptions!$E$64,0) -> -60000 | F71: =-IF(F$3<=4,Assumptions!$E$64,0) -> -60000 | G71: =-IF(G$3<=4,Assumptions!$E$64,0) -> -60000 | H71: =-IF(H$3<=4,Assumptions!$E$64,0) -> 0 | I71: =-IF(I$3<=4,Assumptions!$E$64,0) -> 0 | J71: =-IF(J$3<=4,Assumptions!$E$64,0) -> 0 | K71: =-IF(K$3<=4,Assumptions!$E$64,0) -> 0 | ... AM71: =-IF(AM$3<=4,Assumptions!$E$64,0) -> 0
A72: Legal, regulatory & compliance | B72: $ | C72: =SUM(D72:AM72) -> -810000 | D72: =-IF(D$3<=3,Assumptions!$E$65,Assumptions!$E$66) -> -50000 | E72: =-IF(E$3<=3,Assumptions!$E$65,Assumptions!$E$66) -> -50000 | F72: =-IF(F$3<=3,Assumptions!$E$65,Assumptions!$E$66) -> -50000 | G72: =-IF(G$3<=3,Assumptions!$E$65,Assumptions!$E$66) -> -20000 | H72: =-IF(H$3<=3,Assumptions!$E$65,Assumptions!$E$66) -> -20000 | I72: =-IF(I$3<=3,Assumptions!$E$65,Assumptions!$E$66) -> -20000 | J72: =-IF(J$3<=3,Assumptions!$E$65,Assumptions!$E$66) -> -20000 | K72: =-IF(K$3<=3,Assumptions!$E$65,Assumptions!$E$66) -> -20000 | ... AM72: =-IF(AM$3<=3,Assumptions!$E$65,Assumptions!$E$66) -> -20000
A73: Insurance | B73: $ | C73: =SUM(D73:AM73) -> -232000 | D73: =-IF(D9=1,Assumptions!$E$67,0) -> 0 | E73: =-IF(E9=1,Assumptions!$E$67,0) -> 0 | F73: =-IF(F9=1,Assumptions!$E$67,0) -> 0 | G73: =-IF(G9=1,Assumptions!$E$67,0) -> 0 | H73: =-IF(H9=1,Assumptions!$E$67,0) -> 0 | I73: =-IF(I9=1,Assumptions!$E$67,0) -> 0 | J73: =-IF(J9=1,Assumptions!$E$67,0) -> 0 | K73: =-IF(K9=1,Assumptions!$E$67,0) -> -8000 | ... AM73: =-IF(AM9=1,Assumptions!$E$67,0) -> -8000
A74: Creative & content production | B74: $ | C74: =SUM(D74:AM74) -> -1335000 | D74: =-IF(D9=1,Assumptions!$E$69,Assumptions!$E$68) -> -25000 | E74: =-IF(E9=1,Assumptions!$E$69,Assumptions!$E$68) -> -25000 | F74: =-IF(F9=1,Assumptions!$E$69,Assumptions!$E$68) -> -25000 | G74: =-IF(G9=1,Assumptions!$E$69,Assumptions!$E$68) -> -25000 | H74: =-IF(H9=1,Assumptions!$E$69,Assumptions!$E$68) -> -25000 | I74: =-IF(I9=1,Assumptions!$E$69,Assumptions!$E$68) -> -25000 | J74: =-IF(J9=1,Assumptions!$E$69,Assumptions!$E$68) -> -25000 | K74: =-IF(K9=1,Assumptions!$E$69,Assumptions!$E$68) -> -40000 | ... AM74: =-IF(AM9=1,Assumptions!$E$69,Assumptions!$E$68) -> -40000
A75: Total operating expenses | B75: $ | C75: =SUM(D75:AM75) -> -13051000 | D75: =SUM(D68:D74) -> -227000 | E75: =SUM(E68:E74) -> -227000 | F75: =SUM(F68:F74) -> -227000 | G75: =SUM(G68:G74) -> -257000 | H75: =SUM(H68:H74) -> -197000 | I75: =SUM(I68:I74) -> -197000 | J75: =SUM(J68:J74) -> -197000 | K75: =SUM(K68:K74) -> -298000 | ... AM75: =SUM(AM68:AM74) -> -458000
A76: Profitability and cash
A77: EBITDA / operating profit (loss) | B77: $ | C77: =SUM(D77:AM77) -> 7351793.1 | D77: =D63+D75 -> -247000 | E77: =E63+E75 -> -247000 | F77: =F63+F75 -> -247000 | G77: =G63+G75 -> -277000 | H77: =H63+H75 -> -284112.03 | I77: =I63+I75 -> -273701.37 | J77: =J63+J75 -> -263975.88 | K77: =K63+K75 -> -562066.84 | ... AM77: =AM63+AM75 -> 1231172.7
A78: Working capital investment (non-Rx inventory) | B78: $ | C78: =SUM(D78:AM78) -> -439985.26 | D78: =-Assumptions!$E$80*ABS(D49) -> 0 | E78: =-Assumptions!$E$80*(ABS(E49)-ABS(D49)) -> 0 | F78: =-Assumptions!$E$80*(ABS(F49)-ABS(E49)) -> 0 | G78: =-Assumptions!$E$80*(ABS(G49)-ABS(F49)) -> 0 | H78: =-Assumptions!$E$80*(ABS(H49)-ABS(G49)) -> -15502.95 | I78: =-Assumptions!$E$80*(ABS(I49)-ABS(H49)) -> -2472.2955 | J78: =-Assumptions!$E$80*(ABS(J49)-ABS(I49)) -> -2507.5403 | K78: =-Assumptions!$E$80*(ABS(K49)-ABS(J49)) -> -70118.607 | L78: =-Assumptions!$E$80*(ABS(L49)-ABS(K49)) -> 26530.602 | ... AM78: =-Assumptions!$E$80*(ABS(AM49)-ABS(AL49)) -> -22648.555
A79: Net cash flow | B79: $ | C79: =SUM(D79:AM79) -> 6911807.9 | D79: =D77+D78 -> -247000 | E79: =E77+E78 -> -247000 | F79: =F77+F78 -> -247000 | G79: =G77+G78 -> -277000 | H79: =H77+H78 -> -299614.98 | I79: =I77+I78 -> -276173.66 | J79: =J77+J78 -> -266483.42 | K79: =K77+K78 -> -632185.45 | ... AM79: =AM77+AM78 -> 1208524.1
A80: Cumulative cash flow | B80: $ | D80: =D79 -> -247000 | E80: =D80+E79 -> -494000 | F80: =E80+F79 -> -741000 | G80: =F80+G79 -> -1018000 | H80: =G80+H79 -> -1317615 | I80: =H80+I79 -> -1593788.6 | J80: =I80+J79 -> -1860272.1 | K80: =J80+K79 -> -2492457.5 | L80: =K80+L79 -> -2786328.3 | ... AM80: =AL80+AM79 -> 6911807.9
A81: Cash balance (opening cash + cumulative) | B81: $ | D81: =Assumptions!$E$81+D80 -> -247000 | E81: =Assumptions!$E$81+E80 -> -494000 | F81: =Assumptions!$E$81+F80 -> -741000 | G81: =Assumptions!$E$81+G80 -> -1018000 | H81: =Assumptions!$E$81+H80 -> -1317615 | I81: =Assumptions!$E$81+I80 -> -1593788.6 | J81: =Assumptions!$E$81+J80 -> -1860272.1 | K81: =Assumptions!$E$81+K80 -> -2492457.5 | ... AM81: =Assumptions!$E$81+AM80 -> 6911807.9
A82: Break-even helper (month # if EBITDA > 0, else 999) | B82: # | D82: =IF(D77>0,D$3,999) -> 999 | E82: =IF(E77>0,E$3,999) -> 999 | F82: =IF(F77>0,F$3,999) -> 999 | G82: =IF(G77>0,G$3,999) -> 999 | H82: =IF(H77>0,H$3,999) -> 999 | I82: =IF(I77>0,I$3,999) -> 999 | J82: =IF(J77>0,J$3,999) -> 999 | K82: =IF(K77>0,K$3,999) -> 999 | ... AM82: =IF(AM77>0,AM$3,999) -> 36
A83: Unit economics (steady-state view, per active Rx member)
A84: Revenue per active Rx member-month | B84: $ | D84: =IF(D24=0,0,(D36)/D24) -> 0 | E84: =IF(E24=0,0,(E36)/E24) -> 0 | F84: =IF(F24=0,0,(F36)/F24) -> 0 | G84: =IF(G24=0,0,(G36)/G24) -> 0 | H84: =IF(H24=0,0,(H36)/H24) -> 275 | I84: =IF(I24=0,0,(I36)/I24) -> 275 | J84: =IF(J24=0,0,(J36)/J24) -> 275 | K84: =IF(K24=0,0,(K36)/K24) -> 275 | ... AM84: =IF(AM24=0,0,(AM36)/AM24) -> 275
A85: Contribution per Rx member-month before acquisition | B85: $ | D85: =Assumptions!$E$30*(1-Assumptions!$E$50-Assumptions!$E$49)-Assumptions!$E$44-Assumptions!$E$46-Assumptions!$E$47-Assumptions!$E$51 -> 134.4 | E85: =Assumptions!$E$30*(1-Assumptions!$E$50-Assumptions!$E$49)-Assumptions!$E$44-Assumptions!$E$46-Assumptions!$E$47-Assumptions!$E$51 -> 134.4 | F85: =Assumptions!$E$30*(1-Assumptions!$E$50-Assumptions!$E$49)-Assumptions!$E$44-Assumptions!$E$46-Assumptions!$E$47-Assumptions!$E$51 -> 134.4 | G85: =Assumptions!$E$30*(1-Assumptions!$E$50-Assumptions!$E$49)-Assumptions!$E$44-Assumptions!$E$46-Assumptions!$E$47-Assumptions!$E$51 -> 134.4 | H85: =Assumptions!$E$30*(1-Assumptions!$E$50-Assumptions!$E$49)-Assumptions!$E$44-Assumptions!$E$46-Assumptions!$E$47-Assumptions!$E$51 -> 134.4 | I85: =Assumptions!$E$30*(1-Assumptions!$E$50-Assumptions!$E$49)-Assumptions!$E$44-Assumptions!$E$46-Assumptions!$E$47-Assumptions!$E$51 -> 134.4 | J85: =Assumptions!$E$30*(1-Assumptions!$E$50-Assumptions!$E$49)-Assumptions!$E$44-Assumptions!$E$46-Assumptions!$E$47-Assumptions!$E$51 -> 134.4 | K85: =Assumptions!$E$30*(1-Assumptions!$E$50-Assumptions!$E$49)-Assumptions!$E$44-Assumptions!$E$46-Assumptions!$E$47-Assumptions!$E$51 -> 134.4 | ... AM85: =Assumptions!$E$30*(1-Assumptions!$E$50-Assumptions!$E$49)-Assumptions!$E$44-Assumptions!$E$46-Assumptions!$E$47-Assumptions!$E$51 -> 134.4
A86: LTV (contribution-based) = contribution / churn | B86: $ | D86: =D85/Assumptions!$E$41 -> 1221.8182 | E86: =E85/Assumptions!$E$41 -> 1221.8182 | F86: =F85/Assumptions!$E$41 -> 1221.8182 | G86: =G85/Assumptions!$E$41 -> 1221.8182 | H86: =H85/Assumptions!$E$41 -> 1221.8182 | I86: =I85/Assumptions!$E$41 -> 1221.8182 | J86: =J85/Assumptions!$E$41 -> 1221.8182 | K86: =K85/Assumptions!$E$41 -> 1221.8182 | ... AM86: =AM85/Assumptions!$E$41 -> 1221.8182
A87: LTV : CAC (Rx) | B87: x | D87: =IF(D66=0,0,D86/D66) -> 0 | E87: =IF(E66=0,0,E86/E66) -> 0 | F87: =IF(F66=0,0,F86/F66) -> 0 | G87: =IF(G66=0,0,G86/G66) -> 0 | H87: =IF(H66=0,0,H86/H66) -> 0.73581483 | I87: =IF(I66=0,0,I86/I66) -> 0.7427849 | J87: =IF(J66=0,0,J86/J66) -> 0.75038227 | K87: =IF(K66=0,0,K86/K66) -> 1.3759095 | ... AM87: =IF(AM66=0,0,AM86/AM66) -> 4.6476355
A88: CAC payback (months) | B88: months | D88: =IF(D85<=0,0,D66/D85) -> 0 | E88: =IF(E85<=0,0,E66/E85) -> 0 | F88: =IF(F85<=0,0,F66/F85) -> 0 | G88: =IF(G85<=0,0,G66/G85) -> 0 | H88: =IF(H85<=0,0,H66/H85) -> 12.354887 | I88: =IF(I85<=0,0,I66/I85) -> 12.238952 | J88: =IF(J85<=0,0,J66/J85) -> 12.115037 | K88: =IF(K85<=0,0,K66/K85) -> 6.6072 | ... AM88: =IF(AM85<=0,0,AM66/AM85) -> 1.9560288
A89: Net revenue per active customer (Rx + membership) | B89: $ | D89: =IF((D24+D29)=0,0,D43/(D24+D29)) -> 0 | E89: =IF((E24+E29)=0,0,E43/(E24+E29)) -> 0 | F89: =IF((F24+F29)=0,0,F43/(F24+F29)) -> 0 | G89: =IF((G24+G29)=0,0,G43/(G24+G29)) -> 0 | H89: =IF((H24+H29)=0,0,H43/(H24+H29)) -> 290.13362 | I89: =IF((I24+I29)=0,0,I43/(I24+I29)) -> 199.45341 | J89: =IF((J24+J29)=0,0,J43/(J24+J29)) -> 169.01642 | K89: =IF((K24+K29)=0,0,K43/(K24+K29)) -> 303.5194 | ... AM89: =IF((AM24+AM29)=0,0,AM43/(AM24+AM29)) -> 232.11902

Sheet Model_Upside
A1: Reserve Clinic monthly model — Upside scenario (all cells are formulas driven by the Assumptions sheet)
A2: Units: $ unless noted. Month 1 = start of Phase 0. Prescription programs run through an affiliated medical practice and licensed pharmacies; revenue recognition and merchant-of-record structure subject to counsel.
A3: Line | B3: Unit | C3: 36-mo total | D3: 1 | E3: 2 | F3: 3 | G3: 4 | H3: 5 | I3: 6 | J3: 7 | K3: 8 | L3: 9 | M3: 10 | N3: 11 | O3: 12 | P3: 13 | Q3: 14 | R3: 15 | S3: 16 | T3: 17 | U3: 18 | V3: 19 | W3: 20 | X3: 21 | Y3: 22 | Z3: 23 | AA3: 24 | AB3: 25 | AC3: 26 | AD3: 27 | AE3: 28 | AF3: 29 | AG3: 30 | AH3: 31 | AI3: 32 | AJ3: 33 | AK3: 34 | AL3: 35 | AM3: 36
A4: Timing & coverage
A5: Model month | B5: # | D5: =D$3 -> 1 | E5: =E$3 -> 2 | F5: =F$3 -> 3 | G5: =G$3 -> 4 | H5: =H$3 -> 5 | I5: =I$3 -> 6 | J5: =J$3 -> 7 | K5: =K$3 -> 8 | ... AM5: =AM$3 -> 36
A6: Pre-beta phase flag | B6: flag | D6: =IF(D$3<Assumptions!$F$7,1,0) -> 1 | E6: =IF(E$3<Assumptions!$F$7,1,0) -> 1 | F6: =IF(F$3<Assumptions!$F$7,1,0) -> 1 | G6: =IF(G$3<Assumptions!$F$7,1,0) -> 1 | H6: =IF(H$3<Assumptions!$F$7,1,0) -> 0 | I6: =IF(I$3<Assumptions!$F$7,1,0) -> 0 | J6: =IF(J$3<Assumptions!$F$7,1,0) -> 0 | K6: =IF(K$3<Assumptions!$F$7,1,0) -> 0 | ... AM6: =IF(AM$3<Assumptions!$F$7,1,0) -> 0
A7: Beta/waitlist phase flag | B7: flag | D7: =IF(AND(D$3>=Assumptions!$F$7,D$3<Assumptions!$F$6),1,0) -> 0 | E7: =IF(AND(E$3>=Assumptions!$F$7,E$3<Assumptions!$F$6),1,0) -> 0 | F7: =IF(AND(F$3>=Assumptions!$F$7,F$3<Assumptions!$F$6),1,0) -> 0 | G7: =IF(AND(G$3>=Assumptions!$F$7,G$3<Assumptions!$F$6),1,0) -> 0 | H7: =IF(AND(H$3>=Assumptions!$F$7,H$3<Assumptions!$F$6),1,0) -> 1 | I7: =IF(AND(I$3>=Assumptions!$F$7,I$3<Assumptions!$F$6),1,0) -> 1 | J7: =IF(AND(J$3>=Assumptions!$F$7,J$3<Assumptions!$F$6),1,0) -> 0 | K7: =IF(AND(K$3>=Assumptions!$F$7,K$3<Assumptions!$F$6),1,0) -> 0 | ... AM7: =IF(AND(AM$3>=Assumptions!$F$7,AM$3<Assumptions!$F$6),1,0) -> 0
A8: Launch month flag | B8: flag | D8: =IF(D$3=Assumptions!$F$6,1,0) -> 0 | E8: =IF(E$3=Assumptions!$F$6,1,0) -> 0 | F8: =IF(F$3=Assumptions!$F$6,1,0) -> 0 | G8: =IF(G$3=Assumptions!$F$6,1,0) -> 0 | H8: =IF(H$3=Assumptions!$F$6,1,0) -> 0 | I8: =IF(I$3=Assumptions!$F$6,1,0) -> 0 | J8: =IF(J$3=Assumptions!$F$6,1,0) -> 1 | K8: =IF(K$3=Assumptions!$F$6,1,0) -> 0 | ... AM8: =IF(AM$3=Assumptions!$F$6,1,0) -> 0
A9: Post-launch flag (incl. launch month) | B9: flag | D9: =IF(D$3>=Assumptions!$F$6,1,0) -> 0 | E9: =IF(E$3>=Assumptions!$F$6,1,0) -> 0 | F9: =IF(F$3>=Assumptions!$F$6,1,0) -> 0 | G9: =IF(G$3>=Assumptions!$F$6,1,0) -> 0 | H9: =IF(H$3>=Assumptions!$F$6,1,0) -> 0 | I9: =IF(I$3>=Assumptions!$F$6,1,0) -> 0 | J9: =IF(J$3>=Assumptions!$F$6,1,0) -> 1 | K9: =IF(K$3>=Assumptions!$F$6,1,0) -> 1 | ... AM9: =IF(AM$3>=Assumptions!$F$6,1,0) -> 1
A10: Population coverage of served states (Rx) | B10: % | D10: =IF(D$3<Assumptions!$F$7,0,IF(D$3<Assumptions!$F$6,Assumptions!$F$22*0.5,MIN(Assumptions!$F$24,Assumptions!$F$22+Assumptions!$F$23*(D$3-Assumptions!$F$6)))) -> 0 | E10: =IF(E$3<Assumptions!$F$7,0,IF(E$3<Assumptions!$F$6,Assumptions!$F$22*0.5,MIN(Assumptions!$F$24,Assumptions!$F$22+Assumptions!$F$23*(E$3-Assumptions!$F$6)))) -> 0 | F10: =IF(F$3<Assumptions!$F$7,0,IF(F$3<Assumptions!$F$6,Assumptions!$F$22*0.5,MIN(Assumptions!$F$24,Assumptions!$F$22+Assumptions!$F$23*(F$3-Assumptions!$F$6)))) -> 0 | G10: =IF(G$3<Assumptions!$F$7,0,IF(G$3<Assumptions!$F$6,Assumptions!$F$22*0.5,MIN(Assumptions!$F$24,Assumptions!$F$22+Assumptions!$F$23*(G$3-Assumptions!$F$6)))) -> 0 | H10: =IF(H$3<Assumptions!$F$7,0,IF(H$3<Assumptions!$F$6,Assumptions!$F$22*0.5,MIN(Assumptions!$F$24,Assumptions!$F$22+Assumptions!$F$23*(H$3-Assumptions!$F$6)))) -> 0.225 | I10: =IF(I$3<Assumptions!$F$7,0,IF(I$3<Assumptions!$F$6,Assumptions!$F$22*0.5,MIN(Assumptions!$F$24,Assumptions!$F$22+Assumptions!$F$23*(I$3-Assumptions!$F$6)))) -> 0.225 | J10: =IF(J$3<Assumptions!$F$7,0,IF(J$3<Assumptions!$F$6,Assumptions!$F$22*0.5,MIN(Assumptions!$F$24,Assumptions!$F$22+Assumptions!$F$23*(J$3-Assumptions!$F$6)))) -> 0.45 | K10: =IF(K$3<Assumptions!$F$7,0,IF(K$3<Assumptions!$F$6,Assumptions!$F$22*0.5,MIN(Assumptions!$F$24,Assumptions!$F$22+Assumptions!$F$23*(K$3-Assumptions!$F$6)))) -> 0.485 | ... AM10: =IF(AM$3<Assumptions!$F$7,0,IF(AM$3<Assumptions!$F$6,Assumptions!$F$22*0.5,MIN(Assumptions!$F$24,Assumptions!$F$22+Assumptions!$F$23*(AM$3-Assumptions!$F$6)))) -> 0.9
A11: Traffic
A12: Paid media spend | B12: $ | C12: =SUM(D12:AM12) -> 14061572 | D12: =IF(D$3<Assumptions!$F$7,Assumptions!$F$13,IF(D$3<Assumptions!$F$6,Assumptions!$F$14,IF(D$3=Assumptions!$F$6,Assumptions!$F$15,Assumptions!$F$16*(1+Assumptions!$F$17)^(D$3-Assumptions!$F$6-1)))) -> 30000 | E12: =IF(E$3<Assumptions!$F$7,Assumptions!$F$13,IF(E$3<Assumptions!$F$6,Assumptions!$F$14,IF(E$3=Assumptions!$F$6,Assumptions!$F$15,Assumptions!$F$16*(1+Assumptions!$F$17)^(E$3-Assumptions!$F$6-1)))) -> 30000 | F12: =IF(F$3<Assumptions!$F$7,Assumptions!$F$13,IF(F$3<Assumptions!$F$6,Assumptions!$F$14,IF(F$3=Assumptions!$F$6,Assumptions!$F$15,Assumptions!$F$16*(1+Assumptions!$F$17)^(F$3-Assumptions!$F$6-1)))) -> 30000 | G12: =IF(G$3<Assumptions!$F$7,Assumptions!$F$13,IF(G$3<Assumptions!$F$6,Assumptions!$F$14,IF(G$3=Assumptions!$F$6,Assumptions!$F$15,Assumptions!$F$16*(1+Assumptions!$F$17)^(G$3-Assumptions!$F$6-1)))) -> 30000 | H12: =IF(H$3<Assumptions!$F$7,Assumptions!$F$13,IF(H$3<Assumptions!$F$6,Assumptions!$F$14,IF(H$3=Assumptions!$F$6,Assumptions!$F$15,Assumptions!$F$16*(1+Assumptions!$F$17)^(H$3-Assumptions!$F$6-1)))) -> 100000 | I12: =IF(I$3<Assumptions!$F$7,Assumptions!$F$13,IF(I$3<Assumptions!$F$6,Assumptions!$F$14,IF(I$3=Assumptions!$F$6,Assumptions!$F$15,Assumptions!$F$16*(1+Assumptions!$F$17)^(I$3-Assumptions!$F$6-1)))) -> 100000 | J12: =IF(J$3<Assumptions!$F$7,Assumptions!$F$13,IF(J$3<Assumptions!$F$6,Assumptions!$F$14,IF(J$3=Assumptions!$F$6,Assumptions!$F$15,Assumptions!$F$16*(1+Assumptions!$F$17)^(J$3-Assumptions!$F$6-1)))) -> 500000 | K12: =IF(K$3<Assumptions!$F$7,Assumptions!$F$13,IF(K$3<Assumptions!$F$6,Assumptions!$F$14,IF(K$3=Assumptions!$F$6,Assumptions!$F$15,Assumptions!$F$16*(1+Assumptions!$F$17)^(K$3-Assumptions!$F$6-1)))) -> 250000 | ... AM12: =IF(AM$3<Assumptions!$F$7,Assumptions!$F$13,IF(AM$3<Assumptions!$F$6,Assumptions!$F$14,IF(AM$3=Assumptions!$F$6,Assumptions!$F$15,Assumptions!$F$16*(1+Assumptions!$F$17)^(AM$3-Assumptions!$F$6-1)))) -> 749675.83
A13: Paid sessions | B13: sessions | C13: =SUM(D13:AM13) -> 7811984.2 | D13: =D12/Assumptions!$F$12 -> 16666.667 | E13: =E12/Assumptions!$F$12 -> 16666.667 | F13: =F12/Assumptions!$F$12 -> 16666.667 | G13: =G12/Assumptions!$F$12 -> 16666.667 | H13: =H12/Assumptions!$F$12 -> 55555.556 | I13: =I12/Assumptions!$F$12 -> 55555.556 | J13: =J12/Assumptions!$F$12 -> 277777.78 | K13: =K12/Assumptions!$F$12 -> 138888.89 | ... AM13: =AM12/Assumptions!$F$12 -> 416486.57
A14: Organic + direct sessions | B14: sessions | C14: =SUM(D14:AM14) -> 1967359.5 | D14: =MIN(Assumptions!$F$11,Assumptions!$F$9*(1+Assumptions!$F$10)^(D$3-1))*IF(AND(D9=1,Assumptions!$F$74=1),Assumptions!$F$78,1) -> 4000 | E14: =MIN(Assumptions!$F$11,Assumptions!$F$9*(1+Assumptions!$F$10)^(E$3-1))*IF(AND(E9=1,Assumptions!$F$74=1),Assumptions!$F$78,1) -> 4440 | F14: =MIN(Assumptions!$F$11,Assumptions!$F$9*(1+Assumptions!$F$10)^(F$3-1))*IF(AND(F9=1,Assumptions!$F$74=1),Assumptions!$F$78,1) -> 4928.4 | G14: =MIN(Assumptions!$F$11,Assumptions!$F$9*(1+Assumptions!$F$10)^(G$3-1))*IF(AND(G9=1,Assumptions!$F$74=1),Assumptions!$F$78,1) -> 5470.524 | H14: =MIN(Assumptions!$F$11,Assumptions!$F$9*(1+Assumptions!$F$10)^(H$3-1))*IF(AND(H9=1,Assumptions!$F$74=1),Assumptions!$F$78,1) -> 6072.2816 | I14: =MIN(Assumptions!$F$11,Assumptions!$F$9*(1+Assumptions!$F$10)^(I$3-1))*IF(AND(I9=1,Assumptions!$F$74=1),Assumptions!$F$78,1) -> 6740.2326 | J14: =MIN(Assumptions!$F$11,Assumptions!$F$9*(1+Assumptions!$F$10)^(J$3-1))*IF(AND(J9=1,Assumptions!$F$74=1),Assumptions!$F$78,1) -> 9726.1557 | K14: =MIN(Assumptions!$F$11,Assumptions!$F$9*(1+Assumptions!$F$10)^(K$3-1))*IF(AND(K9=1,Assumptions!$F$74=1),Assumptions!$F$78,1) -> 10796.033 | ... AM14: =MIN(Assumptions!$F$11,Assumptions!$F$9*(1+Assumptions!$F$10)^(AM$3-1))*IF(AND(AM9=1,Assumptions!$F$74=1),Assumptions!$F$78,1) -> 200589.23
A15: Total sessions | B15: sessions | C15: =SUM(D15:AM15) -> 9779343.7 | D15: =D13+D14 -> 20666.667 | E15: =E13+E14 -> 21106.667 | F15: =F13+F14 -> 21595.067 | G15: =G13+G14 -> 22137.191 | H15: =H13+H14 -> 61627.837 | I15: =I13+I14 -> 62295.788 | J15: =J13+J14 -> 287503.93 | K15: =K13+K14 -> 149684.92 | ... AM15: =AM13+AM14 -> 617075.8
A16: Prescription-program funnel (clinical decisions are independent; rates are monitored, not targeted)
A17: Eligibility quiz starts | B17: # | C17: =SUM(D17:AM17) -> 1163260.6 | D17: =D15*Assumptions!$F$19*IF(D$3<Assumptions!$F$7,0,1) -> 0 | E17: =E15*Assumptions!$F$19*IF(E$3<Assumptions!$F$7,0,1) -> 0 | F17: =F15*Assumptions!$F$19*IF(F$3<Assumptions!$F$7,0,1) -> 0 | G17: =G15*Assumptions!$F$19*IF(G$3<Assumptions!$F$7,0,1) -> 0 | H17: =H15*Assumptions!$F$19*IF(H$3<Assumptions!$F$7,0,1) -> 7395.3405 | I17: =I15*Assumptions!$F$19*IF(I$3<Assumptions!$F$7,0,1) -> 7475.4946 | J17: =J15*Assumptions!$F$19*IF(J$3<Assumptions!$F$7,0,1) -> 34500.472 | K17: =K15*Assumptions!$F$19*IF(K$3<Assumptions!$F$7,0,1) -> 17962.191 | ... AM17: =AM15*Assumptions!$F$19*IF(AM$3<Assumptions!$F$7,0,1) -> 74049.096
A18: Quiz completions | B18: # | C18: =SUM(D18:AM18) -> 872445.43 | D18: =D17*Assumptions!$F$20 -> 0 | E18: =E17*Assumptions!$F$20 -> 0 | F18: =F17*Assumptions!$F$20 -> 0 | G18: =G17*Assumptions!$F$20 -> 0 | H18: =H17*Assumptions!$F$20 -> 5546.5053 | I18: =I17*Assumptions!$F$20 -> 5606.6209 | J18: =J17*Assumptions!$F$20 -> 25875.354 | K18: =K17*Assumptions!$F$20 -> 13471.643 | ... AM18: =AM17*Assumptions!$F$20 -> 55536.822
A19: Eligible outcomes (screen + state) | B19: # | C19: =SUM(D19:AM19) -> 470161.28 | D19: =D18*Assumptions!$F$21*D10 -> 0 | E19: =E18*Assumptions!$F$21*E10 -> 0 | F19: =F18*Assumptions!$F$21*F10 -> 0 | G19: =G18*Assumptions!$F$21*G10 -> 0 | H19: =H18*Assumptions!$F$21*H10 -> 811.17641 | I19: =I18*Assumptions!$F$21*I10 -> 819.96831 | J19: =J18*Assumptions!$F$21*J10 -> 7568.541 | K19: =K18*Assumptions!$F$21*K10 -> 4246.9354 | ... AM19: =AM18*Assumptions!$F$21*AM10 -> 32489.041
A20: Intakes submitted (consult fee charged) | B20: # | C20: =SUM(D20:AM20) -> 282096.77 | D20: =D19*Assumptions!$F$25 -> 0 | E20: =E19*Assumptions!$F$25 -> 0 | F20: =F19*Assumptions!$F$25 -> 0 | G20: =G19*Assumptions!$F$25 -> 0 | H20: =H19*Assumptions!$F$25 -> 486.70584 | I20: =I19*Assumptions!$F$25 -> 491.98099 | J20: =J19*Assumptions!$F$25 -> 4541.1246 | K20: =K19*Assumptions!$F$25 -> 2548.1613 | ... AM20: =AM19*Assumptions!$F$25 -> 19493.424
A21: Consults completed | B21: # | C21: =SUM(D21:AM21) -> 248245.15 | D21: =D20*Assumptions!$F$26 -> 0 | E21: =E20*Assumptions!$F$26 -> 0 | F21: =F20*Assumptions!$F$26 -> 0 | G21: =G20*Assumptions!$F$26 -> 0 | H21: =H20*Assumptions!$F$26 -> 428.30114 | I21: =I20*Assumptions!$F$26 -> 432.94327 | J21: =J20*Assumptions!$F$26 -> 3996.1897 | K21: =K20*Assumptions!$F$26 -> 2242.3819 | ... AM21: =AM20*Assumptions!$F$26 -> 17154.214
A22: Prescriptions issued (clinician decision) | B22: # | C22: =SUM(D22:AM22) -> 168806.7 | D22: =D21*Assumptions!$F$27 -> 0 | E22: =E21*Assumptions!$F$27 -> 0 | F22: =F21*Assumptions!$F$27 -> 0 | G22: =G21*Assumptions!$F$27 -> 0 | H22: =H21*Assumptions!$F$27 -> 291.24478 | I22: =I21*Assumptions!$F$27 -> 294.40142 | J22: =J21*Assumptions!$F$27 -> 2717.409 | K22: =K21*Assumptions!$F$27 -> 1524.8197 | ... AM22: =AM21*Assumptions!$F$27 -> 11664.865
A23: New paying Rx program members | B23: # | C23: =SUM(D23:AM23) -> 114788.56 | D23: =D22*Assumptions!$F$28 -> 0 | E23: =E22*Assumptions!$F$28 -> 0 | F23: =F22*Assumptions!$F$28 -> 0 | G23: =G22*Assumptions!$F$28 -> 0 | H23: =H22*Assumptions!$F$28 -> 198.04645 | I23: =I22*Assumptions!$F$28 -> 200.19297 | J23: =J22*Assumptions!$F$28 -> 1847.8381 | K23: =K22*Assumptions!$F$28 -> 1036.8774 | ... AM23: =AM22*Assumptions!$F$28 -> 7932.1083
A24: Active Rx program members (end of month) | B24: # | D24: =D23 -> 0 | E24: =D24*(1-Assumptions!$F$41)+E23 -> 0 | F24: =E24*(1-Assumptions!$F$41)+F23 -> 0 | G24: =F24*(1-Assumptions!$F$41)+G23 -> 0 | H24: =G24*(1-Assumptions!$F$41)+H23 -> 198.04645 | I24: =H24*(1-Assumptions!$F$41)+I23 -> 378.43477 | J24: =I24*(1-Assumptions!$F$41)+J23 -> 2188.4294 | K24: =J24*(1-Assumptions!$F$41)+K23 -> 3006.4639 | L24: =K24*(1-Assumptions!$F$41)+L23 -> 3867.6019 | ... AM24: =AL24*(1-Assumptions!$F$41)+AM23 -> 52299.684
A25: Rx members churned | B25: # | C25: =SUM(D25:AM25) -> 62488.875 | D25: =0 -> 0 | E25: =D24*Assumptions!$F$41 -> 0 | F25: =E24*Assumptions!$F$41 -> 0 | G25: =F24*Assumptions!$F$41 -> 0 | H25: =G24*Assumptions!$F$41 -> 0 | I25: =H24*Assumptions!$F$41 -> 19.804645 | J25: =I24*Assumptions!$F$41 -> 37.843477 | K25: =J24*Assumptions!$F$41 -> 218.84294 | L25: =K24*Assumptions!$F$41 -> 300.64639 | ... AM25: =AL24*Assumptions!$F$41 -> 4929.7306
A26: Lab panels ordered | B26: # | C26: =SUM(D26:AM26) -> 169258.06 | D26: =D20*Assumptions!$F$32 -> 0 | E26: =E20*Assumptions!$F$32 -> 0 | F26: =F20*Assumptions!$F$32 -> 0 | G26: =G20*Assumptions!$F$32 -> 0 | H26: =H20*Assumptions!$F$32 -> 292.02351 | I26: =I20*Assumptions!$F$32 -> 295.18859 | J26: =J20*Assumptions!$F$32 -> 2724.6748 | K26: =K20*Assumptions!$F$32 -> 1528.8968 | ... AM26: =AM20*Assumptions!$F$32 -> 11696.055
A27: Membership and non-prescription commerce
A28: New membership sign-ups | B28: # | C28: =SUM(D28:AM28) -> 46723.489 | D28: =(D18-D19)*Assumptions!$F$35+D15*Assumptions!$F$36*IF(D$3<Assumptions!$F$7,0,1) -> 0 | E28: =(E18-E19)*Assumptions!$F$35+E15*Assumptions!$F$36*IF(E$3<Assumptions!$F$7,0,1) -> 0 | F28: =(F18-F19)*Assumptions!$F$35+F15*Assumptions!$F$36*IF(F$3<Assumptions!$F$7,0,1) -> 0 | G28: =(G18-G19)*Assumptions!$F$35+G15*Assumptions!$F$36*IF(G$3<Assumptions!$F$7,0,1) -> 0 | H28: =(H18-H19)*Assumptions!$F$35+H15*Assumptions!$F$36*IF(H$3<Assumptions!$F$7,0,1) -> 471.26807 | I28: =(I18-I19)*Assumptions!$F$35+I15*Assumptions!$F$36*IF(I$3<Assumptions!$F$7,0,1) -> 476.37589 | J28: =(J18-J19)*Assumptions!$F$35+J15*Assumptions!$F$36*IF(J$3<Assumptions!$F$7,0,1) -> 1895.8009 | K28: =(K18-K19)*Assumptions!$F$35+K15*Assumptions!$F$36*IF(K$3<Assumptions!$F$7,0,1) -> 962.50398 | ... AM28: =(AM18-AM19)*Assumptions!$F$35+AM15*Assumptions!$F$36*IF(AM$3<Assumptions!$F$7,0,1) -> 2769.4362
A29: Active members (end of month) | B29: # | D29: =D28 -> 0 | E29: =D29*(1-Assumptions!$F$42)+E28 -> 0 | F29: =E29*(1-Assumptions!$F$42)+F28 -> 0 | G29: =F29*(1-Assumptions!$F$42)+G28 -> 0 | H29: =G29*(1-Assumptions!$F$42)+H28 -> 471.26807 | I29: =H29*(1-Assumptions!$F$42)+I28 -> 924.08056 | J29: =I29*(1-Assumptions!$F$42)+J28 -> 2773.6775 | K29: =J29*(1-Assumptions!$F$42)+K28 -> 3597.4976 | L29: =K29*(1-Assumptions!$F$42)+L28 -> 4397.8634 | ... AM29: =AL29*(1-Assumptions!$F$42)+AM28 -> 27495.424
A30: Members churned | B30: # | C30: =SUM(D30:AM30) -> 19228.065 | D30: =0 -> 0 | E30: =D29*Assumptions!$F$42 -> 0 | F30: =E29*Assumptions!$F$42 -> 0 | G30: =F29*Assumptions!$F$42 -> 0 | H30: =G29*Assumptions!$F$42 -> 0 | I30: =H29*Assumptions!$F$42 -> 23.563404 | J30: =I29*Assumptions!$F$42 -> 46.204028 | K30: =J29*Assumptions!$F$42 -> 138.68387 | L30: =K29*Assumptions!$F$42 -> 179.87488 | ... AM30: =AL29*Assumptions!$F$42 -> 1301.3678
A31: Non-Rx first orders | B31: # | C31: =SUM(D31:AM31) -> 116326.06 | D31: =D15*Assumptions!$F$37*IF(D$3<Assumptions!$F$7,0,1) -> 0 | E31: =E15*Assumptions!$F$37*IF(E$3<Assumptions!$F$7,0,1) -> 0 | F31: =F15*Assumptions!$F$37*IF(F$3<Assumptions!$F$7,0,1) -> 0 | G31: =G15*Assumptions!$F$37*IF(G$3<Assumptions!$F$7,0,1) -> 0 | H31: =H15*Assumptions!$F$37*IF(H$3<Assumptions!$F$7,0,1) -> 739.53405 | I31: =I15*Assumptions!$F$37*IF(I$3<Assumptions!$F$7,0,1) -> 747.54946 | J31: =J15*Assumptions!$F$37*IF(J$3<Assumptions!$F$7,0,1) -> 3450.0472 | K31: =K15*Assumptions!$F$37*IF(K$3<Assumptions!$F$7,0,1) -> 1796.2191 | ... AM31: =AM15*Assumptions!$F$37*IF(AM$3<Assumptions!$F$7,0,1) -> 7404.9096
A32: Cumulative non-Rx customers | B32: # | D32: =D31 -> 0 | E32: =D32+E31 -> 0 | F32: =E32+F31 -> 0 | G32: =F32+G31 -> 0 | H32: =G32+H31 -> 739.53405 | I32: =H32+I31 -> 1487.0835 | J32: =I32+J31 -> 4937.1307 | K32: =J32+K31 -> 6733.3498 | L32: =K32+L31 -> 8610.4863 | ... AM32: =AL32+AM31 -> 116326.06
A33: Non-Rx repeat orders | B33: # | C33: =SUM(D33:AM33) -> 237591.19 | D33: =0 -> 0 | E33: =D32*Assumptions!$F$39 -> 0 | F33: =E32*Assumptions!$F$39 -> 0 | G33: =F32*Assumptions!$F$39 -> 0 | H33: =G32*Assumptions!$F$39 -> 0 | I33: =H32*Assumptions!$F$39 -> 133.11613 | J33: =I32*Assumptions!$F$39 -> 267.67503 | K33: =J32*Assumptions!$F$39 -> 888.68353 | L33: =K32*Assumptions!$F$39 -> 1212.003 | ... AM33: =AL32*Assumptions!$F$39 -> 19605.807
A34: Total non-Rx orders | B34: # | C34: =SUM(D34:AM34) -> 353917.25 | D34: =D31+D33 -> 0 | E34: =E31+E33 -> 0 | F34: =F31+F33 -> 0 | G34: =G31+G33 -> 0 | H34: =H31+H33 -> 739.53405 | I34: =I31+I33 -> 880.66559 | J34: =J31+J33 -> 3717.7222 | K34: =K31+K33 -> 2684.9026 | ... AM34: =AM31+AM33 -> 27010.716
A35: Revenue
A36: Rx program revenue (all-in monthly) | B36: $ | C36: =SUM(D36:AM36) -> 2.0247934e+08 | D36: =D24*Assumptions!$F$30 -> 0 | E36: =E24*Assumptions!$F$30 -> 0 | F36: =F24*Assumptions!$F$30 -> 0 | G36: =G24*Assumptions!$F$30 -> 0 | H36: =H24*Assumptions!$F$30 -> 59215.888 | I36: =I24*Assumptions!$F$30 -> 113152 | J36: =J24*Assumptions!$F$30 -> 654340.39 | K36: =K24*Assumptions!$F$30 -> 898932.69 | ... AM36: =AM24*Assumptions!$F$30 -> 15637605
A37: Consultation revenue | B37: $ | C37: =SUM(D37:AM37) -> 27927580 | D37: =D20*Assumptions!$F$31 -> 0 | E37: =E20*Assumptions!$F$31 -> 0 | F37: =F20*Assumptions!$F$31 -> 0 | G37: =G20*Assumptions!$F$31 -> 0 | H37: =H20*Assumptions!$F$31 -> 48183.879 | I37: =I20*Assumptions!$F$31 -> 48706.118 | J37: =J20*Assumptions!$F$31 -> 449571.34 | K37: =K20*Assumptions!$F$31 -> 252267.97 | ... AM37: =AM20*Assumptions!$F$31 -> 1929849
A38: Lab revenue | B38: $ | C38: =SUM(D38:AM38) -> 23526870 | D38: =D26*Assumptions!$F$33 -> 0 | E38: =E26*Assumptions!$F$33 -> 0 | F38: =F26*Assumptions!$F$33 -> 0 | G38: =G26*Assumptions!$F$33 -> 0 | H38: =H26*Assumptions!$F$33 -> 40591.267 | I38: =I26*Assumptions!$F$33 -> 41031.214 | J38: =J26*Assumptions!$F$33 -> 378729.79 | K38: =K26*Assumptions!$F$33 -> 212516.65 | ... AM38: =AM26*Assumptions!$F$33 -> 1625751.6
A39: Membership revenue | B39: $ | C39: =SUM(D39:AM39) -> 16070212 | D39: =D29*Assumptions!$F$34 -> 0 | E39: =E29*Assumptions!$F$34 -> 0 | F39: =F29*Assumptions!$F$34 -> 0 | G39: =G29*Assumptions!$F$34 -> 0 | H39: =H29*Assumptions!$F$34 -> 18379.455 | I39: =I29*Assumptions!$F$34 -> 36039.142 | J39: =J29*Assumptions!$F$34 -> 108173.42 | K39: =K29*Assumptions!$F$34 -> 140302.41 | ... AM39: =AM29*Assumptions!$F$34 -> 1072321.5
A40: Non-Rx commerce revenue | B40: $ | C40: =SUM(D40:AM40) -> 30082966 | D40: =D34*Assumptions!$F$38 -> 0 | E40: =E34*Assumptions!$F$38 -> 0 | F40: =F34*Assumptions!$F$38 -> 0 | G40: =G34*Assumptions!$F$38 -> 0 | H40: =H34*Assumptions!$F$38 -> 62860.394 | I40: =I34*Assumptions!$F$38 -> 74856.575 | J40: =J34*Assumptions!$F$38 -> 316006.39 | K40: =K34*Assumptions!$F$38 -> 228216.72 | ... AM40: =AM34*Assumptions!$F$38 -> 2295910.9
A41: Gross revenue | B41: $ | C41: =SUM(D41:AM41) -> 3.0008697e+08 | D41: =D36+D37+D38+D39+D40 -> 0 | E41: =E36+E37+E38+E39+E40 -> 0 | F41: =F36+F37+F38+F39+F40 -> 0 | G41: =G36+G37+G38+G39+G40 -> 0 | H41: =H36+H37+H38+H39+H40 -> 229230.88 | I41: =I36+I37+I38+I39+I40 -> 313785.05 | J41: =J36+J37+J38+J39+J40 -> 1906821.3 | K41: =K36+K37+K38+K39+K40 -> 1732236.4 | ... AM41: =AM36+AM37+AM38+AM39+AM40 -> 22561439
A42: Refunds & chargebacks | B42: $ | C42: =SUM(D42:AM42) -> -7502174.3 | D42: =-D41*Assumptions!$F$50 -> 0 | E42: =-E41*Assumptions!$F$50 -> 0 | F42: =-F41*Assumptions!$F$50 -> 0 | G42: =-G41*Assumptions!$F$50 -> 0 | H42: =-H41*Assumptions!$F$50 -> -5730.7721 | I42: =-I41*Assumptions!$F$50 -> -7844.6261 | J42: =-J41*Assumptions!$F$50 -> -47670.533 | K42: =-K41*Assumptions!$F$50 -> -43305.911 | ... AM42: =-AM41*Assumptions!$F$50 -> -564035.96
A43: Net revenue | B43: $ | C43: =SUM(D43:AM43) -> 2.925848e+08 | D43: =D41+D42 -> 0 | E43: =E41+E42 -> 0 | F43: =F41+F42 -> 0 | G43: =G41+G42 -> 0 | H43: =H41+H42 -> 223500.11 | I43: =I41+I42 -> 305940.42 | J43: =J41+J42 -> 1859150.8 | K43: =K41+K42 -> 1688930.5 | ... AM43: =AM41+AM42 -> 21997403
A44: Cost of revenue
A45: Pharmacy / medication | B45: $ | C45: =SUM(D45:AM45) -> -57561017 | D45: =-D24*Assumptions!$F$44 -> 0 | E45: =-E24*Assumptions!$F$44 -> 0 | F45: =-F24*Assumptions!$F$44 -> 0 | G45: =-G24*Assumptions!$F$44 -> 0 | H45: =-H24*Assumptions!$F$44 -> -16833.948 | I45: =-I24*Assumptions!$F$44 -> -32166.956 | J45: =-J24*Assumptions!$F$44 -> -186016.5 | K45: =-K24*Assumptions!$F$44 -> -255549.43 | ... AM45: =-AM24*Assumptions!$F$44 -> -4445473.1
A46: Clinical (consults + monitoring) | B46: $ | C46: =SUM(D46:AM46) -> -13428899 | D46: =-(D21*Assumptions!$F$45+D24*Assumptions!$F$46) -> 0 | E46: =-(E21*Assumptions!$F$45+E24*Assumptions!$F$46) -> 0 | F46: =-(F21*Assumptions!$F$45+F24*Assumptions!$F$46) -> 0 | G46: =-(G21*Assumptions!$F$45+G24*Assumptions!$F$46) -> 0 | H46: =-(H21*Assumptions!$F$45+H24*Assumptions!$F$46) -> -16376.865 | I46: =-(I21*Assumptions!$F$45+I24*Assumptions!$F$46) -> -17802.058 | J46: =-(J21*Assumptions!$F$45+J24*Assumptions!$F$46) -> -155185.64 | K46: =-(K21*Assumptions!$F$45+K24*Assumptions!$F$46) -> -99528.614 | ... AM46: =-(AM21*Assumptions!$F$45+AM24*Assumptions!$F$46) -> -966495.26
A47: Lab costs | B47: $ | C47: =SUM(D47:AM47) -> -12694354 | D47: =-D26*Assumptions!$F$48 -> 0 | E47: =-E26*Assumptions!$F$48 -> 0 | F47: =-F26*Assumptions!$F$48 -> 0 | G47: =-G26*Assumptions!$F$48 -> 0 | H47: =-H26*Assumptions!$F$48 -> -21901.763 | I47: =-I26*Assumptions!$F$48 -> -22139.144 | J47: =-J26*Assumptions!$F$48 -> -204350.61 | K47: =-K26*Assumptions!$F$48 -> -114667.26 | ... AM47: =-AM26*Assumptions!$F$48 -> -877204.1
A48: Rx fulfillment & shipping | B48: $ | C48: =SUM(D48:AM48) -> -8803449.7 | D48: =-D24*Assumptions!$F$47 -> 0 | E48: =-E24*Assumptions!$F$47 -> 0 | F48: =-F24*Assumptions!$F$47 -> 0 | G48: =-G24*Assumptions!$F$47 -> 0 | H48: =-H24*Assumptions!$F$47 -> -2574.6038 | I48: =-I24*Assumptions!$F$47 -> -4919.652 | J48: =-J24*Assumptions!$F$47 -> -28449.582 | K48: =-K24*Assumptions!$F$47 -> -39084.03 | ... AM48: =-AM24*Assumptions!$F$47 -> -679895.89
A49: Non-Rx COGS + fulfillment | B49: $ | C49: =SUM(D49:AM49) -> -12103970 | D49: =-(D40*Assumptions!$F$52+D34*Assumptions!$F$53) -> 0 | E49: =-(E40*Assumptions!$F$52+E34*Assumptions!$F$53) -> 0 | F49: =-(F40*Assumptions!$F$52+F34*Assumptions!$F$53) -> 0 | G49: =-(G40*Assumptions!$F$52+G34*Assumptions!$F$53) -> 0 | H49: =-(H40*Assumptions!$F$52+H34*Assumptions!$F$53) -> -25292.064 | I49: =-(I40*Assumptions!$F$52+I34*Assumptions!$F$53) -> -30118.763 | J49: =-(J40*Assumptions!$F$52+J34*Assumptions!$F$53) -> -127146.1 | K49: =-(K40*Assumptions!$F$52+K34*Assumptions!$F$53) -> -91823.668 | ... AM49: =-(AM40*Assumptions!$F$52+AM34*Assumptions!$F$53) -> -923766.49
A50: Membership delivery | B50: $ | C50: =SUM(D50:AM50) -> -824113.46 | D50: =-D29*Assumptions!$F$54 -> 0 | E50: =-E29*Assumptions!$F$54 -> 0 | F50: =-F29*Assumptions!$F$54 -> 0 | G50: =-G29*Assumptions!$F$54 -> 0 | H50: =-H29*Assumptions!$F$54 -> -942.53614 | I50: =-I29*Assumptions!$F$54 -> -1848.1611 | J50: =-J29*Assumptions!$F$54 -> -5547.3549 | K50: =-K29*Assumptions!$F$54 -> -7194.9952 | ... AM50: =-AM29*Assumptions!$F$54 -> -54990.848
A51: Payment processing | B51: $ | C51: =SUM(D51:AM51) -> -8102348.2 | D51: =-D41*Assumptions!$F$49 -> 0 | E51: =-E41*Assumptions!$F$49 -> 0 | F51: =-F41*Assumptions!$F$49 -> 0 | G51: =-G41*Assumptions!$F$49 -> 0 | H51: =-H41*Assumptions!$F$49 -> -6189.2338 | I51: =-I41*Assumptions!$F$49 -> -8472.1962 | J51: =-J41*Assumptions!$F$49 -> -51484.176 | K51: =-K41*Assumptions!$F$49 -> -46770.384 | ... AM51: =-AM41*Assumptions!$F$49 -> -609158.84
A52: Customer support (variable) | B52: $ | C52: =SUM(D52:AM52) -> -4356980.7 | D52: =-(D24+D29)*Assumptions!$F$51 -> 0 | E52: =-(E24+E29)*Assumptions!$F$51 -> 0 | F52: =-(F24+F29)*Assumptions!$F$51 -> 0 | G52: =-(G24+G29)*Assumptions!$F$51 -> 0 | H52: =-(H24+H29)*Assumptions!$F$51 -> -2677.2581 | I52: =-(I24+I29)*Assumptions!$F$51 -> -5210.0613 | J52: =-(J24+J29)*Assumptions!$F$51 -> -19848.427 | K52: =-(K24+K29)*Assumptions!$F$51 -> -26415.846 | ... AM52: =-(AM24+AM29)*Assumptions!$F$51 -> -319180.43
A53: Total cost of revenue | B53: $ | C53: =SUM(D53:AM53) -> -1.1787513e+08 | D53: =SUM(D45:D52) -> 0 | E53: =SUM(E45:E52) -> 0 | F53: =SUM(F45:F52) -> 0 | G53: =SUM(G45:G52) -> 0 | H53: =SUM(H45:H52) -> -92788.273 | I53: =SUM(I45:I52) -> -122676.99 | J53: =SUM(J45:J52) -> -778028.39 | K53: =SUM(K45:K52) -> -681034.22 | ... AM53: =SUM(AM45:AM52) -> -8876165
A54: Gross profit | B54: $ | C54: =SUM(D54:AM54) -> 1.7470966e+08 | D54: =D43+D53 -> 0 | E54: =E43+E53 -> 0 | F54: =F43+F53 -> 0 | G54: =G43+G53 -> 0 | H54: =H43+H53 -> 130711.84 | I54: =I43+I53 -> 183263.43 | J54: =J43+J53 -> 1081122.4 | K54: =K43+K53 -> 1007896.3 | ... AM54: =AM43+AM53 -> 13121238
A55: Gross margin % | B55: % | D55: =IF(D43=0,0,D54/D43) -> 0 | E55: =IF(E43=0,0,E54/E43) -> 0 | F55: =IF(F43=0,0,F54/F43) -> 0 | G55: =IF(G43=0,0,G54/G43) -> 0 | H55: =IF(H43=0,0,H54/H43) -> 0.58484015 | I55: =IF(I43=0,0,I54/I43) -> 0.59901672 | J55: =IF(J43=0,0,J54/J43) -> 0.5815141 | K55: =IF(K43=0,0,K54/K43) -> 0.59676599 | ... AM55: =IF(AM43=0,0,AM54/AM43) -> 0.59649031
A56: Acquisition and contribution
A57: Paid media | B57: $ | C57: =SUM(D57:AM57) -> -14061572 | D57: =-D12 -> -30000 | E57: =-E12 -> -30000 | F57: =-F12 -> -30000 | G57: =-G12 -> -30000 | H57: =-H12 -> -100000 | I57: =-I12 -> -100000 | J57: =-J12 -> -500000 | K57: =-K12 -> -250000 | ... AM57: =-AM12 -> -749675.83
A58: Influencer & affiliate | B58: $ | C58: =SUM(D58:AM58) -> -3100000 | D58: =-IF(D$3<Assumptions!$F$7,0,IF(D$3<Assumptions!$F$6,Assumptions!$F$71,Assumptions!$F$72)) -> 0 | E58: =-IF(E$3<Assumptions!$F$7,0,IF(E$3<Assumptions!$F$6,Assumptions!$F$71,Assumptions!$F$72)) -> 0 | F58: =-IF(F$3<Assumptions!$F$7,0,IF(F$3<Assumptions!$F$6,Assumptions!$F$71,Assumptions!$F$72)) -> 0 | G58: =-IF(G$3<Assumptions!$F$7,0,IF(G$3<Assumptions!$F$6,Assumptions!$F$71,Assumptions!$F$72)) -> 0 | H58: =-IF(H$3<Assumptions!$F$7,0,IF(H$3<Assumptions!$F$6,Assumptions!$F$71,Assumptions!$F$72)) -> -50000 | I58: =-IF(I$3<Assumptions!$F$7,0,IF(I$3<Assumptions!$F$6,Assumptions!$F$71,Assumptions!$F$72)) -> -50000 | J58: =-IF(J$3<Assumptions!$F$7,0,IF(J$3<Assumptions!$F$6,Assumptions!$F$71,Assumptions!$F$72)) -> -100000 | K58: =-IF(K$3<Assumptions!$F$7,0,IF(K$3<Assumptions!$F$6,Assumptions!$F$71,Assumptions!$F$72)) -> -100000 | ... AM58: =-IF(AM$3<Assumptions!$F$7,0,IF(AM$3<Assumptions!$F$6,Assumptions!$F$71,Assumptions!$F$72)) -> -100000
A59: Launch PR/events (one-time) | B59: $ | C59: =SUM(D59:AM59) -> -120000 | D59: =-D8*Assumptions!$F$70 -> 0 | E59: =-E8*Assumptions!$F$70 -> 0 | F59: =-F8*Assumptions!$F$70 -> 0 | G59: =-G8*Assumptions!$F$70 -> 0 | H59: =-H8*Assumptions!$F$70 -> 0 | I59: =-I8*Assumptions!$F$70 -> 0 | J59: =-J8*Assumptions!$F$70 -> -120000 | K59: =-K8*Assumptions!$F$70 -> 0 | ... AM59: =-AM8*Assumptions!$F$70 -> 0
A60: Brand partner cash retainer (Scenario A only) | B60: $ | C60: =SUM(D60:AM60) -> -1280000 | D60: =-Assumptions!$F$74*IF(D$3<Assumptions!$F$7,0,Assumptions!$F$75) -> 0 | E60: =-Assumptions!$F$74*IF(E$3<Assumptions!$F$7,0,Assumptions!$F$75) -> 0 | F60: =-Assumptions!$F$74*IF(F$3<Assumptions!$F$7,0,Assumptions!$F$75) -> 0 | G60: =-Assumptions!$F$74*IF(G$3<Assumptions!$F$7,0,Assumptions!$F$75) -> 0 | H60: =-Assumptions!$F$74*IF(H$3<Assumptions!$F$7,0,Assumptions!$F$75) -> -40000 | I60: =-Assumptions!$F$74*IF(I$3<Assumptions!$F$7,0,Assumptions!$F$75) -> -40000 | J60: =-Assumptions!$F$74*IF(J$3<Assumptions!$F$7,0,Assumptions!$F$75) -> -40000 | K60: =-Assumptions!$F$74*IF(K$3<Assumptions!$F$7,0,Assumptions!$F$75) -> -40000 | ... AM60: =-Assumptions!$F$74*IF(AM$3<Assumptions!$F$7,0,Assumptions!$F$75) -> -40000
A61: Brand partner royalty (Scenario A only) | B61: $ | C61: =SUM(D61:AM61) -> -8777543.9 | D61: =-Assumptions!$F$74*D43*Assumptions!$F$76 -> 0 | E61: =-Assumptions!$F$74*E43*Assumptions!$F$76 -> 0 | F61: =-Assumptions!$F$74*F43*Assumptions!$F$76 -> 0 | G61: =-Assumptions!$F$74*G43*Assumptions!$F$76 -> 0 | H61: =-Assumptions!$F$74*H43*Assumptions!$F$76 -> -6705.0033 | I61: =-Assumptions!$F$74*I43*Assumptions!$F$76 -> -9178.2126 | J61: =-Assumptions!$F$74*J43*Assumptions!$F$76 -> -55774.524 | K61: =-Assumptions!$F$74*K43*Assumptions!$F$76 -> -50667.916 | ... AM61: =-Assumptions!$F$74*AM43*Assumptions!$F$76 -> -659922.08
A62: Total acquisition & partner cost | B62: $ | C62: =SUM(D62:AM62) -> -27339115 | D62: =SUM(D57:D61) -> -30000 | E62: =SUM(E57:E61) -> -30000 | F62: =SUM(F57:F61) -> -30000 | G62: =SUM(G57:G61) -> -30000 | H62: =SUM(H57:H61) -> -196705 | I62: =SUM(I57:I61) -> -199178.21 | J62: =SUM(J57:J61) -> -815774.52 | K62: =SUM(K57:K61) -> -440667.92 | ... AM62: =SUM(AM57:AM61) -> -1549597.9
A63: Contribution margin | B63: $ | C63: =SUM(D63:AM63) -> 1.4737055e+08 | D63: =D54+D62 -> -30000 | E63: =E54+E62 -> -30000 | F63: =F54+F62 -> -30000 | G63: =G54+G62 -> -30000 | H63: =H54+H62 -> -65993.165 | I63: =I54+I62 -> -15914.785 | J63: =J54+J62 -> 265347.88 | K63: =K54+K62 -> 567228.38 | ... AM63: =AM54+AM62 -> 11571640
A64: New paying customers (Rx + members + first shop orders) | B64: # | C64: =SUM(D64:AM64) -> 277838.11 | D64: =D23+D28+D31 -> 0 | E64: =E23+E28+E31 -> 0 | F64: =F23+F28+F31 -> 0 | G64: =G23+G28+G31 -> 0 | H64: =H23+H28+H31 -> 1408.8486 | I64: =I23+I28+I31 -> 1424.1183 | J64: =J23+J28+J31 -> 7193.6862 | K64: =K23+K28+K31 -> 3795.6004 | ... AM64: =AM23+AM28+AM31 -> 18106.454
A65: Blended CAC (acquisition cost / new paying customers) | B65: $ | D65: =IF(D64=0,0,-(D57+D58+D59)/D64) -> 0 | E65: =IF(E64=0,0,-(E57+E58+E59)/E64) -> 0 | F65: =IF(F64=0,0,-(F57+F58+F59)/F64) -> 0 | G65: =IF(G64=0,0,-(G57+G58+G59)/G64) -> 0 | H65: =IF(H64=0,0,-(H57+H58+H59)/H64) -> 106.46992 | I65: =IF(I64=0,0,-(I57+I58+I59)/I64) -> 105.32833 | J65: =IF(J64=0,0,-(J57+J58+J59)/J64) -> 100.08777 | K65: =IF(K64=0,0,-(K57+K58+K59)/K64) -> 92.212024 | ... AM65: =IF(AM64=0,0,-(AM57+AM58+AM59)/AM64) -> 46.926683
A66: CAC per new Rx member (all acquisition cost allocated to Rx) | B66: $ | D66: =IF(D23=0,0,-(D57+D58+D59)/D23) -> 0 | E66: =IF(E23=0,0,-(E57+E58+E59)/E23) -> 0 | F66: =IF(F23=0,0,-(F57+F58+F59)/F23) -> 0 | G66: =IF(G23=0,0,-(G57+G58+G59)/G23) -> 0 | H66: =IF(H23=0,0,-(H57+H58+H59)/H23) -> 757.39808 | I66: =IF(I23=0,0,-(I57+I58+I59)/I23) -> 749.27707 | J66: =IF(J23=0,0,-(J57+J58+J59)/J23) -> 389.64452 | K66: =IF(K23=0,0,-(K57+K58+K59)/K23) -> 337.55196 | ... AM66: =IF(AM23=0,0,-(AM57+AM58+AM59)/AM23) -> 107.11854
A67: Operating expenses
A68: Team (fully loaded) | B68: $ | C68: =SUM(D68:AM68) -> -11640000 | D68: =-IF(D$3<=3,Assumptions!$F$56,IF(D$3<Assumptions!$F$6,Assumptions!$F$57,IF(D$3<=12,Assumptions!$F$58,IF(D$3<=24,Assumptions!$F$59,Assumptions!$F$60)))) -> -80000 | E68: =-IF(E$3<=3,Assumptions!$F$56,IF(E$3<Assumptions!$F$6,Assumptions!$F$57,IF(E$3<=12,Assumptions!$F$58,IF(E$3<=24,Assumptions!$F$59,Assumptions!$F$60)))) -> -80000 | F68: =-IF(F$3<=3,Assumptions!$F$56,IF(F$3<Assumptions!$F$6,Assumptions!$F$57,IF(F$3<=12,Assumptions!$F$58,IF(F$3<=24,Assumptions!$F$59,Assumptions!$F$60)))) -> -80000 | G68: =-IF(G$3<=3,Assumptions!$F$56,IF(G$3<Assumptions!$F$6,Assumptions!$F$57,IF(G$3<=12,Assumptions!$F$58,IF(G$3<=24,Assumptions!$F$59,Assumptions!$F$60)))) -> -160000 | H68: =-IF(H$3<=3,Assumptions!$F$56,IF(H$3<Assumptions!$F$6,Assumptions!$F$57,IF(H$3<=12,Assumptions!$F$58,IF(H$3<=24,Assumptions!$F$59,Assumptions!$F$60)))) -> -160000 | I68: =-IF(I$3<=3,Assumptions!$F$56,IF(I$3<Assumptions!$F$6,Assumptions!$F$57,IF(I$3<=12,Assumptions!$F$58,IF(I$3<=24,Assumptions!$F$59,Assumptions!$F$60)))) -> -160000 | J68: =-IF(J$3<=3,Assumptions!$F$56,IF(J$3<Assumptions!$F$6,Assumptions!$F$57,IF(J$3<=12,Assumptions!$F$58,IF(J$3<=24,Assumptions!$F$59,Assumptions!$F$60)))) -> -240000 | K68: =-IF(K$3<=3,Assumptions!$F$56,IF(K$3<Assumptions!$F$6,Assumptions!$F$57,IF(K$3<=12,Assumptions!$F$58,IF(K$3<=24,Assumptions!$F$59,Assumptions!$F$60)))) -> -240000 | ... AM68: =-IF(AM$3<=3,Assumptions!$F$56,IF(AM$3<Assumptions!$F$6,Assumptions!$F$57,IF(AM$3<=12,Assumptions!$F$58,IF(AM$3<=24,Assumptions!$F$59,Assumptions!$F$60)))) -> -450000
A69: Medical leadership & governance | B69: $ | C69: =SUM(D69:AM69) -> -900000 | D69: =-Assumptions!$F$61 -> -25000 | E69: =-Assumptions!$F$61 -> -25000 | F69: =-Assumptions!$F$61 -> -25000 | G69: =-Assumptions!$F$61 -> -25000 | H69: =-Assumptions!$F$61 -> -25000 | I69: =-Assumptions!$F$61 -> -25000 | J69: =-Assumptions!$F$61 -> -25000 | K69: =-Assumptions!$F$61 -> -25000 | ... AM69: =-Assumptions!$F$61 -> -25000
A70: Technology & software | B70: $ | C70: =SUM(D70:AM70) -> -1458000 | D70: =-IF(D9=1,Assumptions!$F$63,Assumptions!$F$62) -> -18000 | E70: =-IF(E9=1,Assumptions!$F$63,Assumptions!$F$62) -> -18000 | F70: =-IF(F9=1,Assumptions!$F$63,Assumptions!$F$62) -> -18000 | G70: =-IF(G9=1,Assumptions!$F$63,Assumptions!$F$62) -> -18000 | H70: =-IF(H9=1,Assumptions!$F$63,Assumptions!$F$62) -> -18000 | I70: =-IF(I9=1,Assumptions!$F$63,Assumptions!$F$62) -> -18000 | J70: =-IF(J9=1,Assumptions!$F$63,Assumptions!$F$62) -> -45000 | K70: =-IF(K9=1,Assumptions!$F$63,Assumptions!$F$62) -> -45000 | ... AM70: =-IF(AM9=1,Assumptions!$F$63,Assumptions!$F$62) -> -45000
A71: Site & portal build (one-time) | B71: $ | C71: =SUM(D71:AM71) -> -320000 | D71: =-IF(D$3<=4,Assumptions!$F$64,0) -> -80000 | E71: =-IF(E$3<=4,Assumptions!$F$64,0) -> -80000 | F71: =-IF(F$3<=4,Assumptions!$F$64,0) -> -80000 | G71: =-IF(G$3<=4,Assumptions!$F$64,0) -> -80000 | H71: =-IF(H$3<=4,Assumptions!$F$64,0) -> 0 | I71: =-IF(I$3<=4,Assumptions!$F$64,0) -> 0 | J71: =-IF(J$3<=4,Assumptions!$F$64,0) -> 0 | K71: =-IF(K$3<=4,Assumptions!$F$64,0) -> 0 | ... AM71: =-IF(AM$3<=4,Assumptions!$F$64,0) -> 0
A72: Legal, regulatory & compliance | B72: $ | C72: =SUM(D72:AM72) -> -1005000 | D72: =-IF(D$3<=3,Assumptions!$F$65,Assumptions!$F$66) -> -60000 | E72: =-IF(E$3<=3,Assumptions!$F$65,Assumptions!$F$66) -> -60000 | F72: =-IF(F$3<=3,Assumptions!$F$65,Assumptions!$F$66) -> -60000 | G72: =-IF(G$3<=3,Assumptions!$F$65,Assumptions!$F$66) -> -25000 | H72: =-IF(H$3<=3,Assumptions!$F$65,Assumptions!$F$66) -> -25000 | I72: =-IF(I$3<=3,Assumptions!$F$65,Assumptions!$F$66) -> -25000 | J72: =-IF(J$3<=3,Assumptions!$F$65,Assumptions!$F$66) -> -25000 | K72: =-IF(K$3<=3,Assumptions!$F$65,Assumptions!$F$66) -> -25000 | ... AM72: =-IF(AM$3<=3,Assumptions!$F$65,Assumptions!$F$66) -> -25000
A73: Insurance | B73: $ | C73: =SUM(D73:AM73) -> -300000 | D73: =-IF(D9=1,Assumptions!$F$67,0) -> 0 | E73: =-IF(E9=1,Assumptions!$F$67,0) -> 0 | F73: =-IF(F9=1,Assumptions!$F$67,0) -> 0 | G73: =-IF(G9=1,Assumptions!$F$67,0) -> 0 | H73: =-IF(H9=1,Assumptions!$F$67,0) -> 0 | I73: =-IF(I9=1,Assumptions!$F$67,0) -> 0 | J73: =-IF(J9=1,Assumptions!$F$67,0) -> -10000 | K73: =-IF(K9=1,Assumptions!$F$67,0) -> -10000 | ... AM73: =-IF(AM9=1,Assumptions!$F$67,0) -> -10000
A74: Creative & content production | B74: $ | C74: =SUM(D74:AM74) -> -2040000 | D74: =-IF(D9=1,Assumptions!$F$69,Assumptions!$F$68) -> -40000 | E74: =-IF(E9=1,Assumptions!$F$69,Assumptions!$F$68) -> -40000 | F74: =-IF(F9=1,Assumptions!$F$69,Assumptions!$F$68) -> -40000 | G74: =-IF(G9=1,Assumptions!$F$69,Assumptions!$F$68) -> -40000 | H74: =-IF(H9=1,Assumptions!$F$69,Assumptions!$F$68) -> -40000 | I74: =-IF(I9=1,Assumptions!$F$69,Assumptions!$F$68) -> -40000 | J74: =-IF(J9=1,Assumptions!$F$69,Assumptions!$F$68) -> -60000 | K74: =-IF(K9=1,Assumptions!$F$69,Assumptions!$F$68) -> -60000 | ... AM74: =-IF(AM9=1,Assumptions!$F$69,Assumptions!$F$68) -> -60000
A75: Total operating expenses | B75: $ | C75: =SUM(D75:AM75) -> -17663000 | D75: =SUM(D68:D74) -> -303000 | E75: =SUM(E68:E74) -> -303000 | F75: =SUM(F68:F74) -> -303000 | G75: =SUM(G68:G74) -> -348000 | H75: =SUM(H68:H74) -> -268000 | I75: =SUM(I68:I74) -> -268000 | J75: =SUM(J68:J74) -> -405000 | K75: =SUM(K68:K74) -> -405000 | ... AM75: =SUM(AM68:AM74) -> -615000
A76: Profitability and cash
A77: EBITDA / operating profit (loss) | B77: $ | C77: =SUM(D77:AM77) -> 1.2970755e+08 | D77: =D63+D75 -> -333000 | E77: =E63+E75 -> -333000 | F77: =F63+F75 -> -333000 | G77: =G63+G75 -> -378000 | H77: =H63+H75 -> -333993.17 | I77: =I63+I75 -> -283914.78 | J77: =J63+J75 -> -139652.12 | K77: =K63+K75 -> 162228.38 | ... AM77: =AM63+AM75 -> 10956640
A78: Working capital investment (non-Rx inventory) | B78: $ | C78: =SUM(D78:AM78) -> -1385649.7 | D78: =-Assumptions!$F$80*ABS(D49) -> 0 | E78: =-Assumptions!$F$80*(ABS(E49)-ABS(D49)) -> 0 | F78: =-Assumptions!$F$80*(ABS(F49)-ABS(E49)) -> 0 | G78: =-Assumptions!$F$80*(ABS(G49)-ABS(F49)) -> 0 | H78: =-Assumptions!$F$80*(ABS(H49)-ABS(G49)) -> -37938.097 | I78: =-Assumptions!$F$80*(ABS(I49)-ABS(H49)) -> -7240.048 | J78: =-Assumptions!$F$80*(ABS(J49)-ABS(I49)) -> -145541.01 | K78: =-Assumptions!$F$80*(ABS(K49)-ABS(J49)) -> 52983.648 | L78: =-Assumptions!$F$80*(ABS(L49)-ABS(K49)) -> -20737.351 | ... AM78: =-Assumptions!$F$80*(ABS(AM49)-ABS(AL49)) -> -86497.416
A79: Net cash flow | B79: $ | C79: =SUM(D79:AM79) -> 1.283219e+08 | D79: =D77+D78 -> -333000 | E79: =E77+E78 -> -333000 | F79: =F77+F78 -> -333000 | G79: =G77+G78 -> -378000 | H79: =H77+H78 -> -371931.26 | I79: =I77+I78 -> -291154.83 | J79: =J77+J78 -> -285193.12 | K79: =K77+K78 -> 215212.03 | ... AM79: =AM77+AM78 -> 10870142
A80: Cumulative cash flow | B80: $ | D80: =D79 -> -333000 | E80: =D80+E79 -> -666000 | F80: =E80+F79 -> -999000 | G80: =F80+G79 -> -1377000 | H80: =G80+H79 -> -1748931.3 | I80: =H80+I79 -> -2040086.1 | J80: =I80+J79 -> -2325279.2 | K80: =J80+K79 -> -2110067.2 | L80: =K80+L79 -> -1766087.7 | ... AM80: =AL80+AM79 -> 1.283219e+08
A81: Cash balance (opening cash + cumulative) | B81: $ | D81: =Assumptions!$F$81+D80 -> -333000 | E81: =Assumptions!$F$81+E80 -> -666000 | F81: =Assumptions!$F$81+F80 -> -999000 | G81: =Assumptions!$F$81+G80 -> -1377000 | H81: =Assumptions!$F$81+H80 -> -1748931.3 | I81: =Assumptions!$F$81+I80 -> -2040086.1 | J81: =Assumptions!$F$81+J80 -> -2325279.2 | K81: =Assumptions!$F$81+K80 -> -2110067.2 | ... AM81: =Assumptions!$F$81+AM80 -> 1.283219e+08
A82: Break-even helper (month # if EBITDA > 0, else 999) | B82: # | D82: =IF(D77>0,D$3,999) -> 999 | E82: =IF(E77>0,E$3,999) -> 999 | F82: =IF(F77>0,F$3,999) -> 999 | G82: =IF(G77>0,G$3,999) -> 999 | H82: =IF(H77>0,H$3,999) -> 999 | I82: =IF(I77>0,I$3,999) -> 999 | J82: =IF(J77>0,J$3,999) -> 999 | K82: =IF(K77>0,K$3,999) -> 8 | ... AM82: =IF(AM77>0,AM$3,999) -> 36
A83: Unit economics (steady-state view, per active Rx member)
A84: Revenue per active Rx member-month | B84: $ | D84: =IF(D24=0,0,(D36)/D24) -> 0 | E84: =IF(E24=0,0,(E36)/E24) -> 0 | F84: =IF(F24=0,0,(F36)/F24) -> 0 | G84: =IF(G24=0,0,(G36)/G24) -> 0 | H84: =IF(H24=0,0,(H36)/H24) -> 299 | I84: =IF(I24=0,0,(I36)/I24) -> 299 | J84: =IF(J24=0,0,(J36)/J24) -> 299 | K84: =IF(K24=0,0,(K36)/K24) -> 299 | ... AM84: =IF(AM24=0,0,(AM36)/AM24) -> 299
A85: Contribution per Rx member-month before acquisition | B85: $ | D85: =Assumptions!$F$30*(1-Assumptions!$F$50-Assumptions!$F$49)-Assumptions!$F$44-Assumptions!$F$46-Assumptions!$F$47-Assumptions!$F$51 -> 174.452 | E85: =Assumptions!$F$30*(1-Assumptions!$F$50-Assumptions!$F$49)-Assumptions!$F$44-Assumptions!$F$46-Assumptions!$F$47-Assumptions!$F$51 -> 174.452 | F85: =Assumptions!$F$30*(1-Assumptions!$F$50-Assumptions!$F$49)-Assumptions!$F$44-Assumptions!$F$46-Assumptions!$F$47-Assumptions!$F$51 -> 174.452 | G85: =Assumptions!$F$30*(1-Assumptions!$F$50-Assumptions!$F$49)-Assumptions!$F$44-Assumptions!$F$46-Assumptions!$F$47-Assumptions!$F$51 -> 174.452 | H85: =Assumptions!$F$30*(1-Assumptions!$F$50-Assumptions!$F$49)-Assumptions!$F$44-Assumptions!$F$46-Assumptions!$F$47-Assumptions!$F$51 -> 174.452 | I85: =Assumptions!$F$30*(1-Assumptions!$F$50-Assumptions!$F$49)-Assumptions!$F$44-Assumptions!$F$46-Assumptions!$F$47-Assumptions!$F$51 -> 174.452 | J85: =Assumptions!$F$30*(1-Assumptions!$F$50-Assumptions!$F$49)-Assumptions!$F$44-Assumptions!$F$46-Assumptions!$F$47-Assumptions!$F$51 -> 174.452 | K85: =Assumptions!$F$30*(1-Assumptions!$F$50-Assumptions!$F$49)-Assumptions!$F$44-Assumptions!$F$46-Assumptions!$F$47-Assumptions!$F$51 -> 174.452 | ... AM85: =Assumptions!$F$30*(1-Assumptions!$F$50-Assumptions!$F$49)-Assumptions!$F$44-Assumptions!$F$46-Assumptions!$F$47-Assumptions!$F$51 -> 174.452
A86: LTV (contribution-based) = contribution / churn | B86: $ | D86: =D85/Assumptions!$F$41 -> 1744.52 | E86: =E85/Assumptions!$F$41 -> 1744.52 | F86: =F85/Assumptions!$F$41 -> 1744.52 | G86: =G85/Assumptions!$F$41 -> 1744.52 | H86: =H85/Assumptions!$F$41 -> 1744.52 | I86: =I85/Assumptions!$F$41 -> 1744.52 | J86: =J85/Assumptions!$F$41 -> 1744.52 | K86: =K85/Assumptions!$F$41 -> 1744.52 | ... AM86: =AM85/Assumptions!$F$41 -> 1744.52
A87: LTV : CAC (Rx) | B87: x | D87: =IF(D66=0,0,D86/D66) -> 0 | E87: =IF(E66=0,0,E86/E66) -> 0 | F87: =IF(F66=0,0,F86/F66) -> 0 | G87: =IF(G66=0,0,G86/G66) -> 0 | H87: =IF(H66=0,0,H86/H66) -> 2.3033066 | I87: =IF(I66=0,0,I86/I66) -> 2.3282709 | J87: =IF(J66=0,0,J86/J66) -> 4.4772091 | K87: =IF(K66=0,0,K86/K66) -> 5.1681524 | ... AM87: =IF(AM66=0,0,AM86/AM66) -> 16.285884
A88: CAC payback (months) | B88: months | D88: =IF(D85<=0,0,D66/D85) -> 0 | E88: =IF(E85<=0,0,E66/E85) -> 0 | F88: =IF(F85<=0,0,F66/F85) -> 0 | G88: =IF(G85<=0,0,G66/G85) -> 0 | H88: =IF(H85<=0,0,H66/H85) -> 4.3415844 | I88: =IF(I85<=0,0,I66/I85) -> 4.2950328 | J88: =IF(J85<=0,0,J66/J85) -> 2.2335343 | K88: =IF(K85<=0,0,K66/K85) -> 1.9349274 | ... AM88: =IF(AM85<=0,0,AM66/AM85) -> 0.61402871
A89: Net revenue per active customer (Rx + membership) | B89: $ | D89: =IF((D24+D29)=0,0,D43/(D24+D29)) -> 0 | E89: =IF((E24+E29)=0,0,E43/(E24+E29)) -> 0 | F89: =IF((F24+F29)=0,0,F43/(F24+F29)) -> 0 | G89: =IF((G24+G29)=0,0,G43/(G24+G29)) -> 0 | H89: =IF((H24+H29)=0,0,H43/(H24+H29)) -> 333.92389 | I89: =IF((I24+I29)=0,0,I43/(I24+I29)) -> 234.88431 | J89: =IF((J24+J29)=0,0,J43/(J24+J29)) -> 374.66964 | K89: =IF((K24+K29)=0,0,K43/(K24+K29)) -> 255.74506 | ... AM89: =IF((AM24+AM29)=0,0,AM43/(AM24+AM29)) -> 275.67357

Sheet Sensitivity
A1: Sensitivity analysis (Base scenario inputs; formulas recalculate when Assumptions change)
A2: Table 1: LTV:CAC as a function of monthly Rx churn (rows) and CAC per Rx member (columns). Table 2: CAC payback months. Table 3: Year-3 Rx program revenue vs price and churn (steady-state approximation: month-36 new members / churn × price × 12).
A4: Table 1 — LTV : CAC (contribution-based LTV = contribution per member-month / churn)
A5: Churn ↓ / CAC → | B5: 150 | C5: 200 | D5: 250 | E5: 300 | F5: 350 | G5: 400 | H5: 500
A6: 0.06 | B6: =((Assumptions!$E$30*(1-Assumptions!$E$50-Assumptions!$E$49)-Assumptions!$E$44-Assumptions!$E$46-Assumptions!$E$47-Assumptions!$E$51)/$A6)/B$5 -> 14.933333 | C6: =((Assumptions!$E$30*(1-Assumptions!$E$50-Assumptions!$E$49)-Assumptions!$E$44-Assumptions!$E$46-Assumptions!$E$47-Assumptions!$E$51)/$A6)/C$5 -> 11.2 | D6: =((Assumptions!$E$30*(1-Assumptions!$E$50-Assumptions!$E$49)-Assumptions!$E$44-Assumptions!$E$46-Assumptions!$E$47-Assumptions!$E$51)/$A6)/D$5 -> 8.96 | E6: =((Assumptions!$E$30*(1-Assumptions!$E$50-Assumptions!$E$49)-Assumptions!$E$44-Assumptions!$E$46-Assumptions!$E$47-Assumptions!$E$51)/$A6)/E$5 -> 7.4666667 | F6: =((Assumptions!$E$30*(1-Assumptions!$E$50-Assumptions!$E$49)-Assumptions!$E$44-Assumptions!$E$46-Assumptions!$E$47-Assumptions!$E$51)/$A6)/F$5 -> 6.4 | G6: =((Assumptions!$E$30*(1-Assumptions!$E$50-Assumptions!$E$49)-Assumptions!$E$44-Assumptions!$E$46-Assumptions!$E$47-Assumptions!$E$51)/$A6)/G$5 -> 5.6 | H6: =((Assumptions!$E$30*(1-Assumptions!$E$50-Assumptions!$E$49)-Assumptions!$E$44-Assumptions!$E$46-Assumptions!$E$47-Assumptions!$E$51)/$A6)/H$5 -> 4.48
A7: 0.08 | B7: =((Assumptions!$E$30*(1-Assumptions!$E$50-Assumptions!$E$49)-Assumptions!$E$44-Assumptions!$E$46-Assumptions!$E$47-Assumptions!$E$51)/$A7)/B$5 -> 11.2 | C7: =((Assumptions!$E$30*(1-Assumptions!$E$50-Assumptions!$E$49)-Assumptions!$E$44-Assumptions!$E$46-Assumptions!$E$47-Assumptions!$E$51)/$A7)/C$5 -> 8.4 | D7: =((Assumptions!$E$30*(1-Assumptions!$E$50-Assumptions!$E$49)-Assumptions!$E$44-Assumptions!$E$46-Assumptions!$E$47-Assumptions!$E$51)/$A7)/D$5 -> 6.72 | E7: =((Assumptions!$E$30*(1-Assumptions!$E$50-Assumptions!$E$49)-Assumptions!$E$44-Assumptions!$E$46-Assumptions!$E$47-Assumptions!$E$51)/$A7)/E$5 -> 5.6 | F7: =((Assumptions!$E$30*(1-Assumptions!$E$50-Assumptions!$E$49)-Assumptions!$E$44-Assumptions!$E$46-Assumptions!$E$47-Assumptions!$E$51)/$A7)/F$5 -> 4.8 | G7: =((Assumptions!$E$30*(1-Assumptions!$E$50-Assumptions!$E$49)-Assumptions!$E$44-Assumptions!$E$46-Assumptions!$E$47-Assumptions!$E$51)/$A7)/G$5 -> 4.2 | H7: =((Assumptions!$E$30*(1-Assumptions!$E$50-Assumptions!$E$49)-Assumptions!$E$44-Assumptions!$E$46-Assumptions!$E$47-Assumptions!$E$51)/$A7)/H$5 -> 3.36
A8: 0.1 | B8: =((Assumptions!$E$30*(1-Assumptions!$E$50-Assumptions!$E$49)-Assumptions!$E$44-Assumptions!$E$46-Assumptions!$E$47-Assumptions!$E$51)/$A8)/B$5 -> 8.96 | C8: =((Assumptions!$E$30*(1-Assumptions!$E$50-Assumptions!$E$49)-Assumptions!$E$44-Assumptions!$E$46-Assumptions!$E$47-Assumptions!$E$51)/$A8)/C$5 -> 6.72 | D8: =((Assumptions!$E$30*(1-Assumptions!$E$50-Assumptions!$E$49)-Assumptions!$E$44-Assumptions!$E$46-Assumptions!$E$47-Assumptions!$E$51)/$A8)/D$5 -> 5.376 | E8: =((Assumptions!$E$30*(1-Assumptions!$E$50-Assumptions!$E$49)-Assumptions!$E$44-Assumptions!$E$46-Assumptions!$E$47-Assumptions!$E$51)/$A8)/E$5 -> 4.48 | F8: =((Assumptions!$E$30*(1-Assumptions!$E$50-Assumptions!$E$49)-Assumptions!$E$44-Assumptions!$E$46-Assumptions!$E$47-Assumptions!$E$51)/$A8)/F$5 -> 3.84 | G8: =((Assumptions!$E$30*(1-Assumptions!$E$50-Assumptions!$E$49)-Assumptions!$E$44-Assumptions!$E$46-Assumptions!$E$47-Assumptions!$E$51)/$A8)/G$5 -> 3.36 | H8: =((Assumptions!$E$30*(1-Assumptions!$E$50-Assumptions!$E$49)-Assumptions!$E$44-Assumptions!$E$46-Assumptions!$E$47-Assumptions!$E$51)/$A8)/H$5 -> 2.688
A9: 0.11 | B9: =((Assumptions!$E$30*(1-Assumptions!$E$50-Assumptions!$E$49)-Assumptions!$E$44-Assumptions!$E$46-Assumptions!$E$47-Assumptions!$E$51)/$A9)/B$5 -> 8.1454545 | C9: =((Assumptions!$E$30*(1-Assumptions!$E$50-Assumptions!$E$49)-Assumptions!$E$44-Assumptions!$E$46-Assumptions!$E$47-Assumptions!$E$51)/$A9)/C$5 -> 6.1090909 | D9: =((Assumptions!$E$30*(1-Assumptions!$E$50-Assumptions!$E$49)-Assumptions!$E$44-Assumptions!$E$46-Assumptions!$E$47-Assumptions!$E$51)/$A9)/D$5 -> 4.8872727 | E9: =((Assumptions!$E$30*(1-Assumptions!$E$50-Assumptions!$E$49)-Assumptions!$E$44-Assumptions!$E$46-Assumptions!$E$47-Assumptions!$E$51)/$A9)/E$5 -> 4.0727273 | F9: =((Assumptions!$E$30*(1-Assumptions!$E$50-Assumptions!$E$49)-Assumptions!$E$44-Assumptions!$E$46-Assumptions!$E$47-Assumptions!$E$51)/$A9)/F$5 -> 3.4909091 | G9: =((Assumptions!$E$30*(1-Assumptions!$E$50-Assumptions!$E$49)-Assumptions!$E$44-Assumptions!$E$46-Assumptions!$E$47-Assumptions!$E$51)/$A9)/G$5 -> 3.0545455 | H9: =((Assumptions!$E$30*(1-Assumptions!$E$50-Assumptions!$E$49)-Assumptions!$E$44-Assumptions!$E$46-Assumptions!$E$47-Assumptions!$E$51)/$A9)/H$5 -> 2.4436364
A10: 0.12 | B10: =((Assumptions!$E$30*(1-Assumptions!$E$50-Assumptions!$E$49)-Assumptions!$E$44-Assumptions!$E$46-Assumptions!$E$47-Assumptions!$E$51)/$A10)/B$5 -> 7.4666667 | C10: =((Assumptions!$E$30*(1-Assumptions!$E$50-Assumptions!$E$49)-Assumptions!$E$44-Assumptions!$E$46-Assumptions!$E$47-Assumptions!$E$51)/$A10)/C$5 -> 5.6 | D10: =((Assumptions!$E$30*(1-Assumptions!$E$50-Assumptions!$E$49)-Assumptions!$E$44-Assumptions!$E$46-Assumptions!$E$47-Assumptions!$E$51)/$A10)/D$5 -> 4.48 | E10: =((Assumptions!$E$30*(1-Assumptions!$E$50-Assumptions!$E$49)-Assumptions!$E$44-Assumptions!$E$46-Assumptions!$E$47-Assumptions!$E$51)/$A10)/E$5 -> 3.7333333 | F10: =((Assumptions!$E$30*(1-Assumptions!$E$50-Assumptions!$E$49)-Assumptions!$E$44-Assumptions!$E$46-Assumptions!$E$47-Assumptions!$E$51)/$A10)/F$5 -> 3.2 | G10: =((Assumptions!$E$30*(1-Assumptions!$E$50-Assumptions!$E$49)-Assumptions!$E$44-Assumptions!$E$46-Assumptions!$E$47-Assumptions!$E$51)/$A10)/G$5 -> 2.8 | H10: =((Assumptions!$E$30*(1-Assumptions!$E$50-Assumptions!$E$49)-Assumptions!$E$44-Assumptions!$E$46-Assumptions!$E$47-Assumptions!$E$51)/$A10)/H$5 -> 2.24
A11: 0.14 | B11: =((Assumptions!$E$30*(1-Assumptions!$E$50-Assumptions!$E$49)-Assumptions!$E$44-Assumptions!$E$46-Assumptions!$E$47-Assumptions!$E$51)/$A11)/B$5 -> 6.4 | C11: =((Assumptions!$E$30*(1-Assumptions!$E$50-Assumptions!$E$49)-Assumptions!$E$44-Assumptions!$E$46-Assumptions!$E$47-Assumptions!$E$51)/$A11)/C$5 -> 4.8 | D11: =((Assumptions!$E$30*(1-Assumptions!$E$50-Assumptions!$E$49)-Assumptions!$E$44-Assumptions!$E$46-Assumptions!$E$47-Assumptions!$E$51)/$A11)/D$5 -> 3.84 | E11: =((Assumptions!$E$30*(1-Assumptions!$E$50-Assumptions!$E$49)-Assumptions!$E$44-Assumptions!$E$46-Assumptions!$E$47-Assumptions!$E$51)/$A11)/E$5 -> 3.2 | F11: =((Assumptions!$E$30*(1-Assumptions!$E$50-Assumptions!$E$49)-Assumptions!$E$44-Assumptions!$E$46-Assumptions!$E$47-Assumptions!$E$51)/$A11)/F$5 -> 2.7428571 | G11: =((Assumptions!$E$30*(1-Assumptions!$E$50-Assumptions!$E$49)-Assumptions!$E$44-Assumptions!$E$46-Assumptions!$E$47-Assumptions!$E$51)/$A11)/G$5 -> 2.4 | H11: =((Assumptions!$E$30*(1-Assumptions!$E$50-Assumptions!$E$49)-Assumptions!$E$44-Assumptions!$E$46-Assumptions!$E$47-Assumptions!$E$51)/$A11)/H$5 -> 1.92
A12: 0.16 | B12: =((Assumptions!$E$30*(1-Assumptions!$E$50-Assumptions!$E$49)-Assumptions!$E$44-Assumptions!$E$46-Assumptions!$E$47-Assumptions!$E$51)/$A12)/B$5 -> 5.6 | C12: =((Assumptions!$E$30*(1-Assumptions!$E$50-Assumptions!$E$49)-Assumptions!$E$44-Assumptions!$E$46-Assumptions!$E$47-Assumptions!$E$51)/$A12)/C$5 -> 4.2 | D12: =((Assumptions!$E$30*(1-Assumptions!$E$50-Assumptions!$E$49)-Assumptions!$E$44-Assumptions!$E$46-Assumptions!$E$47-Assumptions!$E$51)/$A12)/D$5 -> 3.36 | E12: =((Assumptions!$E$30*(1-Assumptions!$E$50-Assumptions!$E$49)-Assumptions!$E$44-Assumptions!$E$46-Assumptions!$E$47-Assumptions!$E$51)/$A12)/E$5 -> 2.8 | F12: =((Assumptions!$E$30*(1-Assumptions!$E$50-Assumptions!$E$49)-Assumptions!$E$44-Assumptions!$E$46-Assumptions!$E$47-Assumptions!$E$51)/$A12)/F$5 -> 2.4 | G12: =((Assumptions!$E$30*(1-Assumptions!$E$50-Assumptions!$E$49)-Assumptions!$E$44-Assumptions!$E$46-Assumptions!$E$47-Assumptions!$E$51)/$A12)/G$5 -> 2.1 | H12: =((Assumptions!$E$30*(1-Assumptions!$E$50-Assumptions!$E$49)-Assumptions!$E$44-Assumptions!$E$46-Assumptions!$E$47-Assumptions!$E$51)/$A12)/H$5 -> 1.68
A15: Table 2 — CAC payback (months) = CAC / contribution per member-month
A16: Churn ↓ / CAC → | B16: 150 | C16: 200 | D16: 250 | E16: 300 | F16: 350 | G16: 400 | H16: 500
A17: 0.06 | B17: =B$16/(Assumptions!$E$30*(1-Assumptions!$E$50-Assumptions!$E$49)-Assumptions!$E$44-Assumptions!$E$46-Assumptions!$E$47-Assumptions!$E$51) -> 1.1160714 | C17: =C$16/(Assumptions!$E$30*(1-Assumptions!$E$50-Assumptions!$E$49)-Assumptions!$E$44-Assumptions!$E$46-Assumptions!$E$47-Assumptions!$E$51) -> 1.4880952 | D17: =D$16/(Assumptions!$E$30*(1-Assumptions!$E$50-Assumptions!$E$49)-Assumptions!$E$44-Assumptions!$E$46-Assumptions!$E$47-Assumptions!$E$51) -> 1.860119 | E17: =E$16/(Assumptions!$E$30*(1-Assumptions!$E$50-Assumptions!$E$49)-Assumptions!$E$44-Assumptions!$E$46-Assumptions!$E$47-Assumptions!$E$51) -> 2.2321429 | F17: =F$16/(Assumptions!$E$30*(1-Assumptions!$E$50-Assumptions!$E$49)-Assumptions!$E$44-Assumptions!$E$46-Assumptions!$E$47-Assumptions!$E$51) -> 2.6041667 | G17: =G$16/(Assumptions!$E$30*(1-Assumptions!$E$50-Assumptions!$E$49)-Assumptions!$E$44-Assumptions!$E$46-Assumptions!$E$47-Assumptions!$E$51) -> 2.9761905 | H17: =H$16/(Assumptions!$E$30*(1-Assumptions!$E$50-Assumptions!$E$49)-Assumptions!$E$44-Assumptions!$E$46-Assumptions!$E$47-Assumptions!$E$51) -> 3.7202381
A18: 0.08 | B18: =B$16/(Assumptions!$E$30*(1-Assumptions!$E$50-Assumptions!$E$49)-Assumptions!$E$44-Assumptions!$E$46-Assumptions!$E$47-Assumptions!$E$51) -> 1.1160714 | C18: =C$16/(Assumptions!$E$30*(1-Assumptions!$E$50-Assumptions!$E$49)-Assumptions!$E$44-Assumptions!$E$46-Assumptions!$E$47-Assumptions!$E$51) -> 1.4880952 | D18: =D$16/(Assumptions!$E$30*(1-Assumptions!$E$50-Assumptions!$E$49)-Assumptions!$E$44-Assumptions!$E$46-Assumptions!$E$47-Assumptions!$E$51) -> 1.860119 | E18: =E$16/(Assumptions!$E$30*(1-Assumptions!$E$50-Assumptions!$E$49)-Assumptions!$E$44-Assumptions!$E$46-Assumptions!$E$47-Assumptions!$E$51) -> 2.2321429 | F18: =F$16/(Assumptions!$E$30*(1-Assumptions!$E$50-Assumptions!$E$49)-Assumptions!$E$44-Assumptions!$E$46-Assumptions!$E$47-Assumptions!$E$51) -> 2.6041667 | G18: =G$16/(Assumptions!$E$30*(1-Assumptions!$E$50-Assumptions!$E$49)-Assumptions!$E$44-Assumptions!$E$46-Assumptions!$E$47-Assumptions!$E$51) -> 2.9761905 | H18: =H$16/(Assumptions!$E$30*(1-Assumptions!$E$50-Assumptions!$E$49)-Assumptions!$E$44-Assumptions!$E$46-Assumptions!$E$47-Assumptions!$E$51) -> 3.7202381
A19: 0.1 | B19: =B$16/(Assumptions!$E$30*(1-Assumptions!$E$50-Assumptions!$E$49)-Assumptions!$E$44-Assumptions!$E$46-Assumptions!$E$47-Assumptions!$E$51) -> 1.1160714 | C19: =C$16/(Assumptions!$E$30*(1-Assumptions!$E$50-Assumptions!$E$49)-Assumptions!$E$44-Assumptions!$E$46-Assumptions!$E$47-Assumptions!$E$51) -> 1.4880952 | D19: =D$16/(Assumptions!$E$30*(1-Assumptions!$E$50-Assumptions!$E$49)-Assumptions!$E$44-Assumptions!$E$46-Assumptions!$E$47-Assumptions!$E$51) -> 1.860119 | E19: =E$16/(Assumptions!$E$30*(1-Assumptions!$E$50-Assumptions!$E$49)-Assumptions!$E$44-Assumptions!$E$46-Assumptions!$E$47-Assumptions!$E$51) -> 2.2321429 | F19: =F$16/(Assumptions!$E$30*(1-Assumptions!$E$50-Assumptions!$E$49)-Assumptions!$E$44-Assumptions!$E$46-Assumptions!$E$47-Assumptions!$E$51) -> 2.6041667 | G19: =G$16/(Assumptions!$E$30*(1-Assumptions!$E$50-Assumptions!$E$49)-Assumptions!$E$44-Assumptions!$E$46-Assumptions!$E$47-Assumptions!$E$51) -> 2.9761905 | H19: =H$16/(Assumptions!$E$30*(1-Assumptions!$E$50-Assumptions!$E$49)-Assumptions!$E$44-Assumptions!$E$46-Assumptions!$E$47-Assumptions!$E$51) -> 3.7202381
A20: 0.11 | B20: =B$16/(Assumptions!$E$30*(1-Assumptions!$E$50-Assumptions!$E$49)-Assumptions!$E$44-Assumptions!$E$46-Assumptions!$E$47-Assumptions!$E$51) -> 1.1160714 | C20: =C$16/(Assumptions!$E$30*(1-Assumptions!$E$50-Assumptions!$E$49)-Assumptions!$E$44-Assumptions!$E$46-Assumptions!$E$47-Assumptions!$E$51) -> 1.4880952 | D20: =D$16/(Assumptions!$E$30*(1-Assumptions!$E$50-Assumptions!$E$49)-Assumptions!$E$44-Assumptions!$E$46-Assumptions!$E$47-Assumptions!$E$51) -> 1.860119 | E20: =E$16/(Assumptions!$E$30*(1-Assumptions!$E$50-Assumptions!$E$49)-Assumptions!$E$44-Assumptions!$E$46-Assumptions!$E$47-Assumptions!$E$51) -> 2.2321429 | F20: =F$16/(Assumptions!$E$30*(1-Assumptions!$E$50-Assumptions!$E$49)-Assumptions!$E$44-Assumptions!$E$46-Assumptions!$E$47-Assumptions!$E$51) -> 2.6041667 | G20: =G$16/(Assumptions!$E$30*(1-Assumptions!$E$50-Assumptions!$E$49)-Assumptions!$E$44-Assumptions!$E$46-Assumptions!$E$47-Assumptions!$E$51) -> 2.9761905 | H20: =H$16/(Assumptions!$E$30*(1-Assumptions!$E$50-Assumptions!$E$49)-Assumptions!$E$44-Assumptions!$E$46-Assumptions!$E$47-Assumptions!$E$51) -> 3.7202381
A21: 0.12 | B21: =B$16/(Assumptions!$E$30*(1-Assumptions!$E$50-Assumptions!$E$49)-Assumptions!$E$44-Assumptions!$E$46-Assumptions!$E$47-Assumptions!$E$51) -> 1.1160714 | C21: =C$16/(Assumptions!$E$30*(1-Assumptions!$E$50-Assumptions!$E$49)-Assumptions!$E$44-Assumptions!$E$46-Assumptions!$E$47-Assumptions!$E$51) -> 1.4880952 | D21: =D$16/(Assumptions!$E$30*(1-Assumptions!$E$50-Assumptions!$E$49)-Assumptions!$E$44-Assumptions!$E$46-Assumptions!$E$47-Assumptions!$E$51) -> 1.860119 | E21: =E$16/(Assumptions!$E$30*(1-Assumptions!$E$50-Assumptions!$E$49)-Assumptions!$E$44-Assumptions!$E$46-Assumptions!$E$47-Assumptions!$E$51) -> 2.2321429 | F21: =F$16/(Assumptions!$E$30*(1-Assumptions!$E$50-Assumptions!$E$49)-Assumptions!$E$44-Assumptions!$E$46-Assumptions!$E$47-Assumptions!$E$51) -> 2.6041667 | G21: =G$16/(Assumptions!$E$30*(1-Assumptions!$E$50-Assumptions!$E$49)-Assumptions!$E$44-Assumptions!$E$46-Assumptions!$E$47-Assumptions!$E$51) -> 2.9761905 | H21: =H$16/(Assumptions!$E$30*(1-Assumptions!$E$50-Assumptions!$E$49)-Assumptions!$E$44-Assumptions!$E$46-Assumptions!$E$47-Assumptions!$E$51) -> 3.7202381
A22: 0.14 | B22: =B$16/(Assumptions!$E$30*(1-Assumptions!$E$50-Assumptions!$E$49)-Assumptions!$E$44-Assumptions!$E$46-Assumptions!$E$47-Assumptions!$E$51) -> 1.1160714 | C22: =C$16/(Assumptions!$E$30*(1-Assumptions!$E$50-Assumptions!$E$49)-Assumptions!$E$44-Assumptions!$E$46-Assumptions!$E$47-Assumptions!$E$51) -> 1.4880952 | D22: =D$16/(Assumptions!$E$30*(1-Assumptions!$E$50-Assumptions!$E$49)-Assumptions!$E$44-Assumptions!$E$46-Assumptions!$E$47-Assumptions!$E$51) -> 1.860119 | E22: =E$16/(Assumptions!$E$30*(1-Assumptions!$E$50-Assumptions!$E$49)-Assumptions!$E$44-Assumptions!$E$46-Assumptions!$E$47-Assumptions!$E$51) -> 2.2321429 | F22: =F$16/(Assumptions!$E$30*(1-Assumptions!$E$50-Assumptions!$E$49)-Assumptions!$E$44-Assumptions!$E$46-Assumptions!$E$47-Assumptions!$E$51) -> 2.6041667 | G22: =G$16/(Assumptions!$E$30*(1-Assumptions!$E$50-Assumptions!$E$49)-Assumptions!$E$44-Assumptions!$E$46-Assumptions!$E$47-Assumptions!$E$51) -> 2.9761905 | H22: =H$16/(Assumptions!$E$30*(1-Assumptions!$E$50-Assumptions!$E$49)-Assumptions!$E$44-Assumptions!$E$46-Assumptions!$E$47-Assumptions!$E$51) -> 3.7202381
A23: 0.16 | B23: =B$16/(Assumptions!$E$30*(1-Assumptions!$E$50-Assumptions!$E$49)-Assumptions!$E$44-Assumptions!$E$46-Assumptions!$E$47-Assumptions!$E$51) -> 1.1160714 | C23: =C$16/(Assumptions!$E$30*(1-Assumptions!$E$50-Assumptions!$E$49)-Assumptions!$E$44-Assumptions!$E$46-Assumptions!$E$47-Assumptions!$E$51) -> 1.4880952 | D23: =D$16/(Assumptions!$E$30*(1-Assumptions!$E$50-Assumptions!$E$49)-Assumptions!$E$44-Assumptions!$E$46-Assumptions!$E$47-Assumptions!$E$51) -> 1.860119 | E23: =E$16/(Assumptions!$E$30*(1-Assumptions!$E$50-Assumptions!$E$49)-Assumptions!$E$44-Assumptions!$E$46-Assumptions!$E$47-Assumptions!$E$51) -> 2.2321429 | F23: =F$16/(Assumptions!$E$30*(1-Assumptions!$E$50-Assumptions!$E$49)-Assumptions!$E$44-Assumptions!$E$46-Assumptions!$E$47-Assumptions!$E$51) -> 2.6041667 | G23: =G$16/(Assumptions!$E$30*(1-Assumptions!$E$50-Assumptions!$E$49)-Assumptions!$E$44-Assumptions!$E$46-Assumptions!$E$47-Assumptions!$E$51) -> 2.9761905 | H23: =H$16/(Assumptions!$E$30*(1-Assumptions!$E$50-Assumptions!$E$49)-Assumptions!$E$44-Assumptions!$E$46-Assumptions!$E$47-Assumptions!$E$51) -> 3.7202381
A26: Table 3 — Steady-state annual Rx program revenue ($) = (Base month-36 new Rx members / churn) × price × 12
A27: Churn ↓ / Price → | B27: 199 | C27: 225 | D27: 249 | E27: 275 | F27: 299 | G27: 325 | H27: 349
A28: 0.06 | B28: =(Model_Base!AM23/$A28)*B$27*12 -> 68101851 | C28: =(Model_Base!AM23/$A28)*C$27*12 -> 76999580 | D28: =(Model_Base!AM23/$A28)*D$27*12 -> 85212869 | E28: =(Model_Base!AM23/$A28)*E$27*12 -> 94110598 | F28: =(Model_Base!AM23/$A28)*F$27*12 -> 1.0232389e+08 | G28: =(Model_Base!AM23/$A28)*G$27*12 -> 1.1122162e+08 | H28: =(Model_Base!AM23/$A28)*H$27*12 -> 1.194349e+08
A29: 0.08 | B29: =(Model_Base!AM23/$A29)*B$27*12 -> 51076388 | C29: =(Model_Base!AM23/$A29)*C$27*12 -> 57749685 | D29: =(Model_Base!AM23/$A29)*D$27*12 -> 63909652 | E29: =(Model_Base!AM23/$A29)*E$27*12 -> 70582948 | F29: =(Model_Base!AM23/$A29)*F$27*12 -> 76742915 | G29: =(Model_Base!AM23/$A29)*G$27*12 -> 83416212 | H29: =(Model_Base!AM23/$A29)*H$27*12 -> 89576178
A30: 0.1 | B30: =(Model_Base!AM23/$A30)*B$27*12 -> 40861111 | C30: =(Model_Base!AM23/$A30)*C$27*12 -> 46199748 | D30: =(Model_Base!AM23/$A30)*D$27*12 -> 51127721 | E30: =(Model_Base!AM23/$A30)*E$27*12 -> 56466359 | F30: =(Model_Base!AM23/$A30)*F$27*12 -> 61394332 | G30: =(Model_Base!AM23/$A30)*G$27*12 -> 66732969 | H30: =(Model_Base!AM23/$A30)*H$27*12 -> 71660943
A31: 0.11 | B31: =(Model_Base!AM23/$A31)*B$27*12 -> 37146464 | C31: =(Model_Base!AM23/$A31)*C$27*12 -> 41999771 | D31: =(Model_Base!AM23/$A31)*D$27*12 -> 46479747 | E31: =(Model_Base!AM23/$A31)*E$27*12 -> 51333053 | F31: =(Model_Base!AM23/$A31)*F$27*12 -> 55813029 | G31: =(Model_Base!AM23/$A31)*G$27*12 -> 60666336 | H31: =(Model_Base!AM23/$A31)*H$27*12 -> 65146311
A32: 0.12 | B32: =(Model_Base!AM23/$A32)*B$27*12 -> 34050925 | C32: =(Model_Base!AM23/$A32)*C$27*12 -> 38499790 | D32: =(Model_Base!AM23/$A32)*D$27*12 -> 42606434 | E32: =(Model_Base!AM23/$A32)*E$27*12 -> 47055299 | F32: =(Model_Base!AM23/$A32)*F$27*12 -> 51161943 | G32: =(Model_Base!AM23/$A32)*G$27*12 -> 55610808 | H32: =(Model_Base!AM23/$A32)*H$27*12 -> 59717452
A33: 0.14 | B33: =(Model_Base!AM23/$A33)*B$27*12 -> 29186508 | C33: =(Model_Base!AM23/$A33)*C$27*12 -> 32999820 | D33: =(Model_Base!AM23/$A33)*D$27*12 -> 36519801 | E33: =(Model_Base!AM23/$A33)*E$27*12 -> 40333113 | F33: =(Model_Base!AM23/$A33)*F$27*12 -> 43853094 | G33: =(Model_Base!AM23/$A33)*G$27*12 -> 47666407 | H33: =(Model_Base!AM23/$A33)*H$27*12 -> 51186388
A34: 0.16 | B34: =(Model_Base!AM23/$A34)*B$27*12 -> 25538194 | C34: =(Model_Base!AM23/$A34)*C$27*12 -> 28874843 | D34: =(Model_Base!AM23/$A34)*D$27*12 -> 31954826 | E34: =(Model_Base!AM23/$A34)*E$27*12 -> 35291474 | F34: =(Model_Base!AM23/$A34)*F$27*12 -> 38371457 | G34: =(Model_Base!AM23/$A34)*G$27*12 -> 41708106 | H34: =(Model_Base!AM23/$A34)*H$27*12 -> 44788089
A37: Table 4 — Single-variable sensitivity (Base): what each high-sensitivity input must be for LTV:CAC = 3.0 at the month-24 Base CAC
A38: Month-24 Base CAC per Rx member | B38: =Model_Base!AA66 -> 312.62201
A39: Required contribution per member-month at Base churn for LTV:CAC = 3 | B39: =3*Model_Base!AA66*Assumptions!$E$41 -> 103.16526
A40: Current Base contribution per member-month | B40: =(Assumptions!$E$30*(1-Assumptions!$E$50-Assumptions!$E$49)-Assumptions!$E$44-Assumptions!$E$46-Assumptions!$E$47-Assumptions!$E$51) -> 134.4
A41: Maximum monthly churn for LTV:CAC = 3 at current contribution | B41: =IF(Model_Base!AA66=0,0,(Assumptions!$E$30*(1-Assumptions!$E$50-Assumptions!$E$49)-Assumptions!$E$44-Assumptions!$E$46-Assumptions!$E$47-Assumptions!$E$51)/(3*Model_Base!AA66)) -> 0.14330405
A42: Maximum CAC for LTV:CAC = 3 at current contribution and churn | B42: =(Assumptions!$E$30*(1-Assumptions!$E$50-Assumptions!$E$49)-Assumptions!$E$44-Assumptions!$E$46-Assumptions!$E$47-Assumptions!$E$51)/Assumptions!$E$41/3 -> 407.27273

Sheet Celebrity Economics
A1: Hypothetical brand-partner compensation structures (no terms have been offered, discussed, or accepted)
A2: Uses Base-scenario net revenue. Equity value is illustrative and depends on an assumed exit multiple; it is not a valuation. All structures require FTC material-connection disclosure and counsel review of NIL, exclusivity, morality, and termination terms.
A4: Inputs
A5: Base net revenue, year 1 | B5: =SUM(Model_Base!D43:O43) -> 3428128.3
A6: Base net revenue, year 2 | B6: =SUM(Model_Base!P43:AA43) -> 19830860
A7: Base net revenue, year 3 | B7: =SUM(Model_Base!AB43:AM43) -> 42820608
A8: Illustrative year-3 revenue multiple for equity value (assumption) | B8: 3
A9: Structure 1 — Cash only: annual retainer | B9: 600000
A10: Structure 2 — Equity only: fully diluted % | B10: 0.1
A11: Structure 3 — Royalty only: % of net revenue | B11: 0.06
A12: Structure 4 — Mixed: annual cash retainer | B12: 360000
A13: Structure 4 — Mixed: royalty % of net revenue | B13: 0.03
A14: Structure 4 — Mixed: equity % (fully diluted) | B14: 0.05
A15: Structure 5 — Performance: royalty % above revenue hurdle | B15: 0.08
A16: Structure 5 — Performance: annual net revenue hurdle | B16: 5000000
A19: Illustrative partner economics by structure
A20: Structure | B20: Year 1 cash | C20: Year 2 cash | D20: Year 3 cash | E20: 3-yr cash total | F20: Illustrative equity value at yr-3 multiple | G20: 3-yr total value | H20: Cash cost as % of 3-yr revenue
A21: 1. Cash retainer only | B21: =$B$9 -> 600000 | C21: =$B$9 -> 600000 | D21: =$B$9 -> 600000 | E21: =SUM(B21:D21) -> 1800000 | F21: =0 -> 0 | G21: =E21+F21 -> 1800000 | H21: =IF(SUM($B$5,$B$6,$B$7)=0,0,E21/SUM($B$5,$B$6,$B$7)) -> 0.027239876
A22: 2. Equity only | B22: =0 -> 0 | C22: =0 -> 0 | D22: =0 -> 0 | E22: =SUM(B22:D22) -> 0 | F22: =$B$10*$B$7*$B$8 -> 12846182 | G22: =E22+F22 -> 12846182 | H22: =IF(SUM($B$5,$B$6,$B$7)=0,0,E22/SUM($B$5,$B$6,$B$7)) -> 0
A23: 3. Royalty only | B23: =$B$11*$B$5 -> 205687.7 | C23: =$B$11*$B$6 -> 1189851.6 | D23: =$B$11*$B$7 -> 2569236.5 | E23: =SUM(B23:D23) -> 3964775.8 | F23: =0 -> 0 | G23: =E23+F23 -> 3964775.8 | H23: =IF(SUM($B$5,$B$6,$B$7)=0,0,E23/SUM($B$5,$B$6,$B$7)) -> 0.06
A24: 4. Mixed (cash + royalty + equity) | B24: =$B$12+$B$13*$B$5 -> 462843.85 | C24: =$B$12+$B$13*$B$6 -> 954925.81 | D24: =$B$12+$B$13*$B$7 -> 1644618.2 | E24: =SUM(B24:D24) -> 3062387.9 | F24: =$B$14*$B$7*$B$8 -> 6423091.2 | G24: =E24+F24 -> 9485479.1 | H24: =IF(SUM($B$5,$B$6,$B$7)=0,0,E24/SUM($B$5,$B$6,$B$7)) -> 0.046343925
A25: 5. Performance royalty above hurdle | B25: =$B$15*MAX(0,$B$5-$B$16) -> 0 | C25: =$B$15*MAX(0,$B$6-$B$16) -> 1186468.8 | D25: =$B$15*MAX(0,$B$7-$B$16) -> 3025648.6 | E25: =SUM(B25:D25) -> 4212117.5 | F25: =0 -> 0 | G25: =E25+F25 -> 4212117.5 | H25: =IF(SUM($B$5,$B$6,$B$7)=0,0,E25/SUM($B$5,$B$6,$B$7)) -> 0.063743087
A27: Reading this table: cash-heavy structures front-load risk onto the company before demand is proven; royalty and equity structures align incentives but dilute margin or ownership. A mixed structure with a modest retainer, a capped royalty, and vesting equity tied to deliverables (content days, launch obligations) is the analyst's recommended starting point, subject to negotiation and counsel. Independent of structure: medical decisions must be insulated from partner influence, and disclosure of ownership/compensation is required in endorsements.

Sheet Assumptions Register
A1: Assumptions register (links to the Assumptions sheet; edit values there)
A3: Assumption | B3: Unit | C3: Base value | D3: Rationale / source | E3: Confidence | F3: Sensitivity | G3: Validation method
A4: Public launch month (model month #) | B4: month | C4: =Assumptions!$E$6 -> 8 | D4: Phase plan in 06_ReserveClinic_Launch_Plan.md: Phase 0-3 precede launch; conservative adds one month of slippage. | E4: Medium | F4: High | G4: Phase exit criteria
A5: Private beta start month | B5: month | C5: =Assumptions!$E$7 -> 5 | D5: Phase 2 begins after internal pilot. | E5: Medium | F5: Low | G5: Phase exit criteria
A6: Organic + direct sessions in month 1 | B6: sessions | C6: =Assumptions!$E$9 -> 2500 | D6: Prototype site with 20 library entries; comparable early-stage health content sites. Analyst assumption. | E6: Low | F6: Medium | G6: GA4 after month 1
A7: Organic monthly growth rate | B7: % | C7: =Assumptions!$E$10 -> 0.09 | D7: Library-led SEO compounding; DTC health benchmarks show 8-15%/mo early growth from a small base (analyst inference from research/06 benchmarks). | E7: Low | F7: High | G7: Search Console trend, quarterly
A8: Organic + direct sessions ceiling per month | B8: sessions | C8: =Assumptions!$E$11 -> 300000 | D8: Caps compounding growth; category-level informational search demand is finite (analyst inference). | E8: Low | F8: Medium | G8: Search Console
A9: Cost per paid session (blended) | B9: $ | C9: =Assumptions!$E$12 -> 2 | D9: Health/wellness CPC and CPM proxies; Meta health-category restrictions raise cost. Analyst assumption. | E9: Medium | F9: High | G9: Ad platform reports
A10: Paid media spend per month, months 1 to beta-1 | B10: $ | C10: =Assumptions!$E$13 -> 20000 | D10: Waitlist/education ads only. | E10: Medium | F10: Low | G10: Budget actuals
A11: Paid media spend per month, beta to launch-1 | B11: $ | C11: =Assumptions!$E$14 -> 60000 | D11: Waitlist building (Phase 3). | E11: Medium | F11: Medium | G11: Budget actuals
A12: Paid media spend, launch month | B12: $ | C12: =Assumptions!$E$15 -> 350000 | D12: Phase 4 budget range. | E12: Medium | F12: Medium | G12: Budget actuals
A13: Paid media spend per month after launch (month launch+1) | B13: $ | C13: =Assumptions!$E$16 -> 180000 | D13: Phase 5 operating range; scaled by growth below. | E13: Medium | F13: High | G13: Payback discipline gate
A14: Monthly growth in post-launch paid spend | B14: % | C14: =Assumptions!$E$17 -> 0.03 | D14: Spend grows only while payback <= target. | E14: Medium | F14: Medium | G14: Monthly CAC review
A15: Quiz start rate (starts / sessions) | B15: % | C15: =Assumptions!$E$19 -> 0.1 | D15: Telehealth quiz-start benchmarks 5-10% (analyst inference). | E15: Medium | F15: High | G15: Analytics
A16: Quiz completion rate | B16: % | C16: =Assumptions!$E$20 -> 0.7 | D16: One-question-per-screen quizzes typically 55-75%. | E16: Medium | F16: Medium | G16: Analytics
A17: Share of completes with an eligible outcome | B17: % | C17: =Assumptions!$E$21 -> 0.6 | D17: Red-flag and state screening remove 40-55%. | E17: Medium | F17: Medium | G17: Analytics
A18: Share of US population in served states at launch | B18: % | C18: =Assumptions!$E$22 -> 0.4 | D18: 4-6 pilot states incl. large states (TX, FL) if licensure achieved. | E18: Medium | F18: High | G18: State readiness tracker
A19: Monthly increase in population coverage after launch | B19: % | C19: =Assumptions!$E$23 -> 0.03 | D19: Tranche-based expansion. | E19: Medium | F19: Medium | G19: State readiness tracker
A20: Maximum population coverage | B20: % | C20: =Assumptions!$E$24 -> 0.85 | D20: Some states excluded for CPOM/async restrictions. | E20: Medium | F20: Low | G20: Counsel memo
A21: Intake submission rate (eligible → intake) | B21: % | C21: =Assumptions!$E$25 -> 0.55 | D21: ID verification and consent friction. | E21: Medium | F21: High | G21: Analytics
A22: Consult completion rate | B22: % | C22: =Assumptions!$E$26 -> 0.82 | D22: Async review completes higher than video. | E22: Medium | F22: Medium | G22: EHR data
A23: Clinician prescribing rate (clinical decision; not a target) | B23: % | C23: =Assumptions!$E$27 -> 0.62 | D23: Observed ranges for telehealth GLP-1/hormone programs 50-70% (third-party reports); monitored for safety only. | E23: Low | F23: High | G23: Medical director audit
A24: Enrollment (paid) rate after prescription | B24: % | C24: =Assumptions!$E$28 -> 0.65 | D24: Price shock at plan stage; all-in pricing shown earlier improves this. | E24: Medium | F24: High | G24: Analytics
A25: All-in program price per member-month (blended) | B25: $ | C25: =Assumptions!$E$30 -> 275 | D25: Competitive bands in 03_Peptide_Product_and_Pricing_Audit.xlsx: compounded peptide programs ~$150-$450/mo; premium positioning. | E25: Medium | F25: High | G25: Van Westendorp + tests
A26: Consultation fee (charged at intake) | B26: $ | C26: =Assumptions!$E$31 -> 79 | D26: Range $0-$150 among competitors; refundable if not eligible is common. | E26: Medium | F26: Medium | G26: Pricing test
A27: Share of new intakes ordering labs | B27: % | C27: =Assumptions!$E$32 -> 0.5 | D27: Programs requiring labs (hormone/metabolic). | E27: Medium | F27: Medium | G27: EHR data
A28: Lab panel price charged | B28: $ | C28: =Assumptions!$E$33 -> 119 | D28: Direct-pay panels via lab partners. | E28: Medium | F28: Low | G28: Vendor quotes
A29: Membership price per month (education, navigation, member pricing) | B29: $ | C29: =Assumptions!$E$34 -> 29 | D29: Function Health $499/yr, Superpower $199-499/yr and Lifeforce $129/mo bracket the range; Reserve Clinic tier is lighter. | E29: Medium | F29: Medium | G29: Pricing test
A30: Membership attach among non-eligible quiz completers | B30: % | C30: =Assumptions!$E$35 -> 0.06 | D30: Analyst assumption. | E30: Low | F30: Medium | G30: Analytics
A31: Membership sign-ups per session (organic) | B31: % | C31: =Assumptions!$E$36 -> 0.001 | D31: Analyst assumption. | E31: Low | F31: Low | G31: Analytics
A32: Non-Rx shop conversion (orders / sessions) | B32: % | C32: =Assumptions!$E$37 -> 0.009 | D32: DTC supplement conversion 0.5-1.5%. | E32: Medium | F32: Medium | G32: Shopify analytics
A33: Non-Rx average order value | B33: $ | C33: =Assumptions!$E$38 -> 75 | D33: Premium supplement/cosmetic AOV. | E33: Medium | F33: Low | G33: Shopify analytics
A34: Monthly reorder rate of prior shop customers | B34: % | C34: =Assumptions!$E$39 -> 0.15 | D34: Subscription attach on consumables. | E34: Low | F34: Medium | G34: Shopify analytics
A35: Monthly churn, prescription programs (blended) | B35: % | C35: =Assumptions!$E$41 -> 0.11 | D35: DTC health subscription churn 8-15%/mo; GLP-1 programs higher. Third-party benchmarks in research/06. | E35: Low | F35: High | G35: Cohort analysis
A36: Monthly churn, membership | B36: % | C36: =Assumptions!$E$42 -> 0.06 | D36: Content memberships 5-8%. | E36: Low | F36: Medium | G36: Cohort analysis
A37: Pharmacy/medication cost per Rx member-month | B37: $ | C37: =Assumptions!$E$44 -> 95 | D37: Compounded peptide and GLP-1 wholesale-to-telehealth cost bands (third-party reports); volume tiers reduce cost. | E37: Low | F37: High | G37: Pharmacy contracts
A38: Clinician cost per completed consult | B38: $ | C38: =Assumptions!$E$45 -> 40 | D38: Async visit cost via provider networks ~$25-60. | E38: Medium | F38: Medium | G38: Vendor contracts
A39: Clinician cost per active Rx member-month (monitoring/refill review) | B39: $ | C39: =Assumptions!$E$46 -> 8 | D39: Monthly check-in review. | E39: Medium | F39: Medium | G39: Vendor contracts
A40: Fulfillment + shipping per Rx shipment (cold chain where needed) | B40: $ | C40: =Assumptions!$E$47 -> 15 | D40: Pharmacy carrier programs. | E40: Medium | F40: Low | G40: Pharmacy contracts
A41: Lab panel cost | B41: $ | C41: =Assumptions!$E$48 -> 80 | D41: Direct-pay lab wholesale. | E41: Medium | F41: Low | G41: Vendor quotes
A42: Payment processing fee (% of revenue) | B42: % | C42: =Assumptions!$E$49 -> 0.029 | D42: Card fees 2.7-3.2% + fixed; high-risk processors cost more. | E42: High | F42: Low | G42: Processor statements
A43: Refunds and chargebacks (% of revenue) | B43: % | C43: =Assumptions!$E$50 -> 0.035 | D43: Benchmark 2-5%. | E43: Medium | F43: Medium | G43: Finance actuals
A44: Support cost per active member-month (non-clinical) | B44: $ | C44: =Assumptions!$E$51 -> 5 | D44: Tooling + staffing per member. | E44: Medium | F44: Low | G44: Support actuals
A45: Non-Rx product COGS (% of revenue) | B45: % | C45: =Assumptions!$E$52 -> 0.35 | D45: Premium supplements 30-40%. | E45: Medium | F45: Low | G45: Supplier quotes
A46: Non-Rx fulfillment per order | B46: $ | C46: =Assumptions!$E$53 -> 8 | D46: 3PL pick/pack/ship. | E46: Medium | F46: Low | G46: 3PL quotes
A47: Membership delivery cost per member-month | B47: $ | C47: =Assumptions!$E$54 -> 2 | D47: Platform + content amortization. | E47: Medium | F47: Low | G47: Actuals
A48: Team cost per month, months 1-3 | B48: $ | C48: =Assumptions!$E$56 -> 60000 | D48: GM, product lead, compliance (fractional), engineering contractors. | E48: Medium | F48: Medium | G48: Hiring plan
A49: Team cost per month, month 4 to launch-1 | B49: $ | C49: =Assumptions!$E$57 -> 120000 | D49: Adds content, support, ops. | E49: Medium | F49: Medium | G49: Hiring plan
A50: Team cost per month, launch to month 12 | B50: $ | C50: =Assumptions!$E$58 -> 180000 | D50: Growth, support scaling. | E50: Medium | F50: Medium | G50: Hiring plan
A51: Team cost per month, months 13-24 | B51: $ | C51: =Assumptions!$E$59 -> 260000 | E51: Low | F51: Medium | G51: Hiring plan
A52: Team cost per month, months 25-36 | B52: $ | C52: =Assumptions!$E$60 -> 340000 | E52: Low | F52: Medium | G52: Hiring plan
A53: Medical leadership (medical director + advisory) per month | B53: $ | C53: =Assumptions!$E$61 -> 20000 | D53: Fractional medical director retainers $10-25k/mo (analyst inference); compensation never tied to Rx volume. | E53: Medium | F53: Low | G53: Agreement
A54: Technology & software per month, pre-launch | B54: $ | C54: =Assumptions!$E$62 -> 12000 | D54: Vendor sandboxes, CMS, analytics, CMP. | E54: Medium | F54: Low | G54: Vendor quotes
A55: Technology & software per month, post-launch | B55: $ | C55: =Assumptions!$E$63 -> 30000 | D55: Telehealth/EHR platform fees, Shopify, Stripe, warehouse, support tools. | E55: Medium | F55: Medium | G55: Vendor quotes
A56: Site & portal build per month, months 1-4 (one-time) | B56: $ | C56: =Assumptions!$E$64 -> 60000 | D56: Option C build $150-300k in 05_ReserveClinic_Website_Strategy.md. | E56: Medium | F56: Low | G56: SOW
A57: Legal, regulatory & compliance per month, months 1-3 | B57: $ | C57: =Assumptions!$E$65 -> 50000 | D57: Structuring, CPOM memos, formulary review, trademark, contracts. | E57: Medium | F57: Low | G57: Counsel estimates
A58: Legal & compliance per month thereafter | B58: $ | C58: =Assumptions!$E$66 -> 20000 | D58: Ongoing review, state expansion, claims review. | E58: Medium | F58: Low | G58: Counsel estimates
A59: Insurance per month (from launch) | B59: $ | C59: =Assumptions!$E$67 -> 8000 | D59: Professional, product, cyber, D&O. | E59: Medium | F59: Low | G59: Broker quotes
A60: Creative & content production per month, pre-launch | B60: $ | C60: =Assumptions!$E$68 -> 25000 | D60: Library, video series, photography. | E60: Medium | F60: Low | G60: Agency quotes
A61: Creative & content production per month, post-launch | B61: $ | C61: =Assumptions!$E$69 -> 40000 | E61: Medium | F61: Low | G61: Agency quotes
A62: Launch PR/events one-time (launch month) | B62: $ | C62: =Assumptions!$E$70 -> 90000 | D62: Phase 4 budget. | E62: Medium | F62: Low | G62: Agency quotes
A63: Influencer/affiliate per month, beta to launch-1 | B63: $ | C63: =Assumptions!$E$71 -> 25000 | D63: Disclosed creator seeding. | E63: Medium | F63: Medium | G63: Contracts
A64: Influencer/affiliate per month, post-launch | B64: $ | C64: =Assumptions!$E$72 -> 50000 | E64: Medium | F64: Medium | G64: Contracts
A65: Named-partner model active? (1 = Scenario A, 0 = Scenario B) | B65: flag | C65: =Assumptions!$E$74 -> 1 | D65: Toggle to compare Scenario A vs B. Set to 0 for the independent-brand model. | E65: n/a | F65: High | G65: Founder decision
A66: Brand partner cash retainer per month (from beta month) | B66: $ | C66: =Assumptions!$E$75 -> 30000 | D66: Hypothetical mixed structure; see Celebrity Economics sheet for alternatives. | E66: Low | F66: High | G66: Negotiation
A67: Brand partner royalty (% of net revenue) | B67: % | C67: =Assumptions!$E$76 -> 0.03 | D67: Hypothetical; licensing royalties in consumer brands commonly 3-10% (third-party reports). | E67: Low | F67: High | G67: Negotiation
A68: Brand partner equity (% fully diluted; non-cash, for reference) | B68: % | C68: =Assumptions!$E$77 -> 0.08 | D68: Hypothetical. | E68: Low | F68: n/a | G68: Negotiation
A69: Traffic uplift multiplier when named-partner model is active (post-launch organic/direct) | B69: x | C69: =Assumptions!$E$78 -> 1.25 | D69: Celebrity-founded brands show launch-window demand spikes (see 04_Celebrity_Founder_Database.xlsx lessons); durability uncertain. | E69: Low | F69: High | G69: Brand-lift study
A70: Non-Rx inventory on hand (months of COGS) | B70: months | C70: =Assumptions!$E$80 -> 1.5 | D70: Initial stock. | E70: Medium | F70: Low | G70: Ops
A71: Opening cash (for cash-balance line; capital requirement computed separately) | B71: $ | C71: =Assumptions!$E$81 -> 0 | D71: Set to committed capital once known. | E71: n/a | F71: n/a | G71: Cap table
