Workbook

Sheet Read_Me
A1: Reserve Clinic - Margin and Growth Model
A3: What this is
A4: A driver-based 36-month model of a two-line peptide and supplement business: a non-prescription supplement line that can trade in all fifty states, and a prescription telehealth line fulfilled by 503A and 503B pharmacies whose state footprint expands over time. It is built for the specific operating structure the project owner described, including a turnkey compliance-and-fulfilment provider at a flat $600 per month. Three scenarios: Conservative, Baseline, Aggressive.
A6: What it is not
A7: Not a forecast, not a valuation, and not legal, medical, tax or investment advice. The outputs follow arithmetically from the drivers on the Assumptions sheet. Change a driver and the answer changes. Several of the most consequential drivers rest on analyst assumptions rather than measurements, and those are labelled Low confidence with a stated validation method.
A9: Status of the people named
A10: The proposed brand partner and the proposed medical co-founder are treated strictly as proposed. No public evidence connects either to this venture, no agreement exists, and nothing in this workbook is an offer or implies endorsement, ownership or authorisation. Partner compensation figures are illustrative arithmetic, not terms.
A12: Colour key
A13: Blue = editable input, on the Assumptions sheet only. Black = formula. Green = link to another sheet. Yellow fill = high-sensitivity driver: get these wrong and the answer changes materially. Peach fill = a caution the reader should not skip.
A15: Sheet order
A16: Summary reads the three scenarios side by side. Unit_Economics shows where margin comes from per order and per member-month. Sensitivity shows which assumptions decide the outcome. Partner_Economics is illustrative deal arithmetic. Provider_Diligence is the twenty questions to answer in writing before signing. Benchmarks is the evidence. Assumptions holds every input. Model_Conservative, Model_Baseline and Model_Aggressive are the monthly grids.
A18: The three things most likely to be wrong
... A25: 2026-09-18. Rebuild with: python3 build/build_margin_model.py outputs/09_ReserveClinic_Margin_and_Growth_Model.xlsx

Sheet Assumptions
A1: Reserve Clinic - Margin and Growth Model: Assumptions
A2: Blue cells are the only inputs. Three scenario columns drive Model_Conservative, Model_Baseline and Model_Aggressive. Yellow fill marks high-sensitivity drivers. Prepared 2026-09-18. Proposed concept: the brand partner's and the medical co-founder's participation is unverified and subject to definitive agreements. Not legal, medical, tax or investment advice.
A4: Key | B4: Driver | C4: Unit | D4: Conservative | E4: Baseline | F4: Aggressive | G4: Rationale / source | H4: Confidence | I4: Sensitivity | J4: Validation method
A5: Timing and sequencing
A6: nonrx_launch | B6: Non-prescription line goes live (model month) | C6: month | D6: 3 | E6: 2 | F6: 2 | G6: Supplement line needs only manufacturing, label/claims review and a storefront. Conservative allows one month of slippage on label review. | H6: High | I6: Medium | J6: Phase exit checklist
A7: rx_launch | B7: Prescription telehealth line goes live (model month) | C7: month | D7: 9 | E7: 7 | F7: 5 | G7: Requires the provider agreement, physician entity, pharmacy contracts, LegitScript certification and a state-by-state licensure map. Benchmark B10, B11. | H7: Medium | I7: High | J7: Counsel and provider go-live sign-off
A8: Audience engine (the proposed brand partner's reach)
A9: followers | B9: Proposed brand partner Instagram followers | C9: # | D9: 27400000 | E9: 27400000 | F9: 27400000 | G9: Third-party trackers report 27,410,219 as of June 2026 (range 27.0M-28.3M). Benchmark B16. Held constant across scenarios because it is measured, not chosen. NOT an audited or first-party figure. | H9: Medium | I9: High | J9: First-party creator analytics export
A10: posts_per_month | B10: Brand posts per month by the partner (feed plus reels) | C10: # | D10: 2 | E10: 4 | F10: 6 | G10: A contract deliverable, not a market variable. Set to whatever the agreement actually obliges. | H10: n/a | I10: High | J10: Signed content schedule
A11: reach_pct | B11: Reach per brand post as a share of followers | C11: % | D11: 0.04 | E11: 0.07 | F11: 0.11 | G11: Analyst assumption bounded by benchmark B15: the 10M-plus tier averages ~1.77% ENGAGEMENT; reach exceeds engagement but organic reach at this tier is heavily throttled and branded content more so. Reels reach higher than static. | H11: Low | I11: High | J11: Creator-account reach data, first 60 days
A12: ctr_reach | B12: Click-through to site per reached impression | C12: % | D12: 0.0035 | E12: 0.006 | F12: 0.009 | G12: Analyst assumption. No tier-level link-click benchmark was retrievable (benchmark B15 notes this gap). This is the single least-evidenced driver in the model. | H12: Low | I12: High | J12: UTM-tagged link data, first 30 days
A13: attn_decay | B13: Monthly decay of partner-driven traffic toward a floor | C13: % | D13: 0.72 | E13: 0.8 | F13: 0.86 | G13: Analyst assumption. Celebrity launch demand spikes then settles; benchmark B14 notes IM8's founders deliberately did not rely on fame for durability. | H13: Low | I13: High | J13: Cohort traffic by source, monthly
A14: attn_floor | B14: Floor for partner-driven traffic as a share of the launch peak | C14: % | D14: 0.28 | E14: 0.36 | F14: 0.45 | G14: Analyst assumption. Represents the durable follower demand that persists after novelty. | H14: Low | I14: High | J14: Cohort traffic by source, monthly
A15: launch_spike | B15: Launch-month multiplier on partner-driven traffic | C15: x | D15: 1.6 | E15: 2.2 | F15: 3 | G15: Announcement window concentrates attention. Analyst assumption. | H15: Low | I15: Medium | J15: Launch-week analytics
A16: Other traffic
A17: organic_m1 | B17: Organic and direct sessions, month 1 | C17: sessions | D17: 1200 | E17: 2200 | F17: 3500 | G17: New domain with an editorial library. Analyst assumption. | H17: Low | I17: Low | J17: GA4 after month 1
A18: organic_growth | B18: Organic monthly growth rate | C18: % | D18: 0.06 | E18: 0.09 | F18: 0.12 | G18: Content-led SEO compounding from a small base. Analyst inference. | H18: Low | I18: Medium | J18: Search Console trend
A19: organic_cap | B19: Organic and direct sessions ceiling | C19: sessions | D19: 90000 | E19: 180000 | F19: 320000 | G19: Caps compounding; category search demand is finite. Analyst inference. | H19: Low | I19: Medium | J19: Search Console
A20: cps | B20: Cost per paid session, blended | C20: $ | D20: 2.6 | E20: 2.15 | F20: 1.85 | G20: Health and wellness CPC proxies; restricted-category ad review raises cost. LegitScript certification is a precondition for scaled healthcare advertising (benchmark B10). | H20: Medium | I20: High | J20: Ad platform reports
A21: paid_pre | B21: Paid media per month before the non-Rx launch | C21: $ | D21: 4000 | E21: 8000 | F21: 15000 | G21: Waitlist and audience building only. | H21: Medium | I21: Low | J21: Budget actuals
A22: paid_floor | B22: Minimum paid media per month after launch | C22: $ | D22: 10000 | E22: 30000 | F22: 60000 | G22: Keeps a spend floor while revenue is small. | H22: Medium | I22: Medium | J22: Budget actuals
A23: paid_pct | B23: Paid media as a share of prior-month net revenue | C23: % | D23: 0.3 | E23: 0.24 | F23: 0.2 | G23: Benchmark B02: the closest listed telehealth comparable ran marketing at 35-40% of revenue. A celebrity-led brand should sit WELL below that, because the point of the partnership is that owned audience substitutes for bought audience; if this driver has to rise toward 35% the partnership is not working. Prior-month basis avoids a circular reference. | H23: Medium | I23: High | J23: Monthly payback review
A24: launch_push | B24: One-time launch marketing and PR, non-Rx launch month | C24: $ | D24: 40000 | E24: 150000 | F24: 400000 | G24: Announcement window spend: PR, production, seeding, paid amplification. Concentrated in a single month by design. | H24: Medium | I24: Medium | J24: Agency scopes
A25: paid_cap | B25: Maximum paid media per month | C25: $ | D25: 200000 | E25: 900000 | F25: 2500000 | G25: A budget ceiling and a reality check. Without one, a percent-of-revenue rule compounds without limit. At the Aggressive ceiling this is roughly 25-30% of revenue at scale, in line with benchmark B02. | H25: Medium | I25: High | J25: Board-approved budget
A26: paid_elast | B26: Paid response elasticity (sessions per marginal dollar) | C26: x | D26: 0.68 | E26: 0.75 | F26: 0.82 | G26: Diminishing returns. Sessions scale as (spend / floor) raised to this power, so at ten times the floor spend the effective cost per session rises about 1.8x at 0.75. Below 1.0 is the whole point: auction competition and audience exhaustion mean the second million never buys what the first did. Analyst assumption, standard media-mix practice. | H26: Low | I26: High | J26: Marginal CAC by spend decile
A27: Non-prescription line: funnel and pricing
A28: cap_m1 | B28: Orders the supply chain can ship in the first live month | C28: # | D28: 600 | E28: 1500 | F28: 3000 | G28: Manufacturing minimum order quantities, batch lead times, label print runs and 3PL onboarding all gate the first months. Demand above this ceiling is treated as LOST, not backlogged, which is the conservative treatment. Analyst assumption; replace with the contract manufacturer's actual run schedule. | H28: Low | I28: High | J28: Manufacturer run schedule and 3PL onboarding plan
A29: cap_growth | B29: Monthly growth in shippable capacity | C29: x | D29: 1.25 | E29: 1.35 | F29: 1.45 | G29: How fast production and fulfilment can be scaled. Binds hard in the first year of the Aggressive case and stops binding thereafter. Analyst assumption. | H29: Low | I29: High | J29: Purchase-order lead times
A30: shop_conv | B30: Order conversion rate, all sessions | C30: % | D30: 0.009 | E30: 0.014 | F30: 0.019 | G30: DTC supplement conversion commonly 0.5-1.5%; a warm follower audience should sit at the top of or above that band, but benchmark B15 warns mega-tier audiences convert worse than their reach implies. | H30: Low | I30: High | J30: Shopify analytics
A31: nonrx_aov | B31: Average order value | C31: $ | D31: 68 | E31: 78 | F31: 88 | G31: Above the $30-65 monthly band in benchmark B06, reflecting a premium multi-product basket. Requires validation. | H31: Medium | I31: High | J31: Shopify analytics
A32: sub_attach | B32: Share of new customers taking a subscription | C32: % | D32: 0.3 | E32: 0.4 | F32: 0.5 | G32: Subscribe-and-save attach on consumables. Analyst assumption. | H32: Low | I32: High | J32: Subscription app data
A33: sub_churn | B33: Monthly subscription churn | C33: % | D33: 0.09 | E33: 0.07 | F33: 0.055 | G33: Benchmark B05: 4-7% monthly well run, 8-12% category average, 12-20% churning in month one alone. | H33: Medium | I33: High | J33: Cohort analysis
A34: onetime_repeat | B34: Monthly reorder rate of one-time buyers | C34: % | D34: 0.08 | E34: 0.11 | F34: 0.14 | G34: Approximation: applied to the prior month's one-time cohort only, which understates a long tail and is deliberately conservative. | H34: Low | I34: Medium | J34: Cohort analysis
A35: Non-prescription line: cost of revenue
A36: nonrx_cogs_pct | B36: Landed product COGS as a share of retail | C36: % | D36: 0.3 | E36: 0.26 | F36: 0.22 | G36: Benchmark B03: landed COGS 20-30% of retail for DTC supplements, giving 70-80% product gross margin. | H36: Medium | I36: High | J36: Contract manufacturer quotes
A37: nonrx_fulfil | B37: Pick, pack and ship per order (ambient) | C37: $ | D37: 8.5 | E37: 7.5 | F37: 6.5 | G37: 3PL pick-pack plus domestic parcel. Ambient, not cold chain. | H37: Medium | I37: Low | J37: 3PL quotes
A38: Prescription line: funnel
A39: rx_intent | B39: Eligibility-quiz start rate, all sessions | C39: % | D39: 0.012 | E39: 0.018 | F39: 0.025 | G39: Analyst assumption. Prescription intent is a small slice of brand traffic. | H39: Low | I39: High | J39: Analytics
A40: quiz_complete | B40: Quiz completion rate | C40: % | D40: 0.6 | E40: 0.7 | F40: 0.76 | G40: One-question-per-screen intake typically 55-75%. | H40: Medium | I40: Medium | J40: Analytics
A41: eligible_rate | B41: Share of completions with a clinically eligible outcome | C41: % | D41: 0.5 | E41: 0.58 | F41: 0.64 | G41: Red-flag screening removes a material share. Never a target; a safety control. | H41: Medium | I41: Medium | J41: Medical director audit
A42: state_cov_launch | B42: US population covered by served states at Rx launch | C42: % | D42: 0.26 | E42: 0.36 | F42: 0.45 | G42: Licensure, asynchronous-prescribing rules and corporate-practice-of-medicine limits gate this. Fifty-state prescription coverage is NOT available on day one. | H42: Medium | I42: High | J42: State readiness tracker
A43: state_cov_step | B43: Monthly increase in covered population | C43: % | D43: 0.015 | E43: 0.025 | F43: 0.035 | G43: Tranche-based state expansion. | H43: Medium | I43: Medium | J43: State readiness tracker
A44: state_cov_cap | B44: Maximum covered population | C44: % | D44: 0.7 | E44: 0.82 | F44: 0.88 | G44: Some states stay excluded on asynchronous or CPOM grounds. | H44: Medium | I44: Medium | J44: Counsel memo
A45: intake_submit | B45: Intake submission rate, eligible to intake | C45: % | D45: 0.48 | E45: 0.56 | F45: 0.62 | G45: Identity verification and consent friction. | H45: Medium | I45: High | J45: Analytics
A46: consult_complete | B46: Consult completion rate | C46: % | D46: 0.76 | E46: 0.83 | F46: 0.88 | G46: Asynchronous review completes above video. | H46: Medium | I46: Medium | J46: EHR data
A47: rx_rate | B47: Clinician prescribing rate | C47: % | D47: 0.55 | E47: 0.62 | F47: 0.68 | G47: A clinical decision, never a target. Observed telehealth ranges 50-70%. Monitored solely for safety and for evidence of undue influence. | H47: Low | I47: High | J47: Independent medical audit
A48: enroll_rate | B48: Paid enrolment rate after a prescription is issued | C48: % | D48: 0.58 | E48: 0.66 | F48: 0.7 | G48: Price friction at the plan step; all-in pricing shown before intake improves this. | H48: Medium | I48: High | J48: Analytics
A49: rx_churn | B49: Monthly churn, prescription programmes | C49: % | D49: 0.13 | E49: 0.11 | F49: 0.095 | G49: Benchmark B17: ~65% discontinuation within 12 months in the comparable telehealth population, 84.4% by 24 months. THE most damaging driver if wrong. | H49: Medium | I49: High | J49: Cohort analysis, monthly
A50: Prescription line: pricing
A51: rx_price | B51: Programme price per member-month, blended | C51: $ | D51: 199 | E51: 249 | F51: 299 | G51: Benchmark B07: sermorelin $96-199 telehealth, tissue protocols $100-300, stacks $80-180, combinations $350-600. | H51: Medium | I51: High | J51: Van Westendorp plus live price tests
A52: consult_fee | B52: Consultation fee charged at intake | C52: $ | D52: 49 | E52: 59 | F52: 79 | G52: Benchmark B08: asynchronous visits price at $15-40 commonly, up to $60 for longer reviews. Charged whether or not a prescription follows; refunded if screened ineligible. | H52: Medium | I52: Medium | J52: Pricing test
A53: Prescription line: cost of revenue
A54: pharm_cost | B54: Pharmacy medication cost per member-month | C54: $ | D54: 105 | E54: 88 | F54: 75 | G54: 503A compounded peptide cost to a telehealth sponsor, volume-tiered. Not independently verified; obtain a written tiered schedule. | H54: Low | I54: High | J54: Pharmacy contract schedule
A55: consult_cost | B55: Clinician cost per completed consult | C55: $ | D55: 45 | E55: 38 | F55: 32 | G55: Benchmark B08 cites provider time around $30 per programme plus platform and support. One-time at enrolment. | H55: Medium | I55: Medium | J55: Provider network contract
A56: refill_cost | B56: Clinician cost per active member-month (monitoring and refill review) | C56: $ | D56: 10 | E56: 8 | F56: 6.5 | G56: Recurring clinical review. Must be paid per unit of clinical work, never as a share of revenue. | H56: Medium | I56: Medium | J56: Provider network contract
A57: coldchain_ship | B57: Cold-chain fulfilment and shipping per fill | C57: $ | D57: 22 | E57: 18 | F57: 15 | G57: Benchmark B09: $1.95 base pack rate plus cold storage, insulated mailers, gel packs and a 2-day temperature-controlled lane. The pack rate alone is NOT the landed cost. | H57: Medium | I57: High | J57: Pharmacy and carrier quotes
A58: rx_support | B58: Non-clinical support cost per active member-month | C58: $ | D58: 6 | E58: 4.5 | F58: 3.5 | G58: Tooling plus staffed support per member. | H58: Medium | I58: Low | J58: Support actuals
A59: Shared cost of revenue
A60: pay_fee | B60: Payment processing | C60: % | D60: 0.032 | E60: 0.029 | F60: 0.027 | G60: Card fees 2.7-3.2%. Healthcare and supplement merchants are frequently underwritten as elevated risk, which raises the rate and makes LegitScript certification close to a prerequisite (benchmark B10). | H60: High | I60: Medium | J60: Processor statements
A61: refund_pct | B61: Refunds and chargebacks | C61: % | D61: 0.04 | E61: 0.03 | F61: 0.022 | G61: 2-5% typical. Auto-renewal programmes attract chargebacks; ROSCA-compliant cancellation reduces them. | H61: Medium | I61: Medium | J61: Finance actuals
A62: Operating expenses
A63: provider_fee | B63: Turnkey compliance and fulfilment provider, flat fee | C63: $ | D63: 600 | E63: 600 | F63: 600 | G63: As specified by the project owner. Modelled as a PLATFORM fee only. Published market pricing for comparable turnkey telehealth infrastructure is $3,000-6,000/month plus $5,000-10,000 onboarding plus per-consult fees (benchmark B11), so a $600 fee is very unlikely to absorb medication, per-consult, cold-chain or processing costs. Those are carried separately above. See the Provider_Diligence sheet. | H63: Low | I63: Medium | J63: Executed agreement and fee schedule
A64: cert_cost | B64: Certification and registrations per month | C64: $ | D64: 320 | E64: 280 | F64: 260 | G64: Benchmark B10: ~$3,125 year one and ~$2,150/yr thereafter per site for LegitScript, plus state registrations and renewals; amortised monthly. | H64: Medium | I64: Low | J64: Live fee schedule
A65: team_pre | B65: Team per month before the non-Rx launch | C65: $ | D65: 8000 | E65: 18000 | F65: 25000 | G65: Founder or GM plus fractional operations and contract creative. Small because the provider carries clinical and fulfilment operations. The Conservative column is deliberately a LEAN operator, not a normal operator with weak demand, so that the Conservative outcome reflects demand risk rather than an arbitrary spending choice. | H65: Medium | I65: Medium | J65: Hiring plan
A66: team_p1 | B66: Team per month, non-Rx launch through month 12 | C66: $ | D66: 16000 | E66: 45000 | F66: 70000 | G66: Adds brand, retention, support oversight and a compliance lead. | H66: Medium | I66: Medium | J66: Hiring plan
A67: team_p2 | B67: Team per month, months 13-24 | C67: $ | D67: 24000 | E67: 62000 | F67: 140000 | G67: Scales with order volume and state count, but stays small relative to revenue because the provider carries clinical operations and fulfilment. A brand at this revenue running team above roughly 15% of net revenue has rebuilt in-house what it is already paying the provider for. | H67: Low | I67: Medium | J67: Hiring plan
A68: team_p3 | B68: Team per month, months 25-36 | C68: $ | D68: 32000 | E68: 92000 | F68: 230000 | H68: Low | I68: Medium | J68: Hiring plan
A69: med_lead | B69: Medical director and clinical oversight per month | C69: $ | D69: 5000 | E69: 9000 | F69: 14000 | G69: Fractional medical director retainer. Compensation must never vary with prescription volume or revenue. | H69: Medium | I69: Low | J69: Executed agreement
A70: tech | B70: Technology and software per month | C70: $ | D70: 1500 | E70: 2500 | F70: 4000 | G70: Storefront, subscription management, analytics, consent management, CRM, helpdesk. Separate from the provider fee. | H70: High | I70: Low | J70: Vendor invoices
A71: legal_p0 | B71: Legal and regulatory per month, months 1-4 | C71: $ | D71: 14000 | E71: 25000 | F71: 32000 | G71: Entity structure and MSO or friendly-PC review, provider agreement review, formulary eligibility opinion, claims and label review, endorsement and disclosure protocol, trademark, privacy. Front-loaded deliberately. | H71: Medium | I71: Low | J71: Counsel estimates
A72: legal_ongoing | B72: Legal and compliance per month thereafter | C72: $ | D72: 4000 | E72: 9000 | F72: 12000 | G72: Ongoing claims review, state expansion opinions, FDA list monitoring, contract maintenance. | H72: Medium | I72: Medium | J72: Counsel estimates
A73: insurance | B73: Insurance per month from the non-Rx launch | C73: $ | D73: 2000 | E73: 3500 | F73: 5000 | G73: Product liability, professional, cyber and D&O. A vendor contract does not transfer the brand's own liability. | H73: Medium | I73: Low | J73: Broker quotes
A74: creative | B74: Creative, content and organic social per month | C74: $ | D74: 4500 | E74: 12000 | F74: 26000 | G74: Production the brand controls, distinct from paid media and from partner compensation. | H74: Medium | I74: Medium | J74: Agency quotes
A75: Proposed brand-partner economics (hypothetical; no terms offered or accepted)
A76: partner_cash | B76: Partner cash retainer per month from the non-Rx launch | C76: $ | D76: 0 | E76: 15000 | F76: 25000 | G76: Illustrative only. Structure, amount and mix are entirely unnegotiated. Conservative case models an equity-only deal with no cash retainer. | H76: n/a | I76: High | J76: Negotiation
A77: partner_royalty | B77: Partner royalty on net revenue | C77: % | D77: 0.05 | E77: 0.05 | F77: 0.05 | G77: Illustrative. Consumer-brand licensing royalties commonly 3-10%. Held flat across scenarios so the scenarios isolate business performance rather than deal terms. | H77: n/a | I77: High | J77: Negotiation
A78: partner_equity | B78: Partner equity, fully diluted (reference only) | C78: % | D78: 0.1 | E78: 0.15 | F78: 0.2 | G78: Illustrative. Non-cash; shown on the Partner_Economics sheet for reference and NOT charged to EBITDA. | H78: n/a | I78: n/a | J78: Negotiation
A79: Working capital
A80: inv_months | B80: Non-Rx inventory held, in months of COGS | C80: months | D80: 2.5 | E80: 2 | F80: 2 | G80: Supplement manufacturing runs have long lead times and minimum order quantities, so inventory is the main working-capital draw. The Rx line carries no inventory; the pharmacy does. | H80: Medium | I80: Medium | J80: Purchase orders

Sheet Summary
A1: Reserve Clinic - Margin and Growth Summary
A2: All figures are model outputs, not forecasts. They follow arithmetically from the drivers on Assumptions. Read them as a band produced by a stated set of assumptions, each of which is listed with its confidence and its validation method. Proposed concept; partner participation unverified.
A4: Metric | B4: Conservative | C4: Baseline | D4: Aggressive
A5: Net revenue, year 1 | B5: =SUM(Model_Conservative!C60:N60) -> 128902.31 | C5: =SUM(Model_Baseline!C60:N60) -> 1837396.5 | D5: =SUM(Model_Aggressive!C60:N60) -> 15330885
A6: Net revenue, year 2 | B6: =SUM(Model_Conservative!O60:Z60) -> 243504.43 | C6: =SUM(Model_Baseline!O60:Z60) -> 4069835.8 | D6: =SUM(Model_Aggressive!O60:Z60) -> 62800309
A7: Net revenue, year 3 | B7: =SUM(Model_Conservative!AA60:AL60) -> 352473.95 | C7: =SUM(Model_Baseline!AA60:AL60) -> 7063186.2 | D7: =SUM(Model_Aggressive!AA60:AL60) -> 1.3854843e+08
A8: Net revenue, 36-month total | B8: =SUM(Model_Conservative!C60:AL60) -> 724880.69 | C8: =SUM(Model_Baseline!C60:AL60) -> 12970419 | D8: =SUM(Model_Aggressive!C60:AL60) -> 2.1667962e+08
A10: Gross profit, year 3 | B10: =SUM(Model_Conservative!AA61:AL61) -> 170760.36 | C10: =SUM(Model_Baseline!AA61:AL61) -> 3999705.8 | D10: =SUM(Model_Aggressive!AA61:AL61) -> 90678495
A11: Blended gross margin, year 1 | B11: =IFERROR(SUM(Model_Conservative!C61:N61)/SUM(Model_Conservative!C60:N60),0) -> 0.51959308 | C11: =IFERROR(SUM(Model_Baseline!C61:N61)/SUM(Model_Baseline!C60:N60),0) -> 0.59376752 | D11: =IFERROR(SUM(Model_Aggressive!C61:N61)/SUM(Model_Aggressive!C60:N60),0) -> 0.66098121
A12: Blended gross margin, year 3 | B12: =IFERROR(SUM(Model_Conservative!AA61:AL61)/SUM(Model_Conservative!AA60:AL60),0) -> 0.48446234 | C12: =IFERROR(SUM(Model_Baseline!AA61:AL61)/SUM(Model_Baseline!AA60:AL60),0) -> 0.56627501 | D12: =IFERROR(SUM(Model_Aggressive!AA61:AL61)/SUM(Model_Aggressive!AA60:AL60),0) -> 0.65448953
A13: Non-Rx gross margin, year 3 | B13: =IFERROR(SUM(Model_Conservative!AA35:AL35)/SUM(Model_Conservative!AA31:AL31),0) -> 0.52529167 | C13: =IFERROR(SUM(Model_Baseline!AA35:AL35)/SUM(Model_Baseline!AA31:AL31),0) -> 0.60383109 | D13: =IFERROR(SUM(Model_Aggressive!AA35:AL35)/SUM(Model_Aggressive!AA31:AL31),0) -> 0.67252593
A14: Rx gross margin, year 3 | B14: =IFERROR(SUM(Model_Conservative!AA58:AL58)/SUM(Model_Conservative!AA51:AL51),0) -> 0.22279008 | C14: =IFERROR(SUM(Model_Baseline!AA58:AL58)/SUM(Model_Baseline!AA51:AL51),0) -> 0.4743331 | D14: =IFERROR(SUM(Model_Aggressive!AA58:AL58)/SUM(Model_Aggressive!AA51:AL51),0) -> 0.62914577
A16: EBITDA, year 1 | B16: =SUM(Model_Conservative!C76:N76) -> -484508.37 | C16: =SUM(Model_Baseline!C76:N76) -> -724853.68 | D16: =SUM(Model_Aggressive!C76:N76) -> 4502759.8
A17: EBITDA, year 2 | B17: =SUM(Model_Conservative!O76:Z76) -> -513822.89 | C17: =SUM(Model_Baseline!O76:Z76) -> -158810.55 | D17: =SUM(Model_Aggressive!O76:Z76) -> 23728727
A18: EBITDA, year 3 | B18: =SUM(Model_Conservative!AA76:AL76) -> -566047.37 | C18: =SUM(Model_Baseline!AA76:AL76) -> 298775.53 | D18: =SUM(Model_Aggressive!AA76:AL76) -> 54507760
A19: EBITDA margin, year 3 | B19: =IFERROR(SUM(Model_Conservative!AA76:AL76)/SUM(Model_Conservative!AA60:AL60),0) -> -1.6059268 | C19: =IFERROR(SUM(Model_Baseline!AA76:AL76)/SUM(Model_Baseline!AA60:AL60),0) -> 0.04230039 | D19: =IFERROR(SUM(Model_Aggressive!AA76:AL76)/SUM(Model_Aggressive!AA60:AL60),0) -> 0.39342028
A20: EBITDA, 36-month total | B20: =SUM(Model_Conservative!C76:AL76) -> -1564378.6 | C20: =SUM(Model_Baseline!C76:AL76) -> -584888.7 | D20: =SUM(Model_Aggressive!C76:AL76) -> 82739247
A22: First EBITDA-positive month | B22: =IF(MIN(Model_Conservative!C82:AL82)=999,"Not within 36 months",MIN(Model_Conservative!C82:AL82)) -> Not within 36 months | C22: =IF(MIN(Model_Baseline!C82:AL82)=999,"Not within 36 months",MIN(Model_Baseline!C82:AL82)) -> 22 | D22: =IF(MIN(Model_Aggressive!C82:AL82)=999,"Not within 36 months",MIN(Model_Aggressive!C82:AL82)) -> 3
A23: Peak cumulative cash deficit | B23: =MIN(0,MIN(Model_Conservative!C81:AL81)) -> -1587578.1 | C23: =MIN(0,MIN(Model_Baseline!C81:AL81)) -> -1095832.8 | D23: =MIN(0,MIN(Model_Aggressive!C81:AL81)) -> -724868.56
A24: Capital required (deficit plus 30% buffer) | B24: =-MIN(0,MIN(Model_Conservative!C81:AL81))*1.3 -> 2063851.6 | C24: =-MIN(0,MIN(Model_Baseline!C81:AL81))*1.3 -> 1424582.6 | D24: =-MIN(0,MIN(Model_Aggressive!C81:AL81))*1.3 -> 942329.13
A25: Cumulative cash at month 36 | B25: =Model_Conservative!AL81 -> -1587578.1 | C25: =Model_Baseline!AL81 -> -863023.6 | D25: =Model_Aggressive!AL81 -> 78769268
A27: Active subscribers at month 36 (non-Rx) | B27: =Model_Conservative!AL25 -> 351.37717 | C27: =Model_Baseline!AL25 -> 5810.4009 | D27: =Model_Aggressive!AL25 -> 92277.511
A28: Active programme members at month 36 (Rx) | B28: =Model_Conservative!AL45 -> 23.714637 | C28: =Model_Baseline!AL45 -> 837.56118 | D28: =Model_Aggressive!AL45 -> 19788.646
A29: Non-Rx share of year-3 net revenue | B29: =IFERROR(SUM(Model_Conservative!AA31:AL31)/SUM(Model_Conservative!AA60:AL60),0) -> 0.86502772 | C29: =IFERROR(SUM(Model_Baseline!AA31:AL31)/SUM(Model_Baseline!AA60:AL60),0) -> 0.70998716 | D29: =IFERROR(SUM(Model_Aggressive!AA31:AL31)/SUM(Model_Aggressive!AA60:AL60),0) -> 0.58422465
A31: Rx contribution per member-month | B31: =Model_Conservative!AL85 -> 41.92672 | C31: =Model_Baseline!AL85 -> 116.02563 | D31: =Model_Aggressive!AL85 -> 184.52661
A32: Rx gross LTV | B32: =Model_Conservative!AL86 -> 322.51323 | C32: =Model_Baseline!AL86 -> 1054.7785 | D32: =Model_Aggressive!AL86 -> 1942.3853
A33: Non-Rx contribution per order | B33: =Model_Conservative!AL87 -> 34.29104 | C33: =Model_Baseline!AL87 -> 45.68586 | D33: =Model_Aggressive!AL87 -> 57.880272
A34: Non-Rx subscriber gross LTV | B34: =Model_Conservative!AL88 -> 381.01156 | C34: =Model_Baseline!AL88 -> 652.65514 | D34: =Model_Aggressive!AL88 -> 1052.3686
A35: Blended CAC, year 3 average | B35: =IFERROR((SUM(Model_Conservative!AA15:AL15)-SUM(Model_Conservative!AA70:AL70))/SUM(Model_Conservative!AA83:AL83),0) -> 122.33752 | C35: =IFERROR((SUM(Model_Baseline!AA15:AL15)-SUM(Model_Baseline!AA70:AL70))/SUM(Model_Baseline!AA83:AL83),0) -> 109.30979 | D35: =IFERROR((SUM(Model_Aggressive!AA15:AL15)-SUM(Model_Aggressive!AA70:AL70))/SUM(Model_Aggressive!AA83:AL83),0) -> 125.76366
A36: Non-Rx LTV:CAC, year 3 | B36: =IFERROR(Model_Conservative!AL88/((SUM(Model_Conservative!AA15:AL15)-SUM(Model_Conservative!AA70:AL70))/SUM(Model_Conservative!AA83:AL83)),0) -> 3.1144293 | C36: =IFERROR(Model_Baseline!AL88/((SUM(Model_Baseline!AA15:AL15)-SUM(Model_Baseline!AA70:AL70))/SUM(Model_Baseline!AA83:AL83)),0) -> 5.9706927 | D36: =IFERROR(Model_Aggressive!AL88/((SUM(Model_Aggressive!AA15:AL15)-SUM(Model_Aggressive!AA70:AL70))/SUM(Model_Aggressive!AA83:AL83)),0) -> 8.3678274

Sheet Unit_Economics
A1: Unit economics: where the margin actually comes from
A2: Two separate businesses with very different shapes. The non-prescription line is a high-margin consumer product that can trade in all fifty states. The prescription line carries medication, clinician and cold-chain cost on every single fill, so its margin is structurally lower and its retention risk structurally higher.
A4: A. Non-prescription order (one shipment)
A5: Line item | B5: Conservative | C5: Baseline | D5: Aggressive
A6: Average order value | B6: =Assumptions!$D$31 -> 68 | C6: =Assumptions!$E$31 -> 78 | D6: =Assumptions!$F$31 -> 88
A7: less refunds and chargebacks | B7: =-Assumptions!$D$31*Assumptions!$D$61 -> -2.72 | C7: =-Assumptions!$E$31*Assumptions!$E$61 -> -2.34 | D7: =-Assumptions!$F$31*Assumptions!$F$61 -> -1.936
A8: Net revenue per order | B8: =B6+B7 -> 65.28 | C8: =C6+C7 -> 75.66 | D8: =D6+D7 -> 86.064
A9: less landed product COGS | B9: =-Assumptions!$D$31*Assumptions!$D$36 -> -20.4 | C9: =-Assumptions!$E$31*Assumptions!$E$36 -> -20.28 | D9: =-Assumptions!$F$31*Assumptions!$F$36 -> -19.36
A10: less pick, pack and ship | B10: =-Assumptions!$D$37 -> -8.5 | C10: =-Assumptions!$E$37 -> -7.5 | D10: =-Assumptions!$F$37 -> -6.5
A11: less payment processing | B11: =-B8*Assumptions!$D$60 -> -2.08896 | C11: =-C8*Assumptions!$E$60 -> -2.19414 | D11: =-D8*Assumptions!$F$60 -> -2.323728
A12: Contribution per order | B12: =B8+B9+B10+B11 -> 34.29104 | C12: =C8+C9+C10+C11 -> 45.68586 | D12: =D8+D9+D10+D11 -> 57.880272
A13: Contribution margin | B13: =IFERROR(B12/B8,0) -> 0.52529167 | C13: =IFERROR(C12/C8,0) -> 0.60383109 | D13: =IFERROR(D12/D8,0) -> 0.67252593
A14: Monthly subscription churn | B14: =Assumptions!$D$33 -> 0.09 | C14: =Assumptions!$E$33 -> 0.07 | D14: =Assumptions!$F$33 -> 0.055
A15: Implied subscriber life | B15: =1/Assumptions!$D$33 -> 11.111111 | C15: =1/Assumptions!$E$33 -> 14.285714 | D15: =1/Assumptions!$F$33 -> 18.181818
A16: Subscriber gross LTV | B16: =B12/Assumptions!$D$33 -> 381.01156 | C16: =C12/Assumptions!$E$33 -> 652.65514 | D16: =D12/Assumptions!$F$33 -> 1052.3686
A19: B. Prescription programme member (steady-state month)
A20: Line item | B20: Conservative | C20: Baseline | D20: Aggressive
A21: Programme price per member-month | B21: =Assumptions!$D$51 -> 199 | C21: =Assumptions!$E$51 -> 249 | D21: =Assumptions!$F$51 -> 299
A22: less refunds and chargebacks | B22: =-Assumptions!$D$51*Assumptions!$D$61 -> -7.96 | C22: =-Assumptions!$E$51*Assumptions!$E$61 -> -7.47 | D22: =-Assumptions!$F$51*Assumptions!$F$61 -> -6.578
A23: Net revenue per member-month | B23: =B21+B22 -> 191.04 | C23: =C21+C22 -> 241.53 | D23: =D21+D22 -> 292.422
A24: less pharmacy medication cost | B24: =-Assumptions!$D$54 -> -105 | C24: =-Assumptions!$E$54 -> -88 | D24: =-Assumptions!$F$54 -> -75
A25: less clinician monitoring and refill review | B25: =-Assumptions!$D$56 -> -10 | C25: =-Assumptions!$E$56 -> -8 | D25: =-Assumptions!$F$56 -> -6.5
A26: less cold-chain fulfilment and shipping | B26: =-Assumptions!$D$57 -> -22 | C26: =-Assumptions!$E$57 -> -18 | D26: =-Assumptions!$F$57 -> -15
A27: less non-clinical support | B27: =-Assumptions!$D$58 -> -6 | C27: =-Assumptions!$E$58 -> -4.5 | D27: =-Assumptions!$F$58 -> -3.5
A28: less payment processing | B28: =-B23*Assumptions!$D$60 -> -6.11328 | C28: =-C23*Assumptions!$E$60 -> -7.00437 | D28: =-D23*Assumptions!$F$60 -> -7.895394
A29: Contribution per member-month | B29: =B23+B24+B25+B26+B27+B28 -> 41.92672 | C29: =C23+C24+C25+C26+C27+C28 -> 116.02563 | D29: =D23+D24+D25+D26+D27+D28 -> 184.52661
A30: Contribution margin | B30: =IFERROR(B29/B23,0) -> 0.21946566 | C30: =IFERROR(C29/C23,0) -> 0.48037772 | D30: =IFERROR(D29/D23,0) -> 0.63102847
A31: Monthly churn | B31: =Assumptions!$D$49 -> 0.13 | C31: =Assumptions!$E$49 -> 0.11 | D31: =Assumptions!$F$49 -> 0.095
A32: Implied member life, months | B32: =1/Assumptions!$D$49 -> 7.6923077 | C32: =1/Assumptions!$E$49 -> 9.0909091 | D32: =1/Assumptions!$F$49 -> 10.526316
A33: Member gross LTV | B33: =B29/Assumptions!$D$49 -> 322.51323 | C33: =C29/Assumptions!$E$49 -> 1054.7785 | D33: =D29/Assumptions!$F$49 -> 1942.3853
A36: C. Prescription enrolment (one-time, at intake)
A37: Line item | B37: Conservative | C37: Baseline | D37: Aggressive
A38: Consultation fee charged | B38: =Assumptions!$D$52 -> 49 | C38: =Assumptions!$E$52 -> 59 | D38: =Assumptions!$F$52 -> 79
A39: less clinician cost per completed consult | B39: =-Assumptions!$D$55 -> -45 | C39: =-Assumptions!$E$55 -> -38 | D39: =-Assumptions!$F$55 -> -32
A40: Net on the consultation step | B40: =B38+B39 -> 4 | C40: =C38+C39 -> 21 | D40: =D38+D39 -> 47
A41: Consults per enrolled member (1 / enrolment rate) | B41: =1/Assumptions!$D$48 -> 1.7241379 | C41: =1/Assumptions!$E$48 -> 1.5151515 | D41: =1/Assumptions!$F$48 -> 1.4285714
A42: Consultation-step cost carried per enrolled member | B42: =B40*B41 -> 6.8965517 | C42: =C40*C41 -> 31.818182 | D42: =D40*D41 -> 67.142857
A45: D. What the flat $600/month provider fee changes, and what it does not
A46: The flat fee removes most FIXED operating cost from the model. It does not remove VARIABLE cost. Medication, per-consult clinician time, cold-chain shipping and card processing all scale with every order and every fill, and they are carried as separate drivers above.
A47: Published pricing for comparable turnkey telehealth infrastructure is $3,000-6,000 per month by tier, plus $5,000-10,000 onboarding, plus per-consult fees (benchmark B11). A $600 flat fee sits at roughly one fifth of the low end of that range.
A48: Read that two ways. Either the fee genuinely covers only software and compliance administration, which is the assumption used here and is the safe way to model it, or the scope is narrower than expected. Both readings lead to the same action: get the fee schedule in writing and confirm line by line what is and is not included.
A49: A vendor contract does not transfer the brand's own legal exposure. The brand remains responsible for its own advertising claims, its own endorsement disclosures, its own auto-renewal terms and its own privacy practices, whoever operates the platform.
A50: At $600 per month the provider has no economic stake in volume. That is good for margin and bad for alignment: nothing in the fee structure funds the provider's scaling, so capacity, turnaround time and service levels need to be contractual rather than assumed.

Sheet Sensitivity
A1: Sensitivity: which assumptions actually decide the outcome
A2: Closed-form grids computed from the Baseline column of Assumptions, so they recalculate with the rest of the workbook rather than needing a what-if table. Change the Baseline inputs and these move.
A4: Grid 1. Prescription LTV:CAC by monthly churn and blended CAC
A5: Rx contribution per member-month (Baseline drivers) | D5: =Assumptions!$E$51*(1-Assumptions!$E$61)*(1-Assumptions!$E$60)-Assumptions!$E$54-Assumptions!$E$56-Assumptions!$E$57-Assumptions!$E$58 -> 116.02563
A6: Below 3.0x the programme does not pay for its own acquisition. Cells at or above 3.0x are viable.
A8: Monthly churn \ CAC | B8: 150 | C8: 250 | D8: 350 | E8: 450 | F8: 600 | G8: 800
A9: 0.08 | B9: =($D$5/$A9)/B$8 -> 9.6688025 | C9: =($D$5/$A9)/C$8 -> 5.8012815 | D9: =($D$5/$A9)/D$8 -> 4.1437725 | E9: =($D$5/$A9)/E$8 -> 3.2229342 | F9: =($D$5/$A9)/F$8 -> 2.4172006 | G9: =($D$5/$A9)/G$8 -> 1.8129005
A10: 0.095 | B10: =($D$5/$A10)/B$8 -> 8.1421495 | C10: =($D$5/$A10)/C$8 -> 4.8852897 | D10: =($D$5/$A10)/D$8 -> 3.4894926 | E10: =($D$5/$A10)/E$8 -> 2.7140498 | F10: =($D$5/$A10)/F$8 -> 2.0355374 | G10: =($D$5/$A10)/G$8 -> 1.526653
A11: 0.11 | B11: =($D$5/$A11)/B$8 -> 7.0318564 | C11: =($D$5/$A11)/C$8 -> 4.2191138 | D11: =($D$5/$A11)/D$8 -> 3.0136527 | E11: =($D$5/$A11)/E$8 -> 2.3439521 | F11: =($D$5/$A11)/F$8 -> 1.7579641 | G11: =($D$5/$A11)/G$8 -> 1.3184731
A12: 0.13 | B12: =($D$5/$A12)/B$8 -> 5.9500323 | C12: =($D$5/$A12)/C$8 -> 3.5700194 | D12: =($D$5/$A12)/D$8 -> 2.5500138 | E12: =($D$5/$A12)/E$8 -> 1.9833441 | F12: =($D$5/$A12)/F$8 -> 1.4875081 | G12: =($D$5/$A12)/G$8 -> 1.1156311
A13: 0.15 | B13: =($D$5/$A13)/B$8 -> 5.1566947 | C13: =($D$5/$A13)/C$8 -> 3.0940168 | D13: =($D$5/$A13)/D$8 -> 2.210012 | E13: =($D$5/$A13)/E$8 -> 1.7188982 | F13: =($D$5/$A13)/F$8 -> 1.2891737 | G13: =($D$5/$A13)/G$8 -> 0.96688025
A14: 0.18 | B14: =($D$5/$A14)/B$8 -> 4.2972456 | C14: =($D$5/$A14)/C$8 -> 2.5783473 | D14: =($D$5/$A14)/D$8 -> 1.8416767 | E14: =($D$5/$A14)/E$8 -> 1.4324152 | F14: =($D$5/$A14)/F$8 -> 1.0743114 | G14: =($D$5/$A14)/G$8 -> 0.80573354
A15: Baseline churn is 11.0%. Benchmark B17 puts real-world discontinuation near 65% at 12 months, which is roughly 8.4% monthly, and 84.4% at 24 months, roughly 7.4% monthly. Churn worse than about 15% monthly makes the prescription line unviable at any plausible CAC.
A18: Grid 2. Month-12 partner-driven sessions by reach per post and click-through
A19: These two drivers are the least evidenced in the model and they multiply, so the band they produce is wide by construction.
A21: Reach % \ CTR | B21: 0.002 | C21: 0.0035 | D21: 0.006 | E21: 0.009 | F21: 0.013
A22: 0.02 | B22: =Assumptions!$E$9*Assumptions!$E$10*$A22*B$21*(Assumptions!$E$14+(1-Assumptions!$E$14)*Assumptions!$E$13^(12-Assumptions!$E$6)) -> 1879.5062 | C22: =Assumptions!$E$9*Assumptions!$E$10*$A22*C$21*(Assumptions!$E$14+(1-Assumptions!$E$14)*Assumptions!$E$13^(12-Assumptions!$E$6)) -> 3289.1358 | D22: =Assumptions!$E$9*Assumptions!$E$10*$A22*D$21*(Assumptions!$E$14+(1-Assumptions!$E$14)*Assumptions!$E$13^(12-Assumptions!$E$6)) -> 5638.5186 | E22: =Assumptions!$E$9*Assumptions!$E$10*$A22*E$21*(Assumptions!$E$14+(1-Assumptions!$E$14)*Assumptions!$E$13^(12-Assumptions!$E$6)) -> 8457.7778 | F22: =Assumptions!$E$9*Assumptions!$E$10*$A22*F$21*(Assumptions!$E$14+(1-Assumptions!$E$14)*Assumptions!$E$13^(12-Assumptions!$E$6)) -> 12216.79
A23: 0.04 | B23: =Assumptions!$E$9*Assumptions!$E$10*$A23*B$21*(Assumptions!$E$14+(1-Assumptions!$E$14)*Assumptions!$E$13^(12-Assumptions!$E$6)) -> 3759.0124 | C23: =Assumptions!$E$9*Assumptions!$E$10*$A23*C$21*(Assumptions!$E$14+(1-Assumptions!$E$14)*Assumptions!$E$13^(12-Assumptions!$E$6)) -> 6578.2717 | D23: =Assumptions!$E$9*Assumptions!$E$10*$A23*D$21*(Assumptions!$E$14+(1-Assumptions!$E$14)*Assumptions!$E$13^(12-Assumptions!$E$6)) -> 11277.037 | E23: =Assumptions!$E$9*Assumptions!$E$10*$A23*E$21*(Assumptions!$E$14+(1-Assumptions!$E$14)*Assumptions!$E$13^(12-Assumptions!$E$6)) -> 16915.556 | F23: =Assumptions!$E$9*Assumptions!$E$10*$A23*F$21*(Assumptions!$E$14+(1-Assumptions!$E$14)*Assumptions!$E$13^(12-Assumptions!$E$6)) -> 24433.58
A24: 0.07 | B24: =Assumptions!$E$9*Assumptions!$E$10*$A24*B$21*(Assumptions!$E$14+(1-Assumptions!$E$14)*Assumptions!$E$13^(12-Assumptions!$E$6)) -> 6578.2717 | C24: =Assumptions!$E$9*Assumptions!$E$10*$A24*C$21*(Assumptions!$E$14+(1-Assumptions!$E$14)*Assumptions!$E$13^(12-Assumptions!$E$6)) -> 11511.975 | D24: =Assumptions!$E$9*Assumptions!$E$10*$A24*D$21*(Assumptions!$E$14+(1-Assumptions!$E$14)*Assumptions!$E$13^(12-Assumptions!$E$6)) -> 19734.815 | E24: =Assumptions!$E$9*Assumptions!$E$10*$A24*E$21*(Assumptions!$E$14+(1-Assumptions!$E$14)*Assumptions!$E$13^(12-Assumptions!$E$6)) -> 29602.222 | F24: =Assumptions!$E$9*Assumptions!$E$10*$A24*F$21*(Assumptions!$E$14+(1-Assumptions!$E$14)*Assumptions!$E$13^(12-Assumptions!$E$6)) -> 42758.766
A25: 0.11 | B25: =Assumptions!$E$9*Assumptions!$E$10*$A25*B$21*(Assumptions!$E$14+(1-Assumptions!$E$14)*Assumptions!$E$13^(12-Assumptions!$E$6)) -> 10337.284 | C25: =Assumptions!$E$9*Assumptions!$E$10*$A25*C$21*(Assumptions!$E$14+(1-Assumptions!$E$14)*Assumptions!$E$13^(12-Assumptions!$E$6)) -> 18090.247 | D25: =Assumptions!$E$9*Assumptions!$E$10*$A25*D$21*(Assumptions!$E$14+(1-Assumptions!$E$14)*Assumptions!$E$13^(12-Assumptions!$E$6)) -> 31011.852 | E25: =Assumptions!$E$9*Assumptions!$E$10*$A25*E$21*(Assumptions!$E$14+(1-Assumptions!$E$14)*Assumptions!$E$13^(12-Assumptions!$E$6)) -> 46517.778 | F25: =Assumptions!$E$9*Assumptions!$E$10*$A25*F$21*(Assumptions!$E$14+(1-Assumptions!$E$14)*Assumptions!$E$13^(12-Assumptions!$E$6)) -> 67192.346
A26: 0.15 | B26: =Assumptions!$E$9*Assumptions!$E$10*$A26*B$21*(Assumptions!$E$14+(1-Assumptions!$E$14)*Assumptions!$E$13^(12-Assumptions!$E$6)) -> 14096.296 | C26: =Assumptions!$E$9*Assumptions!$E$10*$A26*C$21*(Assumptions!$E$14+(1-Assumptions!$E$14)*Assumptions!$E$13^(12-Assumptions!$E$6)) -> 24668.519 | D26: =Assumptions!$E$9*Assumptions!$E$10*$A26*D$21*(Assumptions!$E$14+(1-Assumptions!$E$14)*Assumptions!$E$13^(12-Assumptions!$E$6)) -> 42288.889 | E26: =Assumptions!$E$9*Assumptions!$E$10*$A26*E$21*(Assumptions!$E$14+(1-Assumptions!$E$14)*Assumptions!$E$13^(12-Assumptions!$E$6)) -> 63433.334 | F26: =Assumptions!$E$9*Assumptions!$E$10*$A26*F$21*(Assumptions!$E$14+(1-Assumptions!$E$14)*Assumptions!$E$13^(12-Assumptions!$E$6)) -> 91625.927
A29: Grid 3. Year-3 blended gross margin by non-Rx COGS share and pharmacy cost per member-month
A30: Approximated at the Baseline year-3 revenue mix so the grid is readable. Non-Rx share of year-3 net revenue is taken from the Summary sheet.
A31: Non-Rx share of year-3 net revenue (Baseline) | E31: =Summary!C29 -> 0.70998716
A33: Non-Rx COGS % \ pharmacy $/mm | B33: 60 | C33: 75 | D33: 90 | E33: 105 | F33: 130
A34: 0.2 | B34: =$E$31*(1-$A34/(1-Assumptions!$E$61)-Assumptions!$E$37/(Assumptions!$E$31*(1-Assumptions!$E$61))-Assumptions!$E$60)+(1-$E$31)*(1-(B$33+Assumptions!$E$56+Assumptions!$E$57+Assumptions!$E$58)/(Assumptions!$E$51*(1-Assumptions!$E$61))-Assumptions!$E$60) -> 0.64556526 | C34: =$E$31*(1-$A34/(1-Assumptions!$E$61)-Assumptions!$E$37/(Assumptions!$E$31*(1-Assumptions!$E$61))-Assumptions!$E$60)+(1-$E$31)*(1-(C$33+Assumptions!$E$56+Assumptions!$E$57+Assumptions!$E$58)/(Assumptions!$E$51*(1-Assumptions!$E$61))-Assumptions!$E$60) -> 0.62755427 | D34: =$E$31*(1-$A34/(1-Assumptions!$E$61)-Assumptions!$E$37/(Assumptions!$E$31*(1-Assumptions!$E$61))-Assumptions!$E$60)+(1-$E$31)*(1-(D$33+Assumptions!$E$56+Assumptions!$E$57+Assumptions!$E$58)/(Assumptions!$E$51*(1-Assumptions!$E$61))-Assumptions!$E$60) -> 0.60954329 | E34: =$E$31*(1-$A34/(1-Assumptions!$E$61)-Assumptions!$E$37/(Assumptions!$E$31*(1-Assumptions!$E$61))-Assumptions!$E$60)+(1-$E$31)*(1-(E$33+Assumptions!$E$56+Assumptions!$E$57+Assumptions!$E$58)/(Assumptions!$E$51*(1-Assumptions!$E$61))-Assumptions!$E$60) -> 0.59153231 | F34: =$E$31*(1-$A34/(1-Assumptions!$E$61)-Assumptions!$E$37/(Assumptions!$E$31*(1-Assumptions!$E$61))-Assumptions!$E$60)+(1-$E$31)*(1-(F$33+Assumptions!$E$56+Assumptions!$E$57+Assumptions!$E$58)/(Assumptions!$E$51*(1-Assumptions!$E$61))-Assumptions!$E$60) -> 0.561514
A35: 0.24 | B35: =$E$31*(1-$A35/(1-Assumptions!$E$61)-Assumptions!$E$37/(Assumptions!$E$31*(1-Assumptions!$E$61))-Assumptions!$E$60)+(1-$E$31)*(1-(B$33+Assumptions!$E$56+Assumptions!$E$57+Assumptions!$E$58)/(Assumptions!$E$51*(1-Assumptions!$E$61))-Assumptions!$E$60) -> 0.61628744 | C35: =$E$31*(1-$A35/(1-Assumptions!$E$61)-Assumptions!$E$37/(Assumptions!$E$31*(1-Assumptions!$E$61))-Assumptions!$E$60)+(1-$E$31)*(1-(C$33+Assumptions!$E$56+Assumptions!$E$57+Assumptions!$E$58)/(Assumptions!$E$51*(1-Assumptions!$E$61))-Assumptions!$E$60) -> 0.59827645 | D35: =$E$31*(1-$A35/(1-Assumptions!$E$61)-Assumptions!$E$37/(Assumptions!$E$31*(1-Assumptions!$E$61))-Assumptions!$E$60)+(1-$E$31)*(1-(D$33+Assumptions!$E$56+Assumptions!$E$57+Assumptions!$E$58)/(Assumptions!$E$51*(1-Assumptions!$E$61))-Assumptions!$E$60) -> 0.58026547 | E35: =$E$31*(1-$A35/(1-Assumptions!$E$61)-Assumptions!$E$37/(Assumptions!$E$31*(1-Assumptions!$E$61))-Assumptions!$E$60)+(1-$E$31)*(1-(E$33+Assumptions!$E$56+Assumptions!$E$57+Assumptions!$E$58)/(Assumptions!$E$51*(1-Assumptions!$E$61))-Assumptions!$E$60) -> 0.56225449 | F35: =$E$31*(1-$A35/(1-Assumptions!$E$61)-Assumptions!$E$37/(Assumptions!$E$31*(1-Assumptions!$E$61))-Assumptions!$E$60)+(1-$E$31)*(1-(F$33+Assumptions!$E$56+Assumptions!$E$57+Assumptions!$E$58)/(Assumptions!$E$51*(1-Assumptions!$E$61))-Assumptions!$E$60) -> 0.53223618
A36: 0.28 | B36: =$E$31*(1-$A36/(1-Assumptions!$E$61)-Assumptions!$E$37/(Assumptions!$E$31*(1-Assumptions!$E$61))-Assumptions!$E$60)+(1-$E$31)*(1-(B$33+Assumptions!$E$56+Assumptions!$E$57+Assumptions!$E$58)/(Assumptions!$E$51*(1-Assumptions!$E$61))-Assumptions!$E$60) -> 0.58700961 | C36: =$E$31*(1-$A36/(1-Assumptions!$E$61)-Assumptions!$E$37/(Assumptions!$E$31*(1-Assumptions!$E$61))-Assumptions!$E$60)+(1-$E$31)*(1-(C$33+Assumptions!$E$56+Assumptions!$E$57+Assumptions!$E$58)/(Assumptions!$E$51*(1-Assumptions!$E$61))-Assumptions!$E$60) -> 0.56899863 | D36: =$E$31*(1-$A36/(1-Assumptions!$E$61)-Assumptions!$E$37/(Assumptions!$E$31*(1-Assumptions!$E$61))-Assumptions!$E$60)+(1-$E$31)*(1-(D$33+Assumptions!$E$56+Assumptions!$E$57+Assumptions!$E$58)/(Assumptions!$E$51*(1-Assumptions!$E$61))-Assumptions!$E$60) -> 0.55098765 | E36: =$E$31*(1-$A36/(1-Assumptions!$E$61)-Assumptions!$E$37/(Assumptions!$E$31*(1-Assumptions!$E$61))-Assumptions!$E$60)+(1-$E$31)*(1-(E$33+Assumptions!$E$56+Assumptions!$E$57+Assumptions!$E$58)/(Assumptions!$E$51*(1-Assumptions!$E$61))-Assumptions!$E$60) -> 0.53297667 | F36: =$E$31*(1-$A36/(1-Assumptions!$E$61)-Assumptions!$E$37/(Assumptions!$E$31*(1-Assumptions!$E$61))-Assumptions!$E$60)+(1-$E$31)*(1-(F$33+Assumptions!$E$56+Assumptions!$E$57+Assumptions!$E$58)/(Assumptions!$E$51*(1-Assumptions!$E$61))-Assumptions!$E$60) -> 0.50295836
A37: 0.32 | B37: =$E$31*(1-$A37/(1-Assumptions!$E$61)-Assumptions!$E$37/(Assumptions!$E$31*(1-Assumptions!$E$61))-Assumptions!$E$60)+(1-$E$31)*(1-(B$33+Assumptions!$E$56+Assumptions!$E$57+Assumptions!$E$58)/(Assumptions!$E$51*(1-Assumptions!$E$61))-Assumptions!$E$60) -> 0.55773179 | C37: =$E$31*(1-$A37/(1-Assumptions!$E$61)-Assumptions!$E$37/(Assumptions!$E$31*(1-Assumptions!$E$61))-Assumptions!$E$60)+(1-$E$31)*(1-(C$33+Assumptions!$E$56+Assumptions!$E$57+Assumptions!$E$58)/(Assumptions!$E$51*(1-Assumptions!$E$61))-Assumptions!$E$60) -> 0.53972081 | D37: =$E$31*(1-$A37/(1-Assumptions!$E$61)-Assumptions!$E$37/(Assumptions!$E$31*(1-Assumptions!$E$61))-Assumptions!$E$60)+(1-$E$31)*(1-(D$33+Assumptions!$E$56+Assumptions!$E$57+Assumptions!$E$58)/(Assumptions!$E$51*(1-Assumptions!$E$61))-Assumptions!$E$60) -> 0.52170983 | E37: =$E$31*(1-$A37/(1-Assumptions!$E$61)-Assumptions!$E$37/(Assumptions!$E$31*(1-Assumptions!$E$61))-Assumptions!$E$60)+(1-$E$31)*(1-(E$33+Assumptions!$E$56+Assumptions!$E$57+Assumptions!$E$58)/(Assumptions!$E$51*(1-Assumptions!$E$61))-Assumptions!$E$60) -> 0.50369885 | F37: =$E$31*(1-$A37/(1-Assumptions!$E$61)-Assumptions!$E$37/(Assumptions!$E$31*(1-Assumptions!$E$61))-Assumptions!$E$60)+(1-$E$31)*(1-(F$33+Assumptions!$E$56+Assumptions!$E$57+Assumptions!$E$58)/(Assumptions!$E$51*(1-Assumptions!$E$61))-Assumptions!$E$60) -> 0.47368054
A38: 0.38 | B38: =$E$31*(1-$A38/(1-Assumptions!$E$61)-Assumptions!$E$37/(Assumptions!$E$31*(1-Assumptions!$E$61))-Assumptions!$E$60)+(1-$E$31)*(1-(B$33+Assumptions!$E$56+Assumptions!$E$57+Assumptions!$E$58)/(Assumptions!$E$51*(1-Assumptions!$E$61))-Assumptions!$E$60) -> 0.51381506 | C38: =$E$31*(1-$A38/(1-Assumptions!$E$61)-Assumptions!$E$37/(Assumptions!$E$31*(1-Assumptions!$E$61))-Assumptions!$E$60)+(1-$E$31)*(1-(C$33+Assumptions!$E$56+Assumptions!$E$57+Assumptions!$E$58)/(Assumptions!$E$51*(1-Assumptions!$E$61))-Assumptions!$E$60) -> 0.49580408 | D38: =$E$31*(1-$A38/(1-Assumptions!$E$61)-Assumptions!$E$37/(Assumptions!$E$31*(1-Assumptions!$E$61))-Assumptions!$E$60)+(1-$E$31)*(1-(D$33+Assumptions!$E$56+Assumptions!$E$57+Assumptions!$E$58)/(Assumptions!$E$51*(1-Assumptions!$E$61))-Assumptions!$E$60) -> 0.4777931 | E38: =$E$31*(1-$A38/(1-Assumptions!$E$61)-Assumptions!$E$37/(Assumptions!$E$31*(1-Assumptions!$E$61))-Assumptions!$E$60)+(1-$E$31)*(1-(E$33+Assumptions!$E$56+Assumptions!$E$57+Assumptions!$E$58)/(Assumptions!$E$51*(1-Assumptions!$E$61))-Assumptions!$E$60) -> 0.45978211 | F38: =$E$31*(1-$A38/(1-Assumptions!$E$61)-Assumptions!$E$37/(Assumptions!$E$31*(1-Assumptions!$E$61))-Assumptions!$E$60)+(1-$E$31)*(1-(F$33+Assumptions!$E$56+Assumptions!$E$57+Assumptions!$E$58)/(Assumptions!$E$51*(1-Assumptions!$E$61))-Assumptions!$E$60) -> 0.42976381

Sheet Partner_Economics
A1: Proposed brand-partner economics - illustrative only
A2: No terms have been offered, negotiated or accepted. Nothing on this sheet is an offer. The structure below exists so the conversation can start from arithmetic instead of adjectives. The equity figures use an illustrative revenue multiple and are NOT a valuation; a valuation requires an actual process.
A4: Illustrative revenue multiple on year-3 net revenue | C4: 3 | D4: Editable. DTC and telehealth multiples move with growth, margin and rate cycles; 2-5x net revenue is a commonly quoted range for profitable consumer health at scale. Not a valuation.
A6: Item | B6: Conservative | C6: Baseline | D6: Aggressive
A7: Cash retainer over 36 months | B7: =-SUM(Model_Conservative!C73:AL73) -> 0 | C7: =-SUM(Model_Baseline!C73:AL73) -> 525000 | D7: =-SUM(Model_Aggressive!C73:AL73) -> 875000
A8: Royalty over 36 months | B8: =-SUM(Model_Conservative!C74:AL74) -> 36244.035 | C8: =-SUM(Model_Baseline!C74:AL74) -> 648520.93 | D8: =-SUM(Model_Aggressive!C74:AL74) -> 10833981
A9: Total cash to partner over 36 months | B9: =B7+B8 -> 36244.035 | C9: =C7+C8 -> 1173520.9 | D9: =D7+D8 -> 11708981
A10: Royalty in year 3 alone | B10: =-SUM(Model_Conservative!AA74:AL74) -> 17623.698 | C10: =-SUM(Model_Baseline!AA74:AL74) -> 353159.31 | D10: =-SUM(Model_Aggressive!AA74:AL74) -> 6927421.3
A11: Partner equity, fully diluted | B11: =Assumptions!$D$78 -> 0.1 | C11: =Assumptions!$E$78 -> 0.15 | D11: =Assumptions!$F$78 -> 0.2
A12: Illustrative equity value at year-3 revenue multiple | B12: =Summary!B7*$C$4*B11 -> 105742.19 | C12: =Summary!C7*$C$4*C11 -> 3178433.8 | D12: =Summary!D7*$C$4*D11 -> 83129056
A13: Total illustrative 36-month partner value | B13: =B9+B12 -> 141986.22 | C13: =C9+C12 -> 4351954.7 | D13: =D9+D12 -> 94838037
A14: Partner cash as a share of 36-month net revenue | B14: =IFERROR(B9/Summary!B8,0) -> 0.05 | C14: =IFERROR(C9/Summary!C8,0) -> 0.09047672 | D14: =IFERROR(D9/Summary!D8,0) -> 0.05403822
A16: Constraints that shape any deal here
A17: The partner can promote the brand and the non-prescription line. The partner should not promote specific compounded prescription drugs. 503A compounders operate under advertising and promotion limits, prescription-drug advertising carries its own disclosure requirements, and celebrity promotion of a prescription product invites exactly the scrutiny a new brand cannot absorb. Separating what is promotable from what is prescribable is a design requirement, not a preference.
A18: Every paid or equity-holding endorsement needs a clear and conspicuous disclosure of the material connection, on every post and in every format, under the FTC Endorsement Guides. A founder's equity stake is a material connection. Earlier research in this project found the proposed partner named on the FTC's September 2017 list of influencers sent warning letters about undisclosed endorsements, which makes disclosure discipline a specific and personal risk here rather than a generic one.
A19: Compensation to the medical entity and to clinicians must never vary with prescription volume, programme enrolments or revenue. Partner compensation may be tied to revenue; clinical compensation may not. Keeping those two facts in separate contracts is the point of the structure.
A20: A prior or concurrent promotion of a competing weight-management or GLP-1 product may create a category-exclusivity conflict. Earlier research in this project flagged a possible prior GLP-1-adjacent promotion; brand and paid status were not verified. Resolve it in diligence before any announcement.
A21: Nothing here is an offer, and nothing here should be shared as though terms exist. Until definitive agreements are signed the brand is a proposed concept and the partner's role is proposed.

Sheet Provider_Diligence
A1: Turnkey provider at $600/month - what to confirm before signing
A2: The whole model rests on this vendor. At this fee the vendor carries no volume risk, so scope has to be contractual. Every row is a question to put in writing; the Why column says what breaks in the model if the answer is not what you expect.
A4: # | B4: Question to put in writing | C4: Why it matters to the model | D4: Status
A5: 1 | B5: Does the $600 include per-consult clinician fees, or are those billed separately per visit? | C5: The model assumes separately, at $32-45 per completed consult. If included, Rx gross margin improves by roughly the consult cost divided by enrolments. If excluded and higher than assumed, enrolment economics compress. | D5: Open
A6: 2 | B6: Does the $600 include medication cost, or does the pharmacy bill per fill? | C6: The model assumes the pharmacy bills per fill at $75-105 per member-month. This is the largest single variable cost in the Rx line; a written tiered schedule is essential. | D6: Open
A7: 3 | B7: Does the $600 include cold-chain shipping and packaging, or is that billed per shipment? | C7: The model assumes per shipment at $15-22. Benchmark B09 shows a $1.95 pack rate is only the pack step, not the landed temperature-controlled cost. | D7: Open
A8: 4 | B8: Is payment processing inside the fee, and at what rate and risk classification? | C8: The model carries 2.7-3.2% separately. Healthcare and supplement merchants are frequently underwritten as elevated risk. | D8: Open
A9: 5 | B9: Which specific pharmacies fulfil, under which licences, and in which states? | C9: Drives the state-coverage ramp, which is the gate on the whole Rx funnel. Name the pharmacies; do not accept a count. | D9: Open
A10: 6 | B10: For each pharmacy: 503A, 503B, or both, and which is used for which product? | C10: 503A compounds pursuant to individual patient prescriptions. 503B outsourcing facilities are built for non-patient-specific office stock. They are not interchangeable for a consumer-direct model, and assuming they are is a common and expensive error. | D10: Open
A11: 7 | B11: How does the arrangement handle interstate distribution limits for 503A pharmacies? | C11: Section 503A(b)(3) caps interstate distribution of compounded drugs at 5% of total prescription orders unless the pharmacy's state has signed the FDA memorandum of understanding. FDA's compounding MOU index currently lists only three MOUs, all suspended, and FDA has repeatedly deferred enforcement of the 5% limit pending rulemaking. Deferred enforcement is discretionary and revocable, so a national single-pharmacy Rx model is a policy bet, not a settled structure. | D11: Open
A12: 8 | B12: Which peptides are on the current FDA 503A Category 1 bulks list, as of the signing date? | C12: Determines the formulary. Benchmark B18: FDA removed 12 peptides from Category 2 in April 2026, the PCAC met in July 2026 on three more and will meet again before the end of February 2027 on five others. The list moves; the contract should require the provider to track it. | D12: Open
A13: 9 | B13: Is any product 'essentially a copy' of an approved drug? | C13: Section 503A limits compounding of drugs that are essentially copies of commercially available products. This is where compounded-GLP-1 programmes have drawn enforcement. | D13: Open
A14: 10 | B14: Who holds the LegitScript healthcare merchant certification, and for which website? | C14: Certification is site-specific and gates healthcare advertising across Google, Meta, Microsoft and TikTok. If it is the provider's certification on the provider's domain, the brand's own site may not be covered. No certification means no scaled paid acquisition, which removes most of the paid-traffic line from the model. | D14: Open
A15: 11 | B15: What is the legal structure: MSO and friendly-PC, and who owns the physician entity? | C15: Corporate-practice-of-medicine rules in many states bar a non-physician company from owning a medical practice or splitting professional fees. Get the structure opinion, not a reassurance. | D15: Open
A16: 12 | B16: How are clinicians compensated, and does any element vary with prescribing or revenue? | C16: Any volume- or revenue-linked clinical compensation is a fee-splitting and kickback problem and undermines the clinical-independence position the whole model depends on. | D16: Open
... A24: 20 | B24: Auto-renewal mechanics: consent capture, renewal reminders, cancellation path, and who is liable? | C24: ROSCA and state auto-renewal laws are the most common source of consumer-protection claims in subscription health. The cancellation path must be as easy as the sign-up path, and the brand is liable for it whoever built it. | D24: Open

Sheet Benchmarks
A1: Benchmarks behind the drivers
A2: Third-party unless marked as an analyst assumption. Figures were taken from search-result summaries during a session in which direct page loads were restricted; load-bearing figures were corroborated across two independent queries. Ranges are ranges, not measurements.
A4: ID | B4: Topic | C4: Finding | D4: How it is used | E4: Confidence | F4: Sources
A5: B01 | B5: Public telehealth gross margin (closest listed comparable) | C5: Hims & Hers gross margin 74% FY2025 vs 79% FY2024; 65% in Q1 2026 and 63.8% in Q2 2026. Decline attributed to weight-loss offerings with shorter shipping cadences and higher fulfilment costs, plus international mix. | D5: Ceiling reference for a telehealth blended gross margin. Reserve Clinic's Rx line is modelled well below this because it carries cold-chain shipping on every fill. | E5: High (company-reported) | F5: https://investors.hims.com/news/news-details/2026/Hims--Hers-Health-Inc--Reports-Fourth-Quarter-and-Full-Year-2025-Financial-Results/default.aspx https://www.sec.gov/Archives/edgar/data/1773751/000177375126000022/hims-20251231.htm
A6: B02 | B6: Telehealth marketing intensity | C6: Hims & Hers marketing expense was ~40% of revenue in Q2 2025 (down from ~46% a year earlier) and ~34.8% of revenue in Q2 2026 ($262.2M on $753.2M). | D6: Anchors the paid-media-as-percent-of-revenue driver (25-32% by scenario). A celebrity-led brand should sit below this, not above, or the audience is not doing any work. | E6: High (company-reported) | F6: https://www.sec.gov/Archives/edgar/data/0001773751/000177375126000161/hims-20260630x8xkearningsr.htm https://finance.yahoo.com/markets/stocks/articles/hims-hers-stock-plunges-post-171900613.html
A7: B03 | B7: DTC supplement gross margin and landed COGS | C7: Landed COGS (materials, packaging, manufacturing, inbound freight, duties) typically 20-30% of retail for a DTC supplement, producing 70-80% gross margin. Target range cited as 60-80%. Public DTC median gross margin ~57% for non-food categories. Per-unit COGS $3-15 depending on dosage form and volume. | D7: Non-Rx line COGS driver set at 22-30% of retail. | E7: Medium (aggregator/advisory sources, not audited) | F7: https://eightx.co/blog/supplements-brand-unit-economics https://commercecatalyst.ai/benchmarks/supplements/ https://eightx.co/blog/average-dtc-gross-margin-public-companies https://inventoryready.com/guides/supplement-pricing-strategy
A8: B04 | B8: DTC supplement CAC | C8: CAC $45-80 for supplements per triangulated industry estimates; $53-91 across ecommerce categories generally. | D8: Sanity band for the computed blended CAC output. The model derives CAC rather than assuming it. | E8: Medium | F8: https://commercecatalyst.ai/benchmarks/supplements/ https://foundrycro.com/blog/dtc-supplements-marketing-benchmarks-2026/
A9: B05 | B9: Supplement subscription churn | C9: 4-7% monthly when well run; 8-12% at health-and-wellness category average; 12-20% of subscribers churn in month 1 alone. Below 5% strong, below 4% top-tier, sustained above 10% a retention emergency. | D9: Non-Rx subscription churn driver 5.5-9% monthly by scenario. | E9: Medium | F9: https://eightx.co/blog/supplement-subscription-churn-rate-benchmark https://eightx.co/blog/average-subscription-churn-rate-by-category https://eightx.co/blog/supplements-subscription-economics
A10: B06 | B10: Supplement AOV, LTV and LTV:CAC | C10: AOV $30-65 monthly with 12-month LTV $300-600 (Recharge benchmarks cited). At 8% monthly churn a $40 subscriber at 55% margin returns ~$275 LTV. Healthy LTV:CAC 3.5:1 to 6:1, with 3:1 the floor. | D10: Non-Rx AOV driver $68-88 (premium positioning above the cited band) and the 3.0x LTV:CAC gate. | E10: Medium | F10: https://eightx.co/blog/supplements-subscription-economics https://www.retentionlab.ai/blog/good-ltv-dtc-benchmarks-2026 https://commercecatalyst.ai/benchmarks/supplements/
A11: B07 | B11: Compounded peptide programme pricing, US, 2026 | C11: Sermorelin $96-199/mo via telehealth, $200-400/mo in-clinic. BPC-157 or TB-500 tissue protocols $100-300/mo. CJC-1295/ipamorelin stack $80-180/mo. Sermorelin plus CJC-1295 combination protocols $350-600/mo. | D11: Rx programme price driver $199-299 per member-month, blended across protocols. | E11: Medium (marketing pages and category guides, not a price survey) | F11: https://healingmaps.com/sermorelin-cost-guide/ https://peptidenewsdigest.org/pricing/peptides/ https://www.peptidemark.com/news/peptide-therapy-cost-breakdown-2026 https://healingmaps.com/peptide-telehealth/
A12: B08 | B12: Asynchronous consult cost and price | C12: Asynchronous e-visits price at roughly $15-40 to the patient; raw median prices $20 (5-10 min) to $60 (21+ min). From the operator side a cited COGS breakdown is provider time $30, platform $10, support $10 per ongoing-care programme. Synchronous video $50-100. | D12: Clinician cost per completed consult driver $32-45, and consult fee charged $49-79. | E12: Medium | F12: https://bask.health/blog/pricing-for-telemedicine-services https://www.ncbi.nlm.nih.gov/books/NBK459384/ https://openmypro.com/cost/telehealth-visit-cost
A13: B09 | B13: Cold-chain fulfilment cost for peptides | C13: Quoted base pack rate $1.95 per order plus $350/month cold storage for refrigerated peptide inventory; FedEx 2-Day temperature-controlled is the standard lane. Additional cost for insulated mailers, gel packs, refrigerated carrier surcharges. Most peptides require 2-8 C. | D13: Cold-chain shipping driver $15-22 per Rx fill, which is the pack rate plus the expedited insulated lane, not the pack rate alone. | E13: Medium (vendor marketing pages) | F13: https://rapidfulfillment.com/blogs/news/peptide-fulfillment-pricing https://3plguys.com/articles/peptide-shipping-guide https://amzprep.com/peptide-fulfilment-services/
A14: B10 | B14: LegitScript healthcare merchant certification cost | C14: 2025-2026 schedule cited as $975 application plus $2,150 annual per website; ~$3,125 year one for a single-site brand, ~$2,150/yr ongoing; expedited review ~$2,500 extra. It gates healthcare advertising on Google, Meta, Microsoft, TikTok, LinkedIn and Nextdoor, and is close to a prerequisite for card-not-present acceptance. | D14: Certification line in opex. Also a gating dependency for the paid-media plan: no certification, no paid healthcare advertising at scale. | E14: Medium (third-party summaries of a schedule that changes; confirm live) | F14: https://myorbithealth.com/blog/legitscript-certification-telehealth-guide https://www.legitscript.com/certification/healthcare-certification/ https://www.2accept.net/blog/legitscript-certification-cost
A15: B11 | B15: Market rate for turnkey white-label telehealth infrastructure | C15: One vendor's published pricing is $3,000-6,000 per month by plan tier plus a $5,000-10,000 one-time onboarding fee and separate per-consult fees, as of mid-2026. Other vendors advertise a flat monthly fee with zero revenue share including LegitScript and multi-pharmacy access; most gate pricing behind a demo. The category supplies licensed providers, HIPAA intake and EMR, e-prescribing, pharmacy fulfilment and the MSO / friendly-PC legal structure while the brand owns the customer. | D15: Directly relevant to the stated $600/month flat fee. The model treats $600 as a platform/SaaS fee only and carries per-consult, medication, shipping and processing costs separately, because a fee at one fifth of the low end of published market pricing is very unlikely to absorb per-unit variable costs. | E15: Medium | F15: https://myorbithealth.com/blog/best-white-label-telehealth-platforms https://cuvo.co/blog/best-white-label-telehealth-platforms https://pharmabro.co/ https://thepharmacyhub.com/telehealth/ https://whitelabelmd.com/
... A22: B18 | B22: 503A bulk substances list movement on peptides, 2026 | C22: On 15 April 2026 FDA removed 12 peptides from Category 2 of the 503A bulk drug substances list. First-batch substances under review include BPC-157, KPV, MOTS-c, Emideltide (DSIP), Epitalon, Semax and TB-500. The Pharmacy Compounding Advisory Committee met 23-24 July 2026 on Emideltide, Semax and Epitalon related substances, and FDA announced a further meeting before the end of February 2027 covering GHK-Cu, Melanotan II, Cathelicidin (LL-37), Dihexa acetate and PEG-MGF. Gonadorelin acetate has been added to Category 1. One category guide states CJC-1295 and ipamorelin 'returned to Category 1 in 2026'. | D22: Not a financial driver but the gate on which products the Rx line may legally carry. The formulary must be re-verified against the live FDA list before launch and re-verified on each PCAC action; the CJC-1295/ipamorelin claim in particular rests on a single secondary source and is NOT treated as established. | E22: Medium for the FDA actions, Low for the CJC-1295/ipamorelin Category 1 claim | F22: https://www.fda.gov/advisory-committees/advisory-committee-calendar/july-23-24-2026-meeting-pharmacy-compounding-advisory-committee-07232026 https://www.thefdalawblog.com/2026/04/fdas-peptide-rally-what-compounders-and-industry-need-to-know-post-1-of-2/ https://www.fagronacademy.us/blog/industry-update-503a-and-503b-bulks-lists-new-revisions
A24: Not retrievable in this environment
B25: First-party analytics for any competitor (sessions, conversion rate, CAC, churn) — no traffic tool or ad library was reachable.
B26: Audited financials for any private peptide or celebrity supplement brand. IM8 and Gruns revenue figures are self-reported via press.
B27: Scott Disick's audience composition (US share, age, gender, health-category affinity) and any historical conversion performance on a paid endorsement.
B28: The identity, licences, contract terms, insurance, pharmacy network and LegitScript status of the $600/month provider — no provider was named.

Sheet Model_Conservative
A1: Reserve Clinic - Conservative scenario, months 1-36
A2: Every cell is a formula. Inputs live on Assumptions only. Green = link to Assumptions.
A4: Line | B4: Unit | C4: M1 | D4: M2 | E4: M3 | F4: M4 | G4: M5 | H4: M6 | I4: M7 | J4: M8 | K4: M9 | L4: M10 | M4: M11 | N4: M12 | O4: M13 | P4: M14 | Q4: M15 | R4: M16 | S4: M17 | T4: M18 | U4: M19 | V4: M20 | W4: M21 | X4: M22 | Y4: M23 | Z4: M24 | AA4: M25 | AB4: M26 | AC4: M27 | AD4: M28 | AE4: M29 | AF4: M30 | AG4: M31 | AH4: M32 | AI4: M33 | AJ4: M34 | AK4: M35 | AL4: M36 | AM4: Total / final
A5: Month index | B5: # | C5: 1 | D5: 2 | E5: 3 | F5: 4 | G5: 5 | H5: 6 | I5: 7 | J5: 8 | K5: 9 | L5: 10 | M5: 11 | N5: 12 | O5: 13 | P5: 14 | Q5: 15 | R5: 16 | S5: 17 | T5: 18 | U5: 19 | V5: 20 | W5: 21 | X5: 22 | Y5: 23 | Z5: 24 | AA5: 25 | AB5: 26 | AC5: 27 | AD5: 28 | AE5: 29 | AF5: 30 | AG5: 31 | AH5: 32 | AI5: 33 | AJ5: 34 | AK5: 35 | AL5: 36
A6: Year | B6: # | C6: =ROUNDUP(C$5/12,0) -> 1 | D6: =ROUNDUP(D$5/12,0) -> 1 | E6: =ROUNDUP(E$5/12,0) -> 1 | F6: =ROUNDUP(F$5/12,0) -> 1 | G6: =ROUNDUP(G$5/12,0) -> 1 | H6: =ROUNDUP(H$5/12,0) -> 1 | I6: =ROUNDUP(I$5/12,0) -> 1 | J6: =ROUNDUP(J$5/12,0) -> 1 | ... AL6: =ROUNDUP(AL$5/12,0) -> 3
A8: Non-Rx line live (1/0) | B8: flag | C8: =IF(C$5>=Assumptions!$D$6,1,0) -> 0 | D8: =IF(D$5>=Assumptions!$D$6,1,0) -> 0 | E8: =IF(E$5>=Assumptions!$D$6,1,0) -> 1 | F8: =IF(F$5>=Assumptions!$D$6,1,0) -> 1 | G8: =IF(G$5>=Assumptions!$D$6,1,0) -> 1 | H8: =IF(H$5>=Assumptions!$D$6,1,0) -> 1 | I8: =IF(I$5>=Assumptions!$D$6,1,0) -> 1 | J8: =IF(J$5>=Assumptions!$D$6,1,0) -> 1 | ... AL8: =IF(AL$5>=Assumptions!$D$6,1,0) -> 1
A9: Rx line live (1/0) | B9: flag | C9: =IF(C$5>=Assumptions!$D$7,1,0) -> 0 | D9: =IF(D$5>=Assumptions!$D$7,1,0) -> 0 | E9: =IF(E$5>=Assumptions!$D$7,1,0) -> 0 | F9: =IF(F$5>=Assumptions!$D$7,1,0) -> 0 | G9: =IF(G$5>=Assumptions!$D$7,1,0) -> 0 | H9: =IF(H$5>=Assumptions!$D$7,1,0) -> 0 | I9: =IF(I$5>=Assumptions!$D$7,1,0) -> 0 | J9: =IF(J$5>=Assumptions!$D$7,1,0) -> 0 | ... AL9: =IF(AL$5>=Assumptions!$D$7,1,0) -> 1
A10: Months since non-Rx launch | B10: # | C10: =MAX(0,C$5-Assumptions!$D$6) -> 0 | D10: =MAX(0,D$5-Assumptions!$D$6) -> 0 | E10: =MAX(0,E$5-Assumptions!$D$6) -> 0 | F10: =MAX(0,F$5-Assumptions!$D$6) -> 1 | G10: =MAX(0,G$5-Assumptions!$D$6) -> 2 | H10: =MAX(0,H$5-Assumptions!$D$6) -> 3 | I10: =MAX(0,I$5-Assumptions!$D$6) -> 4 | J10: =MAX(0,J$5-Assumptions!$D$6) -> 5 | ... AL10: =MAX(0,AL$5-Assumptions!$D$6) -> 33
A11: Partner-driven sessions at launch peak | B11: sessions | C11: =Assumptions!$D$9*Assumptions!$D$10*Assumptions!$D$11*Assumptions!$D$12 -> 7672 | D11: =Assumptions!$D$9*Assumptions!$D$10*Assumptions!$D$11*Assumptions!$D$12 -> 7672 | E11: =Assumptions!$D$9*Assumptions!$D$10*Assumptions!$D$11*Assumptions!$D$12 -> 7672 | F11: =Assumptions!$D$9*Assumptions!$D$10*Assumptions!$D$11*Assumptions!$D$12 -> 7672 | G11: =Assumptions!$D$9*Assumptions!$D$10*Assumptions!$D$11*Assumptions!$D$12 -> 7672 | H11: =Assumptions!$D$9*Assumptions!$D$10*Assumptions!$D$11*Assumptions!$D$12 -> 7672 | I11: =Assumptions!$D$9*Assumptions!$D$10*Assumptions!$D$11*Assumptions!$D$12 -> 7672 | J11: =Assumptions!$D$9*Assumptions!$D$10*Assumptions!$D$11*Assumptions!$D$12 -> 7672 | ... AL11: =Assumptions!$D$9*Assumptions!$D$10*Assumptions!$D$11*Assumptions!$D$12 -> 7672
A12: Attention index (decay toward floor) | B12: x | C12: =IF(C8=0,0,IF(C10=0,Assumptions!$D$15,Assumptions!$D$14+(1-Assumptions!$D$14)*Assumptions!$D$13^C10)) -> 0 | D12: =IF(D8=0,0,IF(D10=0,Assumptions!$D$15,Assumptions!$D$14+(1-Assumptions!$D$14)*Assumptions!$D$13^D10)) -> 0 | E12: =IF(E8=0,0,IF(E10=0,Assumptions!$D$15,Assumptions!$D$14+(1-Assumptions!$D$14)*Assumptions!$D$13^E10)) -> 1.6 | F12: =IF(F8=0,0,IF(F10=0,Assumptions!$D$15,Assumptions!$D$14+(1-Assumptions!$D$14)*Assumptions!$D$13^F10)) -> 0.7984 | G12: =IF(G8=0,0,IF(G10=0,Assumptions!$D$15,Assumptions!$D$14+(1-Assumptions!$D$14)*Assumptions!$D$13^G10)) -> 0.653248 | H12: =IF(H8=0,0,IF(H10=0,Assumptions!$D$15,Assumptions!$D$14+(1-Assumptions!$D$14)*Assumptions!$D$13^H10)) -> 0.54873856 | I12: =IF(I8=0,0,IF(I10=0,Assumptions!$D$15,Assumptions!$D$14+(1-Assumptions!$D$14)*Assumptions!$D$13^I10)) -> 0.47349176 | J12: =IF(J8=0,0,IF(J10=0,Assumptions!$D$15,Assumptions!$D$14+(1-Assumptions!$D$14)*Assumptions!$D$13^J10)) -> 0.41931407 | ... AL12: =IF(AL8=0,0,IF(AL10=0,Assumptions!$D$15,Assumptions!$D$14+(1-Assumptions!$D$14)*Assumptions!$D$13^AL10)) -> 0.2800141
A13: Partner-driven sessions | B13: sessions | C13: =C11*C12 -> 0 | D13: =D11*D12 -> 0 | E13: =E11*E12 -> 12275.2 | F13: =F11*F12 -> 6125.3248 | G13: =G11*G12 -> 5011.7187 | H13: =H11*H12 -> 4209.9222 | I13: =I11*I12 -> 3632.6288 | J13: =J11*J12 -> 3216.9775 | ... AL13: =AL11*AL12 -> 2148.2682 | AM13: =SUM(C13:AL13) -> 97368.362
A14: Organic and direct sessions | B14: sessions | C14: =MIN(Assumptions!$D$19,Assumptions!$D$17*(1+Assumptions!$D$18)^(C$5-1)) -> 1200 | D14: =MIN(Assumptions!$D$19,Assumptions!$D$17*(1+Assumptions!$D$18)^(D$5-1)) -> 1272 | E14: =MIN(Assumptions!$D$19,Assumptions!$D$17*(1+Assumptions!$D$18)^(E$5-1)) -> 1348.32 | F14: =MIN(Assumptions!$D$19,Assumptions!$D$17*(1+Assumptions!$D$18)^(F$5-1)) -> 1429.2192 | G14: =MIN(Assumptions!$D$19,Assumptions!$D$17*(1+Assumptions!$D$18)^(G$5-1)) -> 1514.9724 | H14: =MIN(Assumptions!$D$19,Assumptions!$D$17*(1+Assumptions!$D$18)^(H$5-1)) -> 1605.8707 | I14: =MIN(Assumptions!$D$19,Assumptions!$D$17*(1+Assumptions!$D$18)^(I$5-1)) -> 1702.2229 | J14: =MIN(Assumptions!$D$19,Assumptions!$D$17*(1+Assumptions!$D$18)^(J$5-1)) -> 1804.3563 | ... AL14: =MIN(Assumptions!$D$19,Assumptions!$D$17*(1+Assumptions!$D$18)^(AL$5-1)) -> 9223.3042 | AM14: =SUM(C14:AL14) -> 142945.04
A15: Paid media spend | B15: $ | C15: =Assumptions!$D$21 -> 4000 | D15: =IF(D8=0,Assumptions!$D$21,MIN(Assumptions!$D$25,MAX(Assumptions!$D$22,C60*Assumptions!$D$23))) -> 4000 | E15: =IF(E8=0,Assumptions!$D$21,MIN(Assumptions!$D$25,MAX(Assumptions!$D$22,D60*Assumptions!$D$23))) -> 10000 | F15: =IF(F8=0,Assumptions!$D$21,MIN(Assumptions!$D$25,MAX(Assumptions!$D$22,E60*Assumptions!$D$23))) -> 10000 | G15: =IF(G8=0,Assumptions!$D$21,MIN(Assumptions!$D$25,MAX(Assumptions!$D$22,F60*Assumptions!$D$23))) -> 10000 | H15: =IF(H8=0,Assumptions!$D$21,MIN(Assumptions!$D$25,MAX(Assumptions!$D$22,G60*Assumptions!$D$23))) -> 10000 | I15: =IF(I8=0,Assumptions!$D$21,MIN(Assumptions!$D$25,MAX(Assumptions!$D$22,H60*Assumptions!$D$23))) -> 10000 | J15: =IF(J8=0,Assumptions!$D$21,MIN(Assumptions!$D$25,MAX(Assumptions!$D$22,I60*Assumptions!$D$23))) -> 10000 | K15: =IF(K8=0,Assumptions!$D$21,MIN(Assumptions!$D$25,MAX(Assumptions!$D$22,J60*Assumptions!$D$23))) -> 10000 | ... AL15: =IF(AL8=0,Assumptions!$D$21,MIN(Assumptions!$D$25,MAX(Assumptions!$D$22,AK60*Assumptions!$D$23))) -> 10144.033 | AM15: =SUM(C15:AL15) -> 348144.03
A16: Paid sessions (diminishing returns applied) | B16: sessions | C16: =(Assumptions!$D$22/Assumptions!$D$20)*(C15/Assumptions!$D$22)^Assumptions!$D$26 -> 2062.659 | D16: =(Assumptions!$D$22/Assumptions!$D$20)*(D15/Assumptions!$D$22)^Assumptions!$D$26 -> 2062.659 | E16: =(Assumptions!$D$22/Assumptions!$D$20)*(E15/Assumptions!$D$22)^Assumptions!$D$26 -> 3846.1538 | F16: =(Assumptions!$D$22/Assumptions!$D$20)*(F15/Assumptions!$D$22)^Assumptions!$D$26 -> 3846.1538 | G16: =(Assumptions!$D$22/Assumptions!$D$20)*(G15/Assumptions!$D$22)^Assumptions!$D$26 -> 3846.1538 | H16: =(Assumptions!$D$22/Assumptions!$D$20)*(H15/Assumptions!$D$22)^Assumptions!$D$26 -> 3846.1538 | I16: =(Assumptions!$D$22/Assumptions!$D$20)*(I15/Assumptions!$D$22)^Assumptions!$D$26 -> 3846.1538 | J16: =(Assumptions!$D$22/Assumptions!$D$20)*(J15/Assumptions!$D$22)^Assumptions!$D$26 -> 3846.1538 | ... AL16: =(Assumptions!$D$22/Assumptions!$D$20)*(AL15/Assumptions!$D$22)^Assumptions!$D$26 -> 3883.7377 | AM16: =SUM(C16:AL16) -> 134932.13
A17: Effective cost per paid session | B17: $ | C17: =IFERROR(C15/C16,0) -> 1.9392444 | D17: =IFERROR(D15/D16,0) -> 1.9392444 | E17: =IFERROR(E15/E16,0) -> 2.6 | F17: =IFERROR(F15/F16,0) -> 2.6 | G17: =IFERROR(G15/G16,0) -> 2.6 | H17: =IFERROR(H15/H16,0) -> 2.6 | I17: =IFERROR(I15/I16,0) -> 2.6 | J17: =IFERROR(J15/J16,0) -> 2.6 | ... AL17: =IFERROR(AL15/AL16,0) -> 2.6119253 | AM17: =AVERAGE(N17:AL17) -> 2.600477
A18: Total sessions | B18: sessions | C18: =C13+C14+C16 -> 3262.659 | D18: =D13+D14+D16 -> 3334.659 | E18: =E13+E14+E16 -> 17469.674 | F18: =F13+F14+F16 -> 11400.698 | G18: =G13+G14+G16 -> 10372.845 | H18: =H13+H14+H16 -> 9661.9468 | I18: =I13+I14+I16 -> 9181.0056 | J18: =J13+J14+J16 -> 8867.4877 | ... AL18: =AL13+AL14+AL16 -> 15255.31 | AM18: =SUM(C18:AL18) -> 375245.53
A19: Shippable new-order capacity | B19: # | C19: =C8*Assumptions!$D$28*Assumptions!$D$29^C10 -> 0 | D19: =D8*Assumptions!$D$28*Assumptions!$D$29^D10 -> 0 | E19: =E8*Assumptions!$D$28*Assumptions!$D$29^E10 -> 600 | F19: =F8*Assumptions!$D$28*Assumptions!$D$29^F10 -> 750 | G19: =G8*Assumptions!$D$28*Assumptions!$D$29^G10 -> 937.5 | H19: =H8*Assumptions!$D$28*Assumptions!$D$29^H10 -> 1171.875 | I19: =I8*Assumptions!$D$28*Assumptions!$D$29^I10 -> 1464.8438 | J19: =J8*Assumptions!$D$28*Assumptions!$D$29^J10 -> 1831.0547 | ... AL19: =AL8*Assumptions!$D$28*Assumptions!$D$29^AL10 -> 946633.09 | AM19: =AL19 -> 946633.09
A20: New non-Rx customer demand | B20: # | C20: =C18*Assumptions!$D$30*C8 -> 0 | D20: =D18*Assumptions!$D$30*D8 -> 0 | E20: =E18*Assumptions!$D$30*E8 -> 157.22706 | F20: =F18*Assumptions!$D$30*F8 -> 102.60628 | G20: =G18*Assumptions!$D$30*G8 -> 93.355604 | H20: =H18*Assumptions!$D$30*H8 -> 86.957521 | I20: =I18*Assumptions!$D$30*I8 -> 82.62905 | J20: =J18*Assumptions!$D$30*J8 -> 79.807389 | ... AL20: =AL18*Assumptions!$D$30*AL8 -> 137.29779 | AM20: =SUM(C20:AL20) -> 3317.8339
A21: New non-Rx customers served | B21: # | C21: =MIN(C20,C19) -> 0 | D21: =MIN(D20,D19) -> 0 | E21: =MIN(E20,E19) -> 157.22706 | F21: =MIN(F20,F19) -> 102.60628 | G21: =MIN(G20,G19) -> 93.355604 | H21: =MIN(H20,H19) -> 86.957521 | I21: =MIN(I20,I19) -> 82.62905 | J21: =MIN(J20,J19) -> 79.807389 | ... AL21: =MIN(AL20,AL19) -> 137.29779 | AM21: =SUM(C21:AL21) -> 3317.8339
A22: Demand lost to capacity | B22: # | C22: =MAX(0,C20-C19) -> 0 | D22: =MAX(0,D20-D19) -> 0 | E22: =MAX(0,E20-E19) -> 0 | F22: =MAX(0,F20-F19) -> 0 | G22: =MAX(0,G20-G19) -> 0 | H22: =MAX(0,H20-H19) -> 0 | I22: =MAX(0,I20-I19) -> 0 | J22: =MAX(0,J20-J19) -> 0 | ... AL22: =MAX(0,AL20-AL19) -> 0 | AM22: =SUM(C22:AL22) -> 0
A23: New subscribers | B23: # | C23: =C21*Assumptions!$D$32 -> 0 | D23: =D21*Assumptions!$D$32 -> 0 | E23: =E21*Assumptions!$D$32 -> 47.168119 | F23: =F21*Assumptions!$D$32 -> 30.781884 | G23: =G21*Assumptions!$D$32 -> 28.006681 | H23: =H21*Assumptions!$D$32 -> 26.087256 | I23: =I21*Assumptions!$D$32 -> 24.788715 | J23: =J21*Assumptions!$D$32 -> 23.942217 | ... AL23: =AL21*Assumptions!$D$32 -> 41.189337 | AM23: =SUM(C23:AL23) -> 995.35018
A24: New one-time buyers | B24: # | C24: =C21*(1-Assumptions!$D$32) -> 0 | D24: =D21*(1-Assumptions!$D$32) -> 0 | E24: =E21*(1-Assumptions!$D$32) -> 110.05895 | F24: =F21*(1-Assumptions!$D$32) -> 71.824396 | G24: =G21*(1-Assumptions!$D$32) -> 65.348923 | H24: =H21*(1-Assumptions!$D$32) -> 60.870265 | I24: =I21*(1-Assumptions!$D$32) -> 57.840335 | J24: =J21*(1-Assumptions!$D$32) -> 55.865172 | ... AL24: =AL21*(1-Assumptions!$D$32) -> 96.108453 | AM24: =SUM(C24:AL24) -> 2322.4838
A25: Active subscribers (end of month) | B25: # | C25: =C23 -> 0 | D25: =C25*(1-Assumptions!$D$33)+D23 -> 0 | E25: =D25*(1-Assumptions!$D$33)+E23 -> 47.168119 | F25: =E25*(1-Assumptions!$D$33)+F23 -> 73.704873 | G25: =F25*(1-Assumptions!$D$33)+G23 -> 95.078115 | H25: =G25*(1-Assumptions!$D$33)+H23 -> 112.60834 | I25: =H25*(1-Assumptions!$D$33)+I23 -> 127.26231 | J25: =I25*(1-Assumptions!$D$33)+J23 -> 139.75091 | K25: =J25*(1-Assumptions!$D$33)+K23 -> 150.59983 | ... AL25: =AK25*(1-Assumptions!$D$33)+AL23 -> 351.37717 | AM25: =AL25 -> 351.37717
A26: Subscribers churned | B26: # | C26: =0 -> 0 | D26: =C25*Assumptions!$D$33 -> 0 | E26: =D25*Assumptions!$D$33 -> 0 | F26: =E25*Assumptions!$D$33 -> 4.2451307 | G26: =F25*Assumptions!$D$33 -> 6.6334386 | H26: =G25*Assumptions!$D$33 -> 8.5570304 | I26: =H25*Assumptions!$D$33 -> 10.134751 | J26: =I25*Assumptions!$D$33 -> 11.453608 | K26: =J25*Assumptions!$D$33 -> 12.577582 | ... AL26: =AK25*Assumptions!$D$33 -> 30.677917 | AM26: =SUM(C26:AL26) -> 643.97302
A27: Repeat orders from one-time buyers | B27: # | C27: =0 -> 0 | D27: =C24*Assumptions!$D$34 -> 0 | E27: =D24*Assumptions!$D$34 -> 0 | F27: =E24*Assumptions!$D$34 -> 8.8047156 | G27: =F24*Assumptions!$D$34 -> 5.7459517 | H27: =G24*Assumptions!$D$34 -> 5.2279138 | I27: =H24*Assumptions!$D$34 -> 4.8696212 | J27: =I24*Assumptions!$D$34 -> 4.6272268 | K27: =J24*Assumptions!$D$34 -> 4.4692138 | ... AL27: =AK24*Assumptions!$D$34 -> 7.40663 | AM27: =SUM(C27:AL27) -> 178.11002
A28: Non-Rx orders shipped | B28: # | C28: =C24+C25+C27 -> 0 | D28: =D24+D25+D27 -> 0 | E28: =E24+E25+E27 -> 157.22706 | F28: =F24+F25+F27 -> 154.33398 | G28: =G24+G25+G27 -> 166.17299 | H28: =H24+H25+H27 -> 178.70652 | I28: =I24+I25+I27 -> 189.97226 | J28: =J24+J25+J27 -> 200.24331 | ... AL28: =AL24+AL25+AL27 -> 454.89225 | AM28: =SUM(C28:AL28) -> 10007.227
A29: Non-Rx gross revenue | B29: $ | C29: =C28*Assumptions!$D$31 -> 0 | D29: =D28*Assumptions!$D$31 -> 0 | E29: =E28*Assumptions!$D$31 -> 10691.44 | F29: =F28*Assumptions!$D$31 -> 10494.711 | G29: =G28*Assumptions!$D$31 -> 11299.763 | H29: =H28*Assumptions!$D$31 -> 12152.043 | I29: =I28*Assumptions!$D$31 -> 12918.114 | J29: =J28*Assumptions!$D$31 -> 13616.545 | ... AL29: =AL28*Assumptions!$D$31 -> 30932.673 | AM29: =SUM(C29:AL29) -> 680491.42
A30: Non-Rx refunds and chargebacks | B30: $ | C30: =-C29*Assumptions!$D$61 -> 0 | D30: =-D29*Assumptions!$D$61 -> 0 | E30: =-E29*Assumptions!$D$61 -> -427.65762 | F30: =-F29*Assumptions!$D$61 -> -419.78844 | G30: =-G29*Assumptions!$D$61 -> -451.99053 | H30: =-H29*Assumptions!$D$61 -> -486.08173 | I30: =-I29*Assumptions!$D$61 -> -516.72455 | J30: =-J29*Assumptions!$D$61 -> -544.66181 | ... AL30: =-AL29*Assumptions!$D$61 -> -1237.3069 | AM30: =SUM(C30:AL30) -> -27219.657
A31: Non-Rx net revenue | B31: $ | C31: =C29+C30 -> 0 | D31: =D29+D30 -> 0 | E31: =E29+E30 -> 10263.783 | F31: =F29+F30 -> 10074.923 | G31: =G29+G30 -> 10847.773 | H31: =H29+H30 -> 11665.962 | I31: =I29+I30 -> 12401.389 | J31: =J29+J30 -> 13071.884 | ... AL31: =AL29+AL30 -> 29695.366 | AM31: =SUM(C31:AL31) -> 653271.76
A32: Non-Rx product COGS | B32: $ | C32: =-C29*Assumptions!$D$36 -> 0 | D32: =-D29*Assumptions!$D$36 -> 0 | E32: =-E29*Assumptions!$D$36 -> -3207.4321 | F32: =-F29*Assumptions!$D$36 -> -3148.4133 | G32: =-G29*Assumptions!$D$36 -> -3389.929 | H32: =-H29*Assumptions!$D$36 -> -3645.613 | I32: =-I29*Assumptions!$D$36 -> -3875.4341 | J32: =-J29*Assumptions!$D$36 -> -4084.9636 | ... AL32: =-AL29*Assumptions!$D$36 -> -9279.8019 | AM32: =SUM(C32:AL32) -> -204147.42
A33: Non-Rx pick, pack and ship | B33: $ | C33: =-C28*Assumptions!$D$37 -> 0 | D33: =-D28*Assumptions!$D$37 -> 0 | E33: =-E28*Assumptions!$D$37 -> -1336.43 | F33: =-F28*Assumptions!$D$37 -> -1311.8389 | G33: =-G28*Assumptions!$D$37 -> -1412.4704 | H33: =-H28*Assumptions!$D$37 -> -1519.0054 | I33: =-I28*Assumptions!$D$37 -> -1614.7642 | J33: =-J28*Assumptions!$D$37 -> -1702.0682 | ... AL33: =-AL28*Assumptions!$D$37 -> -3866.5841 | AM33: =SUM(C33:AL33) -> -85061.427
A34: Non-Rx payment processing | B34: $ | C34: =-C31*Assumptions!$D$60 -> 0 | D34: =-D31*Assumptions!$D$60 -> 0 | E34: =-E31*Assumptions!$D$60 -> -328.44105 | F34: =-F31*Assumptions!$D$60 -> -322.39752 | G34: =-G31*Assumptions!$D$60 -> -347.12873 | H34: =-H31*Assumptions!$D$60 -> -373.31077 | I34: =-I31*Assumptions!$D$60 -> -396.84446 | J34: =-J31*Assumptions!$D$60 -> -418.30027 | ... AL34: =-AL31*Assumptions!$D$60 -> -950.25171 | AM34: =SUM(C34:AL34) -> -20904.696
A35: Non-Rx gross profit | B35: $ | C35: =C31+C32+C33+C34 -> 0 | D35: =D31+D32+D33+D34 -> 0 | E35: =E31+E32+E33+E34 -> 5391.4796 | F35: =F31+F32+F33+F34 -> 5292.2728 | G35: =G31+G32+G33+G34 -> 5698.2446 | H35: =H31+H32+H33+H34 -> 6128.0324 | I35: =I31+I32+I33+I34 -> 6514.3464 | J35: =J31+J32+J33+J34 -> 6866.5515 | ... AL35: =AL31+AL32+AL33+AL34 -> 15598.728 | AM35: =SUM(C35:AL35) -> 343158.21
A36: Non-Rx gross margin | B36: % | C36: =IFERROR(C35/C31,0) -> 0 | D36: =IFERROR(D35/D31,0) -> 0 | E36: =IFERROR(E35/E31,0) -> 0.52529167 | F36: =IFERROR(F35/F31,0) -> 0.52529167 | G36: =IFERROR(G35/G31,0) -> 0.52529167 | H36: =IFERROR(H35/H31,0) -> 0.52529167 | I36: =IFERROR(I35/I31,0) -> 0.52529167 | J36: =IFERROR(J35/J31,0) -> 0.52529167 | ... AL36: =IFERROR(AL35/AL31,0) -> 0.52529167 | AM36: =AVERAGE(N36:AL36) -> 0.52529167
A37: US population covered by served states | B37: % | C37: =IF(C9=0,0,MIN(Assumptions!$D$44,Assumptions!$D$42+Assumptions!$D$43*(C$5-Assumptions!$D$7))) -> 0 | D37: =IF(D9=0,0,MIN(Assumptions!$D$44,Assumptions!$D$42+Assumptions!$D$43*(D$5-Assumptions!$D$7))) -> 0 | E37: =IF(E9=0,0,MIN(Assumptions!$D$44,Assumptions!$D$42+Assumptions!$D$43*(E$5-Assumptions!$D$7))) -> 0 | F37: =IF(F9=0,0,MIN(Assumptions!$D$44,Assumptions!$D$42+Assumptions!$D$43*(F$5-Assumptions!$D$7))) -> 0 | G37: =IF(G9=0,0,MIN(Assumptions!$D$44,Assumptions!$D$42+Assumptions!$D$43*(G$5-Assumptions!$D$7))) -> 0 | H37: =IF(H9=0,0,MIN(Assumptions!$D$44,Assumptions!$D$42+Assumptions!$D$43*(H$5-Assumptions!$D$7))) -> 0 | I37: =IF(I9=0,0,MIN(Assumptions!$D$44,Assumptions!$D$42+Assumptions!$D$43*(I$5-Assumptions!$D$7))) -> 0 | J37: =IF(J9=0,0,MIN(Assumptions!$D$44,Assumptions!$D$42+Assumptions!$D$43*(J$5-Assumptions!$D$7))) -> 0 | ... AL37: =IF(AL9=0,0,MIN(Assumptions!$D$44,Assumptions!$D$42+Assumptions!$D$43*(AL$5-Assumptions!$D$7))) -> 0.665 | AM37: =AL37 -> 0.665
A38: Eligibility quiz starts | B38: # | C38: =C18*Assumptions!$D$39*C9 -> 0 | D38: =D18*Assumptions!$D$39*D9 -> 0 | E38: =E18*Assumptions!$D$39*E9 -> 0 | F38: =F18*Assumptions!$D$39*F9 -> 0 | G38: =G18*Assumptions!$D$39*G9 -> 0 | H38: =H18*Assumptions!$D$39*H9 -> 0 | I38: =I18*Assumptions!$D$39*I9 -> 0 | J38: =J18*Assumptions!$D$39*J9 -> 0 | ... AL38: =AL18*Assumptions!$D$39*AL9 -> 183.06372 | AM38: =SUM(C38:AL38) -> 3620.3347
A39: Quiz completions | B39: # | C39: =C38*Assumptions!$D$40 -> 0 | D39: =D38*Assumptions!$D$40 -> 0 | E39: =E38*Assumptions!$D$40 -> 0 | F39: =F38*Assumptions!$D$40 -> 0 | G39: =G38*Assumptions!$D$40 -> 0 | H39: =H38*Assumptions!$D$40 -> 0 | I39: =I38*Assumptions!$D$40 -> 0 | J39: =J38*Assumptions!$D$40 -> 0 | ... AL39: =AL38*Assumptions!$D$40 -> 109.83823 | AM39: =SUM(C39:AL39) -> 2172.2008
A40: Eligible outcomes (clinical screen and state) | B40: # | C40: =C39*Assumptions!$D$41*C37 -> 0 | D40: =D39*Assumptions!$D$41*D37 -> 0 | E40: =E39*Assumptions!$D$41*E37 -> 0 | F40: =F39*Assumptions!$D$41*F37 -> 0 | G40: =G39*Assumptions!$D$41*G37 -> 0 | H40: =H39*Assumptions!$D$41*H37 -> 0 | I40: =I39*Assumptions!$D$41*I37 -> 0 | J40: =J39*Assumptions!$D$41*J37 -> 0 | ... AL40: =AL39*Assumptions!$D$41*AL37 -> 36.521212 | AM40: =SUM(C40:AL40) -> 526.51197
A41: Intakes submitted (consult fee charged) | B41: # | C41: =C40*Assumptions!$D$45 -> 0 | D41: =D40*Assumptions!$D$45 -> 0 | E41: =E40*Assumptions!$D$45 -> 0 | F41: =F40*Assumptions!$D$45 -> 0 | G41: =G40*Assumptions!$D$45 -> 0 | H41: =H40*Assumptions!$D$45 -> 0 | I41: =I40*Assumptions!$D$45 -> 0 | J41: =J40*Assumptions!$D$45 -> 0 | ... AL41: =AL40*Assumptions!$D$45 -> 17.530182 | AM41: =SUM(C41:AL41) -> 252.72574
A42: Consults completed | B42: # | C42: =C41*Assumptions!$D$46 -> 0 | D42: =D41*Assumptions!$D$46 -> 0 | E42: =E41*Assumptions!$D$46 -> 0 | F42: =F41*Assumptions!$D$46 -> 0 | G42: =G41*Assumptions!$D$46 -> 0 | H42: =H41*Assumptions!$D$46 -> 0 | I42: =I41*Assumptions!$D$46 -> 0 | J42: =J41*Assumptions!$D$46 -> 0 | ... AL42: =AL41*Assumptions!$D$46 -> 13.322938 | AM42: =SUM(C42:AL42) -> 192.07157
A43: Prescriptions issued (clinician decision) | B43: # | C43: =C42*Assumptions!$D$47 -> 0 | D43: =D42*Assumptions!$D$47 -> 0 | E43: =E42*Assumptions!$D$47 -> 0 | F43: =F42*Assumptions!$D$47 -> 0 | G43: =G42*Assumptions!$D$47 -> 0 | H43: =H42*Assumptions!$D$47 -> 0 | I43: =I42*Assumptions!$D$47 -> 0 | J43: =J42*Assumptions!$D$47 -> 0 | ... AL43: =AL42*Assumptions!$D$47 -> 7.327616 | AM43: =SUM(C43:AL43) -> 105.63936
A44: New paying programme members | B44: # | C44: =C43*Assumptions!$D$48 -> 0 | D44: =D43*Assumptions!$D$48 -> 0 | E44: =E43*Assumptions!$D$48 -> 0 | F44: =F43*Assumptions!$D$48 -> 0 | G44: =G43*Assumptions!$D$48 -> 0 | H44: =H43*Assumptions!$D$48 -> 0 | I44: =I43*Assumptions!$D$48 -> 0 | J44: =J43*Assumptions!$D$48 -> 0 | ... AL44: =AL43*Assumptions!$D$48 -> 4.2500173 | AM44: =SUM(C44:AL44) -> 61.270829
A45: Active programme members (end of month) | B45: # | C45: =C44 -> 0 | D45: =C45*(1-Assumptions!$D$49)+D44 -> 0 | E45: =D45*(1-Assumptions!$D$49)+E44 -> 0 | F45: =E45*(1-Assumptions!$D$49)+F44 -> 0 | G45: =F45*(1-Assumptions!$D$49)+G44 -> 0 | H45: =G45*(1-Assumptions!$D$49)+H44 -> 0 | I45: =H45*(1-Assumptions!$D$49)+I44 -> 0 | J45: =I45*(1-Assumptions!$D$49)+J44 -> 0 | K45: =J45*(1-Assumptions!$D$49)+K44 -> 0.94507209 | ... AL45: =AK45*(1-Assumptions!$D$49)+AL44 -> 23.714637 | AM45: =AL45 -> 23.714637
A46: Programme members churned | B46: # | C46: =0 -> 0 | D46: =C45*Assumptions!$D$49 -> 0 | E46: =D45*Assumptions!$D$49 -> 0 | F46: =E45*Assumptions!$D$49 -> 0 | G46: =F45*Assumptions!$D$49 -> 0 | H46: =G45*Assumptions!$D$49 -> 0 | I46: =H45*Assumptions!$D$49 -> 0 | J46: =I45*Assumptions!$D$49 -> 0 | K46: =J45*Assumptions!$D$49 -> 0 | ... AL46: =AK45*Assumptions!$D$49 -> 2.9085064 | AM46: =SUM(C46:AL46) -> 37.556193
A47: Programme subscription revenue | B47: $ | C47: =C45*Assumptions!$D$51 -> 0 | D47: =D45*Assumptions!$D$51 -> 0 | E47: =E45*Assumptions!$D$51 -> 0 | F47: =F45*Assumptions!$D$51 -> 0 | G47: =G45*Assumptions!$D$51 -> 0 | H47: =H45*Assumptions!$D$51 -> 0 | I47: =I45*Assumptions!$D$51 -> 0 | J47: =J45*Assumptions!$D$51 -> 0 | ... AL47: =AL45*Assumptions!$D$51 -> 4719.2127 | AM47: =SUM(C47:AL47) -> 62209.077
A48: Consultation fee revenue | B48: $ | C48: =C41*Assumptions!$D$52 -> 0 | D48: =D41*Assumptions!$D$52 -> 0 | E48: =E41*Assumptions!$D$52 -> 0 | F48: =F41*Assumptions!$D$52 -> 0 | G48: =G41*Assumptions!$D$52 -> 0 | H48: =H41*Assumptions!$D$52 -> 0 | I48: =I41*Assumptions!$D$52 -> 0 | J48: =J41*Assumptions!$D$52 -> 0 | ... AL48: =AL41*Assumptions!$D$52 -> 858.97891 | AM48: =SUM(C48:AL48) -> 12383.561
A49: Rx gross revenue | B49: $ | C49: =C47+C48 -> 0 | D49: =D47+D48 -> 0 | E49: =E47+E48 -> 0 | F49: =F47+F48 -> 0 | G49: =G47+G48 -> 0 | H49: =H47+H48 -> 0 | I49: =I47+I48 -> 0 | J49: =J47+J48 -> 0 | ... AL49: =AL47+AL48 -> 5578.1917 | AM49: =SUM(C49:AL49) -> 74592.638
A50: Rx refunds and chargebacks | B50: $ | C50: =-C49*Assumptions!$D$61 -> 0 | D50: =-D49*Assumptions!$D$61 -> 0 | E50: =-E49*Assumptions!$D$61 -> 0 | F50: =-F49*Assumptions!$D$61 -> 0 | G50: =-G49*Assumptions!$D$61 -> 0 | H50: =-H49*Assumptions!$D$61 -> 0 | I50: =-I49*Assumptions!$D$61 -> 0 | J50: =-J49*Assumptions!$D$61 -> 0 | ... AL50: =-AL49*Assumptions!$D$61 -> -223.12767 | AM50: =SUM(C50:AL50) -> -2983.7055
A51: Rx net revenue | B51: $ | C51: =C49+C50 -> 0 | D51: =D49+D50 -> 0 | E51: =E49+E50 -> 0 | F51: =F49+F50 -> 0 | G51: =G49+G50 -> 0 | H51: =H49+H50 -> 0 | I51: =I49+I50 -> 0 | J51: =J49+J50 -> 0 | ... AL51: =AL49+AL50 -> 5355.064 | AM51: =SUM(C51:AL51) -> 71608.933
A52: Pharmacy medication cost | B52: $ | C52: =-C45*Assumptions!$D$54 -> 0 | D52: =-D45*Assumptions!$D$54 -> 0 | E52: =-E45*Assumptions!$D$54 -> 0 | F52: =-F45*Assumptions!$D$54 -> 0 | G52: =-G45*Assumptions!$D$54 -> 0 | H52: =-H45*Assumptions!$D$54 -> 0 | I52: =-I45*Assumptions!$D$54 -> 0 | J52: =-J45*Assumptions!$D$54 -> 0 | ... AL52: =-AL45*Assumptions!$D$54 -> -2490.0369 | AM52: =SUM(C52:AL52) -> -32823.885
A53: Clinician cost, new consults | B53: $ | C53: =-C42*Assumptions!$D$55 -> 0 | D53: =-D42*Assumptions!$D$55 -> 0 | E53: =-E42*Assumptions!$D$55 -> 0 | F53: =-F42*Assumptions!$D$55 -> 0 | G53: =-G42*Assumptions!$D$55 -> 0 | H53: =-H42*Assumptions!$D$55 -> 0 | I53: =-I42*Assumptions!$D$55 -> 0 | J53: =-J42*Assumptions!$D$55 -> 0 | ... AL53: =-AL42*Assumptions!$D$55 -> -599.53222 | AM53: =SUM(C53:AL53) -> -8643.2204
A54: Clinician cost, monitoring and refills | B54: $ | C54: =-C45*Assumptions!$D$56 -> 0 | D54: =-D45*Assumptions!$D$56 -> 0 | E54: =-E45*Assumptions!$D$56 -> 0 | F54: =-F45*Assumptions!$D$56 -> 0 | G54: =-G45*Assumptions!$D$56 -> 0 | H54: =-H45*Assumptions!$D$56 -> 0 | I54: =-I45*Assumptions!$D$56 -> 0 | J54: =-J45*Assumptions!$D$56 -> 0 | ... AL54: =-AL45*Assumptions!$D$56 -> -237.14637 | AM54: =SUM(C54:AL54) -> -3126.0843
A55: Cold-chain fulfilment and shipping | B55: $ | C55: =-C45*Assumptions!$D$57 -> 0 | D55: =-D45*Assumptions!$D$57 -> 0 | E55: =-E45*Assumptions!$D$57 -> 0 | F55: =-F45*Assumptions!$D$57 -> 0 | G55: =-G45*Assumptions!$D$57 -> 0 | H55: =-H45*Assumptions!$D$57 -> 0 | I55: =-I45*Assumptions!$D$57 -> 0 | J55: =-J45*Assumptions!$D$57 -> 0 | ... AL55: =-AL45*Assumptions!$D$57 -> -521.72201 | AM55: =SUM(C55:AL55) -> -6877.3854
A56: Rx support cost | B56: $ | C56: =-C45*Assumptions!$D$58 -> 0 | D56: =-D45*Assumptions!$D$58 -> 0 | E56: =-E45*Assumptions!$D$58 -> 0 | F56: =-F45*Assumptions!$D$58 -> 0 | G56: =-G45*Assumptions!$D$58 -> 0 | H56: =-H45*Assumptions!$D$58 -> 0 | I56: =-I45*Assumptions!$D$58 -> 0 | J56: =-J45*Assumptions!$D$58 -> 0 | ... AL56: =-AL45*Assumptions!$D$58 -> -142.28782 | AM56: =SUM(C56:AL56) -> -1875.6506
A57: Rx payment processing | B57: $ | C57: =-C51*Assumptions!$D$60 -> 0 | D57: =-D51*Assumptions!$D$60 -> 0 | E57: =-E51*Assumptions!$D$60 -> 0 | F57: =-F51*Assumptions!$D$60 -> 0 | G57: =-G51*Assumptions!$D$60 -> 0 | H57: =-H51*Assumptions!$D$60 -> 0 | I57: =-I51*Assumptions!$D$60 -> 0 | J57: =-J51*Assumptions!$D$60 -> 0 | ... AL57: =-AL51*Assumptions!$D$60 -> -171.36205 | AM57: =SUM(C57:AL57) -> -2291.4858
A58: Rx gross profit | B58: $ | C58: =C51+C52+C53+C54+C55+C56+C57 -> 0 | D58: =D51+D52+D53+D54+D55+D56+D57 -> 0 | E58: =E51+E52+E53+E54+E55+E56+E57 -> 0 | F58: =F51+F52+F53+F54+F55+F56+F57 -> 0 | G58: =G51+G52+G53+G54+G55+G56+G57 -> 0 | H58: =H51+H52+H53+H54+H55+H56+H57 -> 0 | I58: =I51+I52+I53+I54+I55+I56+I57 -> 0 | J58: =J51+J52+J53+J54+J55+J56+J57 -> 0 | ... AL58: =AL51+AL52+AL53+AL54+AL55+AL56+AL57 -> 1192.9766 | AM58: =SUM(C58:AL58) -> 15971.221
A59: Rx gross margin | B59: % | C59: =IFERROR(C58/C51,0) -> 0 | D59: =IFERROR(D58/D51,0) -> 0 | E59: =IFERROR(E58/E51,0) -> 0 | F59: =IFERROR(F58/F51,0) -> 0 | G59: =IFERROR(G58/G51,0) -> 0 | H59: =IFERROR(H58/H51,0) -> 0 | I59: =IFERROR(I58/I51,0) -> 0 | J59: =IFERROR(J58/J51,0) -> 0 | ... AL59: =IFERROR(AL58/AL51,0) -> 0.22277542 | AM59: =AVERAGE(N59:AL59) -> 0.22311785
A60: TOTAL NET REVENUE | B60: $ | C60: =C31+C51 -> 0 | D60: =D31+D51 -> 0 | E60: =E31+E51 -> 10263.783 | F60: =F31+F51 -> 10074.923 | G60: =G31+G51 -> 10847.773 | H60: =H31+H51 -> 11665.962 | I60: =I31+I51 -> 12401.389 | J60: =J31+J51 -> 13071.884 | ... AL60: =AL31+AL51 -> 35050.43 | AM60: =SUM(C60:AL60) -> 724880.69
A61: TOTAL GROSS PROFIT | B61: $ | C61: =C35+C58 -> 0 | D61: =D35+D58 -> 0 | E61: =E35+E58 -> 5391.4796 | F61: =F35+F58 -> 5292.2728 | G61: =G35+G58 -> 5698.2446 | H61: =H35+H58 -> 6128.0324 | I61: =I35+I58 -> 6514.3464 | J61: =J35+J58 -> 6866.5515 | ... AL61: =AL35+AL58 -> 16791.705 | AM61: =SUM(C61:AL61) -> 359129.43
A62: Blended gross margin | B62: % | C62: =IFERROR(C61/C60,0) -> 0 | D62: =IFERROR(D61/D60,0) -> 0 | E62: =IFERROR(E61/E60,0) -> 0.52529167 | F62: =IFERROR(F61/F60,0) -> 0.52529167 | G62: =IFERROR(G61/G60,0) -> 0.52529167 | H62: =IFERROR(H61/H60,0) -> 0.52529167 | I62: =IFERROR(I61/I60,0) -> 0.52529167 | J62: =IFERROR(J61/J60,0) -> 0.52529167 | ... AL62: =IFERROR(AL61/AL60,0) -> 0.47907272 | AM62: =AVERAGE(N62:AL62) -> 0.49265061
A63: Provider flat fee | B63: $ | C63: =-Assumptions!$D$63 -> -600 | D63: =-Assumptions!$D$63 -> -600 | E63: =-Assumptions!$D$63 -> -600 | F63: =-Assumptions!$D$63 -> -600 | G63: =-Assumptions!$D$63 -> -600 | H63: =-Assumptions!$D$63 -> -600 | I63: =-Assumptions!$D$63 -> -600 | J63: =-Assumptions!$D$63 -> -600 | ... AL63: =-Assumptions!$D$63 -> -600 | AM63: =SUM(C63:AL63) -> -21600
A64: Certification and registrations | B64: $ | C64: =-Assumptions!$D$64 -> -320 | D64: =-Assumptions!$D$64 -> -320 | E64: =-Assumptions!$D$64 -> -320 | F64: =-Assumptions!$D$64 -> -320 | G64: =-Assumptions!$D$64 -> -320 | H64: =-Assumptions!$D$64 -> -320 | I64: =-Assumptions!$D$64 -> -320 | J64: =-Assumptions!$D$64 -> -320 | ... AL64: =-Assumptions!$D$64 -> -320 | AM64: =SUM(C64:AL64) -> -11520
A65: Team | B65: $ | C65: =-IF(C8=0,Assumptions!$D$65,IF(C$5<=12,Assumptions!$D$66,IF(C$5<=24,Assumptions!$D$67,Assumptions!$D$68))) -> -8000 | D65: =-IF(D8=0,Assumptions!$D$65,IF(D$5<=12,Assumptions!$D$66,IF(D$5<=24,Assumptions!$D$67,Assumptions!$D$68))) -> -8000 | E65: =-IF(E8=0,Assumptions!$D$65,IF(E$5<=12,Assumptions!$D$66,IF(E$5<=24,Assumptions!$D$67,Assumptions!$D$68))) -> -16000 | F65: =-IF(F8=0,Assumptions!$D$65,IF(F$5<=12,Assumptions!$D$66,IF(F$5<=24,Assumptions!$D$67,Assumptions!$D$68))) -> -16000 | G65: =-IF(G8=0,Assumptions!$D$65,IF(G$5<=12,Assumptions!$D$66,IF(G$5<=24,Assumptions!$D$67,Assumptions!$D$68))) -> -16000 | H65: =-IF(H8=0,Assumptions!$D$65,IF(H$5<=12,Assumptions!$D$66,IF(H$5<=24,Assumptions!$D$67,Assumptions!$D$68))) -> -16000 | I65: =-IF(I8=0,Assumptions!$D$65,IF(I$5<=12,Assumptions!$D$66,IF(I$5<=24,Assumptions!$D$67,Assumptions!$D$68))) -> -16000 | J65: =-IF(J8=0,Assumptions!$D$65,IF(J$5<=12,Assumptions!$D$66,IF(J$5<=24,Assumptions!$D$67,Assumptions!$D$68))) -> -16000 | ... AL65: =-IF(AL8=0,Assumptions!$D$65,IF(AL$5<=12,Assumptions!$D$66,IF(AL$5<=24,Assumptions!$D$67,Assumptions!$D$68))) -> -32000 | AM65: =SUM(C65:AL65) -> -848000
A66: Medical director and clinical oversight | B66: $ | C66: =-IF(C$5>=Assumptions!$D$7-2,Assumptions!$D$69,0) -> 0 | D66: =-IF(D$5>=Assumptions!$D$7-2,Assumptions!$D$69,0) -> 0 | E66: =-IF(E$5>=Assumptions!$D$7-2,Assumptions!$D$69,0) -> 0 | F66: =-IF(F$5>=Assumptions!$D$7-2,Assumptions!$D$69,0) -> 0 | G66: =-IF(G$5>=Assumptions!$D$7-2,Assumptions!$D$69,0) -> 0 | H66: =-IF(H$5>=Assumptions!$D$7-2,Assumptions!$D$69,0) -> 0 | I66: =-IF(I$5>=Assumptions!$D$7-2,Assumptions!$D$69,0) -> -5000 | J66: =-IF(J$5>=Assumptions!$D$7-2,Assumptions!$D$69,0) -> -5000 | ... AL66: =-IF(AL$5>=Assumptions!$D$7-2,Assumptions!$D$69,0) -> -5000 | AM66: =SUM(C66:AL66) -> -150000
A67: Technology and software | B67: $ | C67: =-Assumptions!$D$70 -> -1500 | D67: =-Assumptions!$D$70 -> -1500 | E67: =-Assumptions!$D$70 -> -1500 | F67: =-Assumptions!$D$70 -> -1500 | G67: =-Assumptions!$D$70 -> -1500 | H67: =-Assumptions!$D$70 -> -1500 | I67: =-Assumptions!$D$70 -> -1500 | J67: =-Assumptions!$D$70 -> -1500 | ... AL67: =-Assumptions!$D$70 -> -1500 | AM67: =SUM(C67:AL67) -> -54000
A68: Legal, regulatory and compliance | B68: $ | C68: =-IF(C$5<=4,Assumptions!$D$71,Assumptions!$D$72) -> -14000 | D68: =-IF(D$5<=4,Assumptions!$D$71,Assumptions!$D$72) -> -14000 | E68: =-IF(E$5<=4,Assumptions!$D$71,Assumptions!$D$72) -> -14000 | F68: =-IF(F$5<=4,Assumptions!$D$71,Assumptions!$D$72) -> -14000 | G68: =-IF(G$5<=4,Assumptions!$D$71,Assumptions!$D$72) -> -4000 | H68: =-IF(H$5<=4,Assumptions!$D$71,Assumptions!$D$72) -> -4000 | I68: =-IF(I$5<=4,Assumptions!$D$71,Assumptions!$D$72) -> -4000 | J68: =-IF(J$5<=4,Assumptions!$D$71,Assumptions!$D$72) -> -4000 | ... AL68: =-IF(AL$5<=4,Assumptions!$D$71,Assumptions!$D$72) -> -4000 | AM68: =SUM(C68:AL68) -> -184000
A69: Insurance | B69: $ | C69: =-C8*Assumptions!$D$73 -> 0 | D69: =-D8*Assumptions!$D$73 -> 0 | E69: =-E8*Assumptions!$D$73 -> -2000 | F69: =-F8*Assumptions!$D$73 -> -2000 | G69: =-G8*Assumptions!$D$73 -> -2000 | H69: =-H8*Assumptions!$D$73 -> -2000 | I69: =-I8*Assumptions!$D$73 -> -2000 | J69: =-J8*Assumptions!$D$73 -> -2000 | ... AL69: =-AL8*Assumptions!$D$73 -> -2000 | AM69: =SUM(C69:AL69) -> -68000
A70: Creative and content | B70: $ | C70: =-Assumptions!$D$74 -> -4500 | D70: =-Assumptions!$D$74 -> -4500 | E70: =-Assumptions!$D$74 -> -4500 | F70: =-Assumptions!$D$74 -> -4500 | G70: =-Assumptions!$D$74 -> -4500 | H70: =-Assumptions!$D$74 -> -4500 | I70: =-Assumptions!$D$74 -> -4500 | J70: =-Assumptions!$D$74 -> -4500 | ... AL70: =-Assumptions!$D$74 -> -4500 | AM70: =SUM(C70:AL70) -> -162000
A71: Paid media | B71: $ | C71: =-C15 -> -4000 | D71: =-D15 -> -4000 | E71: =-E15 -> -10000 | F71: =-F15 -> -10000 | G71: =-G15 -> -10000 | H71: =-H15 -> -10000 | I71: =-I15 -> -10000 | J71: =-J15 -> -10000 | ... AL71: =-AL15 -> -10144.033 | AM71: =SUM(C71:AL71) -> -348144.03
A72: One-time launch marketing and PR | B72: $ | C72: =-IF(C$5=Assumptions!$D$6,Assumptions!$D$24,0) -> 0 | D72: =-IF(D$5=Assumptions!$D$6,Assumptions!$D$24,0) -> 0 | E72: =-IF(E$5=Assumptions!$D$6,Assumptions!$D$24,0) -> -40000 | F72: =-IF(F$5=Assumptions!$D$6,Assumptions!$D$24,0) -> 0 | G72: =-IF(G$5=Assumptions!$D$6,Assumptions!$D$24,0) -> 0 | H72: =-IF(H$5=Assumptions!$D$6,Assumptions!$D$24,0) -> 0 | I72: =-IF(I$5=Assumptions!$D$6,Assumptions!$D$24,0) -> 0 | J72: =-IF(J$5=Assumptions!$D$6,Assumptions!$D$24,0) -> 0 | ... AL72: =-IF(AL$5=Assumptions!$D$6,Assumptions!$D$24,0) -> 0 | AM72: =SUM(C72:AL72) -> -40000
A73: Partner cash retainer | B73: $ | C73: =-C8*Assumptions!$D$76 -> 0 | D73: =-D8*Assumptions!$D$76 -> 0 | E73: =-E8*Assumptions!$D$76 -> 0 | F73: =-F8*Assumptions!$D$76 -> 0 | G73: =-G8*Assumptions!$D$76 -> 0 | H73: =-H8*Assumptions!$D$76 -> 0 | I73: =-I8*Assumptions!$D$76 -> 0 | J73: =-J8*Assumptions!$D$76 -> 0 | ... AL73: =-AL8*Assumptions!$D$76 -> 0 | AM73: =SUM(C73:AL73) -> 0
A74: Partner royalty on net revenue | B74: $ | C74: =-C60*Assumptions!$D$77 -> 0 | D74: =-D60*Assumptions!$D$77 -> 0 | E74: =-E60*Assumptions!$D$77 -> -513.18914 | F74: =-F60*Assumptions!$D$77 -> -503.74613 | G74: =-G60*Assumptions!$D$77 -> -542.38864 | H74: =-H60*Assumptions!$D$77 -> -583.29808 | I74: =-I60*Assumptions!$D$77 -> -620.06946 | J74: =-J60*Assumptions!$D$77 -> -653.59418 | ... AL74: =-AL60*Assumptions!$D$77 -> -1752.5215 | AM74: =SUM(C74:AL74) -> -36244.035
A75: TOTAL OPERATING EXPENSE | B75: $ | C75: =C63+C64+C65+C66+C67+C68+C69+C70+C71+C72+C73+C74 -> -32920 | D75: =D63+D64+D65+D66+D67+D68+D69+D70+D71+D72+D73+D74 -> -32920 | E75: =E63+E64+E65+E66+E67+E68+E69+E70+E71+E72+E73+E74 -> -89433.189 | F75: =F63+F64+F65+F66+F67+F68+F69+F70+F71+F72+F73+F74 -> -49423.746 | G75: =G63+G64+G65+G66+G67+G68+G69+G70+G71+G72+G73+G74 -> -39462.389 | H75: =H63+H64+H65+H66+H67+H68+H69+H70+H71+H72+H73+H74 -> -39503.298 | I75: =I63+I64+I65+I66+I67+I68+I69+I70+I71+I72+I73+I74 -> -44540.069 | J75: =J63+J64+J65+J66+J67+J68+J69+J70+J71+J72+J73+J74 -> -44573.594 | ... AL75: =AL63+AL64+AL65+AL66+AL67+AL68+AL69+AL70+AL71+AL72+AL73+AL74 -> -61816.554 | AM75: =SUM(C75:AL75) -> -1923508.1
A76: EBITDA | B76: $ | C76: =C61+C75 -> -32920 | D76: =D61+D75 -> -32920 | E76: =E61+E75 -> -84041.71 | F76: =F61+F75 -> -44131.473 | G76: =G61+G75 -> -33764.144 | H76: =H61+H75 -> -33375.266 | I76: =I61+I75 -> -38025.723 | J76: =J61+J75 -> -37707.043 | ... AL76: =AL61+AL75 -> -45024.849 | AM76: =SUM(C76:AL76) -> -1564378.6
A77: EBITDA margin | B77: % | C77: =IFERROR(C76/C60,0) -> 0 | D77: =IFERROR(D76/D60,0) -> 0 | E77: =IFERROR(E76/E60,0) -> -8.1881808 | F77: =IFERROR(F76/F60,0) -> -4.3803288 | G77: =IFERROR(G76/G60,0) -> -3.1125416 | H77: =IFERROR(H76/H60,0) -> -2.86091 | I77: =IFERROR(I76/I60,0) -> -3.066247 | J77: =IFERROR(J76/J60,0) -> -2.8845914 | ... AL77: =IFERROR(AL76/AL60,0) -> -1.2845734 | AM77: =AVERAGE(N77:AL77) -> -1.899889
A78: Non-Rx inventory balance | B78: $ | C78: =-C32*Assumptions!$D$80 -> 0 | D78: =-D32*Assumptions!$D$80 -> 0 | E78: =-E32*Assumptions!$D$80 -> 8018.5803 | F78: =-F32*Assumptions!$D$80 -> 7871.0332 | G78: =-G32*Assumptions!$D$80 -> 8474.8225 | H78: =-H32*Assumptions!$D$80 -> 9114.0325 | I78: =-I32*Assumptions!$D$80 -> 9688.5854 | J78: =-J32*Assumptions!$D$80 -> 10212.409 | ... AL78: =-AL32*Assumptions!$D$80 -> 23199.505 | AM78: =AL78 -> 23199.505
A79: Inventory investment (increase in stock) | B79: $ | C79: =-C78 -> 0 | D79: =-(D78-C78) -> 0 | E79: =-(E78-D78) -> -8018.5803 | F79: =-(F78-E78) -> 147.54707 | G79: =-(G78-F78) -> -603.78924 | H79: =-(H78-G78) -> -639.21003 | I79: =-(I78-H78) -> -574.55286 | J79: =-(J78-I78) -> -523.82366 | K79: =-(K78-J78) -> -483.86524 | ... AL79: =-(AL78-AK78) -> -728.54518 | AM79: =SUM(C79:AL79) -> -23199.505
A80: Net cash flow | B80: $ | C80: =C76+C79 -> -32920 | D80: =D76+D79 -> -32920 | E80: =E76+E79 -> -92060.29 | F80: =F76+F79 -> -43983.926 | G80: =G76+G79 -> -34367.933 | H80: =H76+H79 -> -34014.476 | I80: =I76+I79 -> -38600.276 | J80: =J76+J79 -> -38230.866 | ... AL80: =AL76+AL79 -> -45753.394 | AM80: =SUM(C80:AL80) -> -1587578.1
A81: Cumulative cash flow | B81: $ | C81: =C80 -> -32920 | D81: =C81+D80 -> -65840 | E81: =D81+E80 -> -157900.29 | F81: =E81+F80 -> -201884.22 | G81: =F81+G80 -> -236252.15 | H81: =G81+H80 -> -270266.63 | I81: =H81+I80 -> -308866.9 | J81: =I81+J80 -> -347097.77 | K81: =J81+K80 -> -384928.69 | ... AL81: =AK81+AL80 -> -1587578.1 | AM81: =AL81 -> -1587578.1
A82: Break-even helper (month if EBITDA positive, else 999) | B82: # | C82: =IF(C76>0,C$5,999) -> 999 | D82: =IF(D76>0,D$5,999) -> 999 | E82: =IF(E76>0,E$5,999) -> 999 | F82: =IF(F76>0,F$5,999) -> 999 | G82: =IF(G76>0,G$5,999) -> 999 | H82: =IF(H76>0,H$5,999) -> 999 | I82: =IF(I76>0,I$5,999) -> 999 | J82: =IF(J76>0,J$5,999) -> 999 | ... AL82: =IF(AL76>0,AL$5,999) -> 999
A83: New customers, both lines | B83: # | C83: =C21+C44 -> 0 | D83: =D21+D44 -> 0 | E83: =E21+E44 -> 157.22706 | F83: =F21+F44 -> 102.60628 | G83: =G21+G44 -> 93.355604 | H83: =H21+H44 -> 86.957521 | I83: =I21+I44 -> 82.62905 | J83: =J21+J44 -> 79.807389 | ... AL83: =AL21+AL44 -> 141.54781 | AM83: =SUM(C83:AL83) -> 3379.1048
A84: Blended CAC (paid media plus creative) | B84: $ | C84: =IFERROR((C15-C70)/C83,0) -> 0 | D84: =IFERROR((D15-D70)/D83,0) -> 0 | E84: =IFERROR((E15-E70)/E83,0) -> 92.223308 | F84: =IFERROR((F15-F70)/F83,0) -> 141.31689 | G84: =IFERROR((G15-G70)/G83,0) -> 155.32008 | H84: =IFERROR((H15-H70)/H83,0) -> 166.74808 | I84: =IFERROR((I15-I70)/I83,0) -> 175.48308 | J84: =IFERROR((J15-J70)/J83,0) -> 181.68744 | ... AL84: =IFERROR((AL15-AL70)/AL83,0) -> 103.45644 | AM84: =AVERAGE(N84:AL84) -> 147.5329
A85: Rx contribution per member-month, steady state | B85: $ | C85: =Assumptions!$D$51*(1-Assumptions!$D$61)*(1-Assumptions!$D$60)-Assumptions!$D$54-Assumptions!$D$56-Assumptions!$D$57-Assumptions!$D$58 -> 41.92672 | D85: =Assumptions!$D$51*(1-Assumptions!$D$61)*(1-Assumptions!$D$60)-Assumptions!$D$54-Assumptions!$D$56-Assumptions!$D$57-Assumptions!$D$58 -> 41.92672 | E85: =Assumptions!$D$51*(1-Assumptions!$D$61)*(1-Assumptions!$D$60)-Assumptions!$D$54-Assumptions!$D$56-Assumptions!$D$57-Assumptions!$D$58 -> 41.92672 | F85: =Assumptions!$D$51*(1-Assumptions!$D$61)*(1-Assumptions!$D$60)-Assumptions!$D$54-Assumptions!$D$56-Assumptions!$D$57-Assumptions!$D$58 -> 41.92672 | G85: =Assumptions!$D$51*(1-Assumptions!$D$61)*(1-Assumptions!$D$60)-Assumptions!$D$54-Assumptions!$D$56-Assumptions!$D$57-Assumptions!$D$58 -> 41.92672 | H85: =Assumptions!$D$51*(1-Assumptions!$D$61)*(1-Assumptions!$D$60)-Assumptions!$D$54-Assumptions!$D$56-Assumptions!$D$57-Assumptions!$D$58 -> 41.92672 | I85: =Assumptions!$D$51*(1-Assumptions!$D$61)*(1-Assumptions!$D$60)-Assumptions!$D$54-Assumptions!$D$56-Assumptions!$D$57-Assumptions!$D$58 -> 41.92672 | J85: =Assumptions!$D$51*(1-Assumptions!$D$61)*(1-Assumptions!$D$60)-Assumptions!$D$54-Assumptions!$D$56-Assumptions!$D$57-Assumptions!$D$58 -> 41.92672 | ... AL85: =Assumptions!$D$51*(1-Assumptions!$D$61)*(1-Assumptions!$D$60)-Assumptions!$D$54-Assumptions!$D$56-Assumptions!$D$57-Assumptions!$D$58 -> 41.92672 | AM85: =AVERAGE(N85:AL85) -> 41.92672
A86: Rx gross LTV (contribution / churn) | B86: $ | C86: =C85/Assumptions!$D$49 -> 322.51323 | D86: =D85/Assumptions!$D$49 -> 322.51323 | E86: =E85/Assumptions!$D$49 -> 322.51323 | F86: =F85/Assumptions!$D$49 -> 322.51323 | G86: =G85/Assumptions!$D$49 -> 322.51323 | H86: =H85/Assumptions!$D$49 -> 322.51323 | I86: =I85/Assumptions!$D$49 -> 322.51323 | J86: =J85/Assumptions!$D$49 -> 322.51323 | ... AL86: =AL85/Assumptions!$D$49 -> 322.51323 | AM86: =AVERAGE(N86:AL86) -> 322.51323
A87: Non-Rx contribution per order | B87: $ | C87: =Assumptions!$D$31*(1-Assumptions!$D$61)*(1-Assumptions!$D$60)-Assumptions!$D$31*Assumptions!$D$36-Assumptions!$D$37 -> 34.29104 | D87: =Assumptions!$D$31*(1-Assumptions!$D$61)*(1-Assumptions!$D$60)-Assumptions!$D$31*Assumptions!$D$36-Assumptions!$D$37 -> 34.29104 | E87: =Assumptions!$D$31*(1-Assumptions!$D$61)*(1-Assumptions!$D$60)-Assumptions!$D$31*Assumptions!$D$36-Assumptions!$D$37 -> 34.29104 | F87: =Assumptions!$D$31*(1-Assumptions!$D$61)*(1-Assumptions!$D$60)-Assumptions!$D$31*Assumptions!$D$36-Assumptions!$D$37 -> 34.29104 | G87: =Assumptions!$D$31*(1-Assumptions!$D$61)*(1-Assumptions!$D$60)-Assumptions!$D$31*Assumptions!$D$36-Assumptions!$D$37 -> 34.29104 | H87: =Assumptions!$D$31*(1-Assumptions!$D$61)*(1-Assumptions!$D$60)-Assumptions!$D$31*Assumptions!$D$36-Assumptions!$D$37 -> 34.29104 | I87: =Assumptions!$D$31*(1-Assumptions!$D$61)*(1-Assumptions!$D$60)-Assumptions!$D$31*Assumptions!$D$36-Assumptions!$D$37 -> 34.29104 | J87: =Assumptions!$D$31*(1-Assumptions!$D$61)*(1-Assumptions!$D$60)-Assumptions!$D$31*Assumptions!$D$36-Assumptions!$D$37 -> 34.29104 | ... AL87: =Assumptions!$D$31*(1-Assumptions!$D$61)*(1-Assumptions!$D$60)-Assumptions!$D$31*Assumptions!$D$36-Assumptions!$D$37 -> 34.29104 | AM87: =AVERAGE(N87:AL87) -> 34.29104
A88: Non-Rx subscriber gross LTV | B88: $ | C88: =C87/Assumptions!$D$33 -> 381.01156 | D88: =D87/Assumptions!$D$33 -> 381.01156 | E88: =E87/Assumptions!$D$33 -> 381.01156 | F88: =F87/Assumptions!$D$33 -> 381.01156 | G88: =G87/Assumptions!$D$33 -> 381.01156 | H88: =H87/Assumptions!$D$33 -> 381.01156 | I88: =I87/Assumptions!$D$33 -> 381.01156 | J88: =J87/Assumptions!$D$33 -> 381.01156 | ... AL88: =AL87/Assumptions!$D$33 -> 381.01156 | AM88: =AVERAGE(N88:AL88) -> 381.01156

Sheet Model_Baseline
A1: Reserve Clinic - Baseline scenario, months 1-36
A2: Every cell is a formula. Inputs live on Assumptions only. Green = link to Assumptions.
A4: Line | B4: Unit | C4: M1 | D4: M2 | E4: M3 | F4: M4 | G4: M5 | H4: M6 | I4: M7 | J4: M8 | K4: M9 | L4: M10 | M4: M11 | N4: M12 | O4: M13 | P4: M14 | Q4: M15 | R4: M16 | S4: M17 | T4: M18 | U4: M19 | V4: M20 | W4: M21 | X4: M22 | Y4: M23 | Z4: M24 | AA4: M25 | AB4: M26 | AC4: M27 | AD4: M28 | AE4: M29 | AF4: M30 | AG4: M31 | AH4: M32 | AI4: M33 | AJ4: M34 | AK4: M35 | AL4: M36 | AM4: Total / final
A5: Month index | B5: # | C5: 1 | D5: 2 | E5: 3 | F5: 4 | G5: 5 | H5: 6 | I5: 7 | J5: 8 | K5: 9 | L5: 10 | M5: 11 | N5: 12 | O5: 13 | P5: 14 | Q5: 15 | R5: 16 | S5: 17 | T5: 18 | U5: 19 | V5: 20 | W5: 21 | X5: 22 | Y5: 23 | Z5: 24 | AA5: 25 | AB5: 26 | AC5: 27 | AD5: 28 | AE5: 29 | AF5: 30 | AG5: 31 | AH5: 32 | AI5: 33 | AJ5: 34 | AK5: 35 | AL5: 36
A6: Year | B6: # | C6: =ROUNDUP(C$5/12,0) -> 1 | D6: =ROUNDUP(D$5/12,0) -> 1 | E6: =ROUNDUP(E$5/12,0) -> 1 | F6: =ROUNDUP(F$5/12,0) -> 1 | G6: =ROUNDUP(G$5/12,0) -> 1 | H6: =ROUNDUP(H$5/12,0) -> 1 | I6: =ROUNDUP(I$5/12,0) -> 1 | J6: =ROUNDUP(J$5/12,0) -> 1 | ... AL6: =ROUNDUP(AL$5/12,0) -> 3
A8: Non-Rx line live (1/0) | B8: flag | C8: =IF(C$5>=Assumptions!$E$6,1,0) -> 0 | D8: =IF(D$5>=Assumptions!$E$6,1,0) -> 1 | E8: =IF(E$5>=Assumptions!$E$6,1,0) -> 1 | F8: =IF(F$5>=Assumptions!$E$6,1,0) -> 1 | G8: =IF(G$5>=Assumptions!$E$6,1,0) -> 1 | H8: =IF(H$5>=Assumptions!$E$6,1,0) -> 1 | I8: =IF(I$5>=Assumptions!$E$6,1,0) -> 1 | J8: =IF(J$5>=Assumptions!$E$6,1,0) -> 1 | ... AL8: =IF(AL$5>=Assumptions!$E$6,1,0) -> 1
A9: Rx line live (1/0) | B9: flag | C9: =IF(C$5>=Assumptions!$E$7,1,0) -> 0 | D9: =IF(D$5>=Assumptions!$E$7,1,0) -> 0 | E9: =IF(E$5>=Assumptions!$E$7,1,0) -> 0 | F9: =IF(F$5>=Assumptions!$E$7,1,0) -> 0 | G9: =IF(G$5>=Assumptions!$E$7,1,0) -> 0 | H9: =IF(H$5>=Assumptions!$E$7,1,0) -> 0 | I9: =IF(I$5>=Assumptions!$E$7,1,0) -> 1 | J9: =IF(J$5>=Assumptions!$E$7,1,0) -> 1 | ... AL9: =IF(AL$5>=Assumptions!$E$7,1,0) -> 1
A10: Months since non-Rx launch | B10: # | C10: =MAX(0,C$5-Assumptions!$E$6) -> 0 | D10: =MAX(0,D$5-Assumptions!$E$6) -> 0 | E10: =MAX(0,E$5-Assumptions!$E$6) -> 1 | F10: =MAX(0,F$5-Assumptions!$E$6) -> 2 | G10: =MAX(0,G$5-Assumptions!$E$6) -> 3 | H10: =MAX(0,H$5-Assumptions!$E$6) -> 4 | I10: =MAX(0,I$5-Assumptions!$E$6) -> 5 | J10: =MAX(0,J$5-Assumptions!$E$6) -> 6 | ... AL10: =MAX(0,AL$5-Assumptions!$E$6) -> 34
A11: Partner-driven sessions at launch peak | B11: sessions | C11: =Assumptions!$E$9*Assumptions!$E$10*Assumptions!$E$11*Assumptions!$E$12 -> 46032 | D11: =Assumptions!$E$9*Assumptions!$E$10*Assumptions!$E$11*Assumptions!$E$12 -> 46032 | E11: =Assumptions!$E$9*Assumptions!$E$10*Assumptions!$E$11*Assumptions!$E$12 -> 46032 | F11: =Assumptions!$E$9*Assumptions!$E$10*Assumptions!$E$11*Assumptions!$E$12 -> 46032 | G11: =Assumptions!$E$9*Assumptions!$E$10*Assumptions!$E$11*Assumptions!$E$12 -> 46032 | H11: =Assumptions!$E$9*Assumptions!$E$10*Assumptions!$E$11*Assumptions!$E$12 -> 46032 | I11: =Assumptions!$E$9*Assumptions!$E$10*Assumptions!$E$11*Assumptions!$E$12 -> 46032 | J11: =Assumptions!$E$9*Assumptions!$E$10*Assumptions!$E$11*Assumptions!$E$12 -> 46032 | ... AL11: =Assumptions!$E$9*Assumptions!$E$10*Assumptions!$E$11*Assumptions!$E$12 -> 46032
A12: Attention index (decay toward floor) | B12: x | C12: =IF(C8=0,0,IF(C10=0,Assumptions!$E$15,Assumptions!$E$14+(1-Assumptions!$E$14)*Assumptions!$E$13^C10)) -> 0 | D12: =IF(D8=0,0,IF(D10=0,Assumptions!$E$15,Assumptions!$E$14+(1-Assumptions!$E$14)*Assumptions!$E$13^D10)) -> 2.2 | E12: =IF(E8=0,0,IF(E10=0,Assumptions!$E$15,Assumptions!$E$14+(1-Assumptions!$E$14)*Assumptions!$E$13^E10)) -> 0.872 | F12: =IF(F8=0,0,IF(F10=0,Assumptions!$E$15,Assumptions!$E$14+(1-Assumptions!$E$14)*Assumptions!$E$13^F10)) -> 0.7696 | G12: =IF(G8=0,0,IF(G10=0,Assumptions!$E$15,Assumptions!$E$14+(1-Assumptions!$E$14)*Assumptions!$E$13^G10)) -> 0.68768 | H12: =IF(H8=0,0,IF(H10=0,Assumptions!$E$15,Assumptions!$E$14+(1-Assumptions!$E$14)*Assumptions!$E$13^H10)) -> 0.622144 | I12: =IF(I8=0,0,IF(I10=0,Assumptions!$E$15,Assumptions!$E$14+(1-Assumptions!$E$14)*Assumptions!$E$13^I10)) -> 0.5697152 | J12: =IF(J8=0,0,IF(J10=0,Assumptions!$E$15,Assumptions!$E$14+(1-Assumptions!$E$14)*Assumptions!$E$13^J10)) -> 0.52777216 | ... AL12: =IF(AL8=0,0,IF(AL10=0,Assumptions!$E$15,Assumptions!$E$14+(1-Assumptions!$E$14)*Assumptions!$E$13^AL10)) -> 0.36032452
A13: Partner-driven sessions | B13: sessions | C13: =C11*C12 -> 0 | D13: =D11*D12 -> 101270.4 | E13: =E11*E12 -> 40139.904 | F13: =F11*F12 -> 35426.227 | G13: =G11*G12 -> 31655.286 | H13: =H11*H12 -> 28638.533 | I13: =I11*I12 -> 26225.13 | J13: =J11*J12 -> 24294.408 | ... AL13: =AL11*AL12 -> 16586.458 | AM13: =SUM(C13:AL13) -> 782484.25
A14: Organic and direct sessions | B14: sessions | C14: =MIN(Assumptions!$E$19,Assumptions!$E$17*(1+Assumptions!$E$18)^(C$5-1)) -> 2200 | D14: =MIN(Assumptions!$E$19,Assumptions!$E$17*(1+Assumptions!$E$18)^(D$5-1)) -> 2398 | E14: =MIN(Assumptions!$E$19,Assumptions!$E$17*(1+Assumptions!$E$18)^(E$5-1)) -> 2613.82 | F14: =MIN(Assumptions!$E$19,Assumptions!$E$17*(1+Assumptions!$E$18)^(F$5-1)) -> 2849.0638 | G14: =MIN(Assumptions!$E$19,Assumptions!$E$17*(1+Assumptions!$E$18)^(G$5-1)) -> 3105.4795 | H14: =MIN(Assumptions!$E$19,Assumptions!$E$17*(1+Assumptions!$E$18)^(H$5-1)) -> 3384.9727 | I14: =MIN(Assumptions!$E$19,Assumptions!$E$17*(1+Assumptions!$E$18)^(I$5-1)) -> 3689.6202 | J14: =MIN(Assumptions!$E$19,Assumptions!$E$17*(1+Assumptions!$E$18)^(J$5-1)) -> 4021.6861 | ... AL14: =MIN(Assumptions!$E$19,Assumptions!$E$17*(1+Assumptions!$E$18)^(AL$5-1)) -> 44910.729 | AM14: =SUM(C14:AL14) -> 519474.39
A15: Paid media spend | B15: $ | C15: =Assumptions!$E$21 -> 8000 | D15: =IF(D8=0,Assumptions!$E$21,MIN(Assumptions!$E$25,MAX(Assumptions!$E$22,C60*Assumptions!$E$23))) -> 30000 | E15: =IF(E8=0,Assumptions!$E$21,MIN(Assumptions!$E$25,MAX(Assumptions!$E$22,D60*Assumptions!$E$23))) -> 30000 | F15: =IF(F8=0,Assumptions!$E$21,MIN(Assumptions!$E$25,MAX(Assumptions!$E$22,E60*Assumptions!$E$23))) -> 30000 | G15: =IF(G8=0,Assumptions!$E$21,MIN(Assumptions!$E$25,MAX(Assumptions!$E$22,F60*Assumptions!$E$23))) -> 30000 | H15: =IF(H8=0,Assumptions!$E$21,MIN(Assumptions!$E$25,MAX(Assumptions!$E$22,G60*Assumptions!$E$23))) -> 31950.406 | I15: =IF(I8=0,Assumptions!$E$21,MIN(Assumptions!$E$25,MAX(Assumptions!$E$22,H60*Assumptions!$E$23))) -> 34665.723 | J15: =IF(J8=0,Assumptions!$E$21,MIN(Assumptions!$E$25,MAX(Assumptions!$E$22,I60*Assumptions!$E$23))) -> 39441.095 | K15: =IF(K8=0,Assumptions!$E$21,MIN(Assumptions!$E$25,MAX(Assumptions!$E$22,J60*Assumptions!$E$23))) -> 43304.208 | ... AL15: =IF(AL8=0,Assumptions!$E$21,MIN(Assumptions!$E$25,MAX(Assumptions!$E$22,AK60*Assumptions!$E$23))) -> 170343.29 | AM15: =SUM(C15:AL15) -> 2980031.7
A16: Paid sessions (diminishing returns applied) | B16: sessions | C16: =(Assumptions!$E$22/Assumptions!$E$20)*(C15/Assumptions!$E$22)^Assumptions!$E$26 -> 5177.9678 | D16: =(Assumptions!$E$22/Assumptions!$E$20)*(D15/Assumptions!$E$22)^Assumptions!$E$26 -> 13953.488 | E16: =(Assumptions!$E$22/Assumptions!$E$20)*(E15/Assumptions!$E$22)^Assumptions!$E$26 -> 13953.488 | F16: =(Assumptions!$E$22/Assumptions!$E$20)*(F15/Assumptions!$E$22)^Assumptions!$E$26 -> 13953.488 | G16: =(Assumptions!$E$22/Assumptions!$E$20)*(G15/Assumptions!$E$22)^Assumptions!$E$26 -> 13953.488 | H16: =(Assumptions!$E$22/Assumptions!$E$20)*(H15/Assumptions!$E$22)^Assumptions!$E$26 -> 14628.478 | I16: =(Assumptions!$E$22/Assumptions!$E$20)*(I15/Assumptions!$E$22)^Assumptions!$E$26 -> 15551.313 | J16: =(Assumptions!$E$22/Assumptions!$E$20)*(J15/Assumptions!$E$22)^Assumptions!$E$26 -> 17131.823 | ... AL16: =(Assumptions!$E$22/Assumptions!$E$20)*(AL15/Assumptions!$E$22)^Assumptions!$E$26 -> 51325.788 | AM16: =SUM(C16:AL16) -> 1045287.6
A17: Effective cost per paid session | B17: $ | C17: =IFERROR(C15/C16,0) -> 1.5450077 | D17: =IFERROR(D15/D16,0) -> 2.15 | E17: =IFERROR(E15/E16,0) -> 2.15 | F17: =IFERROR(F15/F16,0) -> 2.15 | G17: =IFERROR(G15/G16,0) -> 2.15 | H17: =IFERROR(H15/H16,0) -> 2.1841237 | I17: =IFERROR(I15/I16,0) -> 2.2291188 | J17: =IFERROR(J15/J16,0) -> 2.3022124 | ... AL17: =IFERROR(AL15/AL16,0) -> 3.3188636 | AM17: =AVERAGE(N17:AL17) -> 2.9044856
A18: Total sessions | B18: sessions | C18: =C13+C14+C16 -> 7377.9678 | D18: =D13+D14+D16 -> 117621.89 | E18: =E13+E14+E16 -> 56707.212 | F18: =F13+F14+F16 -> 52228.779 | G18: =G13+G14+G16 -> 48714.254 | H18: =H13+H14+H16 -> 46651.983 | I18: =I13+I14+I16 -> 45466.063 | J18: =J13+J14+J16 -> 45447.917 | ... AL18: =AL13+AL14+AL16 -> 112822.98 | AM18: =SUM(C18:AL18) -> 2347246.2
A19: Shippable new-order capacity | B19: # | C19: =C8*Assumptions!$E$28*Assumptions!$E$29^C10 -> 0 | D19: =D8*Assumptions!$E$28*Assumptions!$E$29^D10 -> 1500 | E19: =E8*Assumptions!$E$28*Assumptions!$E$29^E10 -> 2025 | F19: =F8*Assumptions!$E$28*Assumptions!$E$29^F10 -> 2733.75 | G19: =G8*Assumptions!$E$28*Assumptions!$E$29^G10 -> 3690.5625 | H19: =H8*Assumptions!$E$28*Assumptions!$E$29^H10 -> 4982.2594 | I19: =I8*Assumptions!$E$28*Assumptions!$E$29^I10 -> 6726.0502 | J19: =J8*Assumptions!$E$28*Assumptions!$E$29^J10 -> 9080.1677 | ... AL19: =AL8*Assumptions!$E$28*Assumptions!$E$29^AL10 -> 40498542 | AM19: =AL19 -> 40498542
A20: New non-Rx customer demand | B20: # | C20: =C18*Assumptions!$E$30*C8 -> 0 | D20: =D18*Assumptions!$E$30*D8 -> 1646.7064 | E20: =E18*Assumptions!$E$30*E8 -> 793.90097 | F20: =F18*Assumptions!$E$30*F8 -> 731.20291 | G20: =G18*Assumptions!$E$30*G8 -> 681.99955 | H20: =H18*Assumptions!$E$30*H8 -> 653.12776 | I20: =I18*Assumptions!$E$30*I8 -> 636.52488 | J20: =J18*Assumptions!$E$30*J8 -> 636.27084 | ... AL20: =AL18*Assumptions!$E$30*AL8 -> 1579.5217 | AM20: =SUM(C20:AL20) -> 32758.156
A21: New non-Rx customers served | B21: # | C21: =MIN(C20,C19) -> 0 | D21: =MIN(D20,D19) -> 1500 | E21: =MIN(E20,E19) -> 793.90097 | F21: =MIN(F20,F19) -> 731.20291 | G21: =MIN(G20,G19) -> 681.99955 | H21: =MIN(H20,H19) -> 653.12776 | I21: =MIN(I20,I19) -> 636.52488 | J21: =MIN(J20,J19) -> 636.27084 | ... AL21: =MIN(AL20,AL19) -> 1579.5217 | AM21: =SUM(C21:AL21) -> 32611.449
A22: Demand lost to capacity | B22: # | C22: =MAX(0,C20-C19) -> 0 | D22: =MAX(0,D20-D19) -> 146.70644 | E22: =MAX(0,E20-E19) -> 0 | F22: =MAX(0,F20-F19) -> 0 | G22: =MAX(0,G20-G19) -> 0 | H22: =MAX(0,H20-H19) -> 0 | I22: =MAX(0,I20-I19) -> 0 | J22: =MAX(0,J20-J19) -> 0 | ... AL22: =MAX(0,AL20-AL19) -> 0 | AM22: =SUM(C22:AL22) -> 146.70644
A23: New subscribers | B23: # | C23: =C21*Assumptions!$E$32 -> 0 | D23: =D21*Assumptions!$E$32 -> 600 | E23: =E21*Assumptions!$E$32 -> 317.56039 | F23: =F21*Assumptions!$E$32 -> 292.48116 | G23: =G21*Assumptions!$E$32 -> 272.79982 | H23: =H21*Assumptions!$E$32 -> 261.25111 | I23: =I21*Assumptions!$E$32 -> 254.60995 | J23: =J21*Assumptions!$E$32 -> 254.50834 | ... AL23: =AL21*Assumptions!$E$32 -> 631.80866 | AM23: =SUM(C23:AL23) -> 13044.58
A24: New one-time buyers | B24: # | C24: =C21*(1-Assumptions!$E$32) -> 0 | D24: =D21*(1-Assumptions!$E$32) -> 900 | E24: =E21*(1-Assumptions!$E$32) -> 476.34058 | F24: =F21*(1-Assumptions!$E$32) -> 438.72175 | G24: =G21*(1-Assumptions!$E$32) -> 409.19973 | H24: =H21*(1-Assumptions!$E$32) -> 391.87666 | I24: =I21*(1-Assumptions!$E$32) -> 381.91493 | J24: =J21*(1-Assumptions!$E$32) -> 381.7625 | ... AL24: =AL21*(1-Assumptions!$E$32) -> 947.71299 | AM24: =SUM(C24:AL24) -> 19566.869
A25: Active subscribers (end of month) | B25: # | C25: =C23 -> 0 | D25: =C25*(1-Assumptions!$E$33)+D23 -> 600 | E25: =D25*(1-Assumptions!$E$33)+E23 -> 875.56039 | F25: =E25*(1-Assumptions!$E$33)+F23 -> 1106.7523 | G25: =F25*(1-Assumptions!$E$33)+G23 -> 1302.0795 | H25: =G25*(1-Assumptions!$E$33)+H23 -> 1472.185 | I25: =H25*(1-Assumptions!$E$33)+I23 -> 1623.742 | J25: =I25*(1-Assumptions!$E$33)+J23 -> 1764.5884 | K25: =J25*(1-Assumptions!$E$33)+K23 -> 1895.9175 | ... AL25: =AK25*(1-Assumptions!$E$33)+AL23 -> 5810.4009 | AM25: =AL25 -> 5810.4009
A26: Subscribers churned | B26: # | C26: =0 -> 0 | D26: =C25*Assumptions!$E$33 -> 0 | E26: =D25*Assumptions!$E$33 -> 42 | F26: =E25*Assumptions!$E$33 -> 61.289227 | G26: =F25*Assumptions!$E$33 -> 77.472663 | H26: =G25*Assumptions!$E$33 -> 91.145564 | I26: =H25*Assumptions!$E$33 -> 103.05295 | J26: =I25*Assumptions!$E$33 -> 113.66194 | K26: =J25*Assumptions!$E$33 -> 123.52119 | ... AL26: =AK25*Assumptions!$E$33 -> 389.78651 | AM26: =SUM(C26:AL26) -> 7234.1788
A27: Repeat orders from one-time buyers | B27: # | C27: =0 -> 0 | D27: =C24*Assumptions!$E$34 -> 0 | E27: =D24*Assumptions!$E$34 -> 99 | F27: =E24*Assumptions!$E$34 -> 52.397464 | G27: =F24*Assumptions!$E$34 -> 48.259392 | H27: =G24*Assumptions!$E$34 -> 45.01197 | I27: =H24*Assumptions!$E$34 -> 43.106432 | J27: =I24*Assumptions!$E$34 -> 42.010642 | K27: =J24*Assumptions!$E$34 -> 41.993875 | ... AL27: =AK24*Assumptions!$E$34 -> 99.255354 | AM27: =SUM(C27:AL27) -> 2048.1072
A28: Non-Rx orders shipped | B28: # | C28: =C24+C25+C27 -> 0 | D28: =D24+D25+D27 -> 1500 | E28: =E24+E25+E27 -> 1450.901 | F28: =F24+F25+F27 -> 1597.8715 | G28: =G24+G25+G27 -> 1759.5386 | H28: =H24+H25+H27 -> 1909.0737 | I28: =I24+I25+I27 -> 2048.7634 | J28: =J24+J25+J27 -> 2188.3616 | ... AL28: =AL24+AL25+AL27 -> 6857.3692 | AM28: =SUM(C28:AL28) -> 130770.79
A29: Non-Rx gross revenue | B29: $ | C29: =C28*Assumptions!$E$31 -> 0 | D29: =D28*Assumptions!$E$31 -> 117000 | E29: =E28*Assumptions!$E$31 -> 113170.28 | F29: =F28*Assumptions!$E$31 -> 124633.98 | G29: =G28*Assumptions!$E$31 -> 137244.01 | H29: =H28*Assumptions!$E$31 -> 148907.75 | I29: =I28*Assumptions!$E$31 -> 159803.54 | J29: =J28*Assumptions!$E$31 -> 170692.2 | ... AL29: =AL28*Assumptions!$E$31 -> 534874.8 | AM29: =SUM(C29:AL29) -> 10200122
A30: Non-Rx refunds and chargebacks | B30: $ | C30: =-C29*Assumptions!$E$61 -> 0 | D30: =-D29*Assumptions!$E$61 -> -3510 | E30: =-E29*Assumptions!$E$61 -> -3395.1083 | F30: =-F29*Assumptions!$E$61 -> -3739.0194 | G30: =-G29*Assumptions!$E$61 -> -4117.3203 | H30: =-H29*Assumptions!$E$61 -> -4467.2324 | I30: =-I29*Assumptions!$E$61 -> -4794.1063 | J30: =-J29*Assumptions!$E$61 -> -5120.7661 | ... AL30: =-AL29*Assumptions!$E$61 -> -16046.244 | AM30: =SUM(C30:AL30) -> -306003.65
A31: Non-Rx net revenue | B31: $ | C31: =C29+C30 -> 0 | D31: =D29+D30 -> 113490 | E31: =E29+E30 -> 109775.17 | F31: =F29+F30 -> 120894.96 | G31: =G29+G30 -> 133126.69 | H31: =H29+H30 -> 144440.51 | I31: =I29+I30 -> 155009.44 | J31: =J29+J30 -> 165571.44 | ... AL31: =AL29+AL30 -> 518828.56 | AM31: =SUM(C31:AL31) -> 9894117.9
A32: Non-Rx product COGS | B32: $ | C32: =-C29*Assumptions!$E$36 -> 0 | D32: =-D29*Assumptions!$E$36 -> -30420 | E32: =-E29*Assumptions!$E$36 -> -29424.272 | F32: =-F29*Assumptions!$E$36 -> -32404.835 | G32: =-G29*Assumptions!$E$36 -> -35683.443 | H32: =-H29*Assumptions!$E$36 -> -38716.014 | I32: =-I29*Assumptions!$E$36 -> -41548.921 | J32: =-J29*Assumptions!$E$36 -> -44379.973 | ... AL32: =-AL29*Assumptions!$E$36 -> -139067.45 | AM32: =SUM(C32:AL32) -> -2652031.6
A33: Non-Rx pick, pack and ship | B33: $ | C33: =-C28*Assumptions!$E$37 -> 0 | D33: =-D28*Assumptions!$E$37 -> -11250 | E33: =-E28*Assumptions!$E$37 -> -10881.757 | F33: =-F28*Assumptions!$E$37 -> -11984.037 | G33: =-G28*Assumptions!$E$37 -> -13196.54 | H33: =-H28*Assumptions!$E$37 -> -14318.052 | I33: =-I28*Assumptions!$E$37 -> -15365.725 | J33: =-J28*Assumptions!$E$37 -> -16412.712 | ... AL33: =-AL28*Assumptions!$E$37 -> -51430.269 | AM33: =SUM(C33:AL33) -> -980780.92
A34: Non-Rx payment processing | B34: $ | C34: =-C31*Assumptions!$E$60 -> 0 | D34: =-D31*Assumptions!$E$60 -> -3291.21 | E34: =-E31*Assumptions!$E$60 -> -3183.4799 | F34: =-F31*Assumptions!$E$60 -> -3505.9539 | G34: =-G31*Assumptions!$E$60 -> -3860.674 | H34: =-H31*Assumptions!$E$60 -> -4188.7749 | I34: =-I31*Assumptions!$E$60 -> -4495.2737 | J34: =-J31*Assumptions!$E$60 -> -4801.5716 | ... AL34: =-AL31*Assumptions!$E$60 -> -15046.028 | AM34: =SUM(C34:AL34) -> -286929.42
A35: Non-Rx gross profit | B35: $ | C35: =C31+C32+C33+C34 -> 0 | D35: =D31+D32+D33+D34 -> 68528.79 | E35: =E31+E32+E33+E34 -> 66285.659 | F35: =F31+F32+F33+F34 -> 73000.135 | G35: =G31+G32+G33+G34 -> 80386.034 | H35: =H31+H32+H33+H34 -> 87217.672 | I35: =I31+I32+I33+I34 -> 93599.517 | J35: =J31+J32+J33+J34 -> 99977.18 | ... AL35: =AL31+AL32+AL33+AL34 -> 313284.81 | AM35: =SUM(C35:AL35) -> 5974375.9
A36: Non-Rx gross margin | B36: % | C36: =IFERROR(C35/C31,0) -> 0 | D36: =IFERROR(D35/D31,0) -> 0.60383109 | E36: =IFERROR(E35/E31,0) -> 0.60383109 | F36: =IFERROR(F35/F31,0) -> 0.60383109 | G36: =IFERROR(G35/G31,0) -> 0.60383109 | H36: =IFERROR(H35/H31,0) -> 0.60383109 | I36: =IFERROR(I35/I31,0) -> 0.60383109 | J36: =IFERROR(J35/J31,0) -> 0.60383109 | ... AL36: =IFERROR(AL35/AL31,0) -> 0.60383109 | AM36: =AVERAGE(N36:AL36) -> 0.60383109
A37: US population covered by served states | B37: % | C37: =IF(C9=0,0,MIN(Assumptions!$E$44,Assumptions!$E$42+Assumptions!$E$43*(C$5-Assumptions!$E$7))) -> 0 | D37: =IF(D9=0,0,MIN(Assumptions!$E$44,Assumptions!$E$42+Assumptions!$E$43*(D$5-Assumptions!$E$7))) -> 0 | E37: =IF(E9=0,0,MIN(Assumptions!$E$44,Assumptions!$E$42+Assumptions!$E$43*(E$5-Assumptions!$E$7))) -> 0 | F37: =IF(F9=0,0,MIN(Assumptions!$E$44,Assumptions!$E$42+Assumptions!$E$43*(F$5-Assumptions!$E$7))) -> 0 | G37: =IF(G9=0,0,MIN(Assumptions!$E$44,Assumptions!$E$42+Assumptions!$E$43*(G$5-Assumptions!$E$7))) -> 0 | H37: =IF(H9=0,0,MIN(Assumptions!$E$44,Assumptions!$E$42+Assumptions!$E$43*(H$5-Assumptions!$E$7))) -> 0 | I37: =IF(I9=0,0,MIN(Assumptions!$E$44,Assumptions!$E$42+Assumptions!$E$43*(I$5-Assumptions!$E$7))) -> 0.36 | J37: =IF(J9=0,0,MIN(Assumptions!$E$44,Assumptions!$E$42+Assumptions!$E$43*(J$5-Assumptions!$E$7))) -> 0.385 | ... AL37: =IF(AL9=0,0,MIN(Assumptions!$E$44,Assumptions!$E$42+Assumptions!$E$43*(AL$5-Assumptions!$E$7))) -> 0.82 | AM37: =AL37 -> 0.82
A38: Eligibility quiz starts | B38: # | C38: =C18*Assumptions!$E$39*C9 -> 0 | D38: =D18*Assumptions!$E$39*D9 -> 0 | E38: =E18*Assumptions!$E$39*E9 -> 0 | F38: =F18*Assumptions!$E$39*F9 -> 0 | G38: =G18*Assumptions!$E$39*G9 -> 0 | H38: =H18*Assumptions!$E$39*H9 -> 0 | I38: =I18*Assumptions!$E$39*I9 -> 818.38913 | J38: =J18*Assumptions!$E$39*J9 -> 818.06251 | ... AL38: =AL18*Assumptions!$E$39*AL9 -> 2030.8136 | AM38: =SUM(C38:AL38) -> 36322.995
A39: Quiz completions | B39: # | C39: =C38*Assumptions!$E$40 -> 0 | D39: =D38*Assumptions!$E$40 -> 0 | E39: =E38*Assumptions!$E$40 -> 0 | F39: =F38*Assumptions!$E$40 -> 0 | G39: =G38*Assumptions!$E$40 -> 0 | H39: =H38*Assumptions!$E$40 -> 0 | I39: =I38*Assumptions!$E$40 -> 572.87239 | J39: =J38*Assumptions!$E$40 -> 572.64376 | ... AL39: =AL38*Assumptions!$E$40 -> 1421.5695 | AM39: =SUM(C39:AL39) -> 25426.096
A40: Eligible outcomes (clinical screen and state) | B40: # | C40: =C39*Assumptions!$E$41*C37 -> 0 | D40: =D39*Assumptions!$E$41*D37 -> 0 | E40: =E39*Assumptions!$E$41*E37 -> 0 | F40: =F39*Assumptions!$E$41*F37 -> 0 | G40: =G39*Assumptions!$E$41*G37 -> 0 | H40: =H39*Assumptions!$E$41*H37 -> 0 | I40: =I39*Assumptions!$E$41*I37 -> 119.61576 | J40: =J39*Assumptions!$E$41*J37 -> 127.87135 | ... AL40: =AL39*Assumptions!$E$41*AL37 -> 676.09845 | AM40: =SUM(C40:AL40) -> 10481.208
A41: Intakes submitted (consult fee charged) | B41: # | C41: =C40*Assumptions!$E$45 -> 0 | D41: =D40*Assumptions!$E$45 -> 0 | E41: =E40*Assumptions!$E$45 -> 0 | F41: =F40*Assumptions!$E$45 -> 0 | G41: =G40*Assumptions!$E$45 -> 0 | H41: =H40*Assumptions!$E$45 -> 0 | I41: =I40*Assumptions!$E$45 -> 66.984823 | J41: =J40*Assumptions!$E$45 -> 71.607956 | ... AL41: =AL40*Assumptions!$E$45 -> 378.61513 | AM41: =SUM(C41:AL41) -> 5869.4763
A42: Consults completed | B42: # | C42: =C41*Assumptions!$E$46 -> 0 | D42: =D41*Assumptions!$E$46 -> 0 | E42: =E41*Assumptions!$E$46 -> 0 | F42: =F41*Assumptions!$E$46 -> 0 | G42: =G41*Assumptions!$E$46 -> 0 | H42: =H41*Assumptions!$E$46 -> 0 | I42: =I41*Assumptions!$E$46 -> 55.597403 | J42: =J41*Assumptions!$E$46 -> 59.434604 | ... AL42: =AL41*Assumptions!$E$46 -> 314.25056 | AM42: =SUM(C42:AL42) -> 4871.6653
A43: Prescriptions issued (clinician decision) | B43: # | C43: =C42*Assumptions!$E$47 -> 0 | D43: =D42*Assumptions!$E$47 -> 0 | E43: =E42*Assumptions!$E$47 -> 0 | F43: =F42*Assumptions!$E$47 -> 0 | G43: =G42*Assumptions!$E$47 -> 0 | H43: =H42*Assumptions!$E$47 -> 0 | I43: =I42*Assumptions!$E$47 -> 34.47039 | J43: =J42*Assumptions!$E$47 -> 36.849454 | ... AL43: =AL42*Assumptions!$E$47 -> 194.83535 | AM43: =SUM(C43:AL43) -> 3020.4325
A44: New paying programme members | B44: # | C44: =C43*Assumptions!$E$48 -> 0 | D44: =D43*Assumptions!$E$48 -> 0 | E44: =E43*Assumptions!$E$48 -> 0 | F44: =F43*Assumptions!$E$48 -> 0 | G44: =G43*Assumptions!$E$48 -> 0 | H44: =H43*Assumptions!$E$48 -> 0 | I44: =I43*Assumptions!$E$48 -> 22.750457 | J44: =J43*Assumptions!$E$48 -> 24.32064 | ... AL44: =AL43*Assumptions!$E$48 -> 128.59133 | AM44: =SUM(C44:AL44) -> 1993.4854
A45: Active programme members (end of month) | B45: # | C45: =C44 -> 0 | D45: =C45*(1-Assumptions!$E$49)+D44 -> 0 | E45: =D45*(1-Assumptions!$E$49)+E44 -> 0 | F45: =E45*(1-Assumptions!$E$49)+F44 -> 0 | G45: =F45*(1-Assumptions!$E$49)+G44 -> 0 | H45: =G45*(1-Assumptions!$E$49)+H44 -> 0 | I45: =H45*(1-Assumptions!$E$49)+I44 -> 22.750457 | J45: =I45*(1-Assumptions!$E$49)+J44 -> 44.568547 | K45: =J45*(1-Assumptions!$E$49)+K44 -> 65.600707 | ... AL45: =AK45*(1-Assumptions!$E$49)+AL44 -> 837.56118 | AM45: =AL45 -> 837.56118
A46: Programme members churned | B46: # | C46: =0 -> 0 | D46: =C45*Assumptions!$E$49 -> 0 | E46: =D45*Assumptions!$E$49 -> 0 | F46: =E45*Assumptions!$E$49 -> 0 | G46: =F45*Assumptions!$E$49 -> 0 | H46: =G45*Assumptions!$E$49 -> 0 | I46: =H45*Assumptions!$E$49 -> 0 | J46: =I45*Assumptions!$E$49 -> 2.5025503 | K46: =J45*Assumptions!$E$49 -> 4.9025402 | ... AL46: =AK45*Assumptions!$E$49 -> 87.625487 | AM46: =SUM(C46:AL46) -> 1155.9243
A47: Programme subscription revenue | B47: $ | C47: =C45*Assumptions!$E$51 -> 0 | D47: =D45*Assumptions!$E$51 -> 0 | E47: =E45*Assumptions!$E$51 -> 0 | F47: =F45*Assumptions!$E$51 -> 0 | G47: =G45*Assumptions!$E$51 -> 0 | H47: =H45*Assumptions!$E$51 -> 0 | I47: =I45*Assumptions!$E$51 -> 5664.8639 | J47: =J45*Assumptions!$E$51 -> 11097.568 | ... AL47: =AL45*Assumptions!$E$51 -> 208552.73 | AM47: =SUM(C47:AL47) -> 2825144.9
A48: Consultation fee revenue | B48: $ | C48: =C41*Assumptions!$E$52 -> 0 | D48: =D41*Assumptions!$E$52 -> 0 | E48: =E41*Assumptions!$E$52 -> 0 | F48: =F41*Assumptions!$E$52 -> 0 | G48: =G41*Assumptions!$E$52 -> 0 | H48: =H41*Assumptions!$E$52 -> 0 | I48: =I41*Assumptions!$E$52 -> 3952.1046 | J48: =J41*Assumptions!$E$52 -> 4224.8694 | ... AL48: =AL41*Assumptions!$E$52 -> 22338.293 | AM48: =SUM(C48:AL48) -> 346299.1
A49: Rx gross revenue | B49: $ | C49: =C47+C48 -> 0 | D49: =D47+D48 -> 0 | E49: =E47+E48 -> 0 | F49: =F47+F48 -> 0 | G49: =G47+G48 -> 0 | H49: =H47+H48 -> 0 | I49: =I47+I48 -> 9616.9685 | J49: =J47+J48 -> 15322.438 | ... AL49: =AL47+AL48 -> 230891.03 | AM49: =SUM(C49:AL49) -> 3171444
A50: Rx refunds and chargebacks | B50: $ | C50: =-C49*Assumptions!$E$61 -> 0 | D50: =-D49*Assumptions!$E$61 -> 0 | E50: =-E49*Assumptions!$E$61 -> 0 | F50: =-F49*Assumptions!$E$61 -> 0 | G50: =-G49*Assumptions!$E$61 -> 0 | H50: =-H49*Assumptions!$E$61 -> 0 | I50: =-I49*Assumptions!$E$61 -> -288.50905 | J50: =-J49*Assumptions!$E$61 -> -459.67313 | ... AL50: =-AL49*Assumptions!$E$61 -> -6926.7308 | AM50: =SUM(C50:AL50) -> -95143.321
A51: Rx net revenue | B51: $ | C51: =C49+C50 -> 0 | D51: =D49+D50 -> 0 | E51: =E49+E50 -> 0 | F51: =F49+F50 -> 0 | G51: =G49+G50 -> 0 | H51: =H49+H50 -> 0 | I51: =I49+I50 -> 9328.4594 | J51: =J49+J50 -> 14862.764 | ... AL51: =AL49+AL50 -> 223964.29 | AM51: =SUM(C51:AL51) -> 3076300.7
A52: Pharmacy medication cost | B52: $ | C52: =-C45*Assumptions!$E$54 -> 0 | D52: =-D45*Assumptions!$E$54 -> 0 | E52: =-E45*Assumptions!$E$54 -> 0 | F52: =-F45*Assumptions!$E$54 -> 0 | G52: =-G45*Assumptions!$E$54 -> 0 | H52: =-H45*Assumptions!$E$54 -> 0 | I52: =-I45*Assumptions!$E$54 -> -2002.0403 | J52: =-J45*Assumptions!$E$54 -> -3922.0321 | ... AL52: =-AL45*Assumptions!$E$54 -> -73705.383 | AM52: =SUM(C52:AL52) -> -998444.8
A53: Clinician cost, new consults | B53: $ | C53: =-C42*Assumptions!$E$55 -> 0 | D53: =-D42*Assumptions!$E$55 -> 0 | E53: =-E42*Assumptions!$E$55 -> 0 | F53: =-F42*Assumptions!$E$55 -> 0 | G53: =-G42*Assumptions!$E$55 -> 0 | H53: =-H42*Assumptions!$E$55 -> 0 | I53: =-I42*Assumptions!$E$55 -> -2112.7013 | J53: =-J42*Assumptions!$E$55 -> -2258.5149 | ... AL53: =-AL42*Assumptions!$E$55 -> -11941.521 | AM53: =SUM(C53:AL53) -> -185123.28
A54: Clinician cost, monitoring and refills | B54: $ | C54: =-C45*Assumptions!$E$56 -> 0 | D54: =-D45*Assumptions!$E$56 -> 0 | E54: =-E45*Assumptions!$E$56 -> 0 | F54: =-F45*Assumptions!$E$56 -> 0 | G54: =-G45*Assumptions!$E$56 -> 0 | H54: =-H45*Assumptions!$E$56 -> 0 | I54: =-I45*Assumptions!$E$56 -> -182.00366 | J54: =-J45*Assumptions!$E$56 -> -356.54838 | ... AL54: =-AL45*Assumptions!$E$56 -> -6700.4894 | AM54: =SUM(C54:AL54) -> -90767.709
A55: Cold-chain fulfilment and shipping | B55: $ | C55: =-C45*Assumptions!$E$57 -> 0 | D55: =-D45*Assumptions!$E$57 -> 0 | E55: =-E45*Assumptions!$E$57 -> 0 | F55: =-F45*Assumptions!$E$57 -> 0 | G55: =-G45*Assumptions!$E$57 -> 0 | H55: =-H45*Assumptions!$E$57 -> 0 | I55: =-I45*Assumptions!$E$57 -> -409.50823 | J55: =-J45*Assumptions!$E$57 -> -802.23385 | ... AL55: =-AL45*Assumptions!$E$57 -> -15076.101 | AM55: =SUM(C55:AL55) -> -204227.35
A56: Rx support cost | B56: $ | C56: =-C45*Assumptions!$E$58 -> 0 | D56: =-D45*Assumptions!$E$58 -> 0 | E56: =-E45*Assumptions!$E$58 -> 0 | F56: =-F45*Assumptions!$E$58 -> 0 | G56: =-G45*Assumptions!$E$58 -> 0 | H56: =-H45*Assumptions!$E$58 -> 0 | I56: =-I45*Assumptions!$E$58 -> -102.37706 | J56: =-J45*Assumptions!$E$58 -> -200.55846 | ... AL56: =-AL45*Assumptions!$E$58 -> -3769.0253 | AM56: =SUM(C56:AL56) -> -51056.836
A57: Rx payment processing | B57: $ | C57: =-C51*Assumptions!$E$60 -> 0 | D57: =-D51*Assumptions!$E$60 -> 0 | E57: =-E51*Assumptions!$E$60 -> 0 | F57: =-F51*Assumptions!$E$60 -> 0 | G57: =-G51*Assumptions!$E$60 -> 0 | H57: =-H51*Assumptions!$E$60 -> 0 | I57: =-I51*Assumptions!$E$60 -> -270.52532 | J57: =-J51*Assumptions!$E$60 -> -431.02017 | ... AL57: =-AL51*Assumptions!$E$60 -> -6494.9645 | AM57: =SUM(C57:AL57) -> -89212.721
A58: Rx gross profit | B58: $ | C58: =C51+C52+C53+C54+C55+C56+C57 -> 0 | D58: =D51+D52+D53+D54+D55+D56+D57 -> 0 | E58: =E51+E52+E53+E54+E55+E56+E57 -> 0 | F58: =F51+F52+F53+F54+F55+F56+F57 -> 0 | G58: =G51+G52+G53+G54+G55+G56+G57 -> 0 | H58: =H51+H52+H53+H54+H55+H56+H57 -> 0 | I58: =I51+I52+I53+I54+I55+I56+I57 -> 4249.3036 | J58: =J51+J52+J53+J54+J55+J56+J57 -> 6891.8566 | ... AL58: =AL51+AL52+AL53+AL54+AL55+AL56+AL57 -> 106276.81 | AM58: =SUM(C58:AL58) -> 1457468
A59: Rx gross margin | B59: % | C59: =IFERROR(C58/C51,0) -> 0 | D59: =IFERROR(D58/D51,0) -> 0 | E59: =IFERROR(E58/E51,0) -> 0 | F59: =IFERROR(F58/F51,0) -> 0 | G59: =IFERROR(G58/G51,0) -> 0 | H59: =IFERROR(H58/H51,0) -> 0 | I59: =IFERROR(I58/I51,0) -> 0.4555204 | J59: =IFERROR(J58/J51,0) -> 0.46369951 | ... AL59: =IFERROR(AL58/AL51,0) -> 0.47452568 | AM59: =AVERAGE(N59:AL59) -> 0.47363782
A60: TOTAL NET REVENUE | B60: $ | C60: =C31+C51 -> 0 | D60: =D31+D51 -> 113490 | E60: =E31+E51 -> 109775.17 | F60: =F31+F51 -> 120894.96 | G60: =G31+G51 -> 133126.69 | H60: =H31+H51 -> 144440.51 | I60: =I31+I51 -> 164337.9 | J60: =J31+J51 -> 180434.2 | ... AL60: =AL31+AL51 -> 742792.85 | AM60: =SUM(C60:AL60) -> 12970419
A61: TOTAL GROSS PROFIT | B61: $ | C61: =C35+C58 -> 0 | D61: =D35+D58 -> 68528.79 | E61: =E35+E58 -> 66285.659 | F61: =F35+F58 -> 73000.135 | G61: =G35+G58 -> 80386.034 | H61: =H35+H58 -> 87217.672 | I61: =I35+I58 -> 97848.821 | J61: =J35+J58 -> 106869.04 | ... AL61: =AL35+AL58 -> 419561.62 | AM61: =SUM(C61:AL61) -> 7431844
A62: Blended gross margin | B62: % | C62: =IFERROR(C61/C60,0) -> 0 | D62: =IFERROR(D61/D60,0) -> 0.60383109 | E62: =IFERROR(E61/E60,0) -> 0.60383109 | F62: =IFERROR(F61/F60,0) -> 0.60383109 | G62: =IFERROR(G61/G60,0) -> 0.60383109 | H62: =IFERROR(H61/H60,0) -> 0.60383109 | I62: =IFERROR(I61/I60,0) -> 0.59541239 | J62: =IFERROR(J61/J60,0) -> 0.59228814 | ... AL62: =IFERROR(AL61/AL60,0) -> 0.56484337 | AM62: =AVERAGE(N62:AL62) -> 0.57168724
A63: Provider flat fee | B63: $ | C63: =-Assumptions!$E$63 -> -600 | D63: =-Assumptions!$E$63 -> -600 | E63: =-Assumptions!$E$63 -> -600 | F63: =-Assumptions!$E$63 -> -600 | G63: =-Assumptions!$E$63 -> -600 | H63: =-Assumptions!$E$63 -> -600 | I63: =-Assumptions!$E$63 -> -600 | J63: =-Assumptions!$E$63 -> -600 | ... AL63: =-Assumptions!$E$63 -> -600 | AM63: =SUM(C63:AL63) -> -21600
A64: Certification and registrations | B64: $ | C64: =-Assumptions!$E$64 -> -280 | D64: =-Assumptions!$E$64 -> -280 | E64: =-Assumptions!$E$64 -> -280 | F64: =-Assumptions!$E$64 -> -280 | G64: =-Assumptions!$E$64 -> -280 | H64: =-Assumptions!$E$64 -> -280 | I64: =-Assumptions!$E$64 -> -280 | J64: =-Assumptions!$E$64 -> -280 | ... AL64: =-Assumptions!$E$64 -> -280 | AM64: =SUM(C64:AL64) -> -10080
A65: Team | B65: $ | C65: =-IF(C8=0,Assumptions!$E$65,IF(C$5<=12,Assumptions!$E$66,IF(C$5<=24,Assumptions!$E$67,Assumptions!$E$68))) -> -18000 | D65: =-IF(D8=0,Assumptions!$E$65,IF(D$5<=12,Assumptions!$E$66,IF(D$5<=24,Assumptions!$E$67,Assumptions!$E$68))) -> -45000 | E65: =-IF(E8=0,Assumptions!$E$65,IF(E$5<=12,Assumptions!$E$66,IF(E$5<=24,Assumptions!$E$67,Assumptions!$E$68))) -> -45000 | F65: =-IF(F8=0,Assumptions!$E$65,IF(F$5<=12,Assumptions!$E$66,IF(F$5<=24,Assumptions!$E$67,Assumptions!$E$68))) -> -45000 | G65: =-IF(G8=0,Assumptions!$E$65,IF(G$5<=12,Assumptions!$E$66,IF(G$5<=24,Assumptions!$E$67,Assumptions!$E$68))) -> -45000 | H65: =-IF(H8=0,Assumptions!$E$65,IF(H$5<=12,Assumptions!$E$66,IF(H$5<=24,Assumptions!$E$67,Assumptions!$E$68))) -> -45000 | I65: =-IF(I8=0,Assumptions!$E$65,IF(I$5<=12,Assumptions!$E$66,IF(I$5<=24,Assumptions!$E$67,Assumptions!$E$68))) -> -45000 | J65: =-IF(J8=0,Assumptions!$E$65,IF(J$5<=12,Assumptions!$E$66,IF(J$5<=24,Assumptions!$E$67,Assumptions!$E$68))) -> -45000 | ... AL65: =-IF(AL8=0,Assumptions!$E$65,IF(AL$5<=12,Assumptions!$E$66,IF(AL$5<=24,Assumptions!$E$67,Assumptions!$E$68))) -> -92000 | AM65: =SUM(C65:AL65) -> -2361000
A66: Medical director and clinical oversight | B66: $ | C66: =-IF(C$5>=Assumptions!$E$7-2,Assumptions!$E$69,0) -> 0 | D66: =-IF(D$5>=Assumptions!$E$7-2,Assumptions!$E$69,0) -> 0 | E66: =-IF(E$5>=Assumptions!$E$7-2,Assumptions!$E$69,0) -> 0 | F66: =-IF(F$5>=Assumptions!$E$7-2,Assumptions!$E$69,0) -> 0 | G66: =-IF(G$5>=Assumptions!$E$7-2,Assumptions!$E$69,0) -> -9000 | H66: =-IF(H$5>=Assumptions!$E$7-2,Assumptions!$E$69,0) -> -9000 | I66: =-IF(I$5>=Assumptions!$E$7-2,Assumptions!$E$69,0) -> -9000 | J66: =-IF(J$5>=Assumptions!$E$7-2,Assumptions!$E$69,0) -> -9000 | ... AL66: =-IF(AL$5>=Assumptions!$E$7-2,Assumptions!$E$69,0) -> -9000 | AM66: =SUM(C66:AL66) -> -288000
A67: Technology and software | B67: $ | C67: =-Assumptions!$E$70 -> -2500 | D67: =-Assumptions!$E$70 -> -2500 | E67: =-Assumptions!$E$70 -> -2500 | F67: =-Assumptions!$E$70 -> -2500 | G67: =-Assumptions!$E$70 -> -2500 | H67: =-Assumptions!$E$70 -> -2500 | I67: =-Assumptions!$E$70 -> -2500 | J67: =-Assumptions!$E$70 -> -2500 | ... AL67: =-Assumptions!$E$70 -> -2500 | AM67: =SUM(C67:AL67) -> -90000
A68: Legal, regulatory and compliance | B68: $ | C68: =-IF(C$5<=4,Assumptions!$E$71,Assumptions!$E$72) -> -25000 | D68: =-IF(D$5<=4,Assumptions!$E$71,Assumptions!$E$72) -> -25000 | E68: =-IF(E$5<=4,Assumptions!$E$71,Assumptions!$E$72) -> -25000 | F68: =-IF(F$5<=4,Assumptions!$E$71,Assumptions!$E$72) -> -25000 | G68: =-IF(G$5<=4,Assumptions!$E$71,Assumptions!$E$72) -> -9000 | H68: =-IF(H$5<=4,Assumptions!$E$71,Assumptions!$E$72) -> -9000 | I68: =-IF(I$5<=4,Assumptions!$E$71,Assumptions!$E$72) -> -9000 | J68: =-IF(J$5<=4,Assumptions!$E$71,Assumptions!$E$72) -> -9000 | ... AL68: =-IF(AL$5<=4,Assumptions!$E$71,Assumptions!$E$72) -> -9000 | AM68: =SUM(C68:AL68) -> -388000
A69: Insurance | B69: $ | C69: =-C8*Assumptions!$E$73 -> 0 | D69: =-D8*Assumptions!$E$73 -> -3500 | E69: =-E8*Assumptions!$E$73 -> -3500 | F69: =-F8*Assumptions!$E$73 -> -3500 | G69: =-G8*Assumptions!$E$73 -> -3500 | H69: =-H8*Assumptions!$E$73 -> -3500 | I69: =-I8*Assumptions!$E$73 -> -3500 | J69: =-J8*Assumptions!$E$73 -> -3500 | ... AL69: =-AL8*Assumptions!$E$73 -> -3500 | AM69: =SUM(C69:AL69) -> -122500
A70: Creative and content | B70: $ | C70: =-Assumptions!$E$74 -> -12000 | D70: =-Assumptions!$E$74 -> -12000 | E70: =-Assumptions!$E$74 -> -12000 | F70: =-Assumptions!$E$74 -> -12000 | G70: =-Assumptions!$E$74 -> -12000 | H70: =-Assumptions!$E$74 -> -12000 | I70: =-Assumptions!$E$74 -> -12000 | J70: =-Assumptions!$E$74 -> -12000 | ... AL70: =-Assumptions!$E$74 -> -12000 | AM70: =SUM(C70:AL70) -> -432000
A71: Paid media | B71: $ | C71: =-C15 -> -8000 | D71: =-D15 -> -30000 | E71: =-E15 -> -30000 | F71: =-F15 -> -30000 | G71: =-G15 -> -30000 | H71: =-H15 -> -31950.406 | I71: =-I15 -> -34665.723 | J71: =-J15 -> -39441.095 | ... AL71: =-AL15 -> -170343.29 | AM71: =SUM(C71:AL71) -> -2980031.7
A72: One-time launch marketing and PR | B72: $ | C72: =-IF(C$5=Assumptions!$E$6,Assumptions!$E$24,0) -> 0 | D72: =-IF(D$5=Assumptions!$E$6,Assumptions!$E$24,0) -> -150000 | E72: =-IF(E$5=Assumptions!$E$6,Assumptions!$E$24,0) -> 0 | F72: =-IF(F$5=Assumptions!$E$6,Assumptions!$E$24,0) -> 0 | G72: =-IF(G$5=Assumptions!$E$6,Assumptions!$E$24,0) -> 0 | H72: =-IF(H$5=Assumptions!$E$6,Assumptions!$E$24,0) -> 0 | I72: =-IF(I$5=Assumptions!$E$6,Assumptions!$E$24,0) -> 0 | J72: =-IF(J$5=Assumptions!$E$6,Assumptions!$E$24,0) -> 0 | ... AL72: =-IF(AL$5=Assumptions!$E$6,Assumptions!$E$24,0) -> 0 | AM72: =SUM(C72:AL72) -> -150000
A73: Partner cash retainer | B73: $ | C73: =-C8*Assumptions!$E$76 -> 0 | D73: =-D8*Assumptions!$E$76 -> -15000 | E73: =-E8*Assumptions!$E$76 -> -15000 | F73: =-F8*Assumptions!$E$76 -> -15000 | G73: =-G8*Assumptions!$E$76 -> -15000 | H73: =-H8*Assumptions!$E$76 -> -15000 | I73: =-I8*Assumptions!$E$76 -> -15000 | J73: =-J8*Assumptions!$E$76 -> -15000 | ... AL73: =-AL8*Assumptions!$E$76 -> -15000 | AM73: =SUM(C73:AL73) -> -525000
A74: Partner royalty on net revenue | B74: $ | C74: =-C60*Assumptions!$E$77 -> 0 | D74: =-D60*Assumptions!$E$77 -> -5674.5 | E74: =-E60*Assumptions!$E$77 -> -5488.7584 | F74: =-F60*Assumptions!$E$77 -> -6044.748 | G74: =-G60*Assumptions!$E$77 -> -6656.3346 | H74: =-H60*Assumptions!$E$77 -> -7222.0256 | I74: =-I60*Assumptions!$E$77 -> -8216.8949 | J74: =-J60*Assumptions!$E$77 -> -9021.71 | ... AL74: =-AL60*Assumptions!$E$77 -> -37139.643 | AM74: =SUM(C74:AL74) -> -648520.93
A75: TOTAL OPERATING EXPENSE | B75: $ | C75: =C63+C64+C65+C66+C67+C68+C69+C70+C71+C72+C73+C74 -> -66380 | D75: =D63+D64+D65+D66+D67+D68+D69+D70+D71+D72+D73+D74 -> -289554.5 | E75: =E63+E64+E65+E66+E67+E68+E69+E70+E71+E72+E73+E74 -> -139368.76 | F75: =F63+F64+F65+F66+F67+F68+F69+F70+F71+F72+F73+F74 -> -139924.75 | G75: =G63+G64+G65+G66+G67+G68+G69+G70+G71+G72+G73+G74 -> -133536.33 | H75: =H63+H64+H65+H66+H67+H68+H69+H70+H71+H72+H73+H74 -> -136052.43 | I75: =I63+I64+I65+I66+I67+I68+I69+I70+I71+I72+I73+I74 -> -139762.62 | J75: =J63+J64+J65+J66+J67+J68+J69+J70+J71+J72+J73+J74 -> -145342.81 | ... AL75: =AL63+AL64+AL65+AL66+AL67+AL68+AL69+AL70+AL71+AL72+AL73+AL74 -> -351362.93 | AM75: =SUM(C75:AL75) -> -8016732.7
A76: EBITDA | B76: $ | C76: =C61+C75 -> -66380 | D76: =D61+D75 -> -221025.71 | E76: =E61+E75 -> -73083.1 | F76: =F61+F75 -> -66924.613 | G76: =G61+G75 -> -53150.3 | H76: =H61+H75 -> -48834.76 | I76: =I61+I75 -> -41913.797 | J76: =J61+J75 -> -38473.769 | ... AL76: =AL61+AL75 -> 68198.689 | AM76: =SUM(C76:AL76) -> -584888.7
A77: EBITDA margin | B77: % | C77: =IFERROR(C76/C60,0) -> 0 | D77: =IFERROR(D76/D60,0) -> -1.9475347 | E77: =IFERROR(E76/E60,0) -> -0.66575257 | F77: =IFERROR(F76/F60,0) -> -0.55357653 | G77: =IFERROR(G76/G60,0) -> -0.39924601 | H77: =IFERROR(H76/H60,0) -> -0.338096 | I77: =IFERROR(I76/I60,0) -> -0.25504645 | J77: =IFERROR(J76/J60,0) -> -0.2132288 | ... AL77: =IFERROR(AL76/AL60,0) -> 0.091813874 | AM77: =AVERAGE(N77:AL77) -> -0.0091520419
A78: Non-Rx inventory balance | B78: $ | C78: =-C32*Assumptions!$E$80 -> 0 | D78: =-D32*Assumptions!$E$80 -> 60840 | E78: =-E32*Assumptions!$E$80 -> 58848.543 | F78: =-F32*Assumptions!$E$80 -> 64809.67 | G78: =-G32*Assumptions!$E$80 -> 71366.886 | H78: =-H32*Assumptions!$E$80 -> 77432.027 | I78: =-I32*Assumptions!$E$80 -> 83097.843 | J78: =-J32*Assumptions!$E$80 -> 88759.945 | ... AL78: =-AL32*Assumptions!$E$80 -> 278134.9 | AM78: =AL78 -> 278134.9
A79: Inventory investment (increase in stock) | B79: $ | C79: =-C78 -> 0 | D79: =-(D78-C78) -> -60840 | E79: =-(E78-D78) -> 1991.4565 | F79: =-(F78-E78) -> -5961.1261 | G79: =-(G78-F78) -> -6557.2163 | H79: =-(H78-G78) -> -6065.1415 | I79: =-(I78-H78) -> -5665.8156 | J79: =-(J78-I78) -> -5662.1022 | K79: =-(K78-J78) -> -5346.8322 | ... AL79: =-(AL78-AK78) -> -11845.736 | AM79: =SUM(C79:AL79) -> -278134.9
A80: Net cash flow | B80: $ | C80: =C76+C79 -> -66380 | D80: =D76+D79 -> -281865.71 | E80: =E76+E79 -> -71091.643 | F80: =F76+F79 -> -72885.739 | G80: =G76+G79 -> -59707.516 | H80: =H76+H79 -> -54899.901 | I80: =I76+I79 -> -47579.613 | J80: =J76+J79 -> -44135.871 | ... AL80: =AL76+AL79 -> 56352.954 | AM80: =SUM(C80:AL80) -> -863023.6
A81: Cumulative cash flow | B81: $ | C81: =C80 -> -66380 | D81: =C81+D80 -> -348245.71 | E81: =D81+E80 -> -419337.35 | F81: =E81+F80 -> -492223.09 | G81: =F81+G80 -> -551930.61 | H81: =G81+H80 -> -606830.51 | I81: =H81+I80 -> -654410.12 | J81: =I81+J80 -> -698545.99 | K81: =J81+K80 -> -738418.98 | ... AL81: =AK81+AL80 -> -863023.6 | AM81: =AL81 -> -863023.6
A82: Break-even helper (month if EBITDA positive, else 999) | B82: # | C82: =IF(C76>0,C$5,999) -> 999 | D82: =IF(D76>0,D$5,999) -> 999 | E82: =IF(E76>0,E$5,999) -> 999 | F82: =IF(F76>0,F$5,999) -> 999 | G82: =IF(G76>0,G$5,999) -> 999 | H82: =IF(H76>0,H$5,999) -> 999 | I82: =IF(I76>0,I$5,999) -> 999 | J82: =IF(J76>0,J$5,999) -> 999 | ... AL82: =IF(AL76>0,AL$5,999) -> 36
A83: New customers, both lines | B83: # | C83: =C21+C44 -> 0 | D83: =D21+D44 -> 1500 | E83: =E21+E44 -> 793.90097 | F83: =F21+F44 -> 731.20291 | G83: =G21+G44 -> 681.99955 | H83: =H21+H44 -> 653.12776 | I83: =I21+I44 -> 659.27534 | J83: =J21+J44 -> 660.59148 | ... AL83: =AL21+AL44 -> 1708.113 | AM83: =SUM(C83:AL83) -> 34604.935
A84: Blended CAC (paid media plus creative) | B84: $ | C84: =IFERROR((C15-C70)/C83,0) -> 0 | D84: =IFERROR((D15-D70)/D83,0) -> 28 | E84: =IFERROR((E15-E70)/E83,0) -> 52.903323 | F84: =IFERROR((F15-F70)/F83,0) -> 57.439596 | G84: =IFERROR((G15-G70)/G83,0) -> 61.583618 | H84: =IFERROR((H15-H70)/H83,0) -> 67.292203 | I84: =IFERROR((I15-I70)/I83,0) -> 70.783359 | J84: =IFERROR((J15-J70)/J83,0) -> 77.871267 | ... AL84: =IFERROR((AL15-AL70)/AL83,0) -> 106.7513 | AM84: =AVERAGE(N84:AL84) -> 107.3607
A85: Rx contribution per member-month, steady state | B85: $ | C85: =Assumptions!$E$51*(1-Assumptions!$E$61)*(1-Assumptions!$E$60)-Assumptions!$E$54-Assumptions!$E$56-Assumptions!$E$57-Assumptions!$E$58 -> 116.02563 | D85: =Assumptions!$E$51*(1-Assumptions!$E$61)*(1-Assumptions!$E$60)-Assumptions!$E$54-Assumptions!$E$56-Assumptions!$E$57-Assumptions!$E$58 -> 116.02563 | E85: =Assumptions!$E$51*(1-Assumptions!$E$61)*(1-Assumptions!$E$60)-Assumptions!$E$54-Assumptions!$E$56-Assumptions!$E$57-Assumptions!$E$58 -> 116.02563 | F85: =Assumptions!$E$51*(1-Assumptions!$E$61)*(1-Assumptions!$E$60)-Assumptions!$E$54-Assumptions!$E$56-Assumptions!$E$57-Assumptions!$E$58 -> 116.02563 | G85: =Assumptions!$E$51*(1-Assumptions!$E$61)*(1-Assumptions!$E$60)-Assumptions!$E$54-Assumptions!$E$56-Assumptions!$E$57-Assumptions!$E$58 -> 116.02563 | H85: =Assumptions!$E$51*(1-Assumptions!$E$61)*(1-Assumptions!$E$60)-Assumptions!$E$54-Assumptions!$E$56-Assumptions!$E$57-Assumptions!$E$58 -> 116.02563 | I85: =Assumptions!$E$51*(1-Assumptions!$E$61)*(1-Assumptions!$E$60)-Assumptions!$E$54-Assumptions!$E$56-Assumptions!$E$57-Assumptions!$E$58 -> 116.02563 | J85: =Assumptions!$E$51*(1-Assumptions!$E$61)*(1-Assumptions!$E$60)-Assumptions!$E$54-Assumptions!$E$56-Assumptions!$E$57-Assumptions!$E$58 -> 116.02563 | ... AL85: =Assumptions!$E$51*(1-Assumptions!$E$61)*(1-Assumptions!$E$60)-Assumptions!$E$54-Assumptions!$E$56-Assumptions!$E$57-Assumptions!$E$58 -> 116.02563 | AM85: =AVERAGE(N85:AL85) -> 116.02563
A86: Rx gross LTV (contribution / churn) | B86: $ | C86: =C85/Assumptions!$E$49 -> 1054.7785 | D86: =D85/Assumptions!$E$49 -> 1054.7785 | E86: =E85/Assumptions!$E$49 -> 1054.7785 | F86: =F85/Assumptions!$E$49 -> 1054.7785 | G86: =G85/Assumptions!$E$49 -> 1054.7785 | H86: =H85/Assumptions!$E$49 -> 1054.7785 | I86: =I85/Assumptions!$E$49 -> 1054.7785 | J86: =J85/Assumptions!$E$49 -> 1054.7785 | ... AL86: =AL85/Assumptions!$E$49 -> 1054.7785 | AM86: =AVERAGE(N86:AL86) -> 1054.7785
A87: Non-Rx contribution per order | B87: $ | C87: =Assumptions!$E$31*(1-Assumptions!$E$61)*(1-Assumptions!$E$60)-Assumptions!$E$31*Assumptions!$E$36-Assumptions!$E$37 -> 45.68586 | D87: =Assumptions!$E$31*(1-Assumptions!$E$61)*(1-Assumptions!$E$60)-Assumptions!$E$31*Assumptions!$E$36-Assumptions!$E$37 -> 45.68586 | E87: =Assumptions!$E$31*(1-Assumptions!$E$61)*(1-Assumptions!$E$60)-Assumptions!$E$31*Assumptions!$E$36-Assumptions!$E$37 -> 45.68586 | F87: =Assumptions!$E$31*(1-Assumptions!$E$61)*(1-Assumptions!$E$60)-Assumptions!$E$31*Assumptions!$E$36-Assumptions!$E$37 -> 45.68586 | G87: =Assumptions!$E$31*(1-Assumptions!$E$61)*(1-Assumptions!$E$60)-Assumptions!$E$31*Assumptions!$E$36-Assumptions!$E$37 -> 45.68586 | H87: =Assumptions!$E$31*(1-Assumptions!$E$61)*(1-Assumptions!$E$60)-Assumptions!$E$31*Assumptions!$E$36-Assumptions!$E$37 -> 45.68586 | I87: =Assumptions!$E$31*(1-Assumptions!$E$61)*(1-Assumptions!$E$60)-Assumptions!$E$31*Assumptions!$E$36-Assumptions!$E$37 -> 45.68586 | J87: =Assumptions!$E$31*(1-Assumptions!$E$61)*(1-Assumptions!$E$60)-Assumptions!$E$31*Assumptions!$E$36-Assumptions!$E$37 -> 45.68586 | ... AL87: =Assumptions!$E$31*(1-Assumptions!$E$61)*(1-Assumptions!$E$60)-Assumptions!$E$31*Assumptions!$E$36-Assumptions!$E$37 -> 45.68586 | AM87: =AVERAGE(N87:AL87) -> 45.68586
A88: Non-Rx subscriber gross LTV | B88: $ | C88: =C87/Assumptions!$E$33 -> 652.65514 | D88: =D87/Assumptions!$E$33 -> 652.65514 | E88: =E87/Assumptions!$E$33 -> 652.65514 | F88: =F87/Assumptions!$E$33 -> 652.65514 | G88: =G87/Assumptions!$E$33 -> 652.65514 | H88: =H87/Assumptions!$E$33 -> 652.65514 | I88: =I87/Assumptions!$E$33 -> 652.65514 | J88: =J87/Assumptions!$E$33 -> 652.65514 | ... AL88: =AL87/Assumptions!$E$33 -> 652.65514 | AM88: =AVERAGE(N88:AL88) -> 652.65514

Sheet Model_Aggressive
A1: Reserve Clinic - Aggressive scenario, months 1-36
A2: Every cell is a formula. Inputs live on Assumptions only. Green = link to Assumptions.
A4: Line | B4: Unit | C4: M1 | D4: M2 | E4: M3 | F4: M4 | G4: M5 | H4: M6 | I4: M7 | J4: M8 | K4: M9 | L4: M10 | M4: M11 | N4: M12 | O4: M13 | P4: M14 | Q4: M15 | R4: M16 | S4: M17 | T4: M18 | U4: M19 | V4: M20 | W4: M21 | X4: M22 | Y4: M23 | Z4: M24 | AA4: M25 | AB4: M26 | AC4: M27 | AD4: M28 | AE4: M29 | AF4: M30 | AG4: M31 | AH4: M32 | AI4: M33 | AJ4: M34 | AK4: M35 | AL4: M36 | AM4: Total / final
A5: Month index | B5: # | C5: 1 | D5: 2 | E5: 3 | F5: 4 | G5: 5 | H5: 6 | I5: 7 | J5: 8 | K5: 9 | L5: 10 | M5: 11 | N5: 12 | O5: 13 | P5: 14 | Q5: 15 | R5: 16 | S5: 17 | T5: 18 | U5: 19 | V5: 20 | W5: 21 | X5: 22 | Y5: 23 | Z5: 24 | AA5: 25 | AB5: 26 | AC5: 27 | AD5: 28 | AE5: 29 | AF5: 30 | AG5: 31 | AH5: 32 | AI5: 33 | AJ5: 34 | AK5: 35 | AL5: 36
A6: Year | B6: # | C6: =ROUNDUP(C$5/12,0) -> 1 | D6: =ROUNDUP(D$5/12,0) -> 1 | E6: =ROUNDUP(E$5/12,0) -> 1 | F6: =ROUNDUP(F$5/12,0) -> 1 | G6: =ROUNDUP(G$5/12,0) -> 1 | H6: =ROUNDUP(H$5/12,0) -> 1 | I6: =ROUNDUP(I$5/12,0) -> 1 | J6: =ROUNDUP(J$5/12,0) -> 1 | ... AL6: =ROUNDUP(AL$5/12,0) -> 3
A8: Non-Rx line live (1/0) | B8: flag | C8: =IF(C$5>=Assumptions!$F$6,1,0) -> 0 | D8: =IF(D$5>=Assumptions!$F$6,1,0) -> 1 | E8: =IF(E$5>=Assumptions!$F$6,1,0) -> 1 | F8: =IF(F$5>=Assumptions!$F$6,1,0) -> 1 | G8: =IF(G$5>=Assumptions!$F$6,1,0) -> 1 | H8: =IF(H$5>=Assumptions!$F$6,1,0) -> 1 | I8: =IF(I$5>=Assumptions!$F$6,1,0) -> 1 | J8: =IF(J$5>=Assumptions!$F$6,1,0) -> 1 | ... AL8: =IF(AL$5>=Assumptions!$F$6,1,0) -> 1
A9: Rx line live (1/0) | B9: flag | C9: =IF(C$5>=Assumptions!$F$7,1,0) -> 0 | D9: =IF(D$5>=Assumptions!$F$7,1,0) -> 0 | E9: =IF(E$5>=Assumptions!$F$7,1,0) -> 0 | F9: =IF(F$5>=Assumptions!$F$7,1,0) -> 0 | G9: =IF(G$5>=Assumptions!$F$7,1,0) -> 1 | H9: =IF(H$5>=Assumptions!$F$7,1,0) -> 1 | I9: =IF(I$5>=Assumptions!$F$7,1,0) -> 1 | J9: =IF(J$5>=Assumptions!$F$7,1,0) -> 1 | ... AL9: =IF(AL$5>=Assumptions!$F$7,1,0) -> 1
A10: Months since non-Rx launch | B10: # | C10: =MAX(0,C$5-Assumptions!$F$6) -> 0 | D10: =MAX(0,D$5-Assumptions!$F$6) -> 0 | E10: =MAX(0,E$5-Assumptions!$F$6) -> 1 | F10: =MAX(0,F$5-Assumptions!$F$6) -> 2 | G10: =MAX(0,G$5-Assumptions!$F$6) -> 3 | H10: =MAX(0,H$5-Assumptions!$F$6) -> 4 | I10: =MAX(0,I$5-Assumptions!$F$6) -> 5 | J10: =MAX(0,J$5-Assumptions!$F$6) -> 6 | ... AL10: =MAX(0,AL$5-Assumptions!$F$6) -> 34
A11: Partner-driven sessions at launch peak | B11: sessions | C11: =Assumptions!$F$9*Assumptions!$F$10*Assumptions!$F$11*Assumptions!$F$12 -> 162756 | D11: =Assumptions!$F$9*Assumptions!$F$10*Assumptions!$F$11*Assumptions!$F$12 -> 162756 | E11: =Assumptions!$F$9*Assumptions!$F$10*Assumptions!$F$11*Assumptions!$F$12 -> 162756 | F11: =Assumptions!$F$9*Assumptions!$F$10*Assumptions!$F$11*Assumptions!$F$12 -> 162756 | G11: =Assumptions!$F$9*Assumptions!$F$10*Assumptions!$F$11*Assumptions!$F$12 -> 162756 | H11: =Assumptions!$F$9*Assumptions!$F$10*Assumptions!$F$11*Assumptions!$F$12 -> 162756 | I11: =Assumptions!$F$9*Assumptions!$F$10*Assumptions!$F$11*Assumptions!$F$12 -> 162756 | J11: =Assumptions!$F$9*Assumptions!$F$10*Assumptions!$F$11*Assumptions!$F$12 -> 162756 | ... AL11: =Assumptions!$F$9*Assumptions!$F$10*Assumptions!$F$11*Assumptions!$F$12 -> 162756
A12: Attention index (decay toward floor) | B12: x | C12: =IF(C8=0,0,IF(C10=0,Assumptions!$F$15,Assumptions!$F$14+(1-Assumptions!$F$14)*Assumptions!$F$13^C10)) -> 0 | D12: =IF(D8=0,0,IF(D10=0,Assumptions!$F$15,Assumptions!$F$14+(1-Assumptions!$F$14)*Assumptions!$F$13^D10)) -> 3 | E12: =IF(E8=0,0,IF(E10=0,Assumptions!$F$15,Assumptions!$F$14+(1-Assumptions!$F$14)*Assumptions!$F$13^E10)) -> 0.923 | F12: =IF(F8=0,0,IF(F10=0,Assumptions!$F$15,Assumptions!$F$14+(1-Assumptions!$F$14)*Assumptions!$F$13^F10)) -> 0.85678 | G12: =IF(G8=0,0,IF(G10=0,Assumptions!$F$15,Assumptions!$F$14+(1-Assumptions!$F$14)*Assumptions!$F$13^G10)) -> 0.7998308 | H12: =IF(H8=0,0,IF(H10=0,Assumptions!$F$15,Assumptions!$F$14+(1-Assumptions!$F$14)*Assumptions!$F$13^H10)) -> 0.75085449 | I12: =IF(I8=0,0,IF(I10=0,Assumptions!$F$15,Assumptions!$F$14+(1-Assumptions!$F$14)*Assumptions!$F$13^I10)) -> 0.70873486 | J12: =IF(J8=0,0,IF(J10=0,Assumptions!$F$15,Assumptions!$F$14+(1-Assumptions!$F$14)*Assumptions!$F$13^J10)) -> 0.67251198 | ... AL12: =IF(AL8=0,0,IF(AL10=0,Assumptions!$F$15,Assumptions!$F$14+(1-Assumptions!$F$14)*Assumptions!$F$13^AL10)) -> 0.45326069
A13: Partner-driven sessions | B13: sessions | C13: =C11*C12 -> 0 | D13: =D11*D12 -> 488268 | E13: =E11*E12 -> 150223.79 | F13: =F11*F12 -> 139446.09 | G13: =G11*G12 -> 130177.26 | H13: =H11*H12 -> 122206.07 | I13: =I11*I12 -> 115350.85 | J13: =J11*J12 -> 109455.36 | ... AL13: =AL11*AL12 -> 73770.897 | AM13: =SUM(C13:AL13) -> 3525057.6
A14: Organic and direct sessions | B14: sessions | C14: =MIN(Assumptions!$F$19,Assumptions!$F$17*(1+Assumptions!$F$18)^(C$5-1)) -> 3500 | D14: =MIN(Assumptions!$F$19,Assumptions!$F$17*(1+Assumptions!$F$18)^(D$5-1)) -> 3920 | E14: =MIN(Assumptions!$F$19,Assumptions!$F$17*(1+Assumptions!$F$18)^(E$5-1)) -> 4390.4 | F14: =MIN(Assumptions!$F$19,Assumptions!$F$17*(1+Assumptions!$F$18)^(F$5-1)) -> 4917.248 | G14: =MIN(Assumptions!$F$19,Assumptions!$F$17*(1+Assumptions!$F$18)^(G$5-1)) -> 5507.3178 | H14: =MIN(Assumptions!$F$19,Assumptions!$F$17*(1+Assumptions!$F$18)^(H$5-1)) -> 6168.1959 | I14: =MIN(Assumptions!$F$19,Assumptions!$F$17*(1+Assumptions!$F$18)^(I$5-1)) -> 6908.3794 | J14: =MIN(Assumptions!$F$19,Assumptions!$F$17*(1+Assumptions!$F$18)^(J$5-1)) -> 7737.3849 | ... AL14: =MIN(Assumptions!$F$19,Assumptions!$F$17*(1+Assumptions!$F$18)^(AL$5-1)) -> 184798.67 | AM14: =SUM(C14:AL14) -> 1695620.9
A15: Paid media spend | B15: $ | C15: =Assumptions!$F$21 -> 15000 | D15: =IF(D8=0,Assumptions!$F$21,MIN(Assumptions!$F$25,MAX(Assumptions!$F$22,C60*Assumptions!$F$23))) -> 60000 | E15: =IF(E8=0,Assumptions!$F$21,MIN(Assumptions!$F$25,MAX(Assumptions!$F$22,D60*Assumptions!$F$23))) -> 60000 | F15: =IF(F8=0,Assumptions!$F$21,MIN(Assumptions!$F$25,MAX(Assumptions!$F$22,E60*Assumptions!$F$23))) -> 89186.157 | G15: =IF(G8=0,Assumptions!$F$21,MIN(Assumptions!$F$25,MAX(Assumptions!$F$22,F60*Assumptions!$F$23))) -> 118136.85 | H15: =IF(H8=0,Assumptions!$F$21,MIN(Assumptions!$F$25,MAX(Assumptions!$F$22,G60*Assumptions!$F$23))) -> 171593.6 | I15: =IF(I8=0,Assumptions!$F$21,MIN(Assumptions!$F$25,MAX(Assumptions!$F$22,H60*Assumptions!$F$23))) -> 219656.52 | J15: =IF(J8=0,Assumptions!$F$21,MIN(Assumptions!$F$25,MAX(Assumptions!$F$22,I60*Assumptions!$F$23))) -> 268742.84 | K15: =IF(K8=0,Assumptions!$F$21,MIN(Assumptions!$F$25,MAX(Assumptions!$F$22,J60*Assumptions!$F$23))) -> 319384.38 | ... AL15: =IF(AL8=0,Assumptions!$F$21,MIN(Assumptions!$F$25,MAX(Assumptions!$F$22,AK60*Assumptions!$F$23))) -> 2500000 | AM15: =SUM(C15:AL15) -> 39609379
A16: Paid sessions (diminishing returns applied) | B16: sessions | C16: =(Assumptions!$F$22/Assumptions!$F$20)*(C15/Assumptions!$F$22)^Assumptions!$F$26 -> 10406.156 | D16: =(Assumptions!$F$22/Assumptions!$F$20)*(D15/Assumptions!$F$22)^Assumptions!$F$26 -> 32432.432 | E16: =(Assumptions!$F$22/Assumptions!$F$20)*(E15/Assumptions!$F$22)^Assumptions!$F$26 -> 32432.432 | F16: =(Assumptions!$F$22/Assumptions!$F$20)*(F15/Assumptions!$F$22)^Assumptions!$F$26 -> 44888.946 | G16: =(Assumptions!$F$22/Assumptions!$F$20)*(G15/Assumptions!$F$22)^Assumptions!$F$26 -> 56526.424 | H16: =(Assumptions!$F$22/Assumptions!$F$20)*(H15/Assumptions!$F$22)^Assumptions!$F$26 -> 76769.089 | I16: =(Assumptions!$F$22/Assumptions!$F$20)*(I15/Assumptions!$F$22)^Assumptions!$F$26 -> 93999.526 | J16: =(Assumptions!$F$22/Assumptions!$F$20)*(J15/Assumptions!$F$22)^Assumptions!$F$26 -> 110905.16 | ... AL16: =(Assumptions!$F$22/Assumptions!$F$20)*(AL15/Assumptions!$F$22)^Assumptions!$F$26 -> 690567.77 | AM16: =SUM(C16:AL16) -> 12065004
A17: Effective cost per paid session | B17: $ | C17: =IFERROR(C15/C16,0) -> 1.4414545 | D17: =IFERROR(D15/D16,0) -> 1.85 | E17: =IFERROR(E15/E16,0) -> 1.85 | F17: =IFERROR(F15/F16,0) -> 1.9868178 | G17: =IFERROR(G15/G16,0) -> 2.0899403 | H17: =IFERROR(H15/H16,0) -> 2.2351913 | I17: =IFERROR(I15/I16,0) -> 2.3367833 | J17: =IFERROR(J15/J16,0) -> 2.423177 | ... AL17: =IFERROR(AL15/AL16,0) -> 3.6202095 | AM17: =AVERAGE(N17:AL17) -> 3.2452175
A18: Total sessions | B18: sessions | C18: =C13+C14+C16 -> 13906.156 | D18: =D13+D14+D16 -> 524620.43 | E18: =E13+E14+E16 -> 187046.62 | F18: =F13+F14+F16 -> 189252.28 | G18: =G13+G14+G16 -> 192211 | H18: =H13+H14+H16 -> 205143.36 | I18: =I13+I14+I16 -> 216258.76 | J18: =J13+J14+J16 -> 228097.91 | ... AL18: =AL13+AL14+AL16 -> 949137.33 | AM18: =SUM(C18:AL18) -> 17285682
A19: Shippable new-order capacity | B19: # | C19: =C8*Assumptions!$F$28*Assumptions!$F$29^C10 -> 0 | D19: =D8*Assumptions!$F$28*Assumptions!$F$29^D10 -> 3000 | E19: =E8*Assumptions!$F$28*Assumptions!$F$29^E10 -> 4350 | F19: =F8*Assumptions!$F$28*Assumptions!$F$29^F10 -> 6307.5 | G19: =G8*Assumptions!$F$28*Assumptions!$F$29^G10 -> 9145.875 | H19: =H8*Assumptions!$F$28*Assumptions!$F$29^H10 -> 13261.519 | I19: =I8*Assumptions!$F$28*Assumptions!$F$29^I10 -> 19229.202 | J19: =J8*Assumptions!$F$28*Assumptions!$F$29^J10 -> 27882.343 | ... AL19: =AL8*Assumptions!$F$28*Assumptions!$F$29^AL10 -> 9.1967278e+08 | AM19: =AL19 -> 9.1967278e+08
A20: New non-Rx customer demand | B20: # | C20: =C18*Assumptions!$F$30*C8 -> 0 | D20: =D18*Assumptions!$F$30*D8 -> 9967.7882 | E20: =E18*Assumptions!$F$30*E8 -> 3553.8858 | F20: =F18*Assumptions!$F$30*F8 -> 3595.7933 | G20: =G18*Assumptions!$F$30*G8 -> 3652.0091 | H20: =H18*Assumptions!$F$30*H8 -> 3897.7238 | I20: =I18*Assumptions!$F$30*I8 -> 4108.9164 | J20: =J18*Assumptions!$F$30*J8 -> 4333.8602 | ... AL20: =AL18*Assumptions!$F$30*AL8 -> 18033.609 | AM20: =SUM(C20:AL20) -> 328163.75
A21: New non-Rx customers served | B21: # | C21: =MIN(C20,C19) -> 0 | D21: =MIN(D20,D19) -> 3000 | E21: =MIN(E20,E19) -> 3553.8858 | F21: =MIN(F20,F19) -> 3595.7933 | G21: =MIN(G20,G19) -> 3652.0091 | H21: =MIN(H20,H19) -> 3897.7238 | I21: =MIN(I20,I19) -> 4108.9164 | J21: =MIN(J20,J19) -> 4333.8602 | ... AL21: =MIN(AL20,AL19) -> 18033.609 | AM21: =SUM(C21:AL21) -> 321195.96
A22: Demand lost to capacity | B22: # | C22: =MAX(0,C20-C19) -> 0 | D22: =MAX(0,D20-D19) -> 6967.7882 | E22: =MAX(0,E20-E19) -> 0 | F22: =MAX(0,F20-F19) -> 0 | G22: =MAX(0,G20-G19) -> 0 | H22: =MAX(0,H20-H19) -> 0 | I22: =MAX(0,I20-I19) -> 0 | J22: =MAX(0,J20-J19) -> 0 | ... AL22: =MAX(0,AL20-AL19) -> 0 | AM22: =SUM(C22:AL22) -> 6967.7882
A23: New subscribers | B23: # | C23: =C21*Assumptions!$F$32 -> 0 | D23: =D21*Assumptions!$F$32 -> 1500 | E23: =E21*Assumptions!$F$32 -> 1776.9429 | F23: =F21*Assumptions!$F$32 -> 1797.8967 | G23: =G21*Assumptions!$F$32 -> 1826.0045 | H23: =H21*Assumptions!$F$32 -> 1948.8619 | I23: =I21*Assumptions!$F$32 -> 2054.4582 | J23: =J21*Assumptions!$F$32 -> 2166.9301 | ... AL23: =AL21*Assumptions!$F$32 -> 9016.8047 | AM23: =SUM(C23:AL23) -> 160597.98
A24: New one-time buyers | B24: # | C24: =C21*(1-Assumptions!$F$32) -> 0 | D24: =D21*(1-Assumptions!$F$32) -> 1500 | E24: =E21*(1-Assumptions!$F$32) -> 1776.9429 | F24: =F21*(1-Assumptions!$F$32) -> 1797.8967 | G24: =G21*(1-Assumptions!$F$32) -> 1826.0045 | H24: =H21*(1-Assumptions!$F$32) -> 1948.8619 | I24: =I21*(1-Assumptions!$F$32) -> 2054.4582 | J24: =J21*(1-Assumptions!$F$32) -> 2166.9301 | ... AL24: =AL21*(1-Assumptions!$F$32) -> 9016.8047 | AM24: =SUM(C24:AL24) -> 160597.98
A25: Active subscribers (end of month) | B25: # | C25: =C23 -> 0 | D25: =C25*(1-Assumptions!$F$33)+D23 -> 1500 | E25: =D25*(1-Assumptions!$F$33)+E23 -> 3194.4429 | F25: =E25*(1-Assumptions!$F$33)+F23 -> 4816.6452 | G25: =F25*(1-Assumptions!$F$33)+G23 -> 6377.7342 | H25: =G25*(1-Assumptions!$F$33)+H23 -> 7975.8208 | I25: =H25*(1-Assumptions!$F$33)+I23 -> 9591.6088 | J25: =I25*(1-Assumptions!$F$33)+J23 -> 11231 | K25: =J25*(1-Assumptions!$F$33)+K23 -> 12901.107 | ... AL25: =AK25*(1-Assumptions!$F$33)+AL23 -> 92277.511 | AM25: =AL25 -> 92277.511
A26: Subscribers churned | B26: # | C26: =0 -> 0 | D26: =C25*Assumptions!$F$33 -> 0 | E26: =D25*Assumptions!$F$33 -> 82.5 | F26: =E25*Assumptions!$F$33 -> 175.69436 | G26: =F25*Assumptions!$F$33 -> 264.91549 | H26: =G25*Assumptions!$F$33 -> 350.77538 | I26: =H25*Assumptions!$F$33 -> 438.67014 | J26: =I25*Assumptions!$F$33 -> 527.53848 | K26: =J25*Assumptions!$F$33 -> 617.70502 | ... AL26: =AK25*Assumptions!$F$33 -> 4845.8612 | AM26: =SUM(C26:AL26) -> 68320.47
A27: Repeat orders from one-time buyers | B27: # | C27: =0 -> 0 | D27: =C24*Assumptions!$F$34 -> 0 | E27: =D24*Assumptions!$F$34 -> 210 | F27: =E24*Assumptions!$F$34 -> 248.77201 | G27: =F24*Assumptions!$F$34 -> 251.70553 | H27: =G24*Assumptions!$F$34 -> 255.64063 | I27: =H24*Assumptions!$F$34 -> 272.84067 | J27: =I24*Assumptions!$F$34 -> 287.62415 | K27: =J24*Assumptions!$F$34 -> 303.37021 | ... AL27: =AK24*Assumptions!$F$34 -> 1236.1337 | AM27: =SUM(C27:AL27) -> 21221.365
A28: Non-Rx orders shipped | B28: # | C28: =C24+C25+C27 -> 0 | D28: =D24+D25+D27 -> 3000 | E28: =E24+E25+E27 -> 5181.3858 | F28: =F24+F25+F27 -> 6863.3139 | G28: =G24+G25+G27 -> 8455.4443 | H28: =H24+H25+H27 -> 10180.323 | I28: =I24+I25+I27 -> 11918.908 | J28: =J24+J25+J27 -> 13685.555 | ... AL28: =AL24+AL25+AL27 -> 102530.45 | AM28: =SUM(C28:AL28) -> 1516287.2
A29: Non-Rx gross revenue | B29: $ | C29: =C28*Assumptions!$F$31 -> 0 | D29: =D28*Assumptions!$F$31 -> 264000 | E29: =E28*Assumptions!$F$31 -> 455961.95 | F29: =F28*Assumptions!$F$31 -> 603971.62 | G29: =G28*Assumptions!$F$31 -> 744079.1 | H29: =H28*Assumptions!$F$31 -> 895868.45 | I29: =I28*Assumptions!$F$31 -> 1048863.9 | J29: =J28*Assumptions!$F$31 -> 1204328.8 | ... AL29: =AL28*Assumptions!$F$31 -> 9022679.5 | AM29: =SUM(C29:AL29) -> 1.3343328e+08
A30: Non-Rx refunds and chargebacks | B30: $ | C30: =-C29*Assumptions!$F$61 -> 0 | D30: =-D29*Assumptions!$F$61 -> -5808 | E30: =-E29*Assumptions!$F$61 -> -10031.163 | F30: =-F29*Assumptions!$F$61 -> -13287.376 | G30: =-G29*Assumptions!$F$61 -> -16369.74 | H30: =-H29*Assumptions!$F$61 -> -19709.106 | I30: =-I29*Assumptions!$F$61 -> -23075.005 | J30: =-J29*Assumptions!$F$61 -> -26495.234 | ... AL30: =-AL29*Assumptions!$F$61 -> -198498.95 | AM30: =SUM(C30:AL30) -> -2935532.1
A31: Non-Rx net revenue | B31: $ | C31: =C29+C30 -> 0 | D31: =D29+D30 -> 258192 | E31: =E29+E30 -> 445930.79 | F31: =F29+F30 -> 590684.24 | G31: =G29+G30 -> 727709.36 | H31: =H29+H30 -> 876159.34 | I31: =I29+I30 -> 1025788.9 | J31: =J29+J30 -> 1177833.6 | ... AL31: =AL29+AL30 -> 8824180.6 | AM31: =SUM(C31:AL31) -> 1.3049774e+08
A32: Non-Rx product COGS | B32: $ | C32: =-C29*Assumptions!$F$36 -> 0 | D32: =-D29*Assumptions!$F$36 -> -58080 | E32: =-E29*Assumptions!$F$36 -> -100311.63 | F32: =-F29*Assumptions!$F$36 -> -132873.76 | G32: =-G29*Assumptions!$F$36 -> -163697.4 | H32: =-H29*Assumptions!$F$36 -> -197091.06 | I32: =-I29*Assumptions!$F$36 -> -230750.05 | J32: =-J29*Assumptions!$F$36 -> -264952.34 | ... AL32: =-AL29*Assumptions!$F$36 -> -1984989.5 | AM32: =SUM(C32:AL32) -> -29355321
A33: Non-Rx pick, pack and ship | B33: $ | C33: =-C28*Assumptions!$F$37 -> 0 | D33: =-D28*Assumptions!$F$37 -> -19500 | E33: =-E28*Assumptions!$F$37 -> -33679.008 | F33: =-F28*Assumptions!$F$37 -> -44611.54 | G33: =-G28*Assumptions!$F$37 -> -54960.388 | H33: =-H28*Assumptions!$F$37 -> -66172.101 | I33: =-I28*Assumptions!$F$37 -> -77472.9 | J33: =-J28*Assumptions!$F$37 -> -88956.105 | ... AL33: =-AL28*Assumptions!$F$37 -> -666447.92 | AM33: =SUM(C33:AL33) -> -9855866.9
A34: Non-Rx payment processing | B34: $ | C34: =-C31*Assumptions!$F$60 -> 0 | D34: =-D31*Assumptions!$F$60 -> -6971.184 | E34: =-E31*Assumptions!$F$60 -> -12040.131 | F34: =-F31*Assumptions!$F$60 -> -15948.475 | G34: =-G31*Assumptions!$F$60 -> -19648.153 | H34: =-H31*Assumptions!$F$60 -> -23656.302 | I34: =-I31*Assumptions!$F$60 -> -27696.299 | J34: =-J31*Assumptions!$F$60 -> -31801.507 | ... AL34: =-AL31*Assumptions!$F$60 -> -238252.88 | AM34: =SUM(C34:AL34) -> -3523439.1
A35: Non-Rx gross profit | B35: $ | C35: =C31+C32+C33+C34 -> 0 | D35: =D31+D32+D33+D34 -> 173640.82 | E35: =E31+E32+E33+E34 -> 299900.02 | F35: =F31+F32+F33+F34 -> 397250.47 | G35: =G31+G32+G33+G34 -> 489403.42 | H35: =H31+H32+H33+H34 -> 589239.88 | I35: =I31+I32+I33+I34 -> 689869.62 | J35: =J31+J32+J33+J34 -> 792123.63 | ... AL35: =AL31+AL32+AL33+AL34 -> 5934490.3 | AM35: =SUM(C35:AL35) -> 87763117
A36: Non-Rx gross margin | B36: % | C36: =IFERROR(C35/C31,0) -> 0 | D36: =IFERROR(D35/D31,0) -> 0.67252593 | E36: =IFERROR(E35/E31,0) -> 0.67252593 | F36: =IFERROR(F35/F31,0) -> 0.67252593 | G36: =IFERROR(G35/G31,0) -> 0.67252593 | H36: =IFERROR(H35/H31,0) -> 0.67252593 | I36: =IFERROR(I35/I31,0) -> 0.67252593 | J36: =IFERROR(J35/J31,0) -> 0.67252593 | ... AL36: =IFERROR(AL35/AL31,0) -> 0.67252593 | AM36: =AVERAGE(N36:AL36) -> 0.67252593
A37: US population covered by served states | B37: % | C37: =IF(C9=0,0,MIN(Assumptions!$F$44,Assumptions!$F$42+Assumptions!$F$43*(C$5-Assumptions!$F$7))) -> 0 | D37: =IF(D9=0,0,MIN(Assumptions!$F$44,Assumptions!$F$42+Assumptions!$F$43*(D$5-Assumptions!$F$7))) -> 0 | E37: =IF(E9=0,0,MIN(Assumptions!$F$44,Assumptions!$F$42+Assumptions!$F$43*(E$5-Assumptions!$F$7))) -> 0 | F37: =IF(F9=0,0,MIN(Assumptions!$F$44,Assumptions!$F$42+Assumptions!$F$43*(F$5-Assumptions!$F$7))) -> 0 | G37: =IF(G9=0,0,MIN(Assumptions!$F$44,Assumptions!$F$42+Assumptions!$F$43*(G$5-Assumptions!$F$7))) -> 0.45 | H37: =IF(H9=0,0,MIN(Assumptions!$F$44,Assumptions!$F$42+Assumptions!$F$43*(H$5-Assumptions!$F$7))) -> 0.485 | I37: =IF(I9=0,0,MIN(Assumptions!$F$44,Assumptions!$F$42+Assumptions!$F$43*(I$5-Assumptions!$F$7))) -> 0.52 | J37: =IF(J9=0,0,MIN(Assumptions!$F$44,Assumptions!$F$42+Assumptions!$F$43*(J$5-Assumptions!$F$7))) -> 0.555 | ... AL37: =IF(AL9=0,0,MIN(Assumptions!$F$44,Assumptions!$F$42+Assumptions!$F$43*(AL$5-Assumptions!$F$7))) -> 0.88 | AM37: =AL37 -> 0.88
A38: Eligibility quiz starts | B38: # | C38: =C18*Assumptions!$F$39*C9 -> 0 | D38: =D18*Assumptions!$F$39*D9 -> 0 | E38: =E18*Assumptions!$F$39*E9 -> 0 | F38: =F18*Assumptions!$F$39*F9 -> 0 | G38: =G18*Assumptions!$F$39*G9 -> 4805.2751 | H38: =H18*Assumptions!$F$39*H9 -> 5128.584 | I38: =I18*Assumptions!$F$39*I9 -> 5406.4689 | J38: =J18*Assumptions!$F$39*J9 -> 5702.4476 | ... AL38: =AL18*Assumptions!$F$39*AL9 -> 23728.433 | AM38: =SUM(C38:AL38) -> 409271.42
A39: Quiz completions | B39: # | C39: =C38*Assumptions!$F$40 -> 0 | D39: =D38*Assumptions!$F$40 -> 0 | E39: =E38*Assumptions!$F$40 -> 0 | F39: =F38*Assumptions!$F$40 -> 0 | G39: =G38*Assumptions!$F$40 -> 3652.0091 | H39: =H38*Assumptions!$F$40 -> 3897.7238 | I39: =I38*Assumptions!$F$40 -> 4108.9164 | J39: =J38*Assumptions!$F$40 -> 4333.8602 | ... AL39: =AL38*Assumptions!$F$40 -> 18033.609 | AM39: =SUM(C39:AL39) -> 311046.28
A40: Eligible outcomes (clinical screen and state) | B40: # | C40: =C39*Assumptions!$F$41*C37 -> 0 | D40: =D39*Assumptions!$F$41*D37 -> 0 | E40: =E39*Assumptions!$F$41*E37 -> 0 | F40: =F39*Assumptions!$F$41*F37 -> 0 | G40: =G39*Assumptions!$F$41*G37 -> 1051.7786 | H40: =H39*Assumptions!$F$41*H37 -> 1209.8535 | I40: =I39*Assumptions!$F$41*I37 -> 1367.4474 | J40: =J39*Assumptions!$F$41*J37 -> 1539.3871 | ... AL40: =AL39*Assumptions!$F$41*AL37 -> 10156.529 | AM40: =SUM(C40:AL40) -> 166771.72
A41: Intakes submitted (consult fee charged) | B41: # | C41: =C40*Assumptions!$F$45 -> 0 | D41: =D40*Assumptions!$F$45 -> 0 | E41: =E40*Assumptions!$F$45 -> 0 | F41: =F40*Assumptions!$F$45 -> 0 | G41: =G40*Assumptions!$F$45 -> 652.10274 | H41: =H40*Assumptions!$F$45 -> 750.10915 | I41: =I40*Assumptions!$F$45 -> 847.81737 | J41: =J40*Assumptions!$F$45 -> 954.42003 | ... AL41: =AL40*Assumptions!$F$45 -> 6297.0478 | AM41: =SUM(C41:AL41) -> 103398.47
A42: Consults completed | B42: # | C42: =C41*Assumptions!$F$46 -> 0 | D42: =D41*Assumptions!$F$46 -> 0 | E42: =E41*Assumptions!$F$46 -> 0 | F42: =F41*Assumptions!$F$46 -> 0 | G42: =G41*Assumptions!$F$46 -> 573.85041 | H42: =H41*Assumptions!$F$46 -> 660.09605 | I42: =I41*Assumptions!$F$46 -> 746.07928 | J42: =J41*Assumptions!$F$46 -> 839.88963 | ... AL42: =AL41*Assumptions!$F$46 -> 5541.4021 | AM42: =SUM(C42:AL42) -> 90990.651
A43: Prescriptions issued (clinician decision) | B43: # | C43: =C42*Assumptions!$F$47 -> 0 | D43: =D42*Assumptions!$F$47 -> 0 | E43: =E42*Assumptions!$F$47 -> 0 | F43: =F42*Assumptions!$F$47 -> 0 | G43: =G42*Assumptions!$F$47 -> 390.21828 | H43: =H42*Assumptions!$F$47 -> 448.86532 | I43: =I42*Assumptions!$F$47 -> 507.33391 | J43: =J42*Assumptions!$F$47 -> 571.12495 | ... AL43: =AL42*Assumptions!$F$47 -> 3768.1534 | AM43: =SUM(C43:AL43) -> 61873.643
A44: New paying programme members | B44: # | C44: =C43*Assumptions!$F$48 -> 0 | D44: =D43*Assumptions!$F$48 -> 0 | E44: =E43*Assumptions!$F$48 -> 0 | F44: =F43*Assumptions!$F$48 -> 0 | G44: =G43*Assumptions!$F$48 -> 273.15279 | H44: =H43*Assumptions!$F$48 -> 314.20572 | I44: =I43*Assumptions!$F$48 -> 355.13374 | J44: =J43*Assumptions!$F$48 -> 399.78746 | ... AL44: =AL43*Assumptions!$F$48 -> 2637.7074 | AM44: =SUM(C44:AL44) -> 43311.55
A45: Active programme members (end of month) | B45: # | C45: =C44 -> 0 | D45: =C45*(1-Assumptions!$F$49)+D44 -> 0 | E45: =D45*(1-Assumptions!$F$49)+E44 -> 0 | F45: =E45*(1-Assumptions!$F$49)+F44 -> 0 | G45: =F45*(1-Assumptions!$F$49)+G44 -> 273.15279 | H45: =G45*(1-Assumptions!$F$49)+H44 -> 561.409 | I45: =H45*(1-Assumptions!$F$49)+I44 -> 863.20888 | J45: =I45*(1-Assumptions!$F$49)+J44 -> 1180.9915 | K45: =J45*(1-Assumptions!$F$49)+K44 -> 1517.505 | ... AL45: =AK45*(1-Assumptions!$F$49)+AL44 -> 19788.646 | AM45: =AL45 -> 19788.646
A46: Programme members churned | B46: # | C46: =0 -> 0 | D46: =C45*Assumptions!$F$49 -> 0 | E46: =D45*Assumptions!$F$49 -> 0 | F46: =E45*Assumptions!$F$49 -> 0 | G46: =F45*Assumptions!$F$49 -> 0 | H46: =G45*Assumptions!$F$49 -> 25.949516 | I46: =H45*Assumptions!$F$49 -> 53.333855 | J46: =I45*Assumptions!$F$49 -> 82.004844 | K46: =J45*Assumptions!$F$49 -> 112.19419 | ... AL46: =AK45*Assumptions!$F$49 -> 1800.3748 | AM46: =SUM(C46:AL46) -> 23522.904
A47: Programme subscription revenue | B47: $ | C47: =C45*Assumptions!$F$51 -> 0 | D47: =D45*Assumptions!$F$51 -> 0 | E47: =E45*Assumptions!$F$51 -> 0 | F47: =F45*Assumptions!$F$51 -> 0 | G47: =G45*Assumptions!$F$51 -> 81672.686 | H47: =H45*Assumptions!$F$51 -> 167861.29 | I47: =I45*Assumptions!$F$51 -> 258099.46 | J47: =J45*Assumptions!$F$51 -> 353116.46 | ... AL47: =AL45*Assumptions!$F$51 -> 5916805.1 | AM47: =SUM(C47:AL47) -> 79952050
A48: Consultation fee revenue | B48: $ | C48: =C41*Assumptions!$F$52 -> 0 | D48: =D41*Assumptions!$F$52 -> 0 | E48: =E41*Assumptions!$F$52 -> 0 | F48: =F41*Assumptions!$F$52 -> 0 | G48: =G41*Assumptions!$F$52 -> 51516.116 | H48: =H41*Assumptions!$F$52 -> 59258.623 | I48: =I41*Assumptions!$F$52 -> 66977.572 | J48: =J41*Assumptions!$F$52 -> 75399.182 | ... AL48: =AL41*Assumptions!$F$52 -> 497466.78 | AM48: =SUM(C48:AL48) -> 8168478.9
A49: Rx gross revenue | B49: $ | C49: =C47+C48 -> 0 | D49: =D47+D48 -> 0 | E49: =E47+E48 -> 0 | F49: =F47+F48 -> 0 | G49: =G47+G48 -> 133188.8 | H49: =H47+H48 -> 227119.91 | I49: =I47+I48 -> 325077.03 | J49: =J47+J48 -> 428515.64 | ... AL49: =AL47+AL48 -> 6414271.9 | AM49: =SUM(C49:AL49) -> 88120529
A50: Rx refunds and chargebacks | B50: $ | C50: =-C49*Assumptions!$F$61 -> 0 | D50: =-D49*Assumptions!$F$61 -> 0 | E50: =-E49*Assumptions!$F$61 -> 0 | F50: =-F49*Assumptions!$F$61 -> 0 | G50: =-G49*Assumptions!$F$61 -> -2930.1536 | H50: =-H49*Assumptions!$F$61 -> -4996.6381 | I50: =-I49*Assumptions!$F$61 -> -7151.6946 | J50: =-J49*Assumptions!$F$61 -> -9427.3441 | ... AL50: =-AL49*Assumptions!$F$61 -> -141113.98 | AM50: =SUM(C50:AL50) -> -1938651.6
A51: Rx net revenue | B51: $ | C51: =C49+C50 -> 0 | D51: =D49+D50 -> 0 | E51: =E49+E50 -> 0 | F51: =F49+F50 -> 0 | G51: =G49+G50 -> 130258.65 | H51: =H49+H50 -> 222123.28 | I51: =I49+I50 -> 317925.33 | J51: =J49+J50 -> 419088.3 | ... AL51: =AL49+AL50 -> 6273157.9 | AM51: =SUM(C51:AL51) -> 86181878
A52: Pharmacy medication cost | B52: $ | C52: =-C45*Assumptions!$F$54 -> 0 | D52: =-D45*Assumptions!$F$54 -> 0 | E52: =-E45*Assumptions!$F$54 -> 0 | F52: =-F45*Assumptions!$F$54 -> 0 | G52: =-G45*Assumptions!$F$54 -> -20486.46 | H52: =-H45*Assumptions!$F$54 -> -42105.675 | I52: =-I45*Assumptions!$F$54 -> -64740.666 | J52: =-J45*Assumptions!$F$54 -> -88574.363 | ... AL52: =-AL45*Assumptions!$F$54 -> -1484148.4 | AM52: =SUM(C52:AL52) -> -20054862
A53: Clinician cost, new consults | B53: $ | C53: =-C42*Assumptions!$F$55 -> 0 | D53: =-D42*Assumptions!$F$55 -> 0 | E53: =-E42*Assumptions!$F$55 -> 0 | F53: =-F42*Assumptions!$F$55 -> 0 | G53: =-G42*Assumptions!$F$55 -> -18363.213 | H53: =-H42*Assumptions!$F$55 -> -21123.074 | I53: =-I42*Assumptions!$F$55 -> -23874.537 | J53: =-J42*Assumptions!$F$55 -> -26876.468 | ... AL53: =-AL42*Assumptions!$F$55 -> -177324.87 | AM53: =SUM(C53:AL53) -> -2911700.8
A54: Clinician cost, monitoring and refills | B54: $ | C54: =-C45*Assumptions!$F$56 -> 0 | D54: =-D45*Assumptions!$F$56 -> 0 | E54: =-E45*Assumptions!$F$56 -> 0 | F54: =-F45*Assumptions!$F$56 -> 0 | G54: =-G45*Assumptions!$F$56 -> -1775.4932 | H54: =-H45*Assumptions!$F$56 -> -3649.1585 | I54: =-I45*Assumptions!$F$56 -> -5610.8578 | J54: =-J45*Assumptions!$F$56 -> -7676.4448 | ... AL54: =-AL45*Assumptions!$F$56 -> -128626.2 | AM54: =SUM(C54:AL54) -> -1738088.1
A55: Cold-chain fulfilment and shipping | B55: $ | C55: =-C45*Assumptions!$F$57 -> 0 | D55: =-D45*Assumptions!$F$57 -> 0 | E55: =-E45*Assumptions!$F$57 -> 0 | F55: =-F45*Assumptions!$F$57 -> 0 | G55: =-G45*Assumptions!$F$57 -> -4097.2919 | H55: =-H45*Assumptions!$F$57 -> -8421.135 | I55: =-I45*Assumptions!$F$57 -> -12948.133 | J55: =-J45*Assumptions!$F$57 -> -17714.873 | ... AL55: =-AL45*Assumptions!$F$57 -> -296829.69 | AM55: =SUM(C55:AL55) -> -4010972.4
A56: Rx support cost | B56: $ | C56: =-C45*Assumptions!$F$58 -> 0 | D56: =-D45*Assumptions!$F$58 -> 0 | E56: =-E45*Assumptions!$F$58 -> 0 | F56: =-F45*Assumptions!$F$58 -> 0 | G56: =-G45*Assumptions!$F$58 -> -956.03478 | H56: =-H45*Assumptions!$F$58 -> -1964.9315 | I56: =-I45*Assumptions!$F$58 -> -3021.2311 | J56: =-J45*Assumptions!$F$58 -> -4133.4703 | ... AL56: =-AL45*Assumptions!$F$58 -> -69260.261 | AM56: =SUM(C56:AL56) -> -935893.57
A57: Rx payment processing | B57: $ | C57: =-C51*Assumptions!$F$60 -> 0 | D57: =-D51*Assumptions!$F$60 -> 0 | E57: =-E51*Assumptions!$F$60 -> 0 | F57: =-F51*Assumptions!$F$60 -> 0 | G57: =-G51*Assumptions!$F$60 -> -3516.9835 | H57: =-H51*Assumptions!$F$60 -> -5997.3285 | I57: =-I51*Assumptions!$F$60 -> -8583.984 | J57: =-J51*Assumptions!$F$60 -> -11315.384 | ... AL57: =-AL51*Assumptions!$F$60 -> -169375.26 | AM57: =SUM(C57:AL57) -> -2326910.7
A58: Rx gross profit | B58: $ | C58: =C51+C52+C53+C54+C55+C56+C57 -> 0 | D58: =D51+D52+D53+D54+D55+D56+D57 -> 0 | E58: =E51+E52+E53+E54+E55+E56+E57 -> 0 | F58: =F51+F52+F53+F54+F55+F56+F57 -> 0 | G58: =G51+G52+G53+G54+G55+G56+G57 -> 81063.172 | H58: =H51+H52+H53+H54+H55+H56+H57 -> 138861.97 | I58: =I51+I52+I53+I54+I55+I56+I57 -> 199145.92 | J58: =J51+J52+J53+J54+J55+J56+J57 -> 262797.3 | ... AL58: =AL51+AL52+AL53+AL54+AL55+AL56+AL57 -> 3947593.2 | AM58: =SUM(C58:AL58) -> 54203450
A59: Rx gross margin | B59: % | C59: =IFERROR(C58/C51,0) -> 0 | D59: =IFERROR(D58/D51,0) -> 0 | E59: =IFERROR(E58/E51,0) -> 0 | F59: =IFERROR(F58/F51,0) -> 0 | G59: =IFERROR(G58/G51,0) -> 0.62232468 | H59: =IFERROR(H58/H51,0) -> 0.62515724 | I59: =IFERROR(I58/I51,0) -> 0.62639212 | J59: =IFERROR(J58/J51,0) -> 0.62706904 | ... AL59: =IFERROR(AL58/AL51,0) -> 0.62928325 | AM59: =AVERAGE(N59:AL59) -> 0.62885761
A60: TOTAL NET REVENUE | B60: $ | C60: =C31+C51 -> 0 | D60: =D31+D51 -> 258192 | E60: =E31+E51 -> 445930.79 | F60: =F31+F51 -> 590684.24 | G60: =G31+G51 -> 857968.01 | H60: =H31+H51 -> 1098282.6 | I60: =I31+I51 -> 1343714.2 | J60: =J31+J51 -> 1596921.9 | ... AL60: =AL31+AL51 -> 15097339 | AM60: =SUM(C60:AL60) -> 2.1667962e+08
A61: TOTAL GROSS PROFIT | B61: $ | C61: =C35+C58 -> 0 | D61: =D35+D58 -> 173640.82 | E61: =E35+E58 -> 299900.02 | F61: =F35+F58 -> 397250.47 | G61: =G35+G58 -> 570466.59 | H61: =H35+H58 -> 728101.86 | I61: =I35+I58 -> 889015.54 | J61: =J35+J58 -> 1054920.9 | ... AL61: =AL35+AL58 -> 9882083.5 | AM61: =SUM(C61:AL61) -> 1.4196657e+08
A62: Blended gross margin | B62: % | C62: =IFERROR(C61/C60,0) -> 0 | D62: =IFERROR(D61/D60,0) -> 0.67252593 | E62: =IFERROR(E61/E60,0) -> 0.67252593 | F62: =IFERROR(F61/F60,0) -> 0.67252593 | G62: =IFERROR(G61/G60,0) -> 0.66490427 | H62: =IFERROR(H61/H60,0) -> 0.6629458 | I62: =IFERROR(I61/I60,0) -> 0.66161059 | J62: =IFERROR(J61/J60,0) -> 0.66059645 | ... AL62: =IFERROR(AL61/AL60,0) -> 0.65455799 | AM62: =AVERAGE(N62:AL62) -> 0.65514356
A63: Provider flat fee | B63: $ | C63: =-Assumptions!$F$63 -> -600 | D63: =-Assumptions!$F$63 -> -600 | E63: =-Assumptions!$F$63 -> -600 | F63: =-Assumptions!$F$63 -> -600 | G63: =-Assumptions!$F$63 -> -600 | H63: =-Assumptions!$F$63 -> -600 | I63: =-Assumptions!$F$63 -> -600 | J63: =-Assumptions!$F$63 -> -600 | ... AL63: =-Assumptions!$F$63 -> -600 | AM63: =SUM(C63:AL63) -> -21600
A64: Certification and registrations | B64: $ | C64: =-Assumptions!$F$64 -> -260 | D64: =-Assumptions!$F$64 -> -260 | E64: =-Assumptions!$F$64 -> -260 | F64: =-Assumptions!$F$64 -> -260 | G64: =-Assumptions!$F$64 -> -260 | H64: =-Assumptions!$F$64 -> -260 | I64: =-Assumptions!$F$64 -> -260 | J64: =-Assumptions!$F$64 -> -260 | ... AL64: =-Assumptions!$F$64 -> -260 | AM64: =SUM(C64:AL64) -> -9360
A65: Team | B65: $ | C65: =-IF(C8=0,Assumptions!$F$65,IF(C$5<=12,Assumptions!$F$66,IF(C$5<=24,Assumptions!$F$67,Assumptions!$F$68))) -> -25000 | D65: =-IF(D8=0,Assumptions!$F$65,IF(D$5<=12,Assumptions!$F$66,IF(D$5<=24,Assumptions!$F$67,Assumptions!$F$68))) -> -70000 | E65: =-IF(E8=0,Assumptions!$F$65,IF(E$5<=12,Assumptions!$F$66,IF(E$5<=24,Assumptions!$F$67,Assumptions!$F$68))) -> -70000 | F65: =-IF(F8=0,Assumptions!$F$65,IF(F$5<=12,Assumptions!$F$66,IF(F$5<=24,Assumptions!$F$67,Assumptions!$F$68))) -> -70000 | G65: =-IF(G8=0,Assumptions!$F$65,IF(G$5<=12,Assumptions!$F$66,IF(G$5<=24,Assumptions!$F$67,Assumptions!$F$68))) -> -70000 | H65: =-IF(H8=0,Assumptions!$F$65,IF(H$5<=12,Assumptions!$F$66,IF(H$5<=24,Assumptions!$F$67,Assumptions!$F$68))) -> -70000 | I65: =-IF(I8=0,Assumptions!$F$65,IF(I$5<=12,Assumptions!$F$66,IF(I$5<=24,Assumptions!$F$67,Assumptions!$F$68))) -> -70000 | J65: =-IF(J8=0,Assumptions!$F$65,IF(J$5<=12,Assumptions!$F$66,IF(J$5<=24,Assumptions!$F$67,Assumptions!$F$68))) -> -70000 | ... AL65: =-IF(AL8=0,Assumptions!$F$65,IF(AL$5<=12,Assumptions!$F$66,IF(AL$5<=24,Assumptions!$F$67,Assumptions!$F$68))) -> -230000 | AM65: =SUM(C65:AL65) -> -5235000
A66: Medical director and clinical oversight | B66: $ | C66: =-IF(C$5>=Assumptions!$F$7-2,Assumptions!$F$69,0) -> 0 | D66: =-IF(D$5>=Assumptions!$F$7-2,Assumptions!$F$69,0) -> 0 | E66: =-IF(E$5>=Assumptions!$F$7-2,Assumptions!$F$69,0) -> -14000 | F66: =-IF(F$5>=Assumptions!$F$7-2,Assumptions!$F$69,0) -> -14000 | G66: =-IF(G$5>=Assumptions!$F$7-2,Assumptions!$F$69,0) -> -14000 | H66: =-IF(H$5>=Assumptions!$F$7-2,Assumptions!$F$69,0) -> -14000 | I66: =-IF(I$5>=Assumptions!$F$7-2,Assumptions!$F$69,0) -> -14000 | J66: =-IF(J$5>=Assumptions!$F$7-2,Assumptions!$F$69,0) -> -14000 | ... AL66: =-IF(AL$5>=Assumptions!$F$7-2,Assumptions!$F$69,0) -> -14000 | AM66: =SUM(C66:AL66) -> -476000
A67: Technology and software | B67: $ | C67: =-Assumptions!$F$70 -> -4000 | D67: =-Assumptions!$F$70 -> -4000 | E67: =-Assumptions!$F$70 -> -4000 | F67: =-Assumptions!$F$70 -> -4000 | G67: =-Assumptions!$F$70 -> -4000 | H67: =-Assumptions!$F$70 -> -4000 | I67: =-Assumptions!$F$70 -> -4000 | J67: =-Assumptions!$F$70 -> -4000 | ... AL67: =-Assumptions!$F$70 -> -4000 | AM67: =SUM(C67:AL67) -> -144000
A68: Legal, regulatory and compliance | B68: $ | C68: =-IF(C$5<=4,Assumptions!$F$71,Assumptions!$F$72) -> -32000 | D68: =-IF(D$5<=4,Assumptions!$F$71,Assumptions!$F$72) -> -32000 | E68: =-IF(E$5<=4,Assumptions!$F$71,Assumptions!$F$72) -> -32000 | F68: =-IF(F$5<=4,Assumptions!$F$71,Assumptions!$F$72) -> -32000 | G68: =-IF(G$5<=4,Assumptions!$F$71,Assumptions!$F$72) -> -12000 | H68: =-IF(H$5<=4,Assumptions!$F$71,Assumptions!$F$72) -> -12000 | I68: =-IF(I$5<=4,Assumptions!$F$71,Assumptions!$F$72) -> -12000 | J68: =-IF(J$5<=4,Assumptions!$F$71,Assumptions!$F$72) -> -12000 | ... AL68: =-IF(AL$5<=4,Assumptions!$F$71,Assumptions!$F$72) -> -12000 | AM68: =SUM(C68:AL68) -> -512000
A69: Insurance | B69: $ | C69: =-C8*Assumptions!$F$73 -> 0 | D69: =-D8*Assumptions!$F$73 -> -5000 | E69: =-E8*Assumptions!$F$73 -> -5000 | F69: =-F8*Assumptions!$F$73 -> -5000 | G69: =-G8*Assumptions!$F$73 -> -5000 | H69: =-H8*Assumptions!$F$73 -> -5000 | I69: =-I8*Assumptions!$F$73 -> -5000 | J69: =-J8*Assumptions!$F$73 -> -5000 | ... AL69: =-AL8*Assumptions!$F$73 -> -5000 | AM69: =SUM(C69:AL69) -> -175000
A70: Creative and content | B70: $ | C70: =-Assumptions!$F$74 -> -26000 | D70: =-Assumptions!$F$74 -> -26000 | E70: =-Assumptions!$F$74 -> -26000 | F70: =-Assumptions!$F$74 -> -26000 | G70: =-Assumptions!$F$74 -> -26000 | H70: =-Assumptions!$F$74 -> -26000 | I70: =-Assumptions!$F$74 -> -26000 | J70: =-Assumptions!$F$74 -> -26000 | ... AL70: =-Assumptions!$F$74 -> -26000 | AM70: =SUM(C70:AL70) -> -936000
A71: Paid media | B71: $ | C71: =-C15 -> -15000 | D71: =-D15 -> -60000 | E71: =-E15 -> -60000 | F71: =-F15 -> -89186.157 | G71: =-G15 -> -118136.85 | H71: =-H15 -> -171593.6 | I71: =-I15 -> -219656.52 | J71: =-J15 -> -268742.84 | ... AL71: =-AL15 -> -2500000 | AM71: =SUM(C71:AL71) -> -39609379
A72: One-time launch marketing and PR | B72: $ | C72: =-IF(C$5=Assumptions!$F$6,Assumptions!$F$24,0) -> 0 | D72: =-IF(D$5=Assumptions!$F$6,Assumptions!$F$24,0) -> -400000 | E72: =-IF(E$5=Assumptions!$F$6,Assumptions!$F$24,0) -> 0 | F72: =-IF(F$5=Assumptions!$F$6,Assumptions!$F$24,0) -> 0 | G72: =-IF(G$5=Assumptions!$F$6,Assumptions!$F$24,0) -> 0 | H72: =-IF(H$5=Assumptions!$F$6,Assumptions!$F$24,0) -> 0 | I72: =-IF(I$5=Assumptions!$F$6,Assumptions!$F$24,0) -> 0 | J72: =-IF(J$5=Assumptions!$F$6,Assumptions!$F$24,0) -> 0 | ... AL72: =-IF(AL$5=Assumptions!$F$6,Assumptions!$F$24,0) -> 0 | AM72: =SUM(C72:AL72) -> -400000
A73: Partner cash retainer | B73: $ | C73: =-C8*Assumptions!$F$76 -> 0 | D73: =-D8*Assumptions!$F$76 -> -25000 | E73: =-E8*Assumptions!$F$76 -> -25000 | F73: =-F8*Assumptions!$F$76 -> -25000 | G73: =-G8*Assumptions!$F$76 -> -25000 | H73: =-H8*Assumptions!$F$76 -> -25000 | I73: =-I8*Assumptions!$F$76 -> -25000 | J73: =-J8*Assumptions!$F$76 -> -25000 | ... AL73: =-AL8*Assumptions!$F$76 -> -25000 | AM73: =SUM(C73:AL73) -> -875000
A74: Partner royalty on net revenue | B74: $ | C74: =-C60*Assumptions!$F$77 -> 0 | D74: =-D60*Assumptions!$F$77 -> -12909.6 | E74: =-E60*Assumptions!$F$77 -> -22296.539 | F74: =-F60*Assumptions!$F$77 -> -29534.212 | G74: =-G60*Assumptions!$F$77 -> -42898.4 | H74: =-H60*Assumptions!$F$77 -> -54914.131 | I74: =-I60*Assumptions!$F$77 -> -67185.71 | J74: =-J60*Assumptions!$F$77 -> -79846.094 | ... AL74: =-AL60*Assumptions!$F$77 -> -754866.93 | AM74: =SUM(C74:AL74) -> -10833981
A75: TOTAL OPERATING EXPENSE | B75: $ | C75: =C63+C64+C65+C66+C67+C68+C69+C70+C71+C72+C73+C74 -> -102860 | D75: =D63+D64+D65+D66+D67+D68+D69+D70+D71+D72+D73+D74 -> -635769.6 | E75: =E63+E64+E65+E66+E67+E68+E69+E70+E71+E72+E73+E74 -> -259156.54 | F75: =F63+F64+F65+F66+F67+F68+F69+F70+F71+F72+F73+F74 -> -295580.37 | G75: =G63+G64+G65+G66+G67+G68+G69+G70+G71+G72+G73+G74 -> -317895.25 | H75: =H63+H64+H65+H66+H67+H68+H69+H70+H71+H72+H73+H74 -> -383367.73 | I75: =I63+I64+I65+I66+I67+I68+I69+I70+I71+I72+I73+I74 -> -443702.23 | J75: =J63+J64+J65+J66+J67+J68+J69+J70+J71+J72+J73+J74 -> -505448.93 | ... AL75: =AL63+AL64+AL65+AL66+AL67+AL68+AL69+AL70+AL71+AL72+AL73+AL74 -> -3571726.9 | AM75: =SUM(C75:AL75) -> -59227320
A76: EBITDA | B76: $ | C76: =C61+C75 -> -102860 | D76: =D61+D75 -> -462128.78 | E76: =E61+E75 -> 40743.479 | F76: =F61+F75 -> 101670.1 | G76: =G61+G75 -> 252571.34 | H76: =H61+H75 -> 344734.12 | I76: =I61+I75 -> 445313.31 | J76: =J61+J75 -> 549471.99 | ... AL76: =AL61+AL75 -> 6310356.6 | AM76: =SUM(C76:AL76) -> 82739247
A77: EBITDA margin | B77: % | C77: =IFERROR(C76/C60,0) -> 0 | D77: =IFERROR(D76/D60,0) -> -1.7898648 | E77: =IFERROR(E76/E60,0) -> 0.091367272 | F77: =IFERROR(F76/F60,0) -> 0.17212259 | G77: =IFERROR(G76/G60,0) -> 0.29438317 | H77: =IFERROR(H76/H60,0) -> 0.31388471 | I77: =IFERROR(I76/I60,0) -> 0.33140478 | J77: =IFERROR(J76/J60,0) -> 0.34408195 | ... AL77: =IFERROR(AL76/AL60,0) -> 0.41797808 | AM77: =AVERAGE(N77:AL77) -> 0.38276953
A78: Non-Rx inventory balance | B78: $ | C78: =-C32*Assumptions!$F$80 -> 0 | D78: =-D32*Assumptions!$F$80 -> 116160 | E78: =-E32*Assumptions!$F$80 -> 200623.26 | F78: =-F32*Assumptions!$F$80 -> 265747.51 | G78: =-G32*Assumptions!$F$80 -> 327394.8 | H78: =-H32*Assumptions!$F$80 -> 394182.12 | I78: =-I32*Assumptions!$F$80 -> 461500.1 | J78: =-J32*Assumptions!$F$80 -> 529904.68 | ... AL78: =-AL32*Assumptions!$F$80 -> 3969979 | AM78: =AL78 -> 3969979
A79: Inventory investment (increase in stock) | B79: $ | C79: =-C78 -> 0 | D79: =-(D78-C78) -> -116160 | E79: =-(E78-D78) -> -84463.258 | F79: =-(F78-E78) -> -65124.255 | G79: =-(G78-F78) -> -61647.291 | H79: =-(H78-G78) -> -66787.315 | I79: =-(I78-H78) -> -67317.986 | J79: =-(J78-I78) -> -68404.573 | K79: =-(K78-J78) -> -69956.713 | ... AL79: =-(AL78-AK78) -> -169655.56 | AM79: =SUM(C79:AL79) -> -3969979
A80: Net cash flow | B80: $ | C80: =C76+C79 -> -102860 | D80: =D76+D79 -> -578288.78 | E80: =E76+E79 -> -43719.778 | F80: =F76+F79 -> 36545.848 | G80: =G76+G79 -> 190924.05 | H80: =H76+H79 -> 277946.81 | I80: =I76+I79 -> 377995.32 | J80: =J76+J79 -> 481067.42 | ... AL80: =AL76+AL79 -> 6140701 | AM80: =SUM(C80:AL80) -> 78769268
A81: Cumulative cash flow | B81: $ | C81: =C80 -> -102860 | D81: =C81+D80 -> -681148.78 | E81: =D81+E80 -> -724868.56 | F81: =E81+F80 -> -688322.71 | G81: =F81+G80 -> -497398.67 | H81: =G81+H80 -> -219451.86 | I81: =H81+I80 -> 158543.46 | J81: =I81+J80 -> 639610.88 | K81: =J81+K80 -> 1227499.3 | ... AL81: =AK81+AL80 -> 78769268 | AM81: =AL81 -> 78769268
A82: Break-even helper (month if EBITDA positive, else 999) | B82: # | C82: =IF(C76>0,C$5,999) -> 999 | D82: =IF(D76>0,D$5,999) -> 999 | E82: =IF(E76>0,E$5,999) -> 3 | F82: =IF(F76>0,F$5,999) -> 4 | G82: =IF(G76>0,G$5,999) -> 5 | H82: =IF(H76>0,H$5,999) -> 6 | I82: =IF(I76>0,I$5,999) -> 7 | J82: =IF(J76>0,J$5,999) -> 8 | ... AL82: =IF(AL76>0,AL$5,999) -> 36
A83: New customers, both lines | B83: # | C83: =C21+C44 -> 0 | D83: =D21+D44 -> 3000 | E83: =E21+E44 -> 3553.8858 | F83: =F21+F44 -> 3595.7933 | G83: =G21+G44 -> 3925.1619 | H83: =H21+H44 -> 4211.9295 | I83: =I21+I44 -> 4464.0501 | J83: =J21+J44 -> 4733.6477 | ... AL83: =AL21+AL44 -> 20671.317 | AM83: =SUM(C83:AL83) -> 364507.51
A84: Blended CAC (paid media plus creative) | B84: $ | C84: =IFERROR((C15-C70)/C83,0) -> 0 | D84: =IFERROR((D15-D70)/D83,0) -> 28.666667 | E84: =IFERROR((E15-E70)/E83,0) -> 24.198864 | F84: =IFERROR((F15-F70)/F83,0) -> 32.033587 | G84: =IFERROR((G15-G70)/G83,0) -> 36.72125 | H84: =IFERROR((H15-H70)/H83,0) -> 46.912846 | I84: =IFERROR((I15-I70)/I83,0) -> 55.029966 | J84: =IFERROR((J15-J70)/J83,0) -> 62.265479 | ... AL84: =IFERROR((AL15-AL70)/AL83,0) -> 122.19831 | AM84: =AVERAGE(N84:AL84) -> 114.47825
A85: Rx contribution per member-month, steady state | B85: $ | C85: =Assumptions!$F$51*(1-Assumptions!$F$61)*(1-Assumptions!$F$60)-Assumptions!$F$54-Assumptions!$F$56-Assumptions!$F$57-Assumptions!$F$58 -> 184.52661 | D85: =Assumptions!$F$51*(1-Assumptions!$F$61)*(1-Assumptions!$F$60)-Assumptions!$F$54-Assumptions!$F$56-Assumptions!$F$57-Assumptions!$F$58 -> 184.52661 | E85: =Assumptions!$F$51*(1-Assumptions!$F$61)*(1-Assumptions!$F$60)-Assumptions!$F$54-Assumptions!$F$56-Assumptions!$F$57-Assumptions!$F$58 -> 184.52661 | F85: =Assumptions!$F$51*(1-Assumptions!$F$61)*(1-Assumptions!$F$60)-Assumptions!$F$54-Assumptions!$F$56-Assumptions!$F$57-Assumptions!$F$58 -> 184.52661 | G85: =Assumptions!$F$51*(1-Assumptions!$F$61)*(1-Assumptions!$F$60)-Assumptions!$F$54-Assumptions!$F$56-Assumptions!$F$57-Assumptions!$F$58 -> 184.52661 | H85: =Assumptions!$F$51*(1-Assumptions!$F$61)*(1-Assumptions!$F$60)-Assumptions!$F$54-Assumptions!$F$56-Assumptions!$F$57-Assumptions!$F$58 -> 184.52661 | I85: =Assumptions!$F$51*(1-Assumptions!$F$61)*(1-Assumptions!$F$60)-Assumptions!$F$54-Assumptions!$F$56-Assumptions!$F$57-Assumptions!$F$58 -> 184.52661 | J85: =Assumptions!$F$51*(1-Assumptions!$F$61)*(1-Assumptions!$F$60)-Assumptions!$F$54-Assumptions!$F$56-Assumptions!$F$57-Assumptions!$F$58 -> 184.52661 | ... AL85: =Assumptions!$F$51*(1-Assumptions!$F$61)*(1-Assumptions!$F$60)-Assumptions!$F$54-Assumptions!$F$56-Assumptions!$F$57-Assumptions!$F$58 -> 184.52661 | AM85: =AVERAGE(N85:AL85) -> 184.52661
A86: Rx gross LTV (contribution / churn) | B86: $ | C86: =C85/Assumptions!$F$49 -> 1942.3853 | D86: =D85/Assumptions!$F$49 -> 1942.3853 | E86: =E85/Assumptions!$F$49 -> 1942.3853 | F86: =F85/Assumptions!$F$49 -> 1942.3853 | G86: =G85/Assumptions!$F$49 -> 1942.3853 | H86: =H85/Assumptions!$F$49 -> 1942.3853 | I86: =I85/Assumptions!$F$49 -> 1942.3853 | J86: =J85/Assumptions!$F$49 -> 1942.3853 | ... AL86: =AL85/Assumptions!$F$49 -> 1942.3853 | AM86: =AVERAGE(N86:AL86) -> 1942.3853
A87: Non-Rx contribution per order | B87: $ | C87: =Assumptions!$F$31*(1-Assumptions!$F$61)*(1-Assumptions!$F$60)-Assumptions!$F$31*Assumptions!$F$36-Assumptions!$F$37 -> 57.880272 | D87: =Assumptions!$F$31*(1-Assumptions!$F$61)*(1-Assumptions!$F$60)-Assumptions!$F$31*Assumptions!$F$36-Assumptions!$F$37 -> 57.880272 | E87: =Assumptions!$F$31*(1-Assumptions!$F$61)*(1-Assumptions!$F$60)-Assumptions!$F$31*Assumptions!$F$36-Assumptions!$F$37 -> 57.880272 | F87: =Assumptions!$F$31*(1-Assumptions!$F$61)*(1-Assumptions!$F$60)-Assumptions!$F$31*Assumptions!$F$36-Assumptions!$F$37 -> 57.880272 | G87: =Assumptions!$F$31*(1-Assumptions!$F$61)*(1-Assumptions!$F$60)-Assumptions!$F$31*Assumptions!$F$36-Assumptions!$F$37 -> 57.880272 | H87: =Assumptions!$F$31*(1-Assumptions!$F$61)*(1-Assumptions!$F$60)-Assumptions!$F$31*Assumptions!$F$36-Assumptions!$F$37 -> 57.880272 | I87: =Assumptions!$F$31*(1-Assumptions!$F$61)*(1-Assumptions!$F$60)-Assumptions!$F$31*Assumptions!$F$36-Assumptions!$F$37 -> 57.880272 | J87: =Assumptions!$F$31*(1-Assumptions!$F$61)*(1-Assumptions!$F$60)-Assumptions!$F$31*Assumptions!$F$36-Assumptions!$F$37 -> 57.880272 | ... AL87: =Assumptions!$F$31*(1-Assumptions!$F$61)*(1-Assumptions!$F$60)-Assumptions!$F$31*Assumptions!$F$36-Assumptions!$F$37 -> 57.880272 | AM87: =AVERAGE(N87:AL87) -> 57.880272
A88: Non-Rx subscriber gross LTV | B88: $ | C88: =C87/Assumptions!$F$33 -> 1052.3686 | D88: =D87/Assumptions!$F$33 -> 1052.3686 | E88: =E87/Assumptions!$F$33 -> 1052.3686 | F88: =F87/Assumptions!$F$33 -> 1052.3686 | G88: =G87/Assumptions!$F$33 -> 1052.3686 | H88: =H87/Assumptions!$F$33 -> 1052.3686 | I88: =I87/Assumptions!$F$33 -> 1052.3686 | J88: =J87/Assumptions!$F$33 -> 1052.3686 | ... AL88: =AL87/Assumptions!$F$33 -> 1052.3686 | AM88: =AVERAGE(N88:AL88) -> 1052.3686
